Workbook

Sheet Summary
A1: Rabobank Australia | T1: BD Costs - Questions
A2: FBT return for the year ended 31 March 2025 | T2: Q1 | U2: Isn't it that under Div9A all meals provided to clients irrespective of amount, time or where is not “sustenance”, but entertaiment.
A3: WP2 - Entertainment sensitive GL Accounts for Apr 2024 to Dec 2024 | E3: Tfrred to "WPE1 ME Summary - GL analysis ent accounts" | T3: Q2 | U3: Totally agree, sounds capital and not on rev acct.
F4: =F29 -> 143205.39 | P4: =P29 -> 470911.71 | Q4: =Q29 -> 8576.02
P5: Income tax purposes
A6: Account# | B6: Account Description | D6: Tax Description | E6: ME? Y/N | F6: ME $ | G6: AU001 / MEC | H6: AU052 | I6: Not ME but other type of FB Y/N | J6: Not ME but other type of FB ==> $ | K6: Nets to Nil in GL accts | L6: s58P M&I or Bus Exp - notFB | M6: ME | N6: Car FB - addn op costs | O6: CP Exp FB | P6: Capital expenditure | Q6: No FBT and not ded | S6: Prepared by | T6: Date | U6: Reviewer Queries | V6: Date
A8: 5140001000 | B8: Training expenses | D8: Picked up in Tuition expese analysis - NFA
A9: 5140001010 | B9: External Training and Seminars | D9: Minor ME amounts | E9: Y | F9: ='Ext Training'!V2+'Ext Training'!V3 -> 772.72 | G9: ='Ext Training'!V2 -> 0 | H9: ='Ext Training'!V3 -> 772.72 | I9: ='Ext Training'!W53 -> 0 | J9: ='Ext Training'!X53 -> 0 | K9: ='Ext Training'!Y53 -> 0 | L9: ='Ext Training'!Z53 -> 0 | M9: ='Ext Training'!AA53 -> 0 | N9: ='Ext Training'!AB53 -> 0 | O9: ='Ext Training'!AC53 -> 0 | P9: ='Ext Training'!AF53 -> 0 | Q9: ='Ext Training'!AG53 -> 0 | U9: OK
A10: 5140001030 | B10: Training travel and lodging ex | D10: Minor ME amounts | E10: Y | F10: ='Training Travel&lodging'!V4+'Training Travel&lodging'!V5 -> 35.88 | G10: ='Training Travel&lodging'!V4 -> 0 | H10: ='Training Travel&lodging'!V5 -> 35.88 | U10: OK
A11: 5160001000 | B11: Publicity/advertising | D11: No ME included. Minor cap amounts | E11: N | F11: ='Publicity&Advertising'!U3+'Publicity&Advertising'!U4 -> 1413.94 | G11: ='Publicity&Advertising'!U3 -> 1413.94 | H11: ='Publicity&Advertising'!U4 -> 0 | P11: ='Publicity&Advertising'!AC3+'Publicity&Advertising'!AC4 -> 426.45 | Q11: ='Publicity&Advertising'!AD3+'Publicity&Advertising'!AD4 -> 0 | U11: Noted
A12: 5160006000 | B12: Opening jubilees own buildin | D12: No ME included. All tax deductible | E12: N | F12: ='Opening Jubilees'!S4+'Opening Jubilees'!S5 -> 0 | G12: ='Opening Jubilees'!S4 -> 0 | H12: ='Opening Jubilees'!S5 -> 0 | U12: Noted
A13: 5160007000 | B13: Sponsoring | D13: No ME included. All tax deductible | E13: N | F13: =Sponsoring!U2+Sponsoring!U3 -> 0 | G13: =Sponsoring!U2 -> 0 | H13: =Sponsoring!U3 -> 0 | P13: =Sponsoring!AC2+Sponsoring!AC3 -> 0 | Q13: =Sponsoring!AD2+Sponsoring!AD3 -> 407.73 | U13: Noted
A14: 5160008000 | B14: Promotional gifts | D14: No ME included. Staff gifts are exempt from FBT | E14: N | F14: ='Promotional gifts'!U4+'Promotional gifts'!U5 -> 0 | G14: ='Promotional gifts'!U4 -> 0 | H14: ='Promotional gifts'!U5 -> 0 | U14: Noted
A15: 5160010000 | B15: Marketing expense | D15: Includes meal entertainment subject to FBT using 50/50 method | E15: Y | F15: ='Marketing exp'!V2+'Marketing exp'!V3 -> 6742.26 | G15: ='Marketing exp'!V2 -> 2454.37 | H15: ='Marketing exp'!V3 -> 4287.89 | I15: ='Marketing exp'!W71 -> 0 | J15: ='Marketing exp'!X71 -> 0 | K15: ='Marketing exp'!Y71 -> 0 | L15: ='Marketing exp'!Z71 -> 0 | M15: ='Marketing exp'!AA71 -> 0 | N15: ='Marketing exp'!AB71 -> 0 | O15: ='Marketing exp'!AC71 -> 0 | P15: ='Marketing exp'!AF71 -> 0 | Q15: ='Marketing exp'!AG71 -> 0 | U15: OK
A16: 5160011000 | B16: Business development | D16: Includes ME and recreation expenses not deductible | E16: Y | F16: ='Business Dev'!V3+'Business Dev'!V4 -> 111166.4 | G16: ='Business Dev'!V3 -> 32145.58 | H16: ='Business Dev'!V4 -> 79020.82 | I16: ='Business Dev'!W187 -> 0 | J16: ='Business Dev'!X187 -> 0 | K16: ='Business Dev'!Y187 -> 0 | L16: ='Business Dev'!Z187 -> 0 | M16: ='Business Dev'!AA187 -> 0 | N16: ='Business Dev'!AB187 -> 0 | O16: ='Business Dev'!AC187 -> 0 | P16: ='Business Dev'!AD3+'Business Dev'!AD4 -> 464087.57 | Q16: ='Business Dev'!AE3+'Business Dev'!AE4 -> 415.15 | U16: See 2 Qs above
A17: 5160999000 | B17: Public relations | D17: No ME included. All tax deductible | E17: N | F17: ='Public relations'!V4+'Public relations'!V5 -> 240.1 | G17: ='Public relations'!V4 -> 230.77 | H17: ='Public relations'!V5 -> 9.33 | P17: ='Public relations'!AD3+'Public relations'!AD4 -> 0 | Q17: ='Public relations'!AE3+'Public relations'!AE4 -> 0 | U17: OK
A18: 5180003000 | B18: Advice Tax & Legal expenses | D18: Picked up in Invoices WPE3 expese analysis - NFA | E18: N | U18: OK
A19: 5190001000 | B19: Contributions& club membership | D19: No ME included. All tax deductible | E19: N | F19: =Membership!V3+Membership!V4 -> 0 | G19: =Membership!V3 -> 0 | H19: =Membership!V4 -> 0 | P19: =Membership!AD3+Membership!AD4 -> 0 | Q19: =Membership!AE3+Membership!AE4 -> 352.15 | U19: OK
A20: 5200006000 | B20: Meeting costs | D20: Includes meal entertainment subject to FBT using 50/50 method | E20: Y | F20: ='Meeting costs'!V8 -> 16912.95 | G20: ='Meeting costs'!V6 -> 8362.5 | H20: ='Meeting costs'!V7 -> 8550.45 | P20: ='Meeting costs'!AD6+'Meeting costs'!AD7 -> 0 | Q20: ='Meeting costs'!AE6+'Meeting costs'!AE7 -> 1268.18 | U20: Q on Client sustenance?
A21: 5200999000 | B21: Miscellaneous expenses | D21: No ME included. Check sustainability payment | E21: N | G21: ='Misc exp'!U4 -> 0 | H21: ='Misc exp'!U5 -> 0 | U21: One amount for sustainability benefit. Check against HR report
A22: 5200999010 | B22: Sundry expenses | D22: Includes meal entertainment subject to FBT using 50/50 method | E22: Y | F22: ='Sundry exp'!V4+'Sundry exp'!V5 -> 239.17 | G22: ='Sundry exp'!V4 -> 0 | H22: ='Sundry exp'!V5 -> 239.17 | I22: ='Sundry exp'!W34 -> 0 | J22: ='Sundry exp'!X34 -> 0 | K22: ='Sundry exp'!Y34 -> 0 | L22: ='Sundry exp'!Z34 -> 0 | M22: ='Sundry exp'!AA34 -> 0 | N22: ='Sundry exp'!AB34 -> 0 | O22: ='Sundry exp'!AC34 -> 0 | P22: ='Sundry exp'!AD34 -> 0 | Q22: ='Sundry exp'!AE34 -> 0 | U22: OK
A23: 5200999020 | B23: Miscellaneous expenses (2) - Tours | D23: Inlcudes ME and staff gifts which are exempt from FBT | E23: Y | F23: ='Misc exp (2)'!V173 -> 0 | G23: ='Misc exp (2)'!V6 -> 0 | H23: ='Misc exp (2)'!V7 -> 0 | I23: ='Misc exp (2)'!W173 -> 0 | J23: ='Misc exp (2)'!X173 -> 0 | K23: ='Misc exp (2)'!Y173 -> 0 | L23: ='Misc exp (2)'!Z173 -> 0 | M23: ='Misc exp (2)'!AA173 -> 0 | N23: ='Misc exp (2)'!AB173 -> 0 | O23: ='Misc exp (2)'!AC173 -> 0 | P23: ='Misc exp (2)'!AD4+'Misc exp (2)'!AD5 -> 1248.37 | Q23: ='Misc exp (2)'!AE4+'Misc exp (2)'!AE5 -> 275.56 | U23: OK
A24: 5900050000 | B24: Other non banking expenses | D24: No ME included. All tax deductible | E24: N | F24: ='Other non-bank exp'!U4+'Other non-bank exp'!U5 -> 0 | G24: ='Other non-bank exp'!U4 -> 0 | H24: ='Other non-bank exp'!U5 -> 0 | U24: OK
A25: 5100999000 | B25: Other office expenses | D25: Inlcudes ME, staff gifts which are exempt from FBT and capital expenditure | E25: Y | F25: ='Other exp'!U3+'Other exp'!U4 -> 5241.79 | G25: ='Other exp'!U3 -> 0 | H25: ='Other exp'!U4 -> 5241.79 | I25: ='Other exp'!V312 -> 0 | J25: ='Other exp'!W312 -> 0 | K25: ='Other exp'!X312 -> 0 | L25: ='Other exp'!Y312 -> 0 | M25: ='Other exp'!Z312 -> 0 | N25: ='Other exp'!AA312 -> 0 | O25: ='Other exp'!AB312 -> 0 | P25: ='Other exp'!AC3+'Other exp'!AC4 -> 5149.32 | Q25: ='Other exp'!AD3+'Other exp'!AD4 -> 5401.83 | U25: OK
A26: 5190002000 | B26: Donations | D26: ME and cap | E26: Y | F26: =Donations!V3+Donations!V4 -> 440.18 | G26: =Donations!V3 -> 0 | H26: =Donations!V4 -> 440.18 | P26: =Donations!AD4+Donations!AD3 -> 0 | Q26: =Donations!AE4+Donations!AE3 -> 455.42 | U26: OK
A27: 5160002000 | B27: Client periodicals/magazines | D27: No ME | E27: N | U27: OK
D29: Total | F29: =SUM(F7:F28) -> 143205.39 | G29: =SUM(G8:G25) -> 44607.16 | H29: =SUM(H8:H25) -> 98158.05 | I29: =SUM(I7:I28) -> 0 | J29: =SUM(J7:J28) -> 0 | K29: =SUM(K7:K28) -> 0 | L29: =SUM(L7:L28) -> 0 | M29: =SUM(M7:M28) -> 0 | N29: =SUM(N7:N28) -> 0 | O29: =SUM(O7:O28) -> 0 | P29: =SUM(P7:P28) -> 470911.71 | Q29: =SUM(Q7:Q28) -> 8576.02
U30: LF: Queries dealt with and responses at WPE1. Largely agreed with questions raises but have not made major changes given stage of process. Agreed we need a separate GL account or something for food whilst travelling | V30: LF response to my queries noted and accept calc accordingly. AJL16/5
O31: AU001 Split | P31: 0 | Q31: =Sponsoring!AD2 -> 0
O32: AU052 split | P32: 0 | Q32: =Sponsoring!AD3+'Business Dev'!AE4+Membership!AE4+'Meeting costs'!AE7+'Misc exp (2)'!AE5+'Other exp'!AD4+Donations!AE4 -> 8576.02
Q33: =SUM(Q31:Q32) -> 8576.02

Sheet Ext Training
A1: Account Number | C1: =Summary!A9 -> 5140001010
A2: Account Name | C2: =Summary!B9 -> External Training and Seminars | H2: Notes: | T2: AU001 | V2: =SUMIF($A$10:$A$23974,"AU001",V9:V23973) -> 0 | AC2: AU001 | AD2: =SUMIF($A$10:$A$23974,"AU001",AD9:AD23973) -> 0
A3: GL Total | C3: 507940.78 | H3: Expenditure on university courses and other courses conferences attended by employees. These are not considered REAP but are in | T3: AU052 | V3: =SUMIF($A$10:$A$23975,"AU052",V9:V23974) -> 772.72 | AC3: AU052 | AD3: =SUMIF($A$10:$A$23975,"AU052",AD9:AD23974) -> 0
A4: Per TB | C4: =SUM(E:E) -> 507940.78 | H4: relation to the employees current roles so would be otherwise deductible for income tax purposes. No FBT will apply to these expenses. | AE4: =SUMIF($A$10:$A$23974,"AU001",AE9:AE23973) -> 0
A5: Variance | C5: =C3-C4 -> 0 | AE5: =SUMIF($A$10:$A$23975,"AU052",AE9:AE23974) -> 0
AD6: Income tax purposes
A7: BUSINESS_UNIT_CODE | B7: OPERATING_UNIT_CODE | C7: ACCOUNT_CODE | D7: DESCRIPTION | E7: BASE_AMOUNT | F7: BASE_CURRENCY_CODE | G7: JOURNAL_DATE | H7: DESCR | I7: LINE_DESCR | J7: PURPOSE | K7: INVOICE_DESCR | L7: INVOICE_ID | M7: VENDOR_NAME | N7: EMPLOYEE_NAME | O7: CHARGE_DESCRIPTION | Q7: ABS | R7: Search Terms | S7: Tax Description | T7: ME? Y/N | U7: OU | V7: ME $ | W7: Not ME but other type of FB Y/N | X7: Not ME but other type of FB ==> $ | Y7: Nets to Nil in GL accts | Z7: s58P M&I or Bus Exp - notFB | AA7: ME | AB7: Car FB - addn op costs | AC7: CP Exp FB | AD7: Capital expenditure | AE7: No FBT and not ded | AF7: Additional Comments
A8: AU052 | B8: AU010029 | C8: 5140001010 | D8: External Training and Seminars | E8: 55000 | F8: AUQ | G8: 45638 | H8: ADP Monthly Invoice - Dec2024 | I8: Graduate development workshop | Q8: =ABS(E8) -> 55000
A9: AU052 | B9: AU025074 | C9: 5140001010 | D9: External Training and Seminars | E9: 38303.23 | F9: AUQ | G9: 45642 | H9: AP Accruals | I9: FGH3492105120-OERUD00 | K9: Technical Training | L9: FGH3492105120 | M9: ERUDITUS LEARNING SOLUTIONS PTE LTD | Q9: =ABS(E9) -> 38303.23
A10: AU052 | B10: AU010021 | C10: 5140001010 | D10: External Training and Seminars | E10: 25031.11 | F10: AUQ | G10: 45629 | H10: AP Accruals | I10: INV-0198-ASUCC00 | K10: Co-faciliation of PLE M2 & Pre | L10: INV-0198 | M10: SUCCESS2YOU PTY LTD | Q10: =ABS(E10) -> 25031.11
A11: AU001 | B11: AU032054 | C11: 5140001010 | D11: External Training and Seminars | E11: 21682.78 | F11: AUQ | G11: 45597 | H11: AP Accruals | I11: 2024220-AMCEA00 | K11: Development of Nature 101 trai | L11: 2024220 | M11: ECOSYSTEM THINKING | Q11: =ABS(E11) -> 21682.78
A12: AU001 | B12: AU032055 | C12: 5140001010 | D12: External Training and Seminars | E12: 21450 | F12: AUQ | G12: 45413 | H12: AP Accruals | I12: 863320-AUNIV00 | K12: Geraldton CNAg September 2023 | L12: 863320 | M12: THE UNIVERSITY OF MELBOURNE | Q12: =ABS(E12) -> 21450
A13: AU052 | B13: AU025104 | C13: 5140001010 | D13: External Training and Seminars | E13: 12155 | F13: AUQ | G13: 45629 | H13: AP Accruals | I13: INV-20148-AFINA09 | K13: FEP Enrolment costs | L13: INV-20148 | M13: FINANCIAL EDUCATION PROFFESIONALS PTYLTD | Q13: =ABS(E13) -> 12155
A14: AU001 | B14: AU032055 | C14: 5140001010 | D14: External Training and Seminars | E14: 11022.78 | F14: AUQ | G14: 45467 | H14: AP Accruals | I14: 863376-AUNIV00 | L14: 863376 | M14: THE UNIVERSITY OF MELBOURNE | Q14: =ABS(E14) -> 11022.78
A15: AU052 | B15: AU010030 | C15: 5140001010 | D15: External Training and Seminars | E15: 10468.94 | F15: AUQ | G15: 45488 | H15: AP Accruals | I15: INV-0346-ALEAR00 | K15: IFTI module | L15: INV-0346 | M15: LEARN STUDIOS PTY LTD | Q15: =ABS(E15) -> 10468.94
A16: AU052 | B16: AU073158 | C16: 5140001010 | D16: External Training and Seminars | E16: 8250 | F16: AUQ | G16: 45597 | H16: AP Accruals | I16: INV-7530-AMILA00 | K16: Offsite Training | L16: INV-7530 | M16: MILAN PARTNERS | Q16: =ABS(E16) -> 8250
A17: AU001 | B17: AU032074 | C17: 5140001010 | D17: External Training and Seminars | E17: 7983.47 | F17: AUQ | G17: 45432 | H17: AP Accruals | I17: RAB052-AHUDS00 | K17: HudsonFaciliation_FSW_SVIC.TAS | L17: RAB052 | M17: HUDSON FACILITATION PTY LTD | Q17: =ABS(E17) -> 7983.47
A18: AU052 | B18: AU020016 | C18: 5140001010 | D18: External Training and Seminars | E18: 7630.15 | F18: AUQ | G18: 45580 | H18: AP Accruals | I18: INV-0547-AMADM00 | K18: Leadership training by MAD Min | L18: INV-0547 | M18: MAD MINDWORKS PTY LTD | Q18: =ABS(E18) -> 7630.15
A19: AU001 | B19: AU050115 | C19: 5140001010 | D19: External Training and Seminars | E19: 7559.11 | F19: AUQ | G19: 45475 | H19: AP Accruals | I19: AGSM67775-AUNIV06 | K19: Accelerated Leadership Program | L19: AGSM67775 | M19: UNIVERSITY OF NSW | Q19: =ABS(E19) -> 7559.11
A20: AU001 | B20: AU030055 | C20: 5140001010 | D20: External Training and Seminars | E20: 7557.53 | F20: AUQ | G20: 45475 | H20: AP Accruals | I20: AGSM58206-AUNIV06 | L20: AGSM58206 | M20: UNIVERSITY OF NSW | Q20: =ABS(E20) -> 7557.53
A21: AU001 | B21: AU050119 | C21: 5140001010 | D21: External Training and Seminars | E21: 7523.24 | F21: AUQ | G21: 45505 | H21: AP Accruals | I21: AGSM83092-AUNIV06 | K21: Accelerated Leadership Program | L21: AGSM83092 | M21: UNIVERSITY OF NSW | Q21: =ABS(E21) -> 7523.24
A22: AU052 | B22: AU010021 | C22: 5140001010 | D22: External Training and Seminars | E22: 7485.39 | F22: AUQ | G22: 45566 | H22: AP Accruals | I22: 38247611-19/09/24-AVIEW00 | K22: View By Sydney final deposit | L22: 38247611-19/09/24 | M22: VIEW BY SYDNEY | Q22: =ABS(E22) -> 7485.39
A23: AU001 | B23: AU020080 | C23: 5140001010 | D23: External Training and Seminars | E23: 7368.74 | F23: AUQ | G23: 45579 | H23: AP Accruals | I23: AGSM56780-AUNIV06 | K23: AGSM leadership training | L23: AGSM56780 | M23: UNIVERSITY OF NSW | Q23: =ABS(E23) -> 7368.74
A24: AU001 | B24: AU032074 | C24: 5140001010 | D24: External Training and Seminars | E24: 6541.32 | F24: AUQ | G24: 45425 | H24: AP Accruals | I24: RAB051-AHUDS00 | K24: HudsonFailitation_VirtualFSW_M | L24: RAB051 | M24: HUDSON FACILITATION PTY LTD | Q24: =ABS(E24) -> 6541.32
A25: AU052 | B25: AU020080 | C25: 5140001010 | D25: External Training and Seminars | E25: 6520.8 | F25: AUQ | G25: 45537 | H25: AP Accruals | I25: 11907-A100001 | K25: Half Day Simulation Workshop f | L25: 11907 | M25: 10000 HOURS (AUSTRALIA) PTY LTD | Q25: =ABS(E25) -> 6520.8
A26: AU052 | B26: AU025080 | C26: 5140001010 | D26: External Training and Seminars | E26: 5933.98 | F26: AUQ | G26: 45579 | H26: AP Accruals | I26: INV02157615-OOREI00 | K26: Subscription Renewal | L26: INV02157615 | M26: OREILLY MEDIA INC | Q26: =ABS(E26) -> 5933.98
A27: AU052 | B27: AU025074 | C27: 5140001010 | D27: External Training and Seminars | E27: 5657.3 | F27: AUQ | G27: 45524 | H27: CCMS | I27: KumarA1-Tuition (study) Reimbu | J27: Training | M27: ALC TRAINING | Q27: =ABS(E27) -> 5657.3
A28: AU052 | B28: AU010010 | C28: 5140001010 | D28: External Training and Seminars | E28: 5517.56 | F28: AUQ | G28: 45404 | H28: CCMS | I28: AuYeungS-Default Licensee Merc | K28: USA GreenBiz Sustainability event - payable by the US team | M28: GREENBIZ GROUP INC/GREENBIZ 24/RDNTNKS38YJ | Q28: =ABS(E28) -> 5517.56
A29: AU052 | B29: AU010030 | C29: 5140001010 | D29: External Training and Seminars | E29: 5505.26 | F29: AUQ | G29: 45519 | H29: AP Accruals | I29: MEMC242553-AAUST105 | K29: ACI 12 x users | L29: MEMC242553 | M29: AUSTRALIAN COMPLIANCE INSTITUTE | Q29: =ABS(E29) -> 5505.26
A30: AU052 | B30: AU020099 | C30: 5140001010 | D30: External Training and Seminars | E30: 5241.82 | F30: AUQ | G30: 45538 | H30: AP Accruals | I30: INV-6873-ALANG01 | K30: Langley Group Strength Profile | L30: INV-6873 | M30: LANGLEY GROUP PTY LTD | Q30: =ABS(E30) -> 5241.82
A31: AU001 | B31: AU032074 | C31: 5140001010 | D31: External Training and Seminars | E31: 5231.02 | F31: AUQ | G31: 45602 | H31: AP Accruals | I31: INV-1291-ATRAN10 | K31: SuccessionSessions_QLD_Facilit | L31: INV-1291 | M31: TRANSITION PARTNERS | Q31: =ABS(E31) -> 5231.02
A32: AU052 | B32: AU010021 | C32: 5140001010 | D32: External Training and Seminars | E32: 4948.2 | F32: AUQ | G32: 45554 | H32: AP Accruals | I32: 63507-AVALI01 | K32: Furniture Hire for ALT event | L32: 63507 | M32: VALIANT COMMERCIAL FURNITURE PTY LTD | Q32: =ABS(E32) -> 4948.2
A33: AU052 | B33: AU010014 | C33: 5140001010 | D33: External Training and Seminars | E33: 4183.7 | F33: AUQ | G33: 45546 | H33: AP Accruals | I33: 22228-OMEND00 | K33: Coaching Masterclass Sessions | L33: 22228 | M33: MEND B.V. | Q33: =ABS(E33) -> 4183.7
A34: AU052 | B34: AU010014 | C34: 5140001010 | D34: External Training and Seminars | E34: 4098.39 | F34: AUQ | G34: 45497 | H34: AP Accruals | I34: 22224-OMEND00 | K34: Masterclass Sessions July | L34: 22224 | M34: MEND B.V. | Q34: =ABS(E34) -> 4098.39
A35: AU052 | B35: AU025100 | C35: 5140001010 | D35: External Training and Seminars | E35: 4036.36 | F35: AUQ | G35: 45555 | H35: CCMS | I35: knowlesp-Default Licensee Merc | J35: AusPayNet Summit 2024 | O35: AUSTRALIAN PAYMENTS NE | Q35: =ABS(E35) -> 4036.36
A36: AU052 | B36: AU071197 | C36: 5140001010 | D36: External Training and Seminars | E36: 3929.85 | F36: AUQ | G36: 45475 | H36: AP Accruals | I36: 00058-AWILL01 | K36: RaboResearch Culture Training | L36: 00058 | M36: WILLIAM ALASTAIR WHITE | Q36: =ABS(E36) -> 3929.85
A37: AU001 | B37: AU071197 | C37: 5140001010 | D37: External Training and Seminars | E37: 3843.1 | F37: AUQ | G37: 45631 | H37: AP Accruals | I37: 00094-AWILL01 | K37: Alastair White Virtual Trainin | L37: 00094 | M37: WILLIAM ALASTAIR WHITE | Q37: =ABS(E37) -> 3843.1
A38: AU001 | B38: AU032074 | C38: 5140001010 | D38: External Training and Seminars | E38: 3797.49 | F38: AUQ | G38: 45448 | H38: AP Accruals | I38: INV-1253-ATRAN10 | L38: INV-1253 | M38: TRANSITION PARTNERS | Q38: =ABS(E38) -> 3797.49
A39: AU052 | B39: AU010014 | C39: 5140001010 | D39: External Training and Seminars | E39: 3583.64 | F39: AUQ | G39: 45400 | H39: AP Accruals | I39: 22205-OMEND00 | K39: Coaching Masterclass Leadershi | L39: 22205 | M39: MEND B.V. | Q39: =ABS(E39) -> 3583.64
A40: AU001 | B40: AU070150 | C40: 5140001010 | D40: External Training and Seminars | E40: 3575 | F40: AUQ | G40: 45450 | H40: AP Accruals | I40: 00000207-AZAVE00 | L40: 00000207 | M40: ZAVESKY CONSULTING | Q40: =ABS(E40) -> 3575
A41: AU052 | B41: AU010014 | C41: 5140001010 | D41: External Training and Seminars | E41: 3537.39 | F41: AUQ | G41: 45435 | H41: AP Accruals | I41: 22212-OMEND00 | K41: Coaching Masterclass Sessions | L41: 22212 | M41: MEND B.V. | Q41: =ABS(E41) -> 3537.39
A42: AU052 | B42: AU010014 | C42: 5140001010 | D42: External Training and Seminars | E42: 3512.91 | F42: AUQ | G42: 45497 | H42: AP Accruals | I42: 22217-OMEND00 | K42: Coaching Masterclass Sessions | L42: 22217 | M42: MEND B.V. | Q42: =ABS(E42) -> 3512.91
A43: AU052 | B43: AU032056 | C43: 5140001010 | D43: External Training and Seminars | E43: 3506.58 | F43: AUQ | G43: 45455 | H43: CCMS | I43: ShepherdD-Default Licensee Mer | K43: Professional Development - Hogan Certification Training (Danny Shepherd) | M43: PETER BERRY CONSULTANCY P | Q43: =ABS(E43) -> 3506.58
A44: AU001 | B44: AU025074 | C44: 5140001010 | D44: External Training and Seminars | E44: 3460.7 | F44: AUQ | G44: 45413 | H44: AP Accruals | I44: INV-0195-ALEAD00 | K44: ITS Leadership Team Program | L44: INV-0195 | M44: LEADERSHIP SHAPERS PTY LTD | Q44: =ABS(E44) -> 3460.7
A45: AU052 | B45: AU010021 | C45: 5140001010 | D45: External Training and Seminars | E45: 3293.16 | F45: AUQ | G45: 45538 | H45: AP Accruals | I45: 38247611-27/08/24-AVIEW00 | K45: View By Sydney Venue Hire | L45: 38247611-27/08/24 | M45: VIEW BY SYDNEY | Q45: =ABS(E45) -> 3293.16
A46: AU001 | B46: AU032074 | C46: 5140001010 | D46: External Training and Seminars | E46: 3270.66 | F46: AUQ | G46: 45415 | H46: AP Accruals | I46: RAB050-AHUDS00 | K46: HudsonfacilitationFSW_NQNT_Apr | L46: RAB050 | M46: HUDSON FACILITATION PTY LTD | Q46: =ABS(E46) -> 3270.66
A47: AU052 | B47: AU070150 | C47: 5140001010 | D47: External Training and Seminars | E47: 3150 | F47: AUQ | G47: 45644 | H47: CCMS | I47: AshworthJ-Tuition (study) Reim | J47: UNSW Training l Development | M47: AGSM @ UNSW | Q47: =ABS(E47) -> 3150
A48: AU001 | B48: AU032055 | C48: 5140001010 | D48: External Training and Seminars | E48: 3015.5 | F48: AUQ | G48: 45413 | H48: AP Accruals | I48: 864573-AUNIV00 | K48: Facilitator Expenses - Ayr, Ke | L48: 864573 | M48: THE UNIVERSITY OF MELBOURNE | Q48: =ABS(E48) -> 3015.5
A49: AU052 | B49: AU020016 | C49: 5140001010 | D49: External Training and Seminars | E49: 3000 | F49: AUQ | G49: 45610 | H49: CCMS | I49: CookD-Default Licensee Merchan | J49: Internal Audit RANZ ethics learning Nov24 | M49: IIA-AUST* O #37267 | Q49: =ABS(E49) -> 3000
A50: AU052 | B50: AU010014 | C50: 5140001010 | D50: External Training and Seminars | E50: 2926.22 | F50: AUQ | G50: 45593 | H50: AP Accruals | I50: 22238-OMEND00 | K50: Coaching Masterclass Sessions | L50: 22238 | M50: MEND B.V. | Q50: =ABS(E50) -> 2926.22
A51: AU052 | B51: AU032054 | C51: 5140001010 | D51: External Training and Seminars | E51: 2868.18 | F51: AUQ | G51: 45547 | H51: CCMS | I51: EllisT-Domestic & Overseas lod | K51: Tamworth CNAg F2F Workshop | 14 August 2024 | M51: TAMWORTH HOTEL MANAGEM | Q51: =ABS(E51) -> 2868.18
A52: AU052 | B52: AU032074 | C52: 5140001010 | D52: External Training and Seminars | E52: 2636.36 | F52: AUQ | G52: 45566 | H52: CCMS | I52: EllisT-Domestic & Overseas lod | K52: Tamworth FSW Module 2 | Venue & Catering - 13th Sep 2024 | M52: TAMWORTH HOTEL MANAGEM | Q52: =ABS(E52) -> 2636.36
A53: AU052 | B53: AU073133 | C53: 5140001010 | D53: External Training and Seminars | E53: -2599.96 | F53: AUQ | G53: 45412 | H53: 13494-AGPTP00 | I53: INV-17851-AFINA09 | Q53: =ABS(E53) -> 2599.96
A54: AU052 | B54: AU073158 | C54: 5140001010 | D54: External Training and Seminars | E54: 2599.96 | F54: AUQ | G54: 45412 | H54: 13494-AGPTP00 | I54: INV-17851-AFINA09 | Q54: =ABS(E54) -> 2599.96
A55: AU052 | B55: AU010025 | C55: 5140001010 | D55: External Training and Seminars | E55: 2545.45 | F55: AUQ | G55: 45464 | H55: CCMS | I55: BeckettK-Default Licensee Merc | K55: Training & Development_Governance Institute Course | M55: GOVERNANCE INSTITUTE | Q55: =ABS(E55) -> 2545.45
A56: AU052 | B56: AU010021 | C56: 5140001010 | D56: External Training and Seminars | E56: 2430.01 | F56: AUQ | G56: 45537 | H56: AP Accruals | I56: RB202402-WNIKI01 | K56: Menopause Session 2 | L56: RB202402 | M56: NIKI BEZZANT | Q56: =ABS(E56) -> 2430.01
A57: AU052 | B57: AU010021 | C57: 5140001010 | D57: External Training and Seminars | E57: 2398.33 | F57: AUQ | G57: 45519 | H57: AP Accruals | I57: RB202401-WNIKI01 | K57: Menopause Session 1 - Niki Bez | L57: RB202401 | M57: NIKI BEZZANT | Q57: =ABS(E57) -> 2398.33
A58: AU001 | B58: AU032054 | C58: 5140001010 | D58: External Training and Seminars | E58: 2372.69 | F58: AUQ | G58: 45518 | H58: AP Accruals | I58: 00000236-AZAVE00 | K58: Media Train for Ally Osborne a | L58: 00000236 | M58: ZAVESKY CONSULTING | Q58: =ABS(E58) -> 2372.69
A59: AU052 | B59: AU010023 | C59: 5140001010 | D59: External Training and Seminars | E59: 2354.54 | F59: AUQ | G59: 45600 | H59: CCMS | I59: SchofieldL-Default Licensee Me | K59: Annual TAPS Payroll Conference | M59: THE ASSOCIATION FOR PA/642210354431 | Q59: =ABS(E59) -> 2354.54
A60: AU052 | B60: AU070150 | C60: 5140001010 | D60: External Training and Seminars | E60: 2301.42 | F60: AUQ | G60: 45504 | H60: CCMS | I60: BaxterD-Entertainment Expense | K60: Wind Endergy Conference (Melbourne) | M60: LEADER ASSOCIATES | Q60: =ABS(E60) -> 2301.42
A61: AU052 | B61: AU010021 | C61: 5140001010 | D61: External Training and Seminars | E61: 2254.55 | F61: AUQ | G61: 45637 | H61: CCMS | I61: ParisO-Default Licensee Mercha | K61: 2025 UN Women International Womens Day Virtual Event Tickets x40 | M61: TICKETS*UN WOMEN A/30en6nwz | Q61: =ABS(E61) -> 2254.55
A62: AU052 | B62: AU030055 | C62: 5140001010 | D62: External Training and Seminars | E62: 2216.11 | F62: AUQ | G62: 45541 | H62: AP Accruals | I62: INV-19507-AFINA09 | K62: FEP Enrolment costs | L62: INV-19507 | M62: FINANCIAL EDUCATION PROFFESIONALS PTYLTD | Q62: =ABS(E62) -> 2216.11
A63: AU052 | B63: AU032074 | C63: 5140001010 | D63: External Training and Seminars | E63: 2190.45 | F63: AUQ | G63: 45629 | H63: CCMS | I63: KelleyM-Offshore Meals & Lodgi | J63: succession workshop emerald | M63: WESTERN GATEWAY MOTEL | Q63: =ABS(E63) -> 2190.45
A64: AU052 | B64: AU070150 | C64: 5140001010 | D64: External Training and Seminars | E64: 2097.36 | F64: AUQ | G64: 45554 | H64: CCMS | I64: BaxterD-Entertainment Expense | J64: AFR Clean Energy Summit Conference | M64: Fairfax Business | Q64: =ABS(E64) -> 2097.36
A65: AU001 | B65: AU030310 | C65: 5140001010 | D65: External Training and Seminars | E65: 2048.98 | F65: AUQ | G65: 45387 | H65: AP Accruals | I65: 00000196-AZAVE00 | K65: Media Training - Deb Maskell-D | L65: 00000196 | M65: ZAVESKY CONSULTING | Q65: =ABS(E65) -> 2048.98
A66: AU052 | B66: AU025104 | C66: 5140001010 | D66: External Training and Seminars | E66: 2030 | F66: AUQ | G66: 45446 | H66: AP Accruals | I66: INV-18761-AFINA09 | K66: FEP Enrolment costs | L66: INV-18761 | M66: FINANCIAL EDUCATION PROFFESIONALS PTYLTD | Q66: =ABS(E66) -> 2030
A67: AU052 | B67: AU070150 | C67: 5140001010 | D67: External Training and Seminars | E67: 2000 | F67: AUQ | G67: 45530 | H67: CCMS | I67: BaxterD-Tuition (study) Reimbu | J67: AGSM course | M67: UNSW | Q67: =ABS(E67) -> 2000
A68: AU001 | B68: AU010014 | C68: 5140001010 | D68: External Training and Seminars | E68: 1986.87 | F68: AUQ | G68: 45475 | H68: AP Accruals | I68: INV-7283-APINN01 | K68: EPMO Strategy Day Culture | L68: INV-7283 | M68: PINNACLE TEAMS EVENTS PTY LTD | Q68: =ABS(E68) -> 1986.87
A69: AU052 | B69: AU020084 | C69: 5140001010 | D69: External Training and Seminars | E69: 1909.09 | F69: AUQ | G69: 45576 | H69: CCMS | I69: DuffyP-Default Licensee Mercha | J69: Tax Institute conference | M69: THE TAX INSTITUTE | Q69: =ABS(E69) -> 1909.09
A70: AU052 | B70: AU073158 | C70: 5140001010 | D70: External Training and Seminars | E70: 1900 | F70: AUQ | G70: 45474 | H70: CCMS | I70: OonkWMJ1-Default Licensee Merc | J70: ISDA course | O70: AFMA | Q70: =ABS(E70) -> 1900
A71: AU052 | B71: AU010021 | C71: 5140001010 | D71: External Training and Seminars | E71: 1883.11 | F71: AUQ | G71: 45573 | H71: AP Accruals | I71: RB202403-WNIKI01 | K71: Outstanding Amount for Menopau | L71: RB202403 | M71: NIKI BEZZANT | Q71: =ABS(E71) -> 1883.11
A72: AU052 | B72: AU025104 | C72: 5140001010 | D72: External Training and Seminars | E72: 1860 | F72: AUQ | G72: 45510 | H72: AP Accruals | I72: INV-19299-AFINA09 | K72: FEP Enrolment costs | L72: INV-19299 | M72: FINANCIAL EDUCATION PROFFESIONALS PTYLTD | Q72: =ABS(E72) -> 1860
A73: AU052 | B73: AU036750 | C73: 5140001010 | D73: External Training and Seminars | E73: 1843.64 | F73: AUQ | G73: 45636 | H73: CCMS | I73: WhitesideM-Domestic & Overseas | J73: Venue hire - FEC LT offsite | M73: Pullman Quay Grand OPI | Q73: =ABS(E73) -> 1843.64
A74: AU052 | B74: AU010023 | C74: 5140001010 | D74: External Training and Seminars | E74: 1800 | F74: AUQ | G74: 45503 | H74: CCMS | I74: DijkVS-Default Licensee Mercha | J74: Training TAPs LSL course | M74: THE ASSOCIATION FOR PA/630310455909 | Q74: =ABS(E74) -> 1800
A75: AU052 | B75: AU030055 | C75: 5140001010 | D75: External Training and Seminars | E75: 1788.31 | F75: AUQ | G75: 45387 | H75: AP Accruals | I75: INV-18286-AFINA09 | K75: FEP enrolment costs for releva | L75: INV-18286 | M75: FINANCIAL EDUCATION PROFFESIONALS PTYLTD | Q75: =ABS(E75) -> 1788.31
A76: AU052 | B76: AU032074 | C76: 5140001010 | D76: External Training and Seminars | E76: 1750 | F76: AUQ | G76: 45614 | H76: CCMS | I76: WHITEL-Domestic & Overseas lod | J76: Catering for Roma Succession Planning Workshop - LEE WHITE | M76: ROMA EXPLORERS INN | Q76: =ABS(E76) -> 1750
A77: AU052 | B77: AU010025 | C77: 5140001010 | D77: External Training and Seminars | E77: 1727.82 | F77: AUQ | G77: 45464 | H77: CCMS | I77: DickeyM-Default Licensee Merch | J77: CLOC | M77: CLOC DIREC* 2024 APAC | Q77: =ABS(E77) -> 1727.82
A78: AU001 | B78: AU010029 | C78: 5140001010 | D78: External Training and Seminars | E78: 1646.86 | F78: AUQ | G78: 45637 | H78: AP Accruals | I78: INV-6733-AGRAD00 | K78: AFR Top 100 Event Tickets | L78: INV-6733 | M78: GRADCONNECTION PTY LTD | Q78: =ABS(E78) -> 1646.86
A79: AU052 | B79: AU070150 | C79: 5140001010 | D79: External Training and Seminars | E79: 1609.09 | F79: AUQ | G79: 45504 | H79: CCMS | I79: AshworthJ-Default Licensee Mer | J79: Energy conference | M79: RECEIPT- GST INCLUSIVE | Q79: =ABS(E79) -> 1609.09
A80: AU052 | B80: AU010021 | C80: 5140001010 | D80: External Training and Seminars | E80: 1529.68 | F80: AUQ | G80: 45517 | H80: AP Accruals | I80: 38247611-01/06/24-AVIEW00 | K80: View By Sydney Venue Hire | L80: 38247611-01/06/24 | M80: VIEW BY SYDNEY | Q80: =ABS(E80) -> 1529.68
A81: AU052 | B81: AU073158 | C81: 5140001010 | D81: External Training and Seminars | E81: 1500 | F81: AUQ | G81: 45643 | H81: CCMS | I81: ChongG2-Default Licensee Merch | J81: ASX Course | M81: COMMODITIESWORKSH | Q81: =ABS(E81) -> 1500
A82: AU052 | B82: AU025104 | C82: 5140001010 | D82: External Training and Seminars | E82: 1498.83 | F82: AUQ | G82: 45629 | H82: AP Accruals | I82: INV-20148-AFINA09 | K82: Course modification | L82: INV-20148 | M82: FINANCIAL EDUCATION PROFFESIONALS PTYLTD | Q82: =ABS(E82) -> 1498.83
A83: AU052 | B83: AU030055 | C83: 5140001010 | D83: External Training and Seminars | E83: 1496.85 | F83: AUQ | G83: 45541 | H83: AP Accruals | I83: INV-19507-AFINA09 | K83: Content Customisation | L83: INV-19507 | M83: FINANCIAL EDUCATION PROFFESIONALS PTYLTD | Q83: =ABS(E83) -> 1496.85
A84: AU052 | B84: AU030055 | C84: 5140001010 | D84: External Training and Seminars | E84: 1477.28 | F84: AUQ | G84: 45566 | H84: AP Accruals | I84: INV-19738-AFINA09 | K84: FEP Enrolment costs | L84: INV-19738 | M84: FINANCIAL EDUCATION PROFFESIONALS PTYLTD | Q84: =ABS(E84) -> 1477.28
A85: AU052 | B85: AU030055 | C85: 5140001010 | D85: External Training and Seminars | E85: 1457.38 | F85: AUQ | G85: 45414 | H85: AP Accruals | I85: INV-18522-AFINA09 | K85: FEP costs for April | L85: INV-18522 | M85: FINANCIAL EDUCATION PROFFESIONALS PTYLTD | Q85: =ABS(E85) -> 1457.38
A86: AU052 | B86: AU032053 | C86: 5140001010 | D86: External Training and Seminars | E86: 1405 | F86: AUQ | G86: 45449 | H86: CCMS | I86: BestermanF-Default Licensee Me | J86: Campbell Town Venue Hire FSW May | M86: WWW.THEGRANGE.COM.AU | Q86: =ABS(E86) -> 1405
A87: AU052 | B87: AU071196 | C87: 5140001010 | D87: External Training and Seminars | E87: 1345.45 | F87: AUQ | G87: 45495 | H87: CCMS | I87: Haynest-Default Licensee Merch | J87: Energy & Climate Summit - Vishal Patel | M87: RECEIPT- GST INCLUSIVE | Q87: =ABS(E87) -> 1345.45
A88: AU052 | B88: AU032074 | C88: 5140001010 | D88: External Training and Seminars | E88: 1341.38 | F88: AUQ | G88: 45513 | H88: CCMS | I88: MULLERTA-Entertainment Expense | J88: Longreach FSW - Venue and Catering | M88: QANTAS FOUNDERS MUSEUM | Q88: =ABS(E88) -> 1341.38
A89: AU052 | B89: AU074251 | C89: 5140001010 | D89: External Training and Seminars | E89: 1282.59 | F89: AUQ | G89: 45524 | H89: CCMS | I89: ExmannJ-Default Licensee Merch | J89: Grain conference | M89: GRAIN TRADE AUSTRALIA | Q89: =ABS(E89) -> 1282.59
A90: AU052 | B90: AU074251 | C90: 5140001010 | D90: External Training and Seminars | E90: 1282.59 | F90: AUQ | G90: 45537 | H90: CCMS | I90: JohnstoneI1-Default Licensee M | J90: Grains Conference TIcket | M90: GRAIN TRADE AUSTRALIA | Q90: =ABS(E90) -> 1282.59
A91: AU052 | B91: AU032074 | C91: 5140001010 | D91: External Training and Seminars | E91: 1280.86 | F91: AUQ | G91: 45595 | H91: CCMS | I91: MillettP-Offshore Meals & Lodg | J91: SuccessionSessions_GoulburnNSW_23May_Catering | M91: ALPINE HOTEL OPERATION | Q91: =ABS(E91) -> 1280.86
A92: AU052 | B92: AU010029 | C92: 5140001010 | D92: External Training and Seminars | E92: 1250 | F92: AUQ | G92: 45637 | H92: CCMS | I92: SunT-Default Licensee Merchant | J92: AAGE Conference ticket | M92: PAYPAL/CPF6LRL4RAKX | Q92: =ABS(E92) -> 1250
A93: AU001 | B93: AU071197 | C93: 5140001010 | D93: External Training and Seminars | E93: 1189.54 | F93: AUQ | G93: 45518 | H93: AP Accruals | I93: 00000236-AZAVE00 | K93: Media Training for Paul Joules | L93: 00000236 | M93: ZAVESKY CONSULTING | Q93: =ABS(E93) -> 1189.54
A94: AU052 | B94: AU070150 | C94: 5140001010 | D94: External Training and Seminars | E94: 1167.71 | F94: AUQ | G94: 45516 | H94: CCMS | I94: KellyA4-Contributions & Club M | J94: RUral | M94: RURAL PRESS CLUB QLD | Q94: =ABS(E94) -> 1167.71
A95: AU052 | B95: AU032074 | C95: 5140001010 | D95: External Training and Seminars | E95: 1139.09 | F95: AUQ | G95: 45582 | H95: CCMS | I95: RenshawGC-Default Licensee Mer | J95: Spalding Financials Skills Workshop 10/10/24 - Function cost - Attended by 18 Clients / Facilitator | M95: SQ *SPALDING SPORTS | Q95: =ABS(E95) -> 1139.09
A96: AU052 | B96: AU032074 | C96: 5140001010 | D96: External Training and Seminars | E96: 1099.13 | F96: AUQ | G96: 45552 | H96: CCMS | I96: JonesS2-Offshore Meals & Lodgi | J96: SuccessionSessions_OrangeNSW_5SEPT_Catering | M96: CANOBOLAS PUB PTY LI | Q96: =ABS(E96) -> 1099.13
A97: AU052 | B97: AU010016 | C97: 5140001010 | D97: External Training and Seminars | E97: 1090.91 | F97: AUQ | G97: 45422 | H97: CCMS | I97: LiscoeA-Default Licensee Merch | J97: Recertification of Product Owner | M97: EB *CERTIFIED SCRUM PR | Q97: =ABS(E97) -> 1090.91
A98: AU052 | B98: AU070150 | C98: 5140001010 | D98: External Training and Seminars | E98: 1090.91 | F98: AUQ | G98: 45530 | H98: CCMS | I98: BaxterD-Default Licensee Merch | J98: Energy Transition Seminar | M98: CEIG.ORG.AU | Q98: =ABS(E98) -> 1090.91
A99: AU052 | B99: AU070150 | C99: 5140001010 | D99: External Training and Seminars | E99: 1090.91 | F99: AUQ | G99: 45544 | H99: CCMS | I99: AshworthJ-Default Licensee Mer | J99: Clean Energy Investor Conf | M99: CEIG.ORG.AU | Q99: =ABS(E99) -> 1090.91
A100: AU052 | B100: AU070100 | C100: 5140001010 | D100: External Training and Seminars | E100: 1070 | F100: AUQ | G100: 45642 | H100: CCMS | I100: EbbesM1-Default Licensee Merch | J100: tickets ASFI summit 2x | M100: WWW.ASFI.ORG.AU | Q100: =ABS(E100) -> 1070
...

Sheet Training Travel&lodging
A1: Account Number | C1: =Summary!A10 -> 5140001030
A2: Account Name | C2: =Summary!B10 -> Training travel and lodging ex | G2: Notes:
A3: GL Total | C3: 58301.3 | G3: Expenditure on university courses and other courses conferences attended by employees. These are not considered REAP but are in | AC3: Totals | AD3: =SUM(AD8:AD1048576) -> 0 | AE3: =SUM(AE8:AE1048576) -> 0
A4: Per TB | C4: =SUM(E:E) -> 58301.3 | G4: relation to the employees current roles so would be otherwise deductible for income tax purposes. No FBT will apply to these expenses. | T4: AU001 | V4: =SUMIF($A$10:$A$23974,"AU001",V9:V23973) -> 0
A5: Variance | C5: =C3-C4 -> 0 | T5: AU052 | V5: =SUMIF($A$10:$A$23975,"AU052",V9:V23974) -> 35.88
AD6: Income tax purposes
A7: BUSINESS_UNIT_CODE | B7: OPERATING_UNIT_CODE | C7: ACCOUNT_CODE | D7: DESCRIPTION | E7: BASE_AMOUNT | F7: BASE_CURRENCY_CODE | G7: JOURNAL_DATE | H7: DESCR | I7: LINE_DESCR | J7: PURPOSE | K7: INVOICE_DESCR | L7: INVOICE_ID | M7: VENDOR_NAME | N7: EMPLOYEE_NAME | O7: CHARGE_DESCRIPTION | Q7: ABS | R7: Search Terms | S7: Tax Description | T7: ME? Y/N | U7: OU | V7: ME $ | W7: Not ME but other type of FB Y/N | X7: Not ME but other type of FB ==> $ | Y7: Nets to Nil in GL accts | Z7: s58P M&I or Bus Exp - notFB | AA7: ME | AB7: Car FB - addn op costs | AC7: CP Exp FB | AD7: Capital expenditure | AE7: No FBT and not ded | AF7: Additional Comments
A8: AU052 | B8: AU030055 | C8: 5140001030 | D8: Training travel and lodging ex | E8: 9019.28 | F8: AUQ | G8: 45624 | H8: CCMS | I8: MckinnonR-Domestic & Overseas | K8: Accommodation for the facilitators and VICTAS staff traveling for RRB training in Melbourne (13th & | O8: Novotel On Collins OPI | Q8: =ABS(E8) -> 9019.28 | S8: business related
A9: AU001 | B9: AU032074 | C9: 5140001030 | D9: Training travel and lodging ex | E9: 5715.45 | F9: AUQ | G9: 45530 | H9: AP Accruals | I9: RAB057-AHUDS00 | K9: FSW_Longreach/Blackhall/Emeral | L9: RAB057 | M9: HUDSON FACILITATION PTY LTD | Q9: =ABS(E9) -> 5715.45
A10: AU001 | B10: AU032074 | C10: 5140001030 | D10: Training travel and lodging ex | E10: 4817.63 | F10: AUQ | G10: 45510 | H10: AP Accruals | I10: RAB055-AHUDS00 | K10: FSW_Pittsworth/Goondiwindi_Jul | L10: RAB055 | M10: HUDSON FACILITATION PTY LTD | Q10: =ABS(E10) -> 4817.63
A11: AU001 | B11: AU030055 | C11: 5140001030 | D11: Training travel and lodging ex | E11: 4121.29 | F11: AUQ | G11: 45581 | H11: AP Accruals | I11: 1592537-APARK01 | K11: Accommodation RCA participant | L11: 1592537 | M11: PARKROYAL DARLING HARBOUR | Q11: =ABS(E11) -> 4121.29
A12: AU001 | B12: AU032074 | C12: 5140001030 | D12: Training travel and lodging ex | E12: 3339.11 | F12: AUQ | G12: 45484 | H12: AP Accruals | I12: RAB054-AHUDS00 | L12: RAB054 | M12: HUDSON FACILITATION PTY LTD | Q12: =ABS(E12) -> 3339.11
A13: AU001 | B13: AU032074 | C13: 5140001030 | D13: Training travel and lodging ex | E13: 3196.01 | F13: AUQ | G13: 45586 | H13: AP Accruals | I13: RAB062-AHUDS00 | K13: FSW_Arthurton&Spalding_Facilit | L13: RAB062 | M13: HUDSON FACILITATION PTY LTD | Q13: =ABS(E13) -> 3196.01
A14: AU001 | B14: AU032074 | C14: 5140001030 | D14: Training travel and lodging ex | E14: 3186.76 | F14: AUQ | G14: 45553 | H14: AP Accruals | I14: RAB060-AHUDS00 | K14: FSW_Inverell/Tamworth_Sep_Faci | L14: RAB060 | M14: HUDSON FACILITATION PTY LTD | Q14: =ABS(E14) -> 3186.76
A15: AU001 | B15: AU032074 | C15: 5140001030 | D15: Training travel and lodging ex | E15: 2954.32 | F15: AUQ | G15: 45552 | H15: AP Accruals | I15: RAB058-AHUDS00 | K15: FSW_Ongerup_13Aug_FacilitatorT | L15: RAB058 | M15: HUDSON FACILITATION PTY LTD | Q15: =ABS(E15) -> 2954.32
A16: AU052 | B16: AU061134 | C16: 5140001030 | D16: Training travel and lodging ex | E16: 2106 | F16: AUQ | G16: 45635 | H16: AP Accruals | I16: 20250224.2-ACROW18 | K16: Treasury Offsite | L16: 20250224.2 | M16: CROWNE PLAZA TERRIGAL PACIFIC | Q16: =ABS(E16) -> 2106 | S16: Accept seminar
A17: AU052 | B17: AU061134 | C17: 5140001030 | D17: Training travel and lodging ex | E17: 2106 | F17: AUQ | G17: 45635 | H17: AP Accruals | I17: 20250224.3-ACROW18 | K17: Treasury Offsite | L17: 20250224.3 | M17: CROWNE PLAZA TERRIGAL PACIFIC | Q17: =ABS(E17) -> 2106 | S17: Accept seminar
A18: AU001 | B18: AU032074 | C18: 5140001030 | D18: Training travel and lodging ex | E18: 1865.34 | F18: AUQ | G18: 45510 | H18: AP Accruals | I18: RAB056-AHUDS00 | K18: FSW_Finley/Colleambally_Jul_Tr | L18: RAB056 | M18: HUDSON FACILITATION PTY LTD | Q18: =ABS(E18) -> 1865.34
A19: AU001 | B19: AU032074 | C19: 5140001030 | D19: Training travel and lodging ex | E19: 1844.82 | F19: AUQ | G19: 45553 | H19: AP Accruals | I19: INV-1282-ATRAN10 | K19: SuccessionPlanningInformationS | L19: INV-1282 | M19: TRANSITION PARTNERS | Q19: =ABS(E19) -> 1844.82
A20: AU001 | B20: AU032074 | C20: 5140001030 | D20: Training travel and lodging ex | E20: 1380.73 | F20: AUQ | G20: 45553 | H20: AP Accruals | I20: INV-1279-ATRAN10 | K20: SuccessionPlanningInformationS | L20: INV-1279 | M20: TRANSITION PARTNERS | Q20: =ABS(E20) -> 1380.73
A21: AU052 | B21: AU030055 | C21: 5140001030 | D21: Training travel and lodging ex | E21: 879.25 | F21: AUQ | G21: 45601 | H21: AP Accruals | I21: EEC-830-ESMIT23 | K21: Edwina Smith- Expenses for RCA | L21: EEC-830 | M21: EDWINA SMITH | Q21: =ABS(E21) -> 879.25
A22: AU052 | B22: AU076174 | C22: 5140001030 | D22: Training travel and lodging ex | E22: 868.15 | F22: AUQ | G22: 45404 | H22: CCMS | I22: MiddletonM-Default Licensee Me | J22: PIX Conference | O22: KAM EVENTS | Q22: =ABS(E22) -> 868.15
A23: AU052 | B23: AU030217 | C23: 5140001030 | D23: Training travel and lodging ex | E23: 755.22 | F23: AUQ | G23: 45580 | H23: AP Accruals | I23: EEC-768-EFALC02 | K23: Hotel Claim | L23: EEC-768 | M23: LAUREN FALCONER | Q23: =ABS(E23) -> 755.22
A24: AU052 | B24: AU030317 | C24: 5140001030 | D24: Training travel and lodging ex | E24: 681.82 | F24: AUQ | G24: 45594 | H24: CCMS | I24: BennettA-Domestic & Overseas l | J24: Accommodation in Sydney for RCA | O24: Park Royal Darl Harb OPI | Q24: =ABS(E24) -> 681.82 | S24: Accept business travel food
A25: AU052 | B25: AU032074 | C25: 5140001030 | D25: Training travel and lodging ex | E25: 542.27 | F25: AUQ | G25: 45386 | H25: CCMS | I25: PozziB-Offshore Meals & Lodgin | K25: Financial Skills Workshop Catering Charters Towers 22March - Brad Pozzi | O25: SANTONS GOURMET HOAGIES | Q25: =ABS(E25) -> 542.27
A26: AU001 | B26: AU030325 | C26: 5140001030 | D26: Training travel and lodging ex | E26: 517.44 | F26: AUQ | G26: 45631 | H26: AP Accruals | I26: 31-AAUST23 | K26: Accommodation for Cameron De K | L26: 31 | M26: AUSTRALIAN DAIRY CONFERENCE | Q26: =ABS(E26) -> 517.44
A27: AU052 | B27: AU025080 | C27: 5140001030 | D27: Training travel and lodging ex | E27: 466.27 | F27: AUQ | G27: 45558 | H27: CCMS | I27: NazarenoJ-Airfares | J27: NGON - NZ4 - Flight | O27: EGEN*AUSI142497951/AUBI2024260417261/AUBI2024260417261650 | Q27: =ABS(E27) -> 466.27
A28: AU052 | B28: AU030410 | C28: 5140001030 | D28: Training travel and lodging ex | E28: 460.23 | F28: AUQ | G28: 45607 | H28: CCMS | I28: FlynnA-Domestic & Overseas lod | K28: Accomodation as part of trip to Sydney for Rural Credit Training. | O28: Park Royal Darl Harb OPI | Q28: =ABS(E28) -> 460.23
A29: AU052 | B29: AU032074 | C29: 5140001030 | D29: Training travel and lodging ex | E29: 431.82 | F29: AUQ | G29: 45386 | H29: CCMS | I29: WeatherlyC-Offshore Meals & Lo | K29: Lunch FSW | O29: SQ *PETALS & PINECONES | Q29: =ABS(E29) -> 431.82 | S29: Accept seminar food
A30: AU052 | B30: AU030313 | C30: 5140001030 | D30: Training travel and lodging ex | E30: 398.45 | F30: AUQ | G30: 45639 | H30: CCMS | I30: RistromJ-Airfares | K30: Airfares for travel to RCA training Sydney | O30: VIRGIN AUSTR/79534850626969/79534850626969 | Q30: =ABS(E30) -> 398.45
A31: AU052 | B31: AU030317 | C31: 5140001030 | D31: Training travel and lodging ex | E31: 369.1 | F31: AUQ | G31: 45594 | H31: CCMS | I31: BennettA-Airfares | K31: Flights to sydney for RCA | O31: VIRGIN AUSTR/79558153577409/79558153577409 | Q31: =ABS(E31) -> 369.1
A32: AU052 | B32: AU032074 | C32: 5140001030 | D32: Training travel and lodging ex | E32: 330 | F32: AUQ | G32: 45386 | H32: CCMS | I32: WeatherlyC-Default Licensee Me | K32: venue hire | O32: TABLELANDS R C | Q32: =ABS(E32) -> 330
A33: AU052 | B33: AU030510 | C33: 5140001030 | D33: Training travel and lodging ex | E33: 314.2 | F33: AUQ | G33: 45464 | H33: CCMS | I33: PriceC-Default Licensee Mercha | K33: Horsham Culture Workshop - SYD MEL Return May 24 - N Cross | O33: QANTAS AIR_ABN16009661901/NXGZNWNVGKJNQR32/NXGZNWNVGKJNQR32 | Q33: =ABS(E33) -> 314.2
A34: AU052 | B34: AU030430 | C34: 5140001030 | D34: Training travel and lodging ex | E34: 311.35 | F34: AUQ | G34: 45601 | H34: AP Accruals | I34: EEC-835-EFINL00 | K34: Expenses for RCA Training Syd | L34: EEC-835 | M34: VIVIAN FINLAY | Q34: =ABS(E34) -> 311.35
A35: AU052 | B35: AU020080 | C35: 5140001030 | D35: Training travel and lodging ex | E35: 303 | F35: AUQ | G35: 45510 | H35: AP Accruals | I35: EEC-406-ENGUY01 | K35: Utrecht trip 22-28June 2024 | L35: EEC-406 | M35: HAI NGUYEN | Q35: =ABS(E35) -> 303
A36: AU052 | B36: AU032074 | C36: 5140001030 | D36: Training travel and lodging ex | E36: 290.91 | F36: AUQ | G36: 45449 | H36: CCMS | I36: WebbO-Default Licensee Merchan | K36: FinancialSkillsWorkshops_Goondiwindi_17Jul_VenueHire | O36: GATEWAY TO TRAINING | Q36: =ABS(E36) -> 290.91
A37: AU052 | B37: AU030415 | C37: 5140001030 | D37: Training travel and lodging ex | E37: 283.35 | F37: AUQ | G37: 45601 | H37: AP Accruals | I37: EEC-868-ELYDD00 | K37: Meals & Taxis during RCA train | L37: EEC-868 | M37: SANDY LYDDY | Q37: =ABS(E37) -> 283.35
A38: AU052 | B38: AU030510 | C38: 5140001030 | D38: Training travel and lodging ex | E38: 266.99 | F38: AUQ | G38: 45464 | H38: CCMS | I38: PriceC-Default Licensee Mercha | K38: Airfare SYD ADL RRM3 Training | O38: QANTAS AIR_ABN16009661901/QWPFZ9CRMLG74FH2/QWPFZ9CRMLG74FH2 | Q38: =ABS(E38) -> 266.99
A39: AU052 | B39: AU030316 | C39: 5140001030 | D39: Training travel and lodging ex | E39: 215.94 | F39: AUQ | G39: 45628 | H39: CCMS | I39: WilsonE3-Domestic & Overseas l | K39: 1 x night accomodation at Holiday Inn as part of Rural Credit Academy training in Sydney | O39: Holiday Inn Melb Airport | Q39: =ABS(E39) -> 215.94
A40: AU052 | B40: AU030316 | C40: 5140001030 | D40: Training travel and lodging ex | E40: 208.15 | F40: AUQ | G40: 45628 | H40: CCMS | I40: WilsonE3-Default Licensee Merc | K40: Melbourne to Sydney flight | O40: QANTAS AIR_ABN16009661901/VMSVLL9KC9G5XJF3/VMSVLL9KC9G5XJF3 | Q40: =ABS(E40) -> 208.15
A41: AU052 | B41: AU076174 | C41: 5140001030 | D41: Training travel and lodging ex | E41: 204.55 | F41: AUQ | G41: 45639 | H41: CCMS | I41: MiddletonM-Default Licensee Me | K41: Flight Booking Fee - MAC Global Conference | O41: QANTAS AIR_ABN16009661901/H3QTPM2N5N75GXW3/H3QTPM2N5N75GXW3 | Q41: =ABS(E41) -> 204.55
A42: AU052 | B42: AU076174 | C42: 5140001030 | D42: Training travel and lodging ex | E42: 204.55 | F42: AUQ | G42: 45639 | H42: CCMS | I42: MiddletonM-Default Licensee Me | K42: International Flight MAC Global Program | O42: QANTAS AIR_ABN16009661901/FR589ZSFNL5XKXD3/FR589ZSFNL5XKXD3 | Q42: =ABS(E42) -> 204.55
A43: AU052 | B43: AU025080 | C43: 5140001030 | D43: Training travel and lodging ex | E43: 202.82 | F43: AUQ | G43: 45558 | H43: CCMS | I43: NazarenoJ-Airfares | K43: NGON - NZ4 Flight - Jesus Nazareno | O43: EGEN*AUSI142497980/AUBI2024260417293/AUBI2024260417293310 | Q43: =ABS(E43) -> 202.82
A44: AU052 | B44: AU030316 | C44: 5140001030 | D44: Training travel and lodging ex | E44: 190.09 | F44: AUQ | G44: 45628 | H44: CCMS | I44: WilsonE3-Airfares | K44: Sydney to Melbourne flight - Eric Wilson | O44: VIRGIN AUSTR/79534850909509/79534850909509 | Q44: =ABS(E44) -> 190.09
A45: AU052 | B45: AU025080 | C45: 5140001030 | D45: Training travel and lodging ex | E45: 186.73 | F45: AUQ | G45: 45558 | H45: CCMS | I45: NazarenoJ-Airfares | K45: NGON - NZ4 Flight | O45: EGEN*AUSI142497983/AUBI2024260417293/AUBI2024260417293380 | Q45: =ABS(E45) -> 186.73
A46: AU052 | B46: AU032074 | C46: 5140001030 | D46: Training travel and lodging ex | E46: 174.55 | F46: AUQ | G46: 45386 | H46: CCMS | I46: PozziB-Offshore Meals & Lodgin | K46: Financial Skills Workshop Catering Charters Towers 22March - Brad Pozzi | O46: SQ *COFFEE + FLOWERS IN T | Q46: =ABS(E46) -> 174.55
A47: AU052 | B47: AU030313 | C47: 5140001030 | D47: Training travel and lodging ex | E47: 159.09 | F47: AUQ | G47: 45639 | H47: CCMS | I47: RistromJ-Company Car Parking | K47: Parking while at RRB training | O47: WILSON PARKING AUSTRALIA | Q47: =ABS(E47) -> 159.09
A48: AU052 | B48: AU030510 | C48: 5140001030 | D48: Training travel and lodging ex | E48: 136.81 | F48: AUQ | G48: 45464 | H48: CCMS | I48: PriceC-Airfares | K48: Airfare RRM3 Training ADL SYD Fede Artero | O48: VIRGIN AUSTR/79560681071679/79560681071679 | Q48: =ABS(E48) -> 136.81
A49: AU052 | B49: AU010021 | C49: 5140001030 | D49: Training travel and lodging ex | E49: 103.13 | F49: AUQ | G49: 45475 | H49: AP Accruals | I49: EEC-226-EPARI00 | L49: EEC-226 | Q49: =ABS(E49) -> 103.13
A50: AU052 | B50: AU030313 | C50: 5140001030 | D50: Training travel and lodging ex | E50: 97.63 | F50: AUQ | G50: 45614 | H50: AP Accruals | I50: EEC-921-ECROK02 | K50: Meal Allowance | L50: EEC-921 | Q50: =ABS(E50) -> 97.63
A51: AU052 | B51: AU030315 | C51: 5140001030 | D51: Training travel and lodging ex | E51: 90.91 | F51: AUQ | G51: 45622 | H51: CCMS | I51: KnowlesB-Domestic & Overseas l | K51: Bond - not charged | O51: Novotel Melb On Collins O | Q51: =ABS(E51) -> 90.91
A52: AU052 | B52: AU030315 | C52: 5140001030 | D52: Training travel and lodging ex | E52: 90.91 | F52: AUQ | G52: 45622 | H52: CCMS | I52: KnowlesB-Domestic & Overseas l | K52: Bond for Megan McDonald Novotel | O52: Novotel Melb On Collins O | Q52: =ABS(E52) -> 90.91
A53: AU052 | B53: AU030315 | C53: 5140001030 | D53: Training travel and lodging ex | E53: -90.91 | F53: AUQ | G53: 45622 | H53: CCMS | I53: KnowlesB-Domestic & Overseas l | K53: Bond refund for Megan Mac | O53: Novotel Melb On Collins O | Q53: =ABS(E53) -> 90.91
A54: AU052 | B54: AU030311 | C54: 5140001030 | D54: Training travel and lodging ex | E54: 90.91 | F54: AUQ | G54: 45624 | H54: CCMS | I54: BrooksH-Domestic & Overseas lo | K54: Hotel Bond- returned less breakfast | O54: Novotel Melb On Collins O | Q54: =ABS(E54) -> 90.91
A55: AU052 | B55: AU030311 | C55: 5140001030 | D55: Training travel and lodging ex | E55: 90.91 | F55: AUQ | G55: 45624 | H55: CCMS | I55: BrooksH-Domestic & Overseas lo | K55: Hotel Bond- returned less breakfast- Benjamin Walmsley | O55: Novotel Melb On Collins O | Q55: =ABS(E55) -> 90.91
A56: AU052 | B56: AU030313 | C56: 5140001030 | D56: Training travel and lodging ex | E56: 90.91 | F56: AUQ | G56: 45639 | H56: CCMS | I56: RistromJ-Domestic & Overseas l | K56: Deposit for accommodation - RRB training Melbourne | O56: Novotel Melb On Collins O | Q56: =ABS(E56) -> 90.91
A57: AU052 | B57: AU030613 | C57: 5140001030 | D57: Training travel and lodging ex | E57: 83.66 | F57: AUQ | G57: 45618 | H57: AP Accruals | I57: EEC-953-EFOWL01 | K57: Syd RCA Training Taxi | L57: EEC-953 | M57: DAMON FOWLER | Q57: =ABS(E57) -> 83.66
A58: AU052 | B58: AU030313 | C58: 5140001030 | D58: Training travel and lodging ex | E58: 79.27 | F58: AUQ | G58: 45639 | H58: CCMS | I58: RistromJ-Domestic & Overseas l | K58: Parking Melbourne for training | O58: Novotel DarHarbour OPI | Q58: =ABS(E58) -> 79.27
A59: AU052 | B59: AU010021 | C59: 5140001030 | D59: Training travel and lodging ex | E59: 74.08 | F59: AUQ | G59: 45586 | H59: CCMS | I59: ParisO-Ground Travel | K59: Travel to ALT Basecamp 1 for 6am | O59: UBER *TRIP/j7w7bf3s | Q59: =ABS(E59) -> 74.08
A60: AU052 | B60: AU030613 | C60: 5140001030 | D60: Training travel and lodging ex | E60: 72.83 | F60: AUQ | G60: 45618 | H60: AP Accruals | I60: EEC-948-ETANG05 | K60: Sydney RCA training - taxis to | L60: EEC-948 | M60: VICTOR TANGARIS | Q60: =ABS(E60) -> 72.83
A61: AU052 | B61: AU050119 | C61: 5140001030 | D61: Training travel and lodging ex | E61: 71.82 | F61: AUQ | G61: 45639 | H61: CCMS | I61: KaiteieDT-Company Car Parking | K61: CMI - Brisbane Conference | O61: WILSON PARKING AUSTR | Q61: =ABS(E61) -> 71.82
A62: AU052 | B62: AU030413 | C62: 5140001030 | D62: Training travel and lodging ex | E62: 66.71 | F62: AUQ | G62: 45629 | H62: AP Accruals | I62: EEC-979-EJAKO00 | K62: Breakfast, Lunch & Dinner | L62: EEC-979 | M62: TRINE JAKOBSEN | Q62: =ABS(E62) -> 66.71 | S62: Accept business travel food
A63: AU052 | B63: AU030055 | C63: 5140001030 | D63: Training travel and lodging ex | E63: 62.5 | F63: AUQ | G63: 45645 | H63: CCMS | I63: FrekeK2-Default Licensee Merch | K63: RCA RAF Seat Selection International Flight | O63: QANTAS AIR_ABN16009661901/VSGZMN72VBVBHK52/VSGZMN72VBVBHK52 | Q63: =ABS(E63) -> 62.5
A64: AU052 | B64: AU030711 | C64: 5140001030 | D64: Training travel and lodging ex | E64: 59.09 | F64: AUQ | G64: 45631 | H64: CCMS | I64: HumeH-Company Car Parking | K64: car park Hobart Airport R&B training | O64: HOBART INTERNATIONAL A | Q64: =ABS(E64) -> 59.09
A65: AU052 | B65: AU010021 | C65: 5140001030 | D65: Training travel and lodging ex | E65: 54.39 | F65: AUQ | G65: 45588 | H65: CCMS | I65: ParisO-Ground Travel | K65: ALT- Uber to office with BC3 materials after event | O65: UBER *TRIP/q4nq05n3 | Q65: =ABS(E65) -> 54.39
A66: AU052 | B66: AU030412 | C66: 5140001030 | D66: Training travel and lodging ex | E66: 50 | F66: AUQ | G66: 45630 | H66: CCMS | I66: WebbO-Company Car Parking | K66: Airport Parking - Rural Credit Academy Moodys Training | O66: WELLCAMP PARKING | Q66: =ABS(E66) -> 50
A67: AU052 | B67: AU030055 | C67: 5140001030 | D67: Training travel and lodging ex | E67: 50 | F67: AUQ | G67: 45645 | H67: CCMS | I67: FrekeK2-Default Licensee Merch | K67: RCA RAF Qantas Seat Selection | O67: QANTAS AIR_ABN16009661901/P6TJK5PGQLFGWSD3/P6TJK5PGQLFGWSD3 | Q67: =ABS(E67) -> 50
A68: AU052 | B68: AU060777 | C68: 5140001030 | D68: Training travel and lodging ex | E68: 46.18 | F68: AUQ | G68: 45617 | H68: AP Accruals | I68: EEC-939-EPASC00 | K68: Laundry | L68: EEC-939 | M68: JAMES PASCOE | Q68: =ABS(E68) -> 46.18
A69: AU052 | B69: AU010021 | C69: 5140001030 | D69: Training travel and lodging ex | E69: 41.92 | F69: AUQ | G69: 45590 | H69: CCMS | I69: BaylissK-Ground Travel | K69: travel home from ALT basecamp 3 after pack up | O69: UBER *TRIP/jkpszy3v | Q69: =ABS(E69) -> 41.92
A70: AU052 | B70: AU030315 | C70: 5140001030 | D70: Training travel and lodging ex | E70: -39.55 | F70: AUQ | G70: 45622 | H70: CCMS | I70: KnowlesB-Domestic & Overseas l | K70: Novotel Bond refund | O70: Novotel Melb On Collins O | Q70: =ABS(E70) -> 39.55
A71: AU052 | B71: AU030313 | C71: 5140001030 | D71: Training travel and lodging ex | E71: 39.55 | F71: AUQ | G71: 45639 | H71: CCMS | I71: RistromJ-Domestic & Overseas l | K71: Breakfast - Melbourne RRB training | O71: Novotel Melb On Collins O | Q71: =ABS(E71) -> 39.55
A72: AU052 | B72: AU030613 | C72: 5140001030 | D72: Training travel and lodging ex | E72: 38.77 | F72: AUQ | G72: 45618 | H72: AP Accruals | I72: EEC-953-EFOWL01 | K72: Syd RCA Training Meal | L72: EEC-953 | M72: DAMON FOWLER | Q72: =ABS(E72) -> 38.77
A73: AU052 | B73: AU030317 | C73: 5140001030 | D73: Training travel and lodging ex | E73: 38.68 | F73: AUQ | G73: 45594 | H73: CCMS | I73: BennettA-Ground Travel | K73: Taxi from airport to Darling Harbour | O73: GM TAXIPAY | Q73: =ABS(E73) -> 38.68 | S73: Accept business travel food
A74: AU052 | B74: AU010021 | C74: 5140001030 | D74: Training travel and lodging ex | E74: 38.2 | F74: AUQ | G74: 45520 | H74: AP Accruals | I74: EEC-499-EPARI00 | K74: 10/4 Travel from home to offic | L74: EEC-499 | M74: OLIVIA PARIS | Q74: =ABS(E74) -> 38.2 | S74: 58P
A75: AU052 | B75: AU030317 | C75: 5140001030 | D75: Training travel and lodging ex | E75: 37.96 | F75: AUQ | G75: 45594 | H75: CCMS | I75: BennettA-Default Licensee Merc | K75: Thurs dinner in sydney during RCA training | O75: WWW.ALHGROUP.COM* ME&U | Q75: =ABS(E75) -> 37.96 | S75: Accept business travel food
A76: AU052 | B76: AU010021 | C76: 5140001030 | D76: Training travel and lodging ex | E76: 37.83 | F76: AUQ | G76: 45586 | H76: CCMS | I76: ParisO-Ground Travel | K76: uber receipt - transporting ALT materials | O76: UBER *TRIP/573r2c97 | Q76: =ABS(E76) -> 37.83
A77: AU052 | B77: AU010021 | C77: 5140001030 | D77: Training travel and lodging ex | E77: 37.45 | F77: AUQ | G77: 45588 | H77: CCMS | I77: ParisO-Ground Travel | K77: ALT - Uber home with BC3 Materials post event | O77: UBER *TRIP/ezmvn4r4 | Q77: =ABS(E77) -> 37.45
A78: AU052 | B78: AU030613 | C78: 5140001030 | D78: Training travel and lodging ex | E78: 36.34 | F78: AUQ | G78: 45618 | H78: AP Accruals | I78: EEC-948-ETANG05 | K78: Sydney RCA training, food expe | L78: EEC-948 | Q78: =ABS(E78) -> 36.34
A79: AU052 | B79: AU036742 | C79: 5140001030 | D79: Training travel and lodging ex | E79: 35.88 | F79: AUQ | G79: 45545 | H79: CCMS | I79: TorresR2-Domestic & Overseas l | K79: Dinner with Geert Embrechts - taxi home Mark & Rafa | O79: NOVOTEL TAINUI | Q79: =ABS(E79) -> 35.88 | S79: ME | T79: Y | U79: =B79 -> AU036742 | V79: =E79 -> 35.88
A80: AU052 | B80: AU010021 | C80: 5140001030 | D80: Training travel and lodging ex | E80: 35.25 | F80: AUQ | G80: 45520 | H80: AP Accruals | I80: EEC-499-EPARI00 | K80: 8/4 Travel from Pier One to ho | L80: EEC-499 | M80: OLIVIA PARIS | Q80: =ABS(E80) -> 35.25 | S80: 58P
A81: AU052 | B81: AU030313 | C81: 5140001030 | D81: Training travel and lodging ex | E81: 35 | F81: AUQ | G81: 45639 | H81: CCMS | I81: RistromJ-Airfares | K81: Train travel for training RCA Sydney | O81: DTSOPAL4 | Q81: =ABS(E81) -> 35
A82: AU052 | B82: AU030055 | C82: 5140001030 | D82: Training travel and lodging ex | E82: 32.77 | F82: AUQ | G82: 45645 | H82: CCMS | I82: FrekeK2-Default Licensee Merch | K82: ESTA Visa for RCA RAF trips USA | O82: USCUSTOMS ESTA APPL PMT/421162270/27EFP680 | Q82: =ABS(E82) -> 32.77
A83: AU052 | B83: AU030317 | C83: 5140001030 | D83: Training travel and lodging ex | E83: 32.73 | F83: AUQ | G83: 45594 | H83: CCMS | I83: BennettA-Company Car Parking | K83: Airport Parking | O83: Melbourne Airport | Q83: =ABS(E83) -> 32.73 | S83: Accept business travel
A84: AU052 | B84: AU030315 | C84: 5140001030 | D84: Training travel and lodging ex | E84: 32.73 | F84: AUQ | G84: 45622 | H84: CCMS | I84: KnowlesB-Company Car Parking | K84: parking at airport | O84: Melbourne Airport | Q84: =ABS(E84) -> 32.73
A85: AU052 | B85: AU030316 | C85: 5140001030 | D85: Training travel and lodging ex | E85: 32.73 | F85: AUQ | G85: 45625 | H85: CCMS | I85: WilsonE3-Company Car Parking | K85: Melbourne airport parking | O85: Melbourne Airport | Q85: =ABS(E85) -> 32.73
A86: AU052 | B86: AU030313 | C86: 5140001030 | D86: Training travel and lodging ex | E86: 32.73 | F86: AUQ | G86: 45639 | H86: CCMS | I86: RistromJ-Company Car Parking | K86: Parking while at RCA training | O86: Melbourne Airport | Q86: =ABS(E86) -> 32.73
A87: AU052 | B87: AU030510 | C87: 5140001030 | D87: Training travel and lodging ex | E87: 30.3 | F87: AUQ | G87: 45629 | H87: AP Accruals | I87: EEC-968-EHOWA01 | K87: Meal while travelling to Sydne | L87: EEC-968 | M87: ALEXANDER HOWARD | Q87: =ABS(E87) -> 30.3 | S87: Accept business travel food
A88: AU052 | B88: AU010021 | C88: 5140001030 | D88: Training travel and lodging ex | E88: 29.69 | F88: AUQ | G88: 45520 | H88: AP Accruals | I88: EEC-499-EPARI00 | K88: 9/4 Travel from Pier One to ho | L88: EEC-499 | M88: OLIVIA PARIS | Q88: =ABS(E88) -> 29.69 | S88: 58P
A89: AU052 | B89: AU032074 | C89: 5140001030 | D89: Training travel and lodging ex | E89: 29.27 | F89: AUQ | G89: 45386 | H89: CCMS | I89: WeatherlyC-Office Supplies | K89: Milk Tea Coffee | O89: FRESH ST. MARKET IGA | Q89: =ABS(E89) -> 29.27
A90: AU052 | B90: AU030710 | C90: 5140001030 | D90: Training travel and lodging ex | E90: 26.74 | F90: AUQ | G90: 45631 | H90: CCMS | I90: MccullochB-Domestic & Overseas | K90: Meals & Drinks while on training course | O90: Novotel Melb On Collins S | Q90: =ABS(E90) -> 26.74 | S90: Accept business travel food
A91: AU052 | B91: AU030324 | C91: 5140001030 | D91: Training travel and lodging ex | E91: 26.66 | F91: AUQ | G91: 45645 | H91: CCMS | I91: SchmidtN-Ground Travel | K91: Taxi from airport - Nicholas Schmidt | O91: GM TAXIPAY | Q91: =ABS(E91) -> 26.66
A92: AU052 | B92: AU030324 | C92: 5140001030 | D92: Training travel and lodging ex | E92: 26.66 | F92: AUQ | G92: 45645 | H92: CCMS | I92: SchmidtN-Ground Travel | K92: Taxi from airport - Tom Cohan | O92: GM TAXIPAY | Q92: =ABS(E92) -> 26.66
A93: AU052 | B93: AU030324 | C93: 5140001030 | D93: Training travel and lodging ex | E93: 26.65 | F93: AUQ | G93: 45645 | H93: CCMS | I93: SchmidtN-Ground Travel | K93: Taxi from airport - Bob Knowles - Nicholas Schmidt | O93: GM TAXIPAY | Q93: =ABS(E93) -> 26.65
A94: AU052 | B94: AU030313 | C94: 5140001030 | D94: Training travel and lodging ex | E94: -25.91 | F94: AUQ | G94: 45639 | H94: CCMS | I94: RistromJ-Domestic & Overseas l | K94: Deposit refund - Melbourne RRB training accommodation | O94: Novotel Melb On Collins O | Q94: =ABS(E94) -> 25.91
A95: AU052 | B95: AU030317 | C95: 5140001030 | D95: Training travel and lodging ex | E95: 25.84 | F95: AUQ | G95: 45594 | H95: CCMS | I95: BennettA-Offshore Meals & Lodg | K95: Tues dinner in Sydney before RCA | O95: Chat Thai Westfield | Q95: =ABS(E95) -> 25.84 | S95: Accept business travel food
A96: AU052 | B96: AU030317 | C96: 5140001030 | D96: Training travel and lodging ex | E96: 21.54 | F96: AUQ | G96: 45594 | H96: CCMS | I96: BennettA-Default Licensee Merc | K96: Road tolls to melb airport | O96: LINKT MELBOURNE | Q96: =ABS(E96) -> 21.54 | S96: Accept business travel
A97: AU052 | B97: AU030313 | C97: 5140001030 | D97: Training travel and lodging ex | E97: 21.2 | F97: AUQ | G97: 45614 | H97: AP Accruals | I97: EEC-912-ECROK02 | K97: Train travel | L97: EEC-912 | M97: MISTY CROKER | Q97: =ABS(E97) -> 21.2
A98: AU052 | B98: AU032074 | C98: 5140001030 | D98: Training travel and lodging ex | E98: 19.45 | F98: AUQ | G98: 45386 | H98: CCMS | I98: PozziB-Office Supplies | K98: Financial Skills Workshop Catering Charters Towers 22March - Brad Pozzi | O98: WOOLWORTHS/GILL ST | Q98: =ABS(E98) -> 19.45
A99: AU052 | B99: AU030317 | C99: 5140001030 | D99: Training travel and lodging ex | E99: 18.44 | F99: AUQ | G99: 45594 | H99: CCMS | I99: BennettA-Ground Travel | K99: Train from Darling Harbour to Airport | O99: TRANSPORTFORNSW TAP | Q99: =ABS(E99) -> 18.44 | S99: Accept business travel food
A100: AU052 | B100: AU030317 | C100: 5140001030 | D100: Training travel and lodging ex | E100: 17.53 | F100: AUQ | G100: 45594 | H100: CCMS | I100: BennettA-Office Supplies | K100: Friday Breaky in Sydney during RCA | O100: Mrs. Fields | Q100: =ABS(E100) -> 17.53 | S100: Accept business travel food
...

Sheet Publicity&Advertising
A1: Account Number | C1: =Summary!A11 -> 5160001000
A2: Account Name | C2: =Summary!B11 -> Publicity/advertising | G2: Notes:
A3: GL Total | C3: 5130256.9 | G3: Rabobank truck expenses have been treated as deductible on the basis that they are a marketing expense under s8-1 | T3: AU001 | U3: =SUMIF($A$10:$A$408,"AU001",U9:U408) -> 1413.94 | AB3: AU001 | AC3: =SUMIF($A$8:$A$408,"AU001",AC8:AC408) -> 0 | AD3: =SUMIF($A$8:$A$408,"AU001",AD8:AD408) -> 0
A4: Per TB | C4: =SUM(E:E) -> 5130256.9 | G4: Mostly, No entertainment expenses included below - all relates to Rabotruck, marketing expences and items directly related to businss activities of Rabo | T4: AU052 | U4: =SUMIF($A$10:$A$408,"AU052",U9:U408) -> 0 | AB4: AU052 | AC4: =SUMIF($A$8:$A$408,"AU052",AC8:AC408) -> 426.45 | AD4: =SUMIF($A$8:$A$408,"AU052",AD8:AD408) -> 0
A5: Variance | C5: =C3-C4 -> 0
AC6: Income tax purposes
A7: BUSINESS_UNIT_CODE | B7: OPERATING_UNIT_CODE | C7: ACCOUNT_CODE | D7: DESCRIPTION | E7: BASE_AMOUNT | F7: BASE_CURRENCY_CODE | G7: JOURNAL_DATE | H7: DESCR | I7: LINE_DESCR | J7: PURPOSE | K7: INVOICE_DESCR | L7: INVOICE_ID | M7: VENDOR_NAME | N7: EMPLOYEE_NAME | O7: CHARGE_DESCRIPTION | Q7: ABS | R7: Search Terms | S7: Tax Description | T7: ME? Y/N | U7: ME $ | V7: Not ME but other type of FB Y/N | W7: Not ME but other type of FB ==> $ | X7: Nets to Nil in GL accts | Y7: s58P M&I or Bus Exp - notFB | Z7: ME | AA7: Car FB - addn op costs | AB7: CP Exp FB | AC7: Capital expenditure | AD7: No FBT and not ded | AE7: Additional Comments
A8: AU001 | B8: AU032051 | C8: 5160001000 | D8: Publicity/advertising | E8: 295420.77 | F8: AUQ | G8: 45436 | H8: AP Accruals | I8: INV-12836-ABRYA02 | L8: INV-12836 | M8: BRYANT AND BROTHERS PTY LTD TA SPARRO | Q8: =ABS(E8) -> 295420.77
A9: AU001 | B9: AU032051 | C9: 5160001000 | D9: Publicity/advertising | E9: 242000 | F9: AUQ | G9: 45642 | I9: Rabobank ROS Paid Media-Dec24 | K9: RaboTruck Operation (MNGT fee) | Q9: =ABS(E9) -> 242000
A10: AU001 | B10: AU032051 | C10: 5160001000 | D10: Publicity/advertising | E10: 181315.6 | F10: AUQ | G10: 45397 | H10: AP Accruals | I10: INV-12575-ABRYA02 | K10: Sparro Agency - 2024 Febrauary | L10: INV-12575 | M10: BRYANT AND BROTHERS PTY LTD TA SPARRO | Q10: =ABS(E10) -> 181315.6
A11: AU001 | B11: AU032051 | C11: 5160001000 | D11: Publicity/advertising | E11: 175066.13 | F11: AUQ | G11: 45436 | H11: AP Accruals | I11: INV-13055-ABRYA02 | K11: ROS Search Marketing - April 2 | L11: INV-13055 | M11: BRYANT AND BROTHERS PTY LTD TA SPARRO | Q11: =ABS(E11) -> 175066.13
A12: AU001 | B12: AU032051 | C12: 5160001000 | D12: Publicity/advertising | E12: 155044.16 | F12: AUQ | G12: 45492 | H12: AP Accruals | I12: INV-13346-ABRYA02 | K12: ROS paid media - Search Market | L12: INV-13346 | M12: BRYANT AND BROTHERS PTY LTD TA SPARRO | Q12: =ABS(E12) -> 155044.16
A13: AU001 | B13: AU032051 | C13: 5160001000 | D13: Publicity/advertising | E13: 150728.37 | F13: AUQ | G13: 45512 | H13: AP Accruals | I13: INV-13504-ABRYA02 | K13: ROS search marketing campaigns | L13: INV-13504 | M13: BRYANT AND BROTHERS PTY LTD TA SPARRO | Q13: =ABS(E13) -> 150728.37
A14: AU001 | B14: AU032051 | C14: 5160001000 | D14: Publicity/advertising | E14: 150306.54 | F14: AUQ | G14: 45601 | H14: AP Accruals | I14: INV-13978-ABRYA02 | K14: ROS paid Media - Affiliate cam | L14: INV-13978 | M14: BRYANT AND BROTHERS PTY LTD TA SPARRO | Q14: =ABS(E14) -> 150306.54
A15: AU001 | B15: AU032051 | C15: 5160001000 | D15: Publicity/advertising | E15: 146419.87 | F15: AUQ | G15: 45614 | H15: AP Accruals | I15: INV-14200-ABRYA02 | K15: ROS paid performance - Septemb | L15: INV-14200 | M15: BRYANT AND BROTHERS PTY LTD TA SPARRO | Q15: =ABS(E15) -> 146419.87
A16: AU001 | B16: AU032046 | C16: 5160001000 | D16: Publicity/advertising | E16: 139758.78 | F16: AUQ | G16: 45492 | H16: AP Accruals | I16: INV-13384-ABRYA02 | K16: Rabobank Country Banking - Bee | L16: INV-13384 | M16: BRYANT AND BROTHERS PTY LTD TA SPARRO | Q16: =ABS(E16) -> 139758.78
A17: AU001 | B17: AU032051 | C17: 5160001000 | D17: Publicity/advertising | E17: 134101.14 | F17: AUQ | G17: 45601 | H17: AP Accruals | I17: INV-13985-ABRYA02 | K17: Rabobank ROS - Search Marketin | L17: INV-13985 | M17: BRYANT AND BROTHERS PTY LTD TA SPARRO | Q17: =ABS(E17) -> 134101.14
A18: AU001 | B18: AU032051 | C18: 5160001000 | D18: Publicity/advertising | E18: 132017.26 | F18: AUQ | G18: 45554 | H18: AP Accruals | I18: INV-13757-ABRYA02 | K18: Rabobank search marketing camp | L18: INV-13757 | M18: BRYANT AND BROTHERS PTY LTD TA SPARRO | Q18: =ABS(E18) -> 132017.26
A19: AU001 | B19: AU032051 | C19: 5160001000 | D19: Publicity/advertising | E19: 127528.63 | F19: AUQ | G19: 45492 | H19: AP Accruals | I19: INV-13238-ABRYA02 | K19: ROS Paid Media May 2024 - Affi | L19: INV-13238 | M19: BRYANT AND BROTHERS PTY LTD TA SPARRO | Q19: =ABS(E19) -> 127528.63
A20: AU001 | B20: AU032051 | C20: 5160001000 | D20: Publicity/advertising | E20: 125980.49 | F20: AUQ | G20: 45512 | H20: AP Accruals | I20: INV-13512-ABRYA02 | K20: ROS affiliate marketing campai | L20: INV-13512 | M20: BRYANT AND BROTHERS PTY LTD TA SPARRO | Q20: =ABS(E20) -> 125980.49
A21: AU001 | B21: AU032051 | C21: 5160001000 | D21: Publicity/advertising | E21: 123000.77 | F21: AUQ | G21: 45492 | H21: AP Accruals | I21: INV-12922-ABRYA02 | K21: ROS paid media April 2024 - af | L21: INV-12922 | M21: BRYANT AND BROTHERS PTY LTD TA SPARRO | Q21: =ABS(E21) -> 123000.77
A22: AU001 | B22: AU032046 | C22: 5160001000 | D22: Publicity/advertising | E22: 107045.4 | F22: AUQ | G22: 45642 | I22: Rabo CB Paid Media-Brand-Oct24 | K22: RaboTruck Operation (MNGT fee) | Q22: =ABS(E22) -> 107045.4
A23: AU001 | B23: AU032051 | C23: 5160001000 | D23: Publicity/advertising | E23: 106042.48 | F23: AUQ | G23: 45636 | H23: AP Accruals | I23: INV-14392-ABRYA02 | K23: ROS paid media - Search Market | L23: INV-14392 | M23: BRYANT AND BROTHERS PTY LTD TA SPARRO | Q23: =ABS(E23) -> 106042.48
A24: AU001 | B24: AU032051 | C24: 5160001000 | D24: Publicity/advertising | E24: 102444.18 | F24: AUQ | G24: 45554 | H24: AP Accruals | I24: INV-13878-ABRYA02 | K24: ROS paid performance - July 20 | L24: INV-13878 | M24: BRYANT AND BROTHERS PTY LTD TA SPARRO | Q24: =ABS(E24) -> 102444.18
A25: AU001 | B25: AU032051 | C25: 5160001000 | D25: Publicity/advertising | E25: 100639.5 | F25: AUQ | G25: 45614 | H25: AP Accruals | I25: INV-14191-ABRYA02 | K25: ROS affiliated marketing campa | L25: INV-14191 | M25: BRYANT AND BROTHERS PTY LTD TA SPARRO | Q25: =ABS(E25) -> 100639.5
A26: AU001 | B26: AU032051 | C26: 5160001000 | D26: Publicity/advertising | E26: 97293.9 | F26: AUQ | G26: 45636 | H26: AP Accruals | I26: INV-14674-ABRYA02 | K26: ROS paid Media - Search campai | L26: INV-14674 | M26: BRYANT AND BROTHERS PTY LTD TA SPARRO | Q26: =ABS(E26) -> 97293.9
A27: AU001 | B27: AU032051 | C27: 5160001000 | D27: Publicity/advertising | E27: -75153.27 | F27: AUQ | G27: 45608 | H27: AP Accruals | I27: INV-13978-ABRYA02 | K27: ROS paid Media - Affiliate cam | L27: INV-13978 | M27: BRYANT AND BROTHERS PTY LTD TA SPARRO | Q27: =ABS(E27) -> 75153.27
A28: AU001 | B28: AU036742 | C28: 5160001000 | D28: Publicity/advertising | E28: 65000 | F28: AUQ | G28: 45642 | I28: Brand Health Survey - question | K28: RaboTruck Operation (MNGT fee) | Q28: =ABS(E28) -> 65000
A29: AU001 | B29: AU032051 | C29: 5160001000 | D29: Publicity/advertising | E29: 62569.52 | F29: AUQ | G29: 45431 | H29: AP Accruals | I29: INV-12817-ABRYA02 | K29: ROS Paid Media - Affiliate Fee | L29: INV-12817 | M29: BRYANT AND BROTHERS PTY LTD TA SPARRO | Q29: =ABS(E29) -> 62569.52
A30: AU001 | B30: AU032046 | C30: 5160001000 | D30: Publicity/advertising | E30: 61340.4 | F30: AUQ | G30: 45642 | I30: The Land advertsing camp(NSW) | K30: RaboTruck Operation (MNGT fee) | Q30: =ABS(E30) -> 61340.4
A31: AU001 | B31: AU032051 | C31: 5160001000 | D31: Publicity/advertising | E31: 60787.04 | F31: AUQ | G31: 45636 | H31: AP Accruals | I31: INV-14399-ABRYA02 | K31: ROS Paid Media - affiliates fe | L31: INV-14399 | M31: BRYANT AND BROTHERS PTY LTD TA SPARRO | Q31: =ABS(E31) -> 60787.04
A32: AU001 | B32: AU032051 | C32: 5160001000 | D32: Publicity/advertising | E32: 52840.94 | F32: AUQ | G32: 45636 | H32: AP Accruals | I32: INV-14683-ABRYA02 | K32: Paid Media - ROS Affiliate Fee | L32: INV-14683 | M32: BRYANT AND BROTHERS PTY LTD TA SPARRO | Q32: =ABS(E32) -> 52840.94
A33: AU001 | B33: AU032051 | C33: 5160001000 | D33: Publicity/advertising | E33: 51092.83 | F33: AUQ | G33: 45614 | H33: AP Accruals | I33: INV-14324-ABRYA02 | K33: Rabobank CB brand awareness ca | L33: INV-14324 | M33: BRYANT AND BROTHERS PTY LTD TA SPARRO | Q33: =ABS(E33) -> 51092.83
A34: AU001 | B34: AU032051 | C34: 5160001000 | D34: Publicity/advertising | E34: 49496.85 | F34: AUQ | G34: 45629 | H34: AP Accruals | I34: INV-14612-ABRYA02 | K34: ROS creative refresh | L34: INV-14612 | M34: BRYANT AND BROTHERS PTY LTD TA SPARRO | Q34: =ABS(E34) -> 49496.85
A35: AU001 | B35: AU032046 | C35: 5160001000 | D35: Publicity/advertising | E35: 44679.34 | F35: AUQ | G35: 45434 | H35: AP Accruals | I35: 00013081-AQUAL08 | K35: Beef 2024 marquee & furniture | L35: 00013081 | M35: QUALITY EVENT HIRE PTY LTD | Q35: =ABS(E35) -> 44679.34
A36: AU001 | B36: AU032051 | C36: 5160001000 | D36: Publicity/advertising | E36: 42072.32 | F36: AUQ | G36: 45425 | H36: AP Accruals | I36: INVCAN-900006966-ACANS00 | K36: 2024 Canstar awards licence fe | L36: INVCAN-900006966 | M36: CANSTAR PTY LIMITED | Q36: =ABS(E36) -> 42072.32
A37: AU001 | B37: AU032046 | C37: 5160001000 | D37: Publicity/advertising | E37: 34777.19 | F37: AUQ | G37: 45642 | I37: RaboTruck Operation (MNGT fee) | K37: RaboTruck Operation (MNGT fee) | Q37: =ABS(E37) -> 34777.19
A38: AU001 | B38: AU032051 | C38: 5160001000 | D38: Publicity/advertising | E38: 34644.6 | F38: AUQ | G38: 45637 | H38: AP Accruals | I38: INV-14838-ABRYA02 | K38: Paid Media Retainer fee - Nove | L38: INV-14838 | M38: BRYANT AND BROTHERS PTY LTD TA SPARRO | Q38: =ABS(E38) -> 34644.6
A39: AU001 | B39: AU032054 | C39: 5160001000 | D39: Publicity/advertising | E39: 34632.22 | F39: AUQ | G39: 45597 | H39: AP Accruals | I39: INV-0054-ANUME00 | K39: Nature 101 case study videos | L39: INV-0054 | M39: NUMERAL CREATIVE PTY LTD | Q39: =ABS(E39) -> 34632.22
A40: AU001 | B40: AU036740 | C40: 5160001000 | D40: Publicity/advertising | E40: 33408.17 | F40: AUQ | G40: 45420 | H40: AP Accruals | I40: 24330-AD3PR00 | K40: ROS Digipass trays and labels | L40: 24330 | M40: D3 PRODUCT DESIGN PTY LTD | Q40: =ABS(E40) -> 33408.17
A41: AU001 | B41: AU032046 | C41: 5160001000 | D41: Publicity/advertising | E41: 32807.46 | F41: AUQ | G41: 45637 | H41: AP Accruals | I41: RABO2025/2-ASOLU01 | K41: RaboTruck Operation (Storage, | L41: RABO2025/2 | M41: SOLUTION ENTERTAINMENT | Q41: =ABS(E41) -> 32807.46
A42: AU001 | B42: AU032051 | C42: 5160001000 | D42: Publicity/advertising | E42: 31835.4 | F42: AUQ | G42: 45637 | H42: AP Accruals | I42: INV-14558-ABRYA02 | K42: ROS Paid Media - Social Media | L42: INV-14558 | M42: BRYANT AND BROTHERS PTY LTD TA SPARRO | Q42: =ABS(E42) -> 31835.4
A43: AU052 | B43: AU036742 | C43: 5160001000 | D43: Publicity/advertising | E43: 30184.63 | F43: AUQ | G43: 45400 | H43: AP Accruals | I43: INVKYNAU1921-AKYNE00 | K43: Rural Confidence Survey 23/24 | L43: INVKYNAU1921 | M43: KYNETEC AUSTRALIA PTY LTD | Q43: =ABS(E43) -> 30184.63
A44: AU052 | B44: AU036742 | C44: 5160001000 | D44: Publicity/advertising | E44: 30184.63 | F44: AUQ | G44: 45537 | H44: AP Accruals | I44: INVKYNAU2046-AKYNE00 | K44: Rural Confidence Survey | L44: INVKYNAU2046 | M44: KYNETEC AUSTRALIA PTY LTD | Q44: =ABS(E44) -> 30184.63
A45: AU052 | B45: AU036742 | C45: 5160001000 | D45: Publicity/advertising | E45: 30184.63 | F45: AUQ | G45: 45597 | H45: AP Accruals | I45: INVKYNAU2135-AKYNE00 | K45: Rural Confidence Survey 24/25 | L45: INVKYNAU2135 | M45: KYNETEC AUSTRALIA PTY LTD | Q45: =ABS(E45) -> 30184.63
A46: AU001 | B46: AU032051 | C46: 5160001000 | D46: Publicity/advertising | E46: 30051 | F46: AUQ | G46: 45642 | I46: Rabo Paid Media Reta Fee-Dec24 | K46: RaboTruck Operation (MNGT fee) | Q46: =ABS(E46) -> 30051
A47: AU001 | B47: AU032051 | C47: 5160001000 | D47: Publicity/advertising | E47: 30046.89 | F47: AUQ | G47: 45425 | H47: AP Accruals | I47: INV-13071-ABRYA02 | K47: Sparro Paid Media Retainer Apr | L47: INV-13071 | M47: BRYANT AND BROTHERS PTY LTD TA SPARRO | Q47: =ABS(E47) -> 30046.89
A48: AU001 | B48: AU032051 | C48: 5160001000 | D48: Publicity/advertising | E48: 30046.89 | F48: AUQ | G48: 45478 | H48: AP Accruals | I48: INV-13345-ABRYA02 | L48: INV-13345 | M48: BRYANT AND BROTHERS PTY LTD TA SPARRO | Q48: =ABS(E48) -> 30046.89
A49: AU001 | B49: AU032051 | C49: 5160001000 | D49: Publicity/advertising | E49: 30046.89 | F49: AUQ | G49: 45505 | H49: AP Accruals | I49: INV-13415-ABRYA02 | K49: Sparro Agency media retainer f | L49: INV-13415 | M49: BRYANT AND BROTHERS PTY LTD TA SPARRO | Q49: =ABS(E49) -> 30046.89
A50: AU001 | B50: AU032051 | C50: 5160001000 | D50: Publicity/advertising | E50: 30046.89 | F50: AUQ | G50: 45547 | H50: AP Accruals | I50: INV-13846-ABRYA02 | K50: Paid Media fees - July | L50: INV-13846 | M50: BRYANT AND BROTHERS PTY LTD TA SPARRO | Q50: =ABS(E50) -> 30046.89
A51: AU001 | B51: AU032051 | C51: 5160001000 | D51: Publicity/advertising | E51: 30046.89 | F51: AUQ | G51: 45601 | H51: AP Accruals | I51: INV-14074-ABRYA02 | K51: Sparro Strategy Retainer fee A | L51: INV-14074 | M51: BRYANT AND BROTHERS PTY LTD TA SPARRO | Q51: =ABS(E51) -> 30046.89
A52: AU001 | B52: AU032051 | C52: 5160001000 | D52: Publicity/advertising | E52: 30046.89 | F52: AUQ | G52: 45614 | H52: AP Accruals | I52: INV-14327-ABRYA02 | K52: Sparro Strategy Retainer fee S | L52: INV-14327 | M52: BRYANT AND BROTHERS PTY LTD TA SPARRO | Q52: =ABS(E52) -> 30046.89
A53: AU001 | B53: AU032051 | C53: 5160001000 | D53: Publicity/advertising | E53: 30046.89 | F53: AUQ | G53: 45637 | H53: AP Accruals | I53: INV-14557-ABRYA02 | K53: Paid Media Retainer fee - Octo | L53: INV-14557 | M53: BRYANT AND BROTHERS PTY LTD TA SPARRO | Q53: =ABS(E53) -> 30046.89
A54: AU001 | B54: AU032051 | C54: 5160001000 | D54: Publicity/advertising | E54: 29954.01 | F54: AUQ | G54: 45425 | H54: AP Accruals | I54: INV-12639-ABRYA02 | K54: Paid Media Retainer March 2024 | L54: INV-12639 | M54: BRYANT AND BROTHERS PTY LTD TA SPARRO | Q54: =ABS(E54) -> 29954.01
A55: AU001 | B55: AU032046 | C55: 5160001000 | D55: Publicity/advertising | E55: 29636.06 | F55: AUQ | G55: 45642 | I55: RaboTruck Operation (Proj Mgr) | K55: RaboTruck Operation (MNGT fee) | Q55: =ABS(E55) -> 29636.06
A56: AU001 | B56: AU032046 | C56: 5160001000 | D56: Publicity/advertising | E56: 27500 | F56: AUQ | G56: 45642 | I56: Cattle Australia sponsorship | K56: RaboTruck Operation (MNGT fee) | Q56: =ABS(E56) -> 27500
A57: AU001 | B57: AU032051 | C57: 5160001000 | D57: Publicity/advertising | E57: 27498.25 | F57: AUQ | G57: 45569 | H57: AP Accruals | I57: INV-0029-ASAVE01 | K57: AU2040 | L57: INV-0029 | M57: SAVEFUL WORLDWIDE PTY LTD | Q57: =ABS(E57) -> 27498.25
A58: AU001 | B58: AU032051 | C58: 5160001000 | D58: Publicity/advertising | E58: 26350.71 | F58: AUQ | G58: 45425 | H58: AP Accruals | I58: INV-12635-ABRYA02 | K58: Sparro - ROS paid media - Affi | L58: INV-12635 | M58: BRYANT AND BROTHERS PTY LTD TA SPARRO | Q58: =ABS(E58) -> 26350.71
A59: AU001 | B59: AU032046 | C59: 5160001000 | D59: Publicity/advertising | E59: 25930.77 | F59: AUQ | G59: 45642 | I59: RaboTruck Operation (Driver) | K59: RaboTruck Operation (MNGT fee) | Q59: =ABS(E59) -> 25930.77
A60: AU001 | B60: AU032046 | C60: 5160001000 | D60: Publicity/advertising | E60: 25926.48 | F60: AUQ | G60: 45642 | I60: RaboTruck Operation (CabLease) | K60: RaboTruck Operation (MNGT fee) | Q60: =ABS(E60) -> 25926.48
A61: AU001 | B61: AU032046 | C61: 5160001000 | D61: Publicity/advertising | E61: 25871.8 | F61: AUQ | G61: 45435 | H61: AP Accruals | I61: INV-4990/66-ASOLU01 | K61: Truck prime mover lease Q3 | L61: INV-4990/66 | M61: SOLUTION ENTERTAINMENT | Q61: =ABS(E61) -> 25871.8
A62: AU001 | B62: AU032046 | C62: 5160001000 | D62: Publicity/advertising | E62: 25795.48 | F62: AUQ | G62: 45435 | H62: AP Accruals | I62: INV-4990/67-ASOLU01 | K62: Truck Q3 Operation cost | L62: INV-4990/67 | M62: SOLUTION ENTERTAINMENT | Q62: =ABS(E62) -> 25795.48
A63: AU001 | B63: AU032046 | C63: 5160001000 | D63: Publicity/advertising | E63: 25793.86 | F63: AUQ | G63: 45527 | H63: AP Accruals | I63: 240369359-OMETA00 | K63: Meta Advertising inc Agency | L63: 240369359 | M63: META PLATFORMS IRELAND LIMITED | Q63: =ABS(E63) -> 25793.86
A64: AU001 | B64: AU032051 | C64: 5160001000 | D64: Publicity/advertising | E64: 24315.73 | F64: AUQ | G64: 45601 | H64: AP Accruals | I64: INV-14127-ABRYA02 | K64: ROS paid media - Reddit campai | L64: INV-14127 | M64: BRYANT AND BROTHERS PTY LTD TA SPARRO | Q64: =ABS(E64) -> 24315.73
A65: AU001 | B65: AU032051 | C65: 5160001000 | D65: Publicity/advertising | E65: 24315.73 | F65: AUQ | G65: 45601 | H65: AP Accruals | I65: INV-14127Draft Invo-ABRYA02 | K65: ROS paid media - Reddit campai | L65: INV-14127Draft Invoice | M65: BRYANT AND BROTHERS PTY LTD TA SPARRO | Q65: =ABS(E65) -> 24315.73
A66: AU001 | B66: AU032051 | C66: 5160001000 | D66: Publicity/advertising | E66: -24315.73 | F66: AUQ | G66: 45611 | H66: AP Accruals | I66: INV-14127Draft Invo-ABRYA02 | K66: ROS paid media - Reddit campai | L66: INV-14127Draft Invoice | M66: BRYANT AND BROTHERS PTY LTD TA SPARRO | Q66: =ABS(E66) -> 24315.73
A67: AU001 | B67: AU032051 | C67: 5160001000 | D67: Publicity/advertising | E67: -24315.73 | F67: AUQ | G67: 45615 | H67: AP Closed Vouchers | I67: INV-14127Draft Invo-ABRYA02 | K67: ROS paid media - Reddit campai | L67: INV-14127Draft Invoice | M67: BRYANT AND BROTHERS PTY LTD TA SPARRO | Q67: =ABS(E67) -> 24315.73
A68: AU001 | B68: AU032046 | C68: 5160001000 | D68: Publicity/advertising | E68: 24062.5 | F68: AUQ | G68: 45642 | I68: Farm to Fork Videography | K68: RaboTruck Operation (MNGT fee) | Q68: =ABS(E68) -> 24062.5
A69: AU001 | B69: AU032051 | C69: 5160001000 | D69: Publicity/advertising | E69: 24062.5 | F69: AUQ | G69: 45642 | I69: Farm to Fork Videography - Far | K69: RaboTruck Operation (MNGT fee) | Q69: =ABS(E69) -> 24062.5
A70: AU001 | B70: AU032051 | C70: 5160001000 | D70: Publicity/advertising | E70: 24060.97 | F70: AUQ | G70: 45447 | H70: AP Accruals | I70: INV-0173-ADUAL00 | L70: INV-0173 | M70: DUAL ENTERTAINMENT PTY LTD | Q70: =ABS(E70) -> 24060.97
A71: AU001 | B71: AU032051 | C71: 5160001000 | D71: Publicity/advertising | E71: 24060.97 | F71: AUQ | G71: 45455 | H71: AP Accruals | I71: INV-0185-ADUAL00 | L71: INV-0185 | M71: DUAL ENTERTAINMENT PTY LTD | Q71: =ABS(E71) -> 24060.97
A72: AU001 | B72: AU032051 | C72: 5160001000 | D72: Publicity/advertising | E72: 24060.97 | F72: AUQ | G72: 45455 | H72: AP Accruals | I72: INV-0186-ADUAL00 | L72: INV-0186 | M72: DUAL ENTERTAINMENT PTY LTD | Q72: =ABS(E72) -> 24060.97
A73: AU001 | B73: AU032051 | C73: 5160001000 | D73: Publicity/advertising | E73: 24060.97 | F73: AUQ | G73: 45455 | H73: AP Accruals | I73: INV-0189-ADUAL00 | L73: INV-0189 | M73: DUAL ENTERTAINMENT PTY LTD | Q73: =ABS(E73) -> 24060.97
A74: AU001 | B74: AU032051 | C74: 5160001000 | D74: Publicity/advertising | E74: 24060.97 | F74: AUQ | G74: 45455 | H74: AP Accruals | I74: INV-0190-ADUAL00 | L74: INV-0190 | M74: DUAL ENTERTAINMENT PTY LTD | Q74: =ABS(E74) -> 24060.97
A75: AU001 | B75: AU032051 | C75: 5160001000 | D75: Publicity/advertising | E75: 24060.97 | F75: AUQ | G75: 45614 | H75: AP Accruals | I75: INV-0205-ADUAL00 | K75: Farm to Fork farmer interview | L75: INV-0205 | M75: DUAL ENTERTAINMENT PTY LTD | Q75: =ABS(E75) -> 24060.97
A76: AU001 | B76: AU032051 | C76: 5160001000 | D76: Publicity/advertising | E76: 24060.97 | F76: AUQ | G76: 45614 | H76: AP Accruals | I76: INV-0206-ADUAL00 | K76: Farm to Fork farmer TV, digita | L76: INV-0206 | M76: DUAL ENTERTAINMENT PTY LTD | Q76: =ABS(E76) -> 24060.97
A77: AU001 | B77: AU032046 | C77: 5160001000 | D77: Publicity/advertising | E77: 24011.75 | F77: AUQ | G77: 45429 | H77: AP Accruals | I77: INV-0168-ADUAL00 | K77: - Videography - Farmer intervi | L77: INV-0168 | M77: DUAL ENTERTAINMENT PTY LTD | Q77: =ABS(E77) -> 24011.75
A78: AU001 | B78: AU032046 | C78: 5160001000 | D78: Publicity/advertising | E78: 22571.04 | F78: AUQ | G78: 45434 | H78: AP Accruals | I78: INV-4990/68-ASOLU01 | K78: Truck driver cost Q3 | L78: INV-4990/68 | M78: SOLUTION ENTERTAINMENT | Q78: =ABS(E78) -> 22571.04
A79: AU001 | B79: AU032046 | C79: 5160001000 | D79: Publicity/advertising | E79: 21953.6 | F79: AUQ | G79: 45637 | H79: AP Accruals | I79: INV-0178-AHUMA01 | K79: Humans of Agri podcast and soc | L79: INV-0178 | M79: HUMANS OF AGRICULTURE PTY LTD | Q79: =ABS(E79) -> 21953.6
A80: AU001 | B80: AU032046 | C80: 5160001000 | D80: Publicity/advertising | E80: 19916.31 | F80: AUQ | G80: 45637 | H80: AP Accruals | I80: INV-14839-ABRYA02 | K80: CB paid Media - brand campaig | L80: INV-14839 | M80: BRYANT AND BROTHERS PTY LTD TA SPARRO | Q80: =ABS(E80) -> 19916.31
A81: AU001 | B81: AU032046 | C81: 5160001000 | D81: Publicity/advertising | E81: 18700 | F81: AUQ | G81: 45642 | I81: RaboTruck Gippsland event x 2 | K81: RaboTruck Operation (MNGT fee) | Q81: =ABS(E81) -> 18700
A82: AU001 | B82: AU032046 | C82: 5160001000 | D82: Publicity/advertising | E82: 18515.87 | F82: AUQ | G82: 45601 | H82: AP Accruals | I82: INV-14095-ABRYA02 | K82: Rabobank CB brand awareness ca | L82: INV-14095 | M82: BRYANT AND BROTHERS PTY LTD TA SPARRO | Q82: =ABS(E82) -> 18515.87
A83: AU001 | B83: AU032051 | C83: 5160001000 | D83: Publicity/advertising | E83: 18421.7 | F83: AUQ | G83: 45413 | H83: AP Accruals | I83: MOZO003198-AMOZO02 | K83: Mozo 2024 Awards licence fee f | L83: MOZO003198 | M83: MOZO PTY LTD | Q83: =ABS(E83) -> 18421.7
A84: AU001 | B84: AU032051 | C84: 5160001000 | D84: Publicity/advertising | E84: 17487.43 | F84: AUQ | G84: 45560 | H84: 240369359-OMETA00 | I84: 240369359-OMETA00 | Q84: =ABS(E84) -> 17487.43
A85: AU001 | B85: AU032046 | C85: 5160001000 | D85: Publicity/advertising | E85: -17487.43 | F85: AUQ | G85: 45560 | H85: 240369359-OMETA00 | I85: 240369359-OMETA00 | Q85: =ABS(E85) -> 17487.43
A86: AU052 | B86: AU032046 | C86: 5160001000 | D86: Publicity/advertising | E86: 17400.67 | F86: AUQ | G86: 45538 | H86: AP Accruals | I86: 9899289043-AMICR01 | K86: Microsoft CRM training | L86: 9899289043 | M86: MICROSOFT PTY LTD | Q86: =ABS(E86) -> 17400.67
A87: AU001 | B87: AU032046 | C87: 5160001000 | D87: Publicity/advertising | E87: 17359.97 | F87: AUQ | G87: 45510 | H87: AP Accruals | I87: 239686517-OMETA00 | K87: Meta advertising | L87: 239686517 | M87: META PLATFORMS IRELAND LIMITED | Q87: =ABS(E87) -> 17359.97
A88: AU001 | B88: AU032046 | C88: 5160001000 | D88: Publicity/advertising | E88: 16465.2 | F88: AUQ | G88: 45395 | H88: AP Accruals | I88: INV-0130-AHUMA01 | K88: Humans of Agri Podcast partner | L88: INV-0130 | M88: HUMANS OF AGRICULTURE PTY LTD | Q88: =ABS(E88) -> 16465.2
A89: AU001 | B89: AU032051 | C89: 5160001000 | D89: Publicity/advertising | E89: 16447.95 | F89: AUQ | G89: 45429 | H89: AP Accruals | I89: INVCAN-900006916-ACANS00 | K89: Canstar 2024 product listing f | L89: INVCAN-900006916 | M89: CANSTAR PTY LIMITED | Q89: =ABS(E89) -> 16447.95
A90: AU001 | B90: AU032051 | C90: 5160001000 | D90: Publicity/advertising | E90: 15896.97 | F90: AUQ | G90: 45601 | H90: AP Accruals | I90: INV-14075-ABRYA02 | K90: Rabobank ROS Social Media camp | L90: INV-14075 | M90: BRYANT AND BROTHERS PTY LTD TA SPARRO | Q90: =ABS(E90) -> 15896.97
A91: AU001 | B91: AU032046 | C91: 5160001000 | D91: Publicity/advertising | E91: 15812.5 | F91: AUQ | G91: 45642 | I91: Farm to Fork TV airing inc | K91: RaboTruck Operation (MNGT fee) | Q91: =ABS(E91) -> 15812.5
A92: AU001 | B92: AU032051 | C92: 5160001000 | D92: Publicity/advertising | E92: 15812.5 | F92: AUQ | G92: 45642 | I92: Farm to Fork TV airing Rabofac | K92: RaboTruck Operation (MNGT fee) | Q92: =ABS(E92) -> 15812.5
A93: AU001 | B93: AU032051 | C93: 5160001000 | D93: Publicity/advertising | E93: 15811.49 | F93: AUQ | G93: 45447 | H93: AP Accruals | I93: INV-0174-ADUAL00 | L93: INV-0174 | M93: DUAL ENTERTAINMENT PTY LTD | Q93: =ABS(E93) -> 15811.49
A94: AU001 | B94: AU032051 | C94: 5160001000 | D94: Publicity/advertising | E94: 15811.49 | F94: AUQ | G94: 45455 | H94: AP Accruals | I94: INV-0184-ADUAL00 | L94: INV-0184 | M94: DUAL ENTERTAINMENT PTY LTD | Q94: =ABS(E94) -> 15811.49
A95: AU001 | B95: AU032051 | C95: 5160001000 | D95: Publicity/advertising | E95: 15811.49 | F95: AUQ | G95: 45455 | H95: AP Accruals | I95: INV-0187-ADUAL00 | L95: INV-0187 | M95: DUAL ENTERTAINMENT PTY LTD | Q95: =ABS(E95) -> 15811.49
A96: AU001 | B96: AU032051 | C96: 5160001000 | D96: Publicity/advertising | E96: 15811.49 | F96: AUQ | G96: 45455 | H96: AP Accruals | I96: INV-0188-ADUAL00 | L96: INV-0188 | M96: DUAL ENTERTAINMENT PTY LTD | Q96: =ABS(E96) -> 15811.49
A97: AU001 | B97: AU032051 | C97: 5160001000 | D97: Publicity/advertising | E97: 15811.49 | F97: AUQ | G97: 45455 | H97: AP Accruals | I97: INV-0191-ADUAL00 | L97: INV-0191 | M97: DUAL ENTERTAINMENT PTY LTD | Q97: =ABS(E97) -> 15811.49
A98: AU001 | B98: AU032051 | C98: 5160001000 | D98: Publicity/advertising | E98: 15811.49 | F98: AUQ | G98: 45614 | H98: AP Accruals | I98: INV-0204-ADUAL00 | K98: Farm to Fork client testimonia | L98: INV-0204 | M98: DUAL ENTERTAINMENT PTY LTD | Q98: =ABS(E98) -> 15811.49
A99: AU001 | B99: AU032051 | C99: 5160001000 | D99: Publicity/advertising | E99: 15811.49 | F99: AUQ | G99: 45614 | H99: AP Accruals | I99: INV-0207-ADUAL00 | K99: Farm to Fork recipe and digita | L99: INV-0207 | M99: DUAL ENTERTAINMENT PTY LTD | Q99: =ABS(E99) -> 15811.49
A100: AU001 | B100: AU032046 | C100: 5160001000 | D100: Publicity/advertising | E100: 15779.15 | F100: AUQ | G100: 45425 | H100: AP Accruals | I100: INV-0167-ADUAL00 | K100: Farm to Fork TV airing, websit | L100: INV-0167 | M100: DUAL ENTERTAINMENT PTY LTD | Q100: =ABS(E100) -> 15779.15
...

Sheet Opening Jubilees
A1: Account Number | C1: =Summary!A12 -> 5160006000
A2: Account Name | C2: =Summary!B12 -> Opening jubilees own buildin | G2: Notes:
A3: GL Total | C3: =SUMIFS(#REF!,#REF!,C1) -> #REF! | G3: No entertainment expenses
A4: Per TB | C4: =SUM(D:D) -> 0 | R4: AU001 | S4: =SUMIF($A$10:$A$23974,"AU001",S9:S23973) -> 0
A5: Variance | C5: =C3-C4 -> #REF! | R5: AU052 | S5: =SUMIF($A$10:$A$23975,"AU052",S9:S23974) -> 0
AA6: Income tax purposes
A7: BUSINESS_UNIT_CODE | B7: ACCOUNT_CODE | C7: DESCRIPTION | D7: BASE_AMOUNT | E7: BASE_CURRENCY_CODE | F7: JOURNAL_DATE | G7: DESCR | H7: LINE_DESCR | I7: PURPOSE | J7: INVOICE_DESCR | K7: INVOICE_ID | L7: VENDOR_NAME | M7: EMPLOYEE_NAME | O7: ABS | P7: Search Terms | Q7: Tax Description | R7: ME? Y/N | S7: ME $ | T7: Not ME but other type of FB Y/N | U7: Not ME but other type of FB ==> $ | V7: Nets to Nil in GL accts | W7: s58P M&I or Bus Exp - notFB | X7: ME | Y7: Car FB - addn op costs | Z7: CP Exp FB | AA7: Capital expenditure | AB7: No FBT and not ded | AC7: Additional Comments

Sheet Sponsoring
A1: Account Number | C1: =Summary!A13 -> 5160007000
A2: Account Name | C2: =Summary!B13 -> Sponsoring | G2: Notes: | T2: AU001 | U2: =SUMIF($A$10:$A$23974,"AU001",U9:U23973) -> 0 | AB2: AU001 | AC2: =SUMIF($A$8:$A$408,"AU001",AC8:AC408) -> 0 | AD2: =SUMIF($A$8:$A$408,"AU001",AD8:AD408) -> 0
A3: GL Total | C3: 975192.62 | G3: No entertainment expenses included and all tax deductible | T3: AU052 | U3: =SUMIF($A$10:$A$23975,"AU052",U9:U23974) -> 0 | AB3: AU052 | AC3: =SUMIF($A$8:$A$408,"AU052",AC8:AC408) -> 0 | AD3: =SUMIF($A$8:$A$408,"AU052",AD8:AD408) -> 407.73
A4: Per TB | C4: =SUM(E:E) -> 975192.62 | G4: Charity days/community days have not been treated as recreational activity (arguably does not meet ITAA definition)
A5: Variance | C5: =C3-C4 -> 0
AC6: Income tax purposes
A7: BUSINESS_UNIT_CODE | B7: OPERATING_UNIT_CODE | C7: ACCOUNT_CODE | D7: DESCRIPTION | E7: BASE_AMOUNT | F7: BASE_CURRENCY_CODE | G7: JOURNAL_DATE | H7: DESCR | I7: LINE_DESCR | J7: PURPOSE | K7: INVOICE_DESCR | L7: INVOICE_ID | M7: VENDOR_NAME | N7: EMPLOYEE_NAME | O7: CHARGE_DESCRIPTION | Q7: ABS | R7: Search Terms | S7: Tax Description | T7: ME? Y/N | U7: ME $ | V7: Not ME but other type of FB Y/N | W7: Not ME but other type of FB ==> $ | X7: Nets to Nil in GL accts | Y7: s58P M&I or Bus Exp - notFB | Z7: ME | AA7: Car FB - addn op costs | AB7: CP Exp FB | AC7: Capital expenditure | AD7: No FBT and not ded | AE7: Additional Comments
A8: AU001 | B8: AU032074 | C8: 5160007000 | D8: Sponsoring | E8: 192250.62 | F8: AUQ | G8: 45384 | H8: AP Accruals | I8: INV-3798-ABOYS00 | K8: Boys to the Bush Sponsorship i | L8: INV-3798 | M8: BOYS TO THE BUSH LIMITED | Q8: =ABS(E8) -> 192250.62
A9: AU001 | B9: AU032074 | C9: 5160007000 | D9: Sponsoring | E9: 720.25 | F9: AUQ | G9: 45385 | H9: AP Accruals | I9: INV-2280-AGEOR00 | K9: NZ_GeorgetheFarmerBooks | L9: INV-2280 | M9: GEORGE THE FARMER PTY LTD | Q9: =ABS(E9) -> 720.25
A10: AU052 | B10: AU030212 | C10: 5160007000 | D10: Sponsoring | E10: 111.82 | F10: AUQ | G10: 45385 | H10: CCMS | I10: McKayJ-Default Licensee Mercha | J10: Tickets - MCGA Golf Day x 3 people | M10: SQ *MACQUARIE COTTON GROW | Q10: =ABS(E10) -> 111.82 | S10: recreational entertainment | AD10: =E10 -> 111.82
A11: AU052 | B11: AU010029 | C11: 5160007000 | D11: Sponsoring | E11: 500 | F11: AUQ | G11: 45390 | H11: AP Accruals | I11: 0005-AWOME06 | K11: Student society sponsorship (W | L11: 0005 | M11: WOMEN IN TECHNOLOGY WIT | Q11: =ABS(E11) -> 500
A12: AU052 | B12: AU010029 | C12: 5160007000 | D12: Sponsoring | E12: 1494.45 | F12: AUQ | G12: 45390 | H12: AP Accruals | I12: 104902-AUTSW00 | K12: Women in Business Student Soci | L12: 104902 | M12: UTS WOMEN IN BUSINESS | Q12: =ABS(E12) -> 1494.45
A13: AU052 | B13: AU010029 | C13: 5160007000 | D13: Sponsoring | E13: 464.65 | F13: AUQ | G13: 45391 | H13: CCMS | I13: SunT-Default Licensee Merchant | J13: USYD Ag Soc networking event payment | M13: SQ *SU AGRICULTURAL SOCIE | Q13: =ABS(E13) -> 464.65
A14: AU001 | B14: AU036743 | C14: 5160007000 | D14: Sponsoring | E14: 2200 | F14: AUQ | G14: 45392 | H14: AP Accruals | I14: INV-1460-ASMSF00 | K14: Joint event in Albury - Raboba | L14: INV-1460 | M14: SMSF ASSOCIATION LTD | Q14: =ABS(E14) -> 2200
A15: AU052 | B15: AU030710 | C15: 5160007000 | D15: Sponsoring | E15: 681.82 | F15: AUQ | G15: 45394 | H15: CCMS | I15: GunnHF-Office Supplies | J15: client sponsorship badcock and Melton vale x 2 years | M15: COLES 7659 | Q15: =ABS(E15) -> 681.82
A16: AU052 | B16: AU030612 | C16: 5160007000 | D16: Sponsoring | E16: 102.73 | F16: AUQ | G16: 45394 | H16: CCMS | I16: MELVILLER-Entertainment Expens | J16: Morawa P & C Sponsorship | M16: LIQUORLAND 3083 | Q16: =ABS(E16) -> 102.73 | S16: accept provided to client
A17: AU052 | B17: AU030512 | C17: 5160007000 | D17: Sponsoring | E17: 45.45 | F17: AUQ | G17: 45398 | H17: CCMS | I17: ArnoldS-Default Licensee Merch | J17: Voucher for sponsorship of Kimba Cup | M17: G PEDEMONTE MANUFACTURING | Q17: =ABS(E17) -> 45.45
A18: AU052 | B18: AU075166 | C18: 5160007000 | D18: Sponsoring | E18: 1590.91 | F18: AUQ | G18: 45432 | H18: CCMS | I18: GrootJ5-Default Licensee Merch | J18: sponsorship kingsday event | M18: ROYAL NETHERLANDS EM | Q18: =ABS(E18) -> 1590.91
A19: AU052 | B19: AU010029 | C19: 5160007000 | D19: Sponsoring | E19: 450 | F19: AUQ | G19: 45440 | H19: AP Accruals | I19: FFINV-24020-AUNEF00 | L19: FFINV-24020 | M19: UNE FARMING FUTURES | Q19: =ABS(E19) -> 450
A20: AU001 | B20: AU032066 | C20: 5160007000 | D20: Sponsoring | E20: 4617.36 | F20: AUQ | G20: 45447 | H20: AP Accruals | I20: ATASA00376-AAGRI23 | L20: ATASA00376 | M20: AGRICULTURAL TEACHERS ASSOCIATION OF SA | Q20: =ABS(E20) -> 4617.36
A21: AU052 | B21: AU070150 | C21: 5160007000 | D21: Sponsoring | E21: 7000 | F21: AUQ | G21: 45449 | H21: AP Accruals | I21: INV-1934-AGIAN01 | K21: Giant Steps annual ball | L21: INV-1934 | M21: GIANT STEPS AUSTRALIA LIMITED | Q21: =ABS(E21) -> 7000
A22: AU052 | B22: AU073133 | C22: 5160007000 | D22: Sponsoring | E22: 8382.86 | F22: AUQ | G22: 45457 | H22: AP Accruals | I22: 0127-OSUGA00 | K22: Ticket to Dubai Sugar Conferen | L22: 0127 | M22: SUGAR CONFERENCE ORGANIZERS L.L.C. | Q22: =ABS(E22) -> 8382.86
A23: AU001 | B23: AU032054 | C23: 5160007000 | D23: Sponsoring | E23: 6515.79 | F23: AUQ | G23: 45461 | H23: AP Accruals | I23: INV-3475-ACARB02 | L23: INV-3475 | M23: CARBON MARKET INSTITUTE LIMITED | Q23: =ABS(E23) -> 6515.79
A24: AU052 | B24: AU073158 | C24: 5160007000 | D24: Sponsoring | E24: 1650 | F24: AUQ | G24: 45463 | H24: AP Accruals | I24: 1800000325-ATULL08 | L24: 1800000325 | M24: TULLY SUGAR LIMITED | Q24: =ABS(E24) -> 1650
A25: AU001 | B25: AU032062 | C25: 5160007000 | D25: Sponsoring | E25: 2775.1 | F25: AUQ | G25: 45481 | H25: AP Accruals | I25: 5861-ACOTT07 | L25: 5861 | M25: COTTON AUSTRALIA LTD | Q25: =ABS(E25) -> 2775.1
A26: AU001 | B26: AU032064 | C26: 5160007000 | D26: Sponsoring | E26: 7631.54 | F26: AUQ | G26: 45488 | H26: AP Accruals | I26: 310029263-ANSWH00 | L26: 310029263 | M26: NSW HEALTH MURRUMBIDGEE LOCAL HEALTH | Q26: =ABS(E26) -> 7631.54
A27: AU001 | B27: AU070150 | C27: 5160007000 | D27: Sponsoring | E27: 2000 | F27: AUQ | G27: 45490 | H27: AP Accruals | I27: INV-1121-AONET01 | K27: One Tree Ag RU OK Day Sponosrs | L27: INV-1121 | M27: ONE TREE AGRICULTURAL PTY LTD | Q27: =ABS(E27) -> 2000
A28: AU052 | B28: AU073133 | C28: 5160007000 | D28: Sponsoring | E28: -8382.86 | F28: AUQ | G28: 45504 | H28: Jul 24 YTD Clear to AU073158 | I28: Jul 24 YTD Clear to AU073158 | Q28: =ABS(E28) -> 8382.86
A29: AU052 | B29: AU073158 | C29: 5160007000 | D29: Sponsoring | E29: 8382.86 | F29: AUQ | G29: 45504 | H29: Jul 24 YTD Clear to AU073158 | I29: Jul 24 YTD Clear to AU073158 | Q29: =ABS(E29) -> 8382.86
A30: AU001 | B30: AU032061 | C30: 5160007000 | D30: Sponsoring | E30: 2969.85 | F30: AUQ | G30: 45511 | H30: AP Accruals | I30: 24023-AABLF00 | K30: ABL_NQNT_July_Sponsorship | L30: 24023 | M30: ABL FOUNDATION LIMITED | Q30: =ABS(E30) -> 2969.85
A31: AU001 | B31: AU032062 | C31: 5160007000 | D31: Sponsoring | E31: 4959.02 | F31: AUQ | G31: 45511 | H31: AP Accruals | I31: 24023-AABLF00 | K31: ABL_SQ_July_Sponsorship | L31: 24023 | M31: ABL FOUNDATION LIMITED | Q31: =ABS(E31) -> 4959.02
A32: AU052 | B32: AU030512 | C32: 5160007000 | D32: Sponsoring | E32: 454.55 | F32: AUQ | G32: 45511 | H32: CCMS | I32: ArnoldS-Other Personnel Expens | J32: Support for Lock Health Night | M32: WISH GIFT CARD 6673 | Q32: =ABS(E32) -> 454.55
A33: AU001 | B33: AU032074 | C33: 5160007000 | D33: Sponsoring | E33: 54511 | F33: AUQ | G33: 45516 | H33: AP Accruals | I33: 00000713-AHEAR01 | K33: HeartofAustralia_National_Spon | L33: 00000713 | M33: HEART OF AUSTRALIA | Q33: =ABS(E33) -> 54511
A34: AU052 | B34: AU073158 | C34: 5160007000 | D34: Sponsoring | E34: 7958.78 | F34: AUQ | G34: 45516 | H34: CCMS | I34: Haynest-Entertainment Expense | J34: NZX Global Dairy Seminar 2024 Badge Sponsor - per Graydon | M34: NZX Limited | Q34: =ABS(E34) -> 7958.78
A35: AU052 | B35: AU030313 | C35: 5160007000 | D35: Sponsoring | E35: 1500 | F35: AUQ | G35: 45519 | H35: AP Accruals | I35: RABO-11/06/24-AWELL02 | K35: Sponsorship | L35: RABO-11/06/24 | M35: WELLINGTON BBBBQ INC | Q35: =ABS(E35) -> 1500
A36: AU052 | B36: AU032046 | C36: 5160007000 | D36: Sponsoring | E36: 126233.2 | F36: AUQ | G36: 45530 | H36: AP Accruals | I36: SINV110-002283-ANATI01 | K36: Partnership Fee Aug 2022- Jul | L36: SINV110-002283 | M36: NATIONAL FARMERS FEDERATION | Q36: =ABS(E36) -> 126233.2
A37: AU052 | B37: AU032046 | C37: 5160007000 | D37: Sponsoring | E37: 131721.6 | F37: AUQ | G37: 45530 | H37: AP Accruals | I37: SINV110-002284-ANATI01 | K37: Partnership Fee Aug 2023- Jul | L37: SINV110-002284 | M37: NATIONAL FARMERS FEDERATION | Q37: =ABS(E37) -> 131721.6
A38: AU001 | B38: AU070150 | C38: 5160007000 | D38: Sponsoring | E38: 10000 | F38: AUQ | G38: 45540 | H38: AP Accruals | I38: 06202414-AMANI01 | K38: Gold Sponsorship of Harwood Mi | L38: 06202414 | M38: MANILDRA HARWOOD SUGARS | Q38: =ABS(E38) -> 10000
A39: AU052 | B39: AU073133 | C39: 5160007000 | D39: Sponsoring | E39: 0 | F39: AUQ | G39: 45544 | H39: Clear OU | I39: Clear OU | Q39: =ABS(E39) -> 0
A40: AU001 | B40: AU020099 | C40: 5160007000 | D40: Sponsoring | E40: 1493.82 | F40: AUQ | G40: 45545 | H40: AP Accruals | I40: PSI0015711-ASTVI01 | K40: Staff Community day at Matthew | L40: PSI0015711 | M40: ST VINCENT DE PAUL SOCIETY | Q40: =ABS(E40) -> 1493.82
A41: AU052 | B41: AU070150 | C41: 5160007000 | D41: Sponsoring | E41: 145.91 | F41: AUQ | G41: 45545 | H41: CCMS | I41: DawsonRP-Default Licensee Merc | J41: Tatura 200 Charity Bike Ride & Walk - 2024 | M41: TRYBOOKING*TATURA 200 CHA/219405134613 | Q41: =ABS(E41) -> 145.91 | S41: recreational entertainment | AD41: =E41 -> 145.91
A42: AU052 | B42: AU030618 | C42: 5160007000 | D42: Sponsoring | E42: 150 | F42: AUQ | G42: 45554 | H42: CCMS | I42: ZankerL-Other Personnel Expens | J42: Calingiri golf open day | M42: GOLFBOX | Q42: =ABS(E42) -> 150 | S42: recreational entertainment | AD42: =E42 -> 150
A43: AU001 | B43: AU070150 | C43: 5160007000 | D43: Sponsoring | E43: 1320 | F43: AUQ | G43: 45558 | H43: AP Accruals | I43: 198730-AFOOD09 | K43: volunteer Day for Wholesale me | L43: 198730 | M43: FOODBANK VICTORIA | Q43: =ABS(E43) -> 1320
A44: AU001 | B44: AU030213 | C44: 5160007000 | D44: Sponsoring | E44: 500 | F44: AUQ | G44: 45558 | H44: AP Accruals | I44: INV-0025-ALOCK03 | K44: Lockhart Picnic Races Sponsors | L44: INV-0025 | M44: LOCKHART PICNIC RACE CLUB INCORPORATED | Q44: =ABS(E44) -> 500
A45: AU052 | B45: AU030616 | C45: 5160007000 | D45: Sponsoring | E45: 381.82 | F45: AUQ | G45: 45565 | H45: CCMS | I45: ThompsonP-Default Licensee Mer | J45: Judges Vests - Katanning Ram Show | M45: BAREFOOT CLOTHING | Q45: =ABS(E45) -> 381.82
A46: AU001 | B46: AU032067 | C46: 5160007000 | D46: Sponsoring | E46: 196.24 | F46: AUQ | G46: 45568 | H46: AP Accruals | I46: 1907-APARA00 | K46: TeacherFarmExperience_WACC_Con | L46: 1907 | M46: PARAPHERNALIA DESIGN | Q46: =ABS(E46) -> 196.24
A47: AU052 | B47: AU030414 | C47: 5160007000 | D47: Sponsoring | E47: 1100 | F47: AUQ | G47: 45573 | H47: CCMS | I47: CarterJ1-Default Licensee Merc | J47: Cotton Growers Awards Dinner - James Carter | M47: DARLING DOWNS COTTON | Q47: =ABS(E47) -> 1100
A48: AU052 | B48: AU030511 | C48: 5160007000 | D48: Sponsoring | E48: 121.18 | F48: AUQ | G48: 45594 | H48: CCMS | I48: HawkeA-Offshore Meals & Lodgin | J48: Davidson Ram sale | M48: DUXTON ROYAL OAK HOTEL | Q48: =ABS(E48) -> 121.18
A49: AU052 | B49: AU030511 | C49: 5160007000 | D49: Sponsoring | E49: 121.8 | F49: AUQ | G49: 45594 | H49: CCMS | I49: HawkeA-Offshore Meals & Lodgin | J49: Dowdy Ram Sale | M49: NARACOORTE HOTEL APP | Q49: =ABS(E49) -> 121.8
A50: AU052 | B50: AU036745 | C50: 5160007000 | D50: Sponsoring | E50: 132.85 | F50: AUQ | G50: 45595 | H50: CCMS | I50: KimI-Default Licensee Merchant | J50: Community day expense | M50: WHEEN BEE FOUNDATION | Q50: =ABS(E50) -> 132.85
A51: AU001 | B51: AU010025 | C51: 5160007000 | D51: Sponsoring | E51: 10313.77 | F51: AUQ | G51: 45597 | H51: AP Accruals | I51: CONF447262410221-ATELE04 | K51: AgriLaw Conference | L51: CONF447262410221 | M51: TELEVISION EDUCATION NETWORK PTY | Q51: =ABS(E51) -> 10313.77
A52: AU052 | B52: AU030432 | C52: 5160007000 | D52: Sponsoring | E52: 92.36 | F52: AUQ | G52: 45618 | H52: CCMS | I52: GroganC-Entertainment Expense | J52: Home Hill Golf Club End of Harvest - Team sponsorship | M52: SQ *HOME HILL GOLF CLUB I | Q52: =ABS(E52) -> 92.36
A53: AU001 | B53: AU032074 | C53: 5160007000 | D53: Sponsoring | E53: 4360.88 | F53: AUQ | G53: 45621 | H53: AP Accruals | I53: 00000762-AHEAR01 | K53: HealthChecks_YoungBeefProducer | L53: 00000762 | M53: HEART OF AUSTRALIA | Q53: =ABS(E53) -> 4360.88
A54: AU001 | B54: AU070150 | C54: 5160007000 | D54: Sponsoring | E54: 20000 | F54: AUQ | G54: 45621 | H54: AP Accruals | I54: 18112024-ABEGA02 | K54: 2025 Bega corporate event | L54: 18112024 | M54: BEGA CHEESE LIMITED | Q54: =ABS(E54) -> 20000
A55: AU001 | B55: AU032062 | C55: 5160007000 | D55: Sponsoring | E55: 9911.09 | F55: AUQ | G55: 45628 | H55: AP Accruals | I55: C-1366464-INV-ALIFE03 | K55: SQ Client Council_LifeFlight_W | L55: C-1366464-INV | M55: LIFEFLIGHT FOUNDATION | Q55: =ABS(E55) -> 9911.09
A56: AU001 | B56: AU032053 | C56: 5160007000 | D56: Sponsoring | E56: 14866.64 | F56: AUQ | G56: 45628 | H56: AP Accruals | I56: INV-0119-ACARM00 | K56: Farm Office Plus Online course | L56: INV-0119 | M56: AGRIFOCUSED | Q56: =ABS(E56) -> 14866.64
A57: AU001 | B57: AU032063 | C57: 5160007000 | D57: Sponsoring | E57: 8919.98 | F57: AUQ | G57: 45628 | H57: AP Accruals | I57: INV-0119-ACARM00 | K57: Farm Office Plus Online course | L57: INV-0119 | M57: AGRIFOCUSED | Q57: =ABS(E57) -> 8919.98
A58: AU052 | B58: AU010029 | C58: 5160007000 | D58: Sponsoring | E58: 1646.86 | F58: AUQ | G58: 45628 | H58: AP Accruals | I58: 105965-AACTI08 | K58: 2025 sponsorship for the UTS W | L58: 105965 | M58: ACTIVATEUTS | Q58: =ABS(E58) -> 1646.86
A59: AU001 | B59: AU032065 | C59: 5160007000 | D59: Sponsoring | E59: 7928.87 | F59: AUQ | G59: 45629 | H59: AP Accruals | I59: 159642-AWDHS00 | K59: Sponsorship of the National Ce | L59: 159642 | M59: WESTERN DISTRICT HEALTH SERVICE | Q59: =ABS(E59) -> 7928.87
A60: AU001 | B60: AU032074 | C60: 5160007000 | D60: Sponsoring | E60: 19822.18 | F60: AUQ | G60: 45629 | H60: AP Accruals | I60: 4-AABLF00 | K60: ABLFoundation_National_Sponsor | L60: 4 | M60: ABL FOUNDATION LIMITED | Q60: =ABS(E60) -> 19822.18
A61: AU001 | B61: AU032065 | C61: 5160007000 | D61: Sponsoring | E61: 14866.63 | F61: AUQ | G61: 45629 | H61: AP Accruals | I61: INV-5300-ABOYS00 | K61: BoystotheBush_BendigoVehicle_S | L61: INV-5300 | M61: BOYS TO THE BUSH LIMITED | Q61: =ABS(E61) -> 14866.63
A62: AU001 | B62: AU032074 | C62: 5160007000 | D62: Sponsoring | E62: 87217.61 | F62: AUQ | G62: 45629 | H62: AP Accruals | I62: INV-5300-ABOYS00 | K62: BoystotheBush_Orange_Sponsorsh | L62: INV-5300 | M62: BOYS TO THE BUSH LIMITED | Q62: =ABS(E62) -> 87217.61
A63: AU001 | B63: AU032062 | C63: 5160007000 | D63: Sponsoring | E63: 1090.22 | F63: AUQ | G63: 45631 | H63: AP Accruals | I63: 1800165967-AAGRI24 | K63: SQCC_DAFSchoolScienceComp_S/sh | L63: 1800165967 | M63: AGRI SCIENCE QUEENSLAND | Q63: =ABS(E63) -> 1090.22
A64: AU001 | B64: AU032063 | C64: 5160007000 | D64: Sponsoring | E64: 12500 | F64: AUQ | G64: 45631 | H64: AP Accruals | I64: ASCF-0069-AAUST86 | K64: CNNSW Client Council Sponsorsh | L64: ASCF-0069 | M64: AUSTRALIAN SKIN CANCER FOUNDATION LTD | Q64: =ABS(E64) -> 12500
A65: AU052 | B65: AU030055 | C65: 5160007000 | D65: Sponsoring | E65: 490 | F65: AUQ | G65: 45631 | H65: CCMS | I65: FIRTHG-Default Licensee Mercha | J65: City Farm Community Day | M65: CITY OF SYDNEY OBG | Q65: =ABS(E65) -> 490
A66: AU052 | B66: AU030055 | C66: 5160007000 | D66: Sponsoring | E66: 70 | F66: AUQ | G66: 45631 | H66: CCMS | I66: FIRTHG-Default Licensee Mercha | J66: Community Day - Angus Keeble | M66: CITY OF SYDNEY OBG | Q66: =ABS(E66) -> 70
A67: AU052 | B67: AU030055 | C67: 5160007000 | D67: Sponsoring | E67: 70 | F67: AUQ | G67: 45631 | H67: CCMS | I67: FIRTHG-Default Licensee Mercha | J67: Community Day - John Djukanovic | M67: CITY OF SYDNEY OBG | Q67: =ABS(E67) -> 70
A68: AU001 | B68: AU032064 | C68: 5160007000 | D68: Sponsoring | E68: 3270.66 | F68: AUQ | G68: 45632 | H68: AP Accruals | I68: INV-0071-ANETR03 | K68: Sponsorship of the 2025 Food a | L68: INV-0071 | M68: NE TRACKS LLEN | Q68: =ABS(E68) -> 3270.66
A69: AU001 | B69: AU032064 | C69: 5160007000 | D69: Sponsoring | E69: 7928.87 | F69: AUQ | G69: 45632 | H69: AP Accruals | I69: INV-0120-ACARM00 | K69: Farm Office Plus Online course | L69: INV-0120 | M69: AGRIFOCUSED | Q69: =ABS(E69) -> 7928.87
A70: AU001 | B70: AU032061 | C70: 5160007000 | D70: Sponsoring | E70: 20000 | F70: AUQ | G70: 45632 | H70: AP Accruals | I70: INV-0221-ASOBE01 | K70: QLDCC_SoberintheCountry_Sponso | L70: INV-0221 | M70: SOBER IN THE COUNTRY LTD | Q70: =ABS(E70) -> 20000
A71: AU001 | B71: AU032062 | C71: 5160007000 | D71: Sponsoring | E71: 2000 | F71: AUQ | G71: 45632 | H71: AP Accruals | I71: INV-0221-ASOBE01 | K71: QLDCC_SoberintheCountry_Sponso | L71: INV-0221 | M71: SOBER IN THE COUNTRY LTD | Q71: =ABS(E71) -> 2000
A72: AU001 | B72: AU032062 | C72: 5160007000 | D72: Sponsoring | E72: 2180.44 | F72: AUQ | G72: 45635 | H72: AP Accruals | I72: 1800171110-AAGRI24 | K72: SQCC_2025DAFSchoolsSienceComp_ | L72: 1800171110 | M72: AGRI SCIENCE QUEENSLAND | Q72: =ABS(E72) -> 2180.44
A73: AU052 | B73: AU030215 | C73: 5160007000 | D73: Sponsoring | E73: 57.66 | F73: AUQ | G73: 45635 | H73: CCMS | I73: MillettP-Offshore Meals & Lodg | K73: Sponsorship & Industry Events - Crookwell & Taralga APH Society Pasture Competition - Meals | M73: SMP*The Criterion Hote | Q73: =ABS(E73) -> 57.66
A74: AU001 | B74: AU032054 | C74: 5160007000 | D74: Sponsoring | E74: 109509 | F74: AUQ | G74: 45636 | H74: AP Accruals | I74: INV-0071-AZERO00 | K74: Partnership payment to the Ag | L74: INV-0071 | M74: ZERO NET EMISSIONS AGRICULTURE CRC LTD | Q74: =ABS(E74) -> 109509
A75: AU001 | B75: AU030202 | C75: 5160007000 | D75: Sponsoring | E75: 27500 | F75: AUQ | G75: 45636 | H75: HO reimbursment write off | I75: HO reimbursment write off | Q75: =ABS(E75) -> 27500
A76: AU052 | B76: AU030217 | C76: 5160007000 | D76: Sponsoring | E76: 25.87 | F76: AUQ | G76: 45644 | H76: CCMS | I76: CutcliffeJ-Office Supplies | J76: Moree Public School Luncheon - Rolls | M76: SMP*Balo Square Bakery | Q76: =ABS(E76) -> 25.87
A77: AU052 | B77: AU030612 | C77: 5160007000 | D77: Sponsoring | E77: 1396.06 | F77: AUQ | G77: 45644 | H77: CCMS | I77: ShortN-Offshore Meals & Lodgin | J77: West Coast Rock Lobster Coastal Tour Sponsorship | M77: The Gerald | Q77: =ABS(E77) -> 1396.06

Sheet Promotional gifts
A1: Account Number | C1: =Summary!A14 -> 5160008000
A2: Account Name | C2: =Summary!B14 -> Promotional gifts | G2: Notes:
A3: GL Total | C3: 61100.46 | G3: No entertainment expenses included and all tax deductible
A4: Per TB | C4: =SUM(E:E) -> 61100.46 | T4: AU001 | U4: =SUMIF($A$10:$A$23973,"AU001",U9:U23972) -> 0
A5: Variance | C5: =C3-C4 -> 0 | T5: AU052 | U5: =SUMIF($A$10:$A$23974,"AU052",U9:U23973) -> 0
AC6: Income tax purposes
A7: BUSINESS_UNIT_CODE | B7: OPERATING_UNIT_CODE | C7: ACCOUNT_CODE | D7: DESCRIPTION | E7: BASE_AMOUNT | F7: BASE_CURRENCY_CODE | G7: JOURNAL_DATE | H7: DESCR | I7: LINE_DESCR | J7: PURPOSE | K7: INVOICE_DESCR | L7: INVOICE_ID | M7: VENDOR_NAME | N7: EMPLOYEE_NAME | O7: CHARGE_DESCRIPTION | Q7: ABS | R7: Search Terms | S7: Tax Description | T7: ME? Y/N | U7: ME $ | V7: Not ME but other type of FB Y/N | W7: Not ME but other type of FB ==> $ | X7: Nets to Nil in GL accts | Y7: s58P M&I or Bus Exp - notFB | Z7: ME | AA7: Car FB - addn op costs | AB7: CP Exp FB | AC7: Capital expenditure | AD7: No FBT and not ded | AE7: Additional Comments
A8: AU001 | B8: AU032074 | C8: 5160008000 | D8: Promotional gifts | E8: 11806.55 | F8: AUQ | G8: 45523 | H8: AP Accruals | I8: INV-2383-AGEOR00 | K8: GeorgeTheFarmer_National_Aug_B | L8: INV-2383 | M8: GEORGE THE FARMER PTY LTD | Q8: =ABS(E8) -> 11806.55 | S8: books provided to clients - accept as promotional
A9: AU052 | B9: AU025091 | C9: 5160008000 | D9: Promotional gifts | E9: 10044.09 | F9: AUQ | G9: 45645 | H9: CCMS | I9: ExmannJ-Default Licensee Merch | K9: JPMorgan Run Shirt Invoice | M9: SCODY | Q9: =ABS(E9) -> 10044.09 | S9: Each shirt under $300
A10: AU001 | B10: AU032063 | C10: 5160008000 | D10: Promotional gifts | E10: 5394.45 | F10: AUQ | G10: 45630 | H10: AP Accruals | I10: INV-2508-AGEOR00 | K10: GTF_CNNSW_Books_Nov24 | L10: INV-2508 | M10: GEORGE THE FARMER PTY LTD | Q10: =ABS(E10) -> 5394.45 | S10: books provided to clients - accept as promotional
A11: AU001 | B11: AU010021 | C11: 5160008000 | D11: Promotional gifts | E11: 5304.69 | F11: AUQ | G11: 45637 | H11: AP Accruals | I11: 2738-ATURN01 | K11: Promotional merchandise - Rabo | L11: 2738 | M11: TURNKEY PROMOTIONS | Q11: =ABS(E11) -> 5304.69 | S11: Accept promotional
A12: AU052 | B12: AU010021 | C12: 5160008000 | D12: Promotional gifts | E12: 3049.09 | F12: AUQ | G12: 45642 | H12: CCMS | I12: BaylissK-Offshore Meals & Lodg | K12: New Starter Welcome Gifts | M12: SQ *LONG TRACK PANTRY ONL | Q12: =ABS(E12) -> 3049.09 | S12: Each item under $300
A13: AU001 | B13: AU032066 | C13: 5160008000 | D13: Promotional gifts | E13: 2987.75 | F13: AUQ | G13: 45630 | H13: AP Accruals | I13: INV-2508-AGEOR00 | K13: GTF_SA_Books_Nov24 | L13: INV-2508 | M13: GEORGE THE FARMER PTY LTD | Q13: =ABS(E13) -> 2987.75 | S13: books provided to clients - accept as promotional
A14: AU001 | B14: AU032067 | C14: 5160008000 | D14: Promotional gifts | E14: 2731.98 | F14: AUQ | G14: 45630 | H14: AP Accruals | I14: INV-2508-AGEOR00 | K14: GTF_WA_Books_Nov24 | L14: INV-2508 | M14: GEORGE THE FARMER PTY LTD | Q14: =ABS(E14) -> 2731.98 | S14: books provided to clients - accept as promotional
A15: AU001 | B15: AU032061 | C15: 5160008000 | D15: Promotional gifts | E15: 2719.16 | F15: AUQ | G15: 45630 | H15: AP Accruals | I15: INV-2508-AGEOR00 | K15: GTF_NQNT_Books_Nov24 | L15: INV-2508 | M15: GEORGE THE FARMER PTY LTD | Q15: =ABS(E15) -> 2719.16 | S15: books provided to clients - accept as promotional
A16: AU001 | B16: AU032064 | C16: 5160008000 | D16: Promotional gifts | E16: 2707.64 | F16: AUQ | G16: 45630 | H16: AP Accruals | I16: INV-2508-AGEOR00 | K16: GTF_Riverina_Books_Nov24 | L16: INV-2508 | M16: GEORGE THE FARMER PTY LTD | Q16: =ABS(E16) -> 2707.64 | S16: books provided to clients - accept as promotional
A17: AU001 | B17: AU032062 | C17: 5160008000 | D17: Promotional gifts | E17: 2707.63 | F17: AUQ | G17: 45630 | H17: AP Accruals | I17: INV-2508-AGEOR00 | K17: GTF_SQ_Books_Nov24 | L17: INV-2508 | M17: GEORGE THE FARMER PTY LTD | Q17: =ABS(E17) -> 2707.63 | S17: books provided to clients - accept as promotional
A18: AU001 | B18: AU032065 | C18: 5160008000 | D18: Promotional gifts | E18: 2707.63 | F18: AUQ | G18: 45630 | H18: AP Accruals | I18: INV-2508-AGEOR00 | K18: GTF_SVT_Books_Nov24 | L18: INV-2508 | M18: GEORGE THE FARMER PTY LTD | Q18: =ABS(E18) -> 2707.63 | S18: books provided to clients - accept as promotional
A19: AU001 | B19: AU036740 | C19: 5160008000 | D19: Promotional gifts | E19: 1979.87 | F19: AUQ | G19: 45449 | H19: AP Accruals | I19: 2397-ATURN01 | L19: 2397 | M19: TURNKEY PROMOTIONS | Q19: =ABS(E19) -> 1979.87
A20: AU052 | B20: AU010021 | C20: 5160008000 | D20: Promotional gifts | E20: 1808.18 | F20: AUQ | G20: 45642 | H20: CCMS | I20: BaylissK-Offshore Meals & Lodg | K20: New Starter Welcome Gift | M20: BEECHWORTH HONEY PTY L | Q20: =ABS(E20) -> 1808.18 | S20: Each item under $300
A21: AU052 | B21: AU070150 | C21: 5160008000 | D21: Promotional gifts | E21: 769.91 | F21: AUQ | G21: 45505 | H21: CCMS | I21: Haynest-Offshore Meals & Lodgi | K21: archibald gifts | M21: Koko Black QVB North | Q21: =ABS(E21) -> 769.91 | S21: Gifts - not provided to staff
A22: AU001 | B22: AU036740 | C22: 5160008000 | D22: Promotional gifts | E22: 664.69 | F22: AUQ | G22: 45567 | H22: AP Accruals | I22: 240822-ATURN01 | K22: Rabobank branded notebooks for | L22: 240822 | M22: TURNKEY PROMOTIONS | Q22: =ABS(E22) -> 664.69 | S22: Promotional - office supplies
A23: AU001 | B23: AU036746 | C23: 5160008000 | D23: Promotional gifts | E23: 500 | F23: AUQ | G23: 45532 | H23: FT24241V1B14 Darwin Comp | I23: FT24241015C6 Darwin Comp | Q23: =ABS(E23) -> 500
A24: AU001 | B24: AU036746 | C24: 5160008000 | D24: Promotional gifts | E24: 500 | F24: AUQ | G24: 45532 | H24: FT24241V1B14 Darwin Comp | I24: FT24241V1B14 Darwin Comp | Q24: =ABS(E24) -> 500
A25: AU052 | B25: AU030512 | C25: 5160008000 | D25: Promotional gifts | E25: 474.36 | F25: AUQ | G25: 45414 | H25: CCMS | I25: ArnoldS-Entertainment Expense | K25: Property Settlement Gift Boxes for: Doudles, Schaefers, Peters and Crettendens (Total $16.3m new biz | M25: LS PORT LINCOLN GOURM | Q25: =ABS(E25) -> 474.36 | S25: Under $300 - accept 58P
A26: AU052 | B26: AU030512 | C26: 5160008000 | D26: Promotional gifts | E26: 368.36 | F26: AUQ | G26: 45639 | H26: CCMS | I26: ArnoldS-Entertainment Expense | K26: Settlement gifts for Modra x 2 and Pope | M26: LS PORT LINCOLN GOURM | Q26: =ABS(E26) -> 368.36 | S26: Under $300 - accept 58P
A27: AU052 | B27: AU010029 | C27: 5160008000 | D27: Promotional gifts | E27: 199.41 | F27: AUQ | G27: 45637 | H27: CCMS | I27: SunT-Office Supplies | K27: 2025 graduates welcomes hamper - client products | M27: SP GALLO DAIRYLAND | Q27: =ABS(E27) -> 199.41 | S27: Under $300 - accept 58P
A28: AU052 | B28: AU010029 | C28: 5160008000 | D28: Promotional gifts | E28: 195 | F28: AUQ | G28: 45637 | H28: CCMS | I28: SunT-Offshore Meals & Lodging | K28: 2025 graduates welcomes hamper - client products | M28: RASPBERRYFARMCAFE.COM | Q28: =ABS(E28) -> 195 | S28: Under $300 - accept 58P
A29: AU052 | B29: AU071196 | C29: 5160008000 | D29: Promotional gifts | E29: 181.45 | F29: AUQ | G29: 45642 | H29: CCMS | I29: RigbyC-Default Licensee Mercha | K29: Baby Gift - Trang & Shaun Tupou | M29: CR QVB | Q29: =ABS(E29) -> 181.45 | S29: Under $300 - accept 58P
A30: AU052 | B30: AU030422 | C30: 5160008000 | D30: Promotional gifts | E30: 168.14 | F30: AUQ | G30: 45506 | H30: CCMS | I30: ADAMSC-Software | K30: Gift - for David Kemp for venue of Rabo Truck event | M30: OUTBACK TRADERS A | Q30: =ABS(E30) -> 168.14
A31: AU052 | B31: AU010029 | C31: 5160008000 | D31: Promotional gifts | E31: 152.45 | F31: AUQ | G31: 45637 | H31: CCMS | I31: SunT-Offshore Meals & Lodging | K31: 2025 graduates welcomes hamper - client products | M31: SQ *LONG TRACK PANTRY ONL | Q31: =ABS(E31) -> 152.45
A32: AU052 | B32: AU032053 | C32: 5160008000 | D32: Promotional gifts | E32: 150.26 | F32: AUQ | G32: 45475 | H32: AP Accruals | I32: INV-2327-AGEOR00 | L32: INV-2327 | M32: GEORGE THE FARMER PTY LTD | Q32: =ABS(E32) -> 150.26
A33: AU052 | B33: AU030422 | C33: 5160008000 | D33: Promotional gifts | E33: 136.36 | F33: AUQ | G33: 45502 | H33: CCMS | I33: ADAMSC-Other Personnel Expense | K33: Gift - Flowers for Lynda Kemp Truck event | M33: ENCHANTED FLOWERS MA | Q33: =ABS(E33) -> 136.36
A34: AU052 | B34: AU010029 | C34: 5160008000 | D34: Promotional gifts | E34: 112.62 | F34: AUQ | G34: 45637 | H34: CCMS | I34: SunT-Office Supplies | K34: 2025 graduates welcomes hamper - client products | M34: SP SHOPIFY-ASHGROVEC | Q34: =ABS(E34) -> 112.62
A35: AU052 | B35: AU010011 | C35: 5160008000 | D35: Promotional gifts | E35: 111.65 | F35: AUQ | G35: 45387 | H35: CCMS | I35: BeckettK-Printing | K35: Farewell Sign_RBAL Chair_RANZ Cocktail Evening (19 March 2024) | M35: KWIK KOPY CENTRAL CITY | Q35: =ABS(E35) -> 111.65 | S35: Accept - promotional
A36: AU052 | B36: AU010029 | C36: 5160008000 | D36: Promotional gifts | E36: 100.91 | F36: AUQ | G36: 45637 | H36: CCMS | I36: SunT-Offshore Meals & Lodging | K36: 2025 graduates welcomes hamper - client products | M36: BEECHWORTH HONEY | Q36: =ABS(E36) -> 100.91
A37: AU052 | B37: AU073158 | C37: 5160008000 | D37: Promotional gifts | E37: 99.09 | F37: AUQ | G37: 45594 | H37: CCMS | I37: vanderstelta-Default Licensee | K37: Gift for Gemma organising the Markets offsite | M37: iKOU QVB | Q37: =ABS(E37) -> 99.09 | S37: Under $300 - accept 58P
A38: AU052 | B38: AU030512 | C38: 5160008000 | D38: Promotional gifts | E38: 95.45 | F38: AUQ | G38: 45639 | H38: CCMS | I38: ArnoldS-Office Supplies | K38: Gift card for Kimba School Ag scholarship | M38: COLES 0440 | Q38: =ABS(E38) -> 95.45 | S38: Client - accept
A39: AU052 | B39: AU030422 | C39: 5160008000 | D39: Promotional gifts | E39: 92.73 | F39: AUQ | G39: 45502 | H39: CCMS | I39: ADAMSC-Default Licensee Mercha | K39: Gift Hat for David Kemp Truck Event | M39: P COMINO & SONS/144625004507 | Q39: =ABS(E39) -> 92.73 | S39: Client - accept
A40: AU052 | B40: AU030422 | C40: 5160008000 | D40: Promotional gifts | E40: -92.73 | F40: AUQ | G40: 45506 | H40: CCMS | I40: ADAMSC-Default Licensee Mercha | K40: Refund of return gift | M40: P COMINO & SONS/145934004782 | Q40: =ABS(E40) -> 92.73 | S40: Client - accept
A41: AU052 | B41: AU030212 | C41: 5160008000 | D41: Promotional gifts | E41: 69 | F41: AUQ | G41: 45454 | H41: CCMS | I41: YoungB-Default Licensee Mercha | K41: Coffee mugs and gifts for staff | M41: VISITOR CENTRE | Q41: =ABS(E41) -> 69 | S41: Under $300 - accept 58P
A42: AU052 | B42: AU071196 | C42: 5160008000 | D42: Promotional gifts | E42: 40.64 | F42: AUQ | G42: 45624 | H42: CCMS | I42: RigbyC-Office Supplies | K42: Gift - Floor Voets | M42: WOOLWORTHS/CNR 540 GEORGE | Q42: =ABS(E42) -> 40.64 | S42: Under $300 - accept 58P
A43: AU052 | B43: AU010029 | C43: 5160008000 | D43: Promotional gifts | E43: 22.95 | F43: AUQ | G43: 45637 | H43: CCMS | I43: SunT-Office Supplies | K43: 2025 graduates welcomes hamper - client products | M43: WOOLWORTHS/CNR 540 GEORGE | Q43: =ABS(E43) -> 22.95 | S43: Accept
A44: AU052 | B44: AU071196 | C44: 5160008000 | D44: Promotional gifts | E44: 20.88 | F44: AUQ | G44: 45614 | H44: CCMS | I44: RigbyC-Default Licensee Mercha | K44: Gift - Floor Vets | M44: CWH SYDNEY PARK STREET | Q44: =ABS(E44) -> 20.88 | S44: Under $300 - accept 58P
A45: AU052 | B45: AU071196 | C45: 5160008000 | D45: Promotional gifts | E45: 18.17 | F45: AUQ | G45: 45624 | H45: CCMS | I45: RigbyC-Literature (Books, News | K45: Gift - Floor Voets | M45: THE LUCKY CHARM QVB | Q45: =ABS(E45) -> 18.17 | S45: Under $300 - accept 58P

Sheet Marketing exp
A1: Account Number | C1: =Summary!A15 -> 5160010000
A2: Account Name | C2: =Summary!B15 -> Marketing expense | H2: Notes: | T2: AU001 | V2: =SUMIF($A$8:$A$23972,"AU001",V8:V23972) -> 2454.37 | AC2: AU001 | AD2: =SUMIF($A$8:$A$408,"AU001",AD8:AD408) -> 0 | AE2: =SUMIF($A$8:$A$408,"AU001",AE8:AE408) -> 0
A3: GL Total | C3: 130942.29 | H3: All field day expenses have been treated as deductible | T3: AU052 | V3: =SUMIF($A$8:$A$23973,"AU052",V8:V23973) -> 4287.89 | AC3: AU052 | AD3: =SUMIF($A$8:$A$408,"AU052",AD8:AD408) -> 0 | AE3: =SUMIF($A$8:$A$408,"AU052",AE8:AE408) -> 0
A4: Per TB | C4: =SUM(E:E) -> 130942.29 | H4: All branch Anniversary expenses have been treated as ME | V4: =SUM(V2:V3) -> 6742.26
A5: Variance | C5: =C3-C4 -> 0
AD6: Income tax purposes
A7: BUSINESS_UNIT_CODE | B7: OPERATING_UNIT_CODE | C7: ACCOUNT_CODE | D7: DESCRIPTION | E7: BASE_AMOUNT | F7: BASE_CURRENCY_CODE | G7: JOURNAL_DATE | H7: DESCR | I7: LINE_DESCR | J7: PURPOSE | K7: INVOICE_DESCR | L7: INVOICE_ID | M7: VENDOR_NAME | N7: EMPLOYEE_NAME | O7: CHARGE_DESCRIPTION | Q7: ABS | R7: Search Terms | S7: Tax Description | T7: ME? Y/N | U7: OU | V7: ME $ | W7: Not ME but other type of FB Y/N | X7: Not ME but other type of FB ==> $ | Y7: Nets to Nil in GL accts | Z7: s58P M&I or Bus Exp - notFB | AA7: ME | AB7: Car FB - addn op costs | AC7: CP Exp FB | AD7: Capital expenditure | AE7: No FBT and not ded | AF7: Additional Comments
A8: AU001 | B8: AU032067 | C8: 5160010000 | D8: Marketing expense | E8: 10000 | F8: AUQ | G8: 45608 | H8: AP Accruals | I8: INV-0022-AHURT01 | K8: WA Client Council Community Fu | L8: INV-0022 | M8: HURT TO HELP LIMITED | Q8: =ABS(E8) -> 10000 | S8: Business expense - donation/sponsorship
A9: AU001 | B9: AU032061 | C9: 5160010000 | D9: Marketing expense | E9: 7334.22 | F9: AUQ | G9: 45629 | H9: AP Accruals | I9: IN13653-AROYA05 | K9: QLD Client Councils s/ship to | L9: IN13653 | M9: ROYAL FLYING DOCTOR SERVICE(QLD SECTION) | Q9: =ABS(E9) -> 7334.22 | S9: Business expense - sponsorship
A10: AU001 | B10: AU030613 | C10: 5160010000 | D10: Marketing expense | E10: 5582.97 | F10: AUQ | G10: 45637 | H10: AP Accruals | I10: 241907367-AHILT05 | K10: YFF WA March 2025: Deposit for | L10: 241907367 | M10: HILTON GARDEN INN BUSSELTON | Q10: =ABS(E10) -> 5582.97 | S10: Business expense - sponsorship
A11: AU001 | B11: AU032062 | C11: 5160010000 | D11: Marketing expense | E11: 4955.54 | F11: AUQ | G11: 45629 | H11: AP Accruals | I11: IN13653-AROYA05 | K11: QLD Client Councils s/ship to | L11: IN13653 | M11: ROYAL FLYING DOCTOR SERVICE(QLD SECTION) | Q11: =ABS(E11) -> 4955.54 | S11: Business expense - sponsorship | T11: PL
A12: AU052 | B12: AU032067 | C12: 5160010000 | D12: Marketing expense | E12: 4530.45 | F12: AUQ | G12: 45540 | H12: CCMS | I12: RyanC1-Entertainment Expense | K12: WA CC Meeting in Perth 23.08.24 - remainder of accom and meeting costs | M12: MANDOON ESTATE PTY LTD | Q12: =ABS(E12) -> 4530.45 | S12: Sponsorship - OK
A13: AU001 | B13: AU032046 | C13: 5160010000 | D13: Marketing expense | E13: 4282.07 | F13: AUQ | G13: 45481 | H13: AP Accruals | I13: INV-0205-ALION04 | L13: INV-0205 | M13: LIONS CLUB OF STRZELECKI | Q13: =ABS(E13) -> 4282.07 | S13: Sponsorship - OK
A14: AU001 | B14: AU032046 | C14: 5160010000 | D14: Marketing expense | E14: 3841.88 | F14: AUQ | G14: 45474 | H14: AP Accruals | I14: INV-0348-AWOTL00 | K14: Thriving Women | L14: INV-0348 | M14: WOTL LTD | Q14: =ABS(E14) -> 3841.88 | S14: Sponsorship - OK
A15: AU052 | B15: AU073133 | C15: 5160010000 | D15: Marketing expense | E15: -3434 | F15: AUQ | G15: 45412 | H15: 13494-AGPTP00 | I15: OoiS-Default Licensee Merchant | Q15: =ABS(E15) -> 3434 | S15: disregard
A16: AU052 | B16: AU073158 | C16: 5160010000 | D16: Marketing expense | E16: 3434 | F16: AUQ | G16: 45412 | H16: 13494-AGPTP00 | I16: OoiS-Default Licensee Merchant | Q16: =ABS(E16) -> 3434 | S16: disregard
A17: AU001 | B17: AU036740 | C17: 5160010000 | D17: Marketing expense | E17: 3299.79 | F17: AUQ | G17: 45474 | H17: AP Accruals | I17: INV-1501-ASMSF00 | L17: INV-1501 | M17: SMSF ASSOCIATION LTD | Q17: =ABS(E17) -> 3299.79 | S17: Sponsorship - OK
A18: AU001 | B18: AU036740 | C18: 5160010000 | D18: Marketing expense | E18: 3299.79 | F18: AUQ | G18: 45538 | H18: AP Accruals | I18: INV-1518-ASMSF00 | K18: SMSF Association event sponsor | L18: INV-1518 | M18: SMSF ASSOCIATION LTD | Q18: =ABS(E18) -> 3299.79 | S18: Sponsorship - OK
A19: AU001 | B19: AU030511 | C19: 5160010000 | D19: Marketing expense | E19: 3192.7 | F19: AUQ | G19: 45400 | H19: AP Accruals | I19: INV-0667-ALUCI04 | K19: SE Field Days Catering | L19: INV-0667 | M19: LUCINDALE COUNTRY CLUB | Q19: =ABS(E19) -> 3192.7 | S19: Accept as part of work - mostly clients and prospects
A20: AU001 | B20: AU032067 | C20: 5160010000 | D20: Marketing expense | E20: 3056.58 | F20: AUQ | G20: 45551 | H20: AP Accruals | I20: 50807-APINN05 | K20: WA CC Teacher FX: Bus for prog | L20: 50807 | M20: PINNACLE COACHLINES | Q20: =ABS(E20) -> 3056.58 | S20: Business expense
A21: AU052 | B21: AU073158 | C21: 5160010000 | D21: Marketing expense | E21: 2878.5 | F21: AUQ | G21: 45580 | H21: CCMS | I21: OoiS-Default Licensee Merchant | J21: Wholesale SMS text to clients | M21: WholesaleSMS Pty Ltd | Q21: =ABS(E21) -> 2878.5 | S21: Business expense
A22: AU052 | B22: AU032053 | C22: 5160010000 | D22: Marketing expense | E22: 2544.32 | F22: AUQ | G22: 45621 | H22: AP Accruals | I22: EEC-963-ASPUR00 | K22: Reimbursements for Sonia Spurd | L22: EEC-963 | M22: SPURDLE FAMILY TRUST | Q22: =ABS(E22) -> 2544.32 | S22: Business expense
A23: AU052 | B23: AU032053 | C23: 5160010000 | D23: Marketing expense | E23: -2544.32 | F23: AUQ | G23: 45623 | H23: AP Closed Vouchers | I23: EEC-963-ASPUR00 | K23: Reimbursements for Sonia Spurd | L23: EEC-963 | M23: SPURDLE FAMILY TRUST | Q23: =ABS(E23) -> 2544.32 | S23: Business expense
A24: AU001 | B24: AU032053 | C24: 5160010000 | D24: Marketing expense | E24: 2544.32 | F24: AUQ | G24: 45629 | H24: AP Accruals | I24: CEC-5-ASPUR00 | K24: Reimbursements for Sonia Spurd | L24: CEC-5 | M24: SPURDLE FAMILY TRUST | Q24: =ABS(E24) -> 2544.32 | S24: Business expense
A25: AU001 | B25: AU030613 | C25: 5160010000 | D25: Marketing expense | E25: 2483.7 | F25: AUQ | G25: 45495 | H25: AP Accruals | I25: 769810-AFREM00 | K25: Seafood client event in Perth: | L25: 769810 | M25: FREMANTLE SAILING CLUB | Q25: =ABS(E25) -> 2483.7 | S25: Business expense
A26: AU052 | B26: AU073158 | C26: 5160010000 | D26: Marketing expense | E26: 2222 | F26: AUQ | G26: 45474 | H26: CCMS | I26: OoiS-Default Licensee Merchant | J26: Wholesale SMS text to clients | M26: WholesaleSMS Pty Ltd | Q26: =ABS(E26) -> 2222 | S26: Business expense
A27: AU001 | B27: AU030613 | C27: 5160010000 | D27: Marketing expense | E27: 2213.7 | F27: AUQ | G27: 45512 | H27: AP Accruals | I27: INV-0902-ADOWE00 | K27: Dowerin 2024 Sundowner | L27: INV-0902 | M27: DOWERIN EVENTS MANAGEMENT | Q27: =ABS(E27) -> 2213.7 | S27: Business expense
A28: AU052 | B28: AU032046 | C28: 5160010000 | D28: Marketing expense | E28: 2166.3 | F28: AUQ | G28: 45583 | H28: CCMS | I28: TaylorF-Ground Travel | J28: Bus for Croppa Creek Crop Tour (out of Moree sponsorship budget) | M28: MOREE BUS SERVICE | Q28: =ABS(E28) -> 2166.3 | S28: Business expense
A29: AU001 | B29: AU030622 | C29: 5160010000 | D29: Marketing expense | E29: 2000 | F29: AUQ | G29: 45566 | H29: AP Accruals | I29: 67-ALAKE24 | K29: Newdegate Field Day: Sundowner | L29: 67 | M29: LAKE GRACE P AND C ASSOCIATION | Q29: =ABS(E29) -> 2000 | S29: Business expense
A30: AU052 | B30: AU032067 | C30: 5160010000 | D30: Marketing expense | E30: 1885.45 | F30: AUQ | G30: 45546 | H30: CCMS | I30: RyanC1-Entertainment Expense | J30: WA Client Council Meeting - Perth 22nd & 23rd August - Deposit | M30: MANDOON ESTATE PTY LTD | Q30: =ABS(E30) -> 1885.45 | S30: Business expense
A31: AU001 | B31: AU032062 | C31: 5160010000 | D31: Marketing expense | E31: 1800 | F31: AUQ | G31: 45621 | H31: AP Accruals | I31: 11241-AYUMY00 | K31: YumYum4kids_SQCC_Nov24_purchas | L31: 11241 | M31: YUM YUM 4 KIDS | Q31: =ABS(E31) -> 1800 | S31: Business expense
A32: AU001 | B32: AU032062 | C32: 5160010000 | D32: Marketing expense | E32: 1674.49 | F32: AUQ | G32: 45617 | H32: AP Accruals | I32: CEC-3-AMICH01 | K32: KM allowance reimbursement for | L32: CEC-3 | M32: MICHELLE RAMSAY | Q32: =ABS(E32) -> 1674.49 | S32: Business expense
A33: AU001 | B33: AU032051 | C33: 5160010000 | D33: Marketing expense | E33: 1645.74 | F33: AUQ | G33: 45425 | H33: AP Accruals | I33: 0163-WNICK00 | K33: AU001 AU032051 516001000 | L33: 0163 | M33: NICK BAKER | Q33: =ABS(E33) -> 1645.74 | S33: Business expense
A34: AU052 | B34: AU073158 | C34: 5160010000 | D34: Marketing expense | E34: 1565.5 | F34: AUQ | G34: 45397 | H34: CCMS | I34: OoiS-Default Licensee Merchant | K34: Wholesale SMS text to clients | M34: WholesaleSMS Pty Ltd | Q34: =ABS(E34) -> 1565.5 | S34: Business expense
A35: AU052 | B35: AU073158 | C35: 5160010000 | D35: Marketing expense | E35: 1565.5 | F35: AUQ | G35: 45446 | H35: CCMS | I35: OoiS-Default Licensee Merchant | K35: Wholesale SMS text to clients | M35: WholesaleSMS Pty Ltd | Q35: =ABS(E35) -> 1565.5 | S35: Business expense
A36: AU052 | B36: AU073158 | C36: 5160010000 | D36: Marketing expense | E36: 1565.5 | F36: AUQ | G36: 45524 | H36: CCMS | I36: OoiS-Default Licensee Merchant | K36: Wholesale SMS text to clients | M36: WholesaleSMS Pty Ltd | Q36: =ABS(E36) -> 1565.5 | S36: Business expense
A37: AU052 | B37: AU073158 | C37: 5160010000 | D37: Marketing expense | E37: 1565.5 | F37: AUQ | G37: 45600 | H37: CCMS | I37: OoiS-Default Licensee Merchant | K37: Wholesale SMS text to clients | M37: WholesaleSMS Pty Ltd | Q37: =ABS(E37) -> 1565.5 | S37: Business expense
A38: AU052 | B38: AU073158 | C38: 5160010000 | D38: Marketing expense | E38: 1565.5 | F38: AUQ | G38: 45645 | H38: CCMS | I38: OoiS-Default Licensee Merchant | K38: Wholesale SMS text to clients | M38: WholesaleSMS Pty Ltd | Q38: =ABS(E38) -> 1565.5 | S38: Business expense
A39: AU052 | B39: AU032067 | C39: 5160010000 | D39: Marketing expense | E39: 1478.56 | F39: AUQ | G39: 45614 | H39: CCMS | I39: RyanC1-Offshore Meals & Lodgin | K39: WA Teacher FX: negotiated 50% dinner cost | M39: CUBALLING TAVERN | Q39: =ABS(E39) -> 1478.56 | S39: Teachers - staff involved. ME | T39: Y | U39: =B39 -> AU032067 | V39: =E39 -> 1478.56
A40: AU052 | B40: AU032055 | C40: 5160010000 | D40: Marketing expense | E40: 1436.36 | F40: AUQ | G40: 45516 | H40: CCMS | I40: fennellLJ-Offshore Meals & Lod | K40: Carbon Workshop Bendigo 29 - 30/07/2024 venue hire | M40: BENDIGO HOTEL FUND OP | Q40: =ABS(E40) -> 1436.36 | S40: Business expense
A41: AU001 | B41: AU032073 | C41: 5160010000 | D41: Marketing expense | E41: 1432.55 | F41: AUQ | G41: 45630 | H41: AP Accruals | I41: CEC-7-AMMTI00 | K41: Client Council Chairs Meeting_ | L41: CEC-7 | M41: MONIQUE BRYANT | Q41: =ABS(E41) -> 1432.55 | S41: Business expense
A42: AU052 | B42: AU032065 | C42: 5160010000 | D42: Marketing expense | E42: 1352.63 | F42: AUQ | G42: 45384 | H42: CCMS | I42: MaskellD-Offshore Meals & Lodg | K42: Dinner - SVT Client Council Meeting Melbourne - 01022024 | M42: San Telmo | Q42: =ABS(E42) -> 1352.63 | S42: ME | T42: Y | U42: =B42 -> AU032065 | V42: =E42 -> 1352.63
A43: AU052 | B43: AU032067 | C43: 5160010000 | D43: Marketing expense | E43: 1328.73 | F43: AUQ | G43: 45614 | H43: CCMS | I43: RyanC1-Domestic & Overseas lod | K43: WA Teacher FX: non refundable accomm charge: Bus driver, CC members, staff on program | M43: ALBERT FACEY MOTOR I | Q43: =ABS(E43) -> 1328.73 | S43: Business expense
A44: AU001 | B44: AU030613 | C44: 5160010000 | D44: Marketing expense | E44: 1317.68 | F44: AUQ | G44: 45512 | H44: AP Accruals | I44: INV-0910-ADOWE00 | K44: Dowerin 2024 Catering | L44: INV-0910 | M44: DOWERIN EVENTS MANAGEMENT | Q44: =ABS(E44) -> 1317.68 | S44: ME | T44: Y | U44: =B44 -> AU030613 | V44: =E44 -> 1317.68
A45: AU001 | B45: AU032067 | C45: 5160010000 | D45: Marketing expense | E45: -1291.91 | F45: AUQ | G45: 45637 | H45: 50807-APINN05 | I45: 50807-APINN05 | Q45: =ABS(E45) -> 1291.91 | S45: Business expense
A46: AU001 | B46: AU032074 | C46: 5160010000 | D46: Marketing expense | E46: 1248.8 | F46: AUQ | G46: 45510 | H46: AP Accruals | I46: INV-8509-AGOON20 | K46: FinancialSkillsWorkshops_Goond | L46: INV-8509 | M46: GOONDIWINDI SILO TA GATEWAY TO TRAINING | Q46: =ABS(E46) -> 1248.8 | S46: Business expense
A47: AU001 | B47: AU032051 | C47: 5160010000 | D47: Marketing expense | E47: 1238.36 | F47: AUQ | G47: 45395 | H47: AP Accruals | I47: 0155-WNICK00 | K47: AU001 AU032051 516001000 | L47: 0155 | M47: NICK BAKER | Q47: =ABS(E47) -> 1238.36 | S47: Business expense
A48: AU001 | B48: AU032051 | C48: 5160010000 | D48: Marketing expense | E48: 1228.16 | F48: AUQ | G48: 45425 | H48: AP Accruals | I48: 0162-WNICK00 | K48: AU001 AU032051 516001000 | L48: 0162 | M48: NICK BAKER | Q48: =ABS(E48) -> 1228.16 | S48: Business expense
A49: AU001 | B49: AU036740 | C49: 5160010000 | D49: Marketing expense | E49: 1201.12 | F49: AUQ | G49: 45474 | H49: AP Accruals | I49: 33481-APROD00 | K49: Deposits banners | L49: 33481 | M49: PRODEUCE PTY LTD | Q49: =ABS(E49) -> 1201.12 | S49: Business expense
A50: AU001 | B50: AU032074 | C50: 5160010000 | D50: Marketing expense | E50: 1122.14 | F50: AUQ | G50: 45384 | H50: AP Accruals | I50: INV00551-ADOWE01 | K50: FinancialSkillsWorkshop_Doweri | L50: INV00551 | M50: DOWERIN COMMUNITY CLUB INC | Q50: =ABS(E50) -> 1122.14 | S50: Business expense
A51: AU001 | B51: AU032067 | C51: 5160010000 | D51: Marketing expense | E51: 1100.61 | F51: AUQ | G51: 45567 | H51: AP Accruals | I51: 240808-ATURN01 | K51: WA Teacher FX Gift Bags | L51: 240808 | M51: TURNKEY PROMOTIONS | Q51: =ABS(E51) -> 1100.61 | S51: Clients - OK
A52: AU052 | B52: AU032046 | C52: 5160010000 | D52: Marketing expense | E52: 1072.73 | F52: AUQ | G52: 45629 | H52: CCMS | I52: RyanC1-Default Licensee Mercha | J52: Wagin Woolorama 2025 site application | M52: WOOLORAMA | Q52: =ABS(E52) -> 1072.73 | S52: Business expense
A53: AU001 | B53: AU030613 | C53: 5160010000 | D53: Marketing expense | E53: 1044.2 | F53: AUQ | G53: 45413 | H53: AP Accruals | I53: 751187-AFREM00 | K53: Perth Seafood Client Event on | L53: 751187 | M53: FREMANTLE SAILING CLUB | Q53: =ABS(E53) -> 1044.2 | S53: Business expense
A54: AU001 | B54: AU070150 | C54: 5160010000 | D54: Marketing expense | E54: 990 | F54: AUQ | G54: 45601 | H54: AP Accruals | I54: 36-30/10/24-AAUST23 | K54: Australian Dairy Conference Sp | L54: 36-30/10/24 | M54: AUSTRALIAN DAIRY CONFERENCE | Q54: =ABS(E54) -> 990 | S54: Business expense
A55: AU001 | B55: AU032046 | C55: 5160010000 | D55: Marketing expense | E55: 972.94 | F55: AUQ | G55: 45449 | H55: AP Accruals | I55: 2024066-ANEWD01 | L55: 2024066 | M55: NEWDEGATE MACHINERY FIELD DAYS INC | Q55: =ABS(E55) -> 972.94 | S55: Business expense
A56: AU001 | B56: AU032053 | C56: 5160010000 | D56: Marketing expense | E56: 953.51 | F56: AUQ | G56: 45635 | H56: AP Accruals | I56: CEC-8-AWAMA00 | K56: Client Council Chairs Meeting_ | L56: CEC-8 | M56: WAMARA FARMING TRUST | Q56: =ABS(E56) -> 953.51 | S56: Business expense
A57: AU001 | B57: AU030320 | C57: 5160010000 | D57: Marketing expense | E57: 948.6 | F57: AUQ | G57: 45485 | H57: AP Accruals | I57: 502-A28NA00 | K57: LambEx | L57: 502 | M57: 28 NATIONAL LTD TRADING AS LAMBEX | Q57: =ABS(E57) -> 948.6 | S57: Business expense
A58: AU052 | B58: AU073158 | C58: 5160010000 | D58: Marketing expense | E58: 909 | F58: AUQ | G58: 45412 | H58: CCMS | I58: OoiS-Default Licensee Merchant | J58: Wholesale SMS text to clients | M58: WholesaleSMS Pty Ltd | Q58: =ABS(E58) -> 909 | S58: Business expense
A59: AU052 | B59: AU073158 | C59: 5160010000 | D59: Marketing expense | E59: 909 | F59: AUQ | G59: 45495 | H59: CCMS | I59: OoiS-Default Licensee Merchant | J59: Wholesale SMS text to clients | M59: WholesaleSMS Pty Ltd | Q59: =ABS(E59) -> 909 | S59: Business expense
A60: AU052 | B60: AU073158 | C60: 5160010000 | D60: Marketing expense | E60: 909 | F60: AUQ | G60: 45615 | H60: CCMS | I60: OoiS-Default Licensee Merchant | J60: Wholesale SMS text to clients | M60: WholesaleSMS Pty Ltd | Q60: =ABS(E60) -> 909 | S60: Business expense
A61: AU001 | B61: AU032053 | C61: 5160010000 | D61: Marketing expense | E61: 878.25 | F61: AUQ | G61: 45629 | H61: AP Accruals | I61: RABO-13/11/24-ANICO00 | K61: ADL CBR Return 18 and 21 Nov | L61: RABO-13/11/24 | M61: NICOLE KIRKLAND | Q61: =ABS(E61) -> 878.25 | S61: Business expense
A62: AU001 | B62: AU032061 | C62: 5160010000 | D62: Marketing expense | E62: 813.29 | F62: AUQ | G62: 45617 | H62: AP Accruals | I62: CEC-4-AARDI00 | K62: Return flights Brisbane-Townsv | L62: CEC-4 | M62: ARDIE LORD | Q62: =ABS(E62) -> 813.29 | S62: Business expense
A63: AU001 | B63: AU032063 | C63: 5160010000 | D63: Marketing expense | E63: 767.46 | F63: AUQ | G63: 45573 | H63: AP Accruals | I63: RABO-27/09/24-AMACQ00 | K63: Return Airfares Dubbo Sydney | L63: RABO-27/09/24 | M63: MACQUARIE ACCOUNTING NARROMINE | Q63: =ABS(E63) -> 767.46 | S63: Business expense
A64: AU052 | B64: AU030619 | C64: 5160010000 | D64: Marketing expense | E64: 713.14 | F64: AUQ | G64: 45565 | H64: CCMS | I64: DEVREEV-Offshore Meals & Lodgi | J64: Newdegate Field Day Sundowner Beverages | M64: MAGADASHLY PTY LTD | Q64: =ABS(E64) -> 713.14 | S64: Business expense
A65: AU052 | B65: AU030611 | C65: 5160010000 | D65: Marketing expense | E65: 709.42 | F65: AUQ | G65: 45600 | H65: CCMS | I65: CampbellT-Default Licensee Mer | J65: 2024 Esperance Field Day Supplies | M65: MBL FOOD & PACKAGING L | Q65: =ABS(E65) -> 709.42 | S65: Business expense
A66: AU052 | B66: AU073158 | C66: 5160010000 | D66: Marketing expense | E66: 656.5 | F66: AUQ | G66: 45397 | H66: CCMS | I66: OoiS-Default Licensee Merchant | J66: Wholesale SMS text to clients | M66: WholesaleSMS Pty Ltd | Q66: =ABS(E66) -> 656.5 | S66: Business expense
A67: AU052 | B67: AU073158 | C67: 5160010000 | D67: Marketing expense | E67: 656.5 | F67: AUQ | G67: 45484 | H67: CCMS | I67: OoiS-Default Licensee Merchant | J67: Wholesale SMS text to clients | M67: WholesaleSMS Pty Ltd | Q67: =ABS(E67) -> 656.5 | S67: Business expense
A68: AU052 | B68: AU073133 | C68: 5160010000 | D68: Marketing expense | E68: 656.5 | F68: AUQ | G68: 45524 | H68: CCMS | I68: OoiS-Default Licensee Merchant | J68: Wholesale SMS text to clients | M68: WholesaleSMS Pty Ltd | Q68: =ABS(E68) -> 656.5 | S68: Business expense
A69: AU052 | B69: AU073158 | C69: 5160010000 | D69: Marketing expense | E69: 656.5 | F69: AUQ | G69: 45534 | H69: CCMS | I69: OoiS-Default Licensee Merchant | J69: Wholesale SMS text to clients | M69: WholesaleSMS Pty Ltd | Q69: =ABS(E69) -> 656.5 | S69: Business expense
A70: AU052 | B70: AU073158 | C70: 5160010000 | D70: Marketing expense | E70: 656.5 | F70: AUQ | G70: 45544 | H70: CCMS | I70: OoiS-Default Licensee Merchant | J70: Wholesale SMS text to clients | M70: WholesaleSMS Pty Ltd | Q70: =ABS(E70) -> 656.5 | S70: Business expense
A71: AU052 | B71: AU073133 | C71: 5160010000 | D71: Marketing expense | E71: -656.5 | F71: AUQ | G71: 45544 | H71: Clear OU | I71: Clear OU | Q71: =ABS(E71) -> 656.5 | S71: Business expense
A72: AU052 | B72: AU073158 | C72: 5160010000 | D72: Marketing expense | E72: 656.5 | F72: AUQ | G72: 45544 | H72: Clear OU | I72: Clear OU | Q72: =ABS(E72) -> 656.5 | S72: Business expense
A73: AU052 | B73: AU073158 | C73: 5160010000 | D73: Marketing expense | E73: 656.5 | F73: AUQ | G73: 45624 | H73: CCMS | I73: OoiS-Default Licensee Merchant | J73: Wholesale SMS text to clients | M73: WholesaleSMS Pty Ltd | Q73: =ABS(E73) -> 656.5 | S73: Business expense
A74: AU001 | B74: AU030611 | C74: 5160010000 | D74: Marketing expense | E74: 630.07 | F74: AUQ | G74: 45579 | H74: AP Accruals | I74: 1087-ALAUR00 | K74: Ruminati Workshop client cater | L74: 1087 | M74: LAURENS LARDER | Q74: =ABS(E74) -> 630.07 | S74: ME | T74: Y | U74: =B74 -> AU030611 | V74: =E74 -> 630.07
A75: AU052 | B75: AU032067 | C75: 5160010000 | D75: Marketing expense | E75: 563.64 | F75: AUQ | G75: 45614 | H75: CCMS | I75: RyanC1-Offshore Meals & Lodgin | K75: WA Teacher FX: non refundable catering expense | M75: JUSTEAT GROUP PTY LTD | Q75: =ABS(E75) -> 563.64 | S75: ME | T75: Y | U75: =B75 -> AU032067 | V75: =E75 -> 563.64
A76: AU052 | B76: AU030213 | C76: 5160010000 | D76: Marketing expense | E76: 550 | F76: AUQ | G76: 45586 | H76: CCMS | I76: GallowayM-Software | K76: Updated team photos | M76: JACKOFHEARTSSTUDIO | Q76: =ABS(E76) -> 550
A77: AU052 | B77: AU030322 | C77: 5160010000 | D77: Marketing expense | E77: 548.56 | F77: AUQ | G77: 45586 | H77: AP Accruals | I77: INV29686-ATERA03 | K77: Rabo sponsored event | L77: INV29686 | M77: TERANG AND DIST RACING CLUB INC | Q77: =ABS(E77) -> 548.56 | S77: Business expense
A78: AU052 | B78: AU030213 | C78: 5160010000 | D78: Marketing expense | E78: 500 | F78: AUQ | G78: 45595 | H78: CCMS | I78: MitchellB-Offshore Meals & Lod | J78: Sponsorship- Illabo Show | M78: SQ *ILLABO SHOW SOCIETY I | Q78: =ABS(E78) -> 500
A79: AU001 | B79: AU030613 | C79: 5160010000 | D79: Marketing expense | E79: 497.24 | F79: AUQ | G79: 45637 | H79: AP Accruals | I79: INV-7132-ASHEL03 | K79: YFF WA March 2025: Deposit for | L79: INV-7132 | M79: SHELTER BREWING | Q79: =ABS(E79) -> 497.24
A80: AU052 | B80: AU032046 | C80: 5160010000 | D80: Marketing expense | E80: 454.55 | F80: AUQ | G80: 45537 | H80: CCMS | I80: PozziB-Default Licensee Mercha | K80: Rural Women Unite Raffle Donation | O80: SQ *RURAL WOMEN UNITE INC | Q80: =ABS(E80) -> 454.55
A81: AU052 | B81: AU030213 | C81: 5160010000 | D81: Marketing expense | E81: 440 | F81: AUQ | G81: 45574 | H81: CCMS | I81: MitchellB-Default Licensee Mer | K81: Charity golf day marketing event | O81: ROTARY CLUB OF NARRAN | Q81: =ABS(E81) -> 440 | S81: Accept marketing
A82: AU001 | B82: AU032061 | C82: 5160010000 | D82: Marketing expense | E82: 419.18 | F82: AUQ | G82: 45629 | H82: AP Accruals | I82: CEC-6-AFLOR01 | K82: Return flights for Tony Olsen | L82: CEC-6 | M82: FLOR-HANLY | Q82: =ABS(E82) -> 419.18
A83: AU001 | B83: AU032061 | C83: 5160010000 | D83: Marketing expense | E83: 416.45 | F83: AUQ | G83: 45614 | H83: AP Accruals | I83: CEC-2-AANDR00 | K83: Return flights for Melissa Deg | L83: CEC-2 | M83: ANDREW AND MELISSA DEGUARA | Q83: =ABS(E83) -> 416.45
A84: AU052 | B84: AU030613 | C84: 5160010000 | D84: Marketing expense | E84: 411.07 | F84: AUQ | G84: 45546 | H84: CCMS | I84: RyanC1-Entertainment Expense | K84: Dowerin Field Day: Staff Tickets | O84: MEGATIX.COM.AU | Q84: =ABS(E84) -> 411.07
A85: AU052 | B85: AU032055 | C85: 5160010000 | D85: Marketing expense | E85: 409.09 | F85: AUQ | G85: 45516 | H85: CCMS | I85: fennellLJ-Domestic & Overseas | K85: Venue Booking - Carbon Workshop Bendigo 29 - 30/07/2025 | O85: BENDIGO HOTEL FUND OP | Q85: =ABS(E85) -> 409.09
A86: AU052 | B86: AU030217 | C86: 5160010000 | D86: Marketing expense | E86: 400 | F86: AUQ | G86: 45629 | H86: CCMS | I86: TaylorF-Other Personnel Expens | K86: Sponsorship of Young Aggies Moree | O86: CUSTOM CUTTING STUDIO | Q86: =ABS(E86) -> 400
A87: AU001 | B87: AU030613 | C87: 5160010000 | D87: Marketing expense | E87: -399.78 | F87: AUQ | G87: 45516 | H87: VISA JULY 2024 | I87: 769810-AFREM00 | Q87: =ABS(E87) -> 399.78
A88: AU052 | B88: AU032065 | C88: 5160010000 | D88: Marketing expense | E88: 393.16 | F88: AUQ | G88: 45385 | H88: CCMS | I88: BrennanS1-Offshore Meals & Lod | K88: Catering - SVT Client Council Meeting - Melbourne 2 Feb 2024 | O88: ELIZABETH ANDREWS/219235264581 | Q88: =ABS(E88) -> 393.16 | S88: Accept sustenance
A89: AU001 | B89: AU032053 | C89: 5160010000 | D89: Marketing expense | E89: 368.14 | F89: AUQ | G89: 45629 | H89: AP Accruals | I89: RABO-13/11/24-ANICO00 | K89: MGB ADL Return Rex Airlines | L89: RABO-13/11/24 | M89: NICOLE KIRKLAND | Q89: =ABS(E89) -> 368.14
A90: AU001 | B90: AU030513 | C90: 5160010000 | D90: Marketing expense | E90: 328.34 | F90: AUQ | G90: 45553 | H90: AP Accruals | I90: 22-AARTH00 | K90: Fin Skills Workshop venue | L90: 22 | M90: ARTHURTON WAR MEMORIAL SPORTS CLUB | Q90: =ABS(E90) -> 328.34
A91: AU052 | B91: AU032046 | C91: 5160010000 | D91: Marketing expense | E91: 300.91 | F91: AUQ | G91: 45595 | H91: CCMS | I91: fennellLJ-Rental - Office Equi | K91: RaboTruck Colbinabbin - toilet hire | M91: KENNARDS HIRE HO VIC | Q91: =ABS(E91) -> 300.91
A92: AU052 | B92: AU032067 | C92: 5160010000 | D92: Marketing expense | E92: 298.18 | F92: AUQ | G92: 45540 | H92: CCMS | I92: RyanC1-Default Licensee Mercha | K92: WA CC Meeting: Ben McTaggart PER-GER flight | M92: QANTAS AIR_ABN16009661901/JM9J8KGCXXGN3RF6/JM9J8KGCXXGN3RF6 | Q92: =ABS(E92) -> 298.18
A93: AU052 | B93: AU032065 | C93: 5160010000 | D93: Marketing expense | E93: 294.87 | F93: AUQ | G93: 45384 | H93: CCMS | I93: BrennanS1-Offshore Meals & Lod | K93: Lunch Catering - SVT Client Council Meeting - Melbourne 1 Feb 2024 | M93: ELIZABETH ANDREWS/219235264725 | Q93: =ABS(E93) -> 294.87 | S93: ME | T93: Y | U93: =B93 -> AU032065 | V93: =E93 -> 294.87
A94: AU001 | B94: AU030611 | C94: 5160010000 | D94: Marketing expense | E94: 273.11 | F94: AUQ | G94: 45401 | H94: AP Accruals | I94: 11-ASCAD00 | K94: Esperance: Client Event w Stef | L94: 11 | M94: SCADDAN COUNTRY CLUB | Q94: =ABS(E94) -> 273.11 | S94: ME | T94: Y | U94: =B94 -> AU030611 | V94: =E94 -> 273.11
A95: AU001 | B95: AU030611 | C95: 5160010000 | D95: Marketing expense | E95: -273.11 | F95: AUQ | G95: 45411 | H95: AP Accruals | I95: 11-ASCAD00 | K95: Esperance: Client Event w Stef | L95: 11 | M95: SCADDAN COUNTRY CLUB | Q95: =ABS(E95) -> 273.11 | S95: ME | T95: Y | U95: =B95 -> AU030611 | V95: =E95 -> -273.11
A96: AU001 | B96: AU030611 | C96: 5160010000 | D96: Marketing expense | E96: 273.11 | F96: AUQ | G96: 45413 | H96: AP Accruals | I96: 11-ASCAD00 | K96: Esperance: Client Event w Stef | L96: 11 | M96: SCADDAN COUNTRY CLUB | Q96: =ABS(E96) -> 273.11 | S96: ME | T96: Y | U96: =B96 -> AU030611 | V96: =E96 -> 273.11
A97: AU052 | B97: AU032055 | C97: 5160010000 | D97: Marketing expense | E97: 272.73 | F97: AUQ | G97: 45516 | H97: CCMS | I97: fennellLJ-Offshore Meals & Lod | K97: Room Hire - Bendigo Carbon Workshop attendee dinner 29/07/2024 | O97: LAKE VIEW HOTEL | Q97: =ABS(E97) -> 272.73 | S97: ME | T97: Y | U97: =B97 -> AU032055 | V97: =E97 -> 272.73
A98: AU052 | B98: AU030321 | C98: 5160010000 | D98: Marketing expense | E98: 272.73 | F98: AUQ | G98: 45636 | H98: CCMS | I98: WarrenL-Offshore Meals & Lodgi | K98: 27 Sept - Room Hire - Renmark Bowling Club - Lee-Anne Warren | O98: Renmark Bowling Club I | Q98: =ABS(E98) -> 272.73
A99: AU052 | B99: AU032065 | C99: 5160010000 | D99: Marketing expense | E99: 264.75 | F99: AUQ | G99: 45384 | H99: CCMS | I99: BrennanS1-Airfares | K99: SVT CC Meeting - accommodation - Caitlin Radford 1 Feb 2024 | O99: EGEN*AUSI142228683/AUBI2024331254631/AUBI2024331254631300 | Q99: =ABS(E99) -> 264.75
A100: AU052 | B100: AU032065 | C100: 5160010000 | D100: Marketing expense | E100: 264.75 | F100: AUQ | G100: 45384 | H100: CCMS | I100: BrennanS1-Airfares | K100: SVT CC Meeting - accommodation - Chris Griffin 1 Feb 2024 | O100: EGEN*AUSI142228682/AUBI2024331254630/AUBI2024331254630700 | Q100: =ABS(E100) -> 264.75
...

Sheet Business Dev
A1: Account Number | C1: =Summary!A16 -> 5160011000 | Q1: Q1 | S1: Isn't it that under Div9A all meals provided to clients irrespective of amount, time or where is not “sustenance”, but entertaiment.
A2: Account Name | C2: =Summary!B16 -> Business development | G2: Notes: | Q2: Q2 | S2: Totally agree, sounds capital and not on rev acct.
A3: GL Total | C3: 2312939.7 | G3: Marquees, furniture and other associated costs at field day events are a business expense and not a recreational event - treated as tax deductible and not subject to FBT | T3: AU001 | V3: =SUMIF($A$8:$A$23974,"AU001",V8:V23974) -> 32145.58 | AC3: AU001 | AD3: =SUMIF($A$8:$A$20000,"AU001",AD8:AD20000) -> 463437.57 | AE3: =SUMIF($A$8:$A$20000,"AU001",AE8:AE20000) -> 0
A4: Per TB | C4: =SUM(E:E) -> 2312939.7 | G4: Sponsorship is deductible under s8-1 as it promotes the business and the expectation is that it will generate future business | T4: AU052 | V4: =SUMIF($A$8:$A$23974,"AU052",V8:V23974) -> 79020.82 | AC4: AU052 | AD4: =SUMIF($A$8:$A$408,"AU052",AD8:AD20000) -> 650 | AE4: =SUMIF($A$8:$A$20000,"AU052",AE8:AE20000) -> 415.15
A5: Variance | C5: =C3-C4 -> -5.5879354e-09 | G5: Rabobank truck expenses have been treated as deductible on the basis that they are a marketing expense under s8-1. | V5: =SUM(V3:V4) -> 111166.4 | AD5: =SUM(AD3:AD4) -> 464087.57 | AE5: =SUM(AE3:AE4) -> 415.15
G6: Field days include alcohol - but staff are not able to drink on jobs. Intention is to assist prospective clients or existing clients. Run sheets are available. Days usually wrap up mid afternoon. | AD6: Income tax purposes
A7: BUSINESS_UNIT_CODE | B7: OPERATING_UNIT_CODE | C7: ACCOUNT_CODE | D7: DESCRIPTION | E7: BASE_AMOUNT | F7: BASE_CURRENCY_CODE | G7: JOURNAL_DATE | H7: DESCR | I7: LINE_DESCR | J7: PURPOSE | K7: INVOICE_DESCR | L7: INVOICE_ID | M7: VENDOR_NAME | N7: EMPLOYEE_NAME | O7: CHARGE_DESCRIPTION | Q7: ABS | R7: Search Terms | S7: Tax Description | T7: ME? Y/N | U7: OU | V7: ME $ | W7: Not ME but other type of FB Y/N | X7: Not ME but other type of FB ==> $ | Y7: Nets to Nil in GL accts | Z7: s58P M&I or Bus Exp - notFB | AA7: ME | AB7: Car FB - addn op costs | AC7: CP Exp FB | AD7: Capital expenditure | AE7: No FBT and not ded | AF7: Additional Comments
A8: AU001 | B8: AU032046 | C8: 5160011000 | D8: Business development | E8: 348744.41 | F8: AUQ | G8: 45631 | H8: AP Accruals | I8: RAB497/1-ASOLU01 | K8: RaboTruck rebuild deposit | L8: RAB497/1 | M8: SOLUTION ENTERTAINMENT | Q8: =ABS(E8) -> 348744.41 | S8: RaboTruck - capital item? | V8: =IF(T8="Y",E8,"") | AD8: =E8 -> 348744.41
A9: AU001 | B9: AU032046 | C9: 5160011000 | D9: Business development | E9: 170425.8 | F9: AUQ | G9: 45636 | H9: AP Accruals | I9: 2713-ATURN01 | K9: Merch Promo item National | L9: 2713 | M9: TURNKEY PROMOTIONS | Q9: =ABS(E9) -> 170425.8 | S9: marketing - OK | V9: =IF(T9="Y",E9,"")
A10: AU001 | B10: AU032046 | C10: 5160011000 | D10: Business development | E10: 43907.2 | F10: AUQ | G10: 45425 | H10: AP Accruals | I10: 00013065-AQUAL08 | K10: Beef cutom made wall and print | L10: 00013065 | M10: QUALITY EVENT HIRE PTY LTD | Q10: =ABS(E10) -> 43907.2 | S10: To consider if capital? | V10: =IF(T10="Y",E10,"") | AD10: =E10 -> 43907.2
A11: AU001 | B11: AU032046 | C11: 5160011000 | D11: Business development | E11: 43153.11 | F11: AUQ | G11: 45434 | H11: AP Accruals | I11: 00013069-AQUAL08 | L11: 00013069 | M11: QUALITY EVENT HIRE PTY LTD | Q11: =ABS(E11) -> 43153.11 | S11: To consider if capital? | V11: =IF(T11="Y",E11,"") | AD11: =E11 -> 43153.11
A12: AU001 | B12: AU032046 | C12: 5160011000 | D12: Business development | E12: 38418.8 | F12: AUQ | G12: 45586 | H12: AP Accruals | I12: 1051489-AANGU01 | K12: World Angus Forum 2025 Sponsor | L12: 1051489 | M12: THE ANGUS SOCIETY OF AUSTRALIA | Q12: =ABS(E12) -> 38418.8 | S12: Sponsorship | V12: =IF(T12="Y",E12,"")
A13: AU001 | B13: AU032046 | C13: 5160011000 | D13: Business development | E13: 38418.8 | F13: AUQ | G13: 45614 | H13: AP Accruals | I13: INV-0230-AAUST23 | K13: Australian Dairy Conference 20 | L13: INV-0230 | M13: AUSTRALIAN DAIRY CONFERENCE | Q13: =ABS(E13) -> 38418.8 | S13: Sponsorship | V13: =IF(T13="Y",E13,"")
A14: AU001 | B14: AU032046 | C14: 5160011000 | D14: Business development | E14: 34650 | F14: AUQ | G14: 45642 | I14: Nuffield Scholar Sponsorship | K14: Nuffield Scholar Sponsorship | Q14: =ABS(E14) -> 34650 | S14: Sponsorship | V14: =IF(T14="Y",E14,"")
A15: AU001 | B15: AU032046 | C15: 5160011000 | D15: Business development | E15: 33981.05 | F15: AUQ | G15: 45460 | H15: AP Accruals | I15: 2367-ATURN01 | K15: Trucker Caps & Key Tags | L15: 2367 | M15: TURNKEY PROMOTIONS | Q15: =ABS(E15) -> 33981.05 | S15: marketing - OK | V15: =IF(T15="Y",E15,"")
A16: AU001 | B16: AU032046 | C16: 5160011000 | D16: Business development | E16: 31076.42 | F16: AUQ | G16: 45520 | H16: AP Accruals | I16: 00013131-AQUAL08 | K16: LambEx site & furniture | L16: 00013131 | M16: QUALITY EVENT HIRE PTY LTD | Q16: =ABS(E16) -> 31076.42 | S16: Hire - OK | V16: =IF(T16="Y",E16,"")
A17: AU001 | B17: AU032046 | C17: 5160011000 | D17: Business development | E17: 26591.31 | F17: AUQ | G17: 45447 | H17: AP Accruals | I17: INV-4990/65-ASOLU01 | L17: INV-4990/65 | M17: SOLUTION ENTERTAINMENT | Q17: =ABS(E17) -> 26591.31 | S17: Hire - OK | V17: =IF(T17="Y",E17,"")
A18: AU001 | B18: AU032046 | C18: 5160011000 | D18: Business development | E18: 25871.8 | F18: AUQ | G18: 45402 | H18: AP Accruals | I18: INV-4990/63-ASOLU01 | K18: Truck prime mover lease annaul | L18: INV-4990/63 | M18: SOLUTION ENTERTAINMENT | Q18: =ABS(E18) -> 25871.8 | S18: Hire - OK | V18: =IF(T18="Y",E18,"")
A19: AU001 | B19: AU032046 | C19: 5160011000 | D19: Business development | E19: 25871.8 | F19: AUQ | G19: 45614 | H19: AP Accruals | I19: INV-4990/72-ASOLU01 | K19: RaboTruck Prime Mover Lease Q4 | L19: INV-4990/72 | M19: SOLUTION ENTERTAINMENT | Q19: =ABS(E19) -> 25871.8 | S19: Hire - OK | V19: =IF(T19="Y",E19,"")
A20: AU001 | B20: AU032046 | C20: 5160011000 | D20: Business development | E20: 25795.48 | F20: AUQ | G20: 45614 | H20: AP Accruals | I20: INV-4990/73-ASOLU01 | K20: RaboTruck Project Manager Q4 | L20: INV-4990/73 | M20: SOLUTION ENTERTAINMENT | Q20: =ABS(E20) -> 25795.48 | S20: Hire - OK | V20: =IF(T20="Y",E20,"")
A21: AU001 | B21: AU032051 | C21: 5160011000 | D21: Business development | E21: 24090.63 | F21: AUQ | G21: 45635 | H21: AP Accruals | I21: INV-10370_AU_202411-WTRAC04 | K21: ROS brand tracker | L21: INV-10370_AU_20241101 | M21: TRACKSUIT LIMITED | Q21: =ABS(E21) -> 24090.63 | S21: Hire - OK | V21: =IF(T21="Y",E21,"")
A22: AU001 | B22: AU032046 | C22: 5160011000 | D22: Business development | E22: 22571.04 | F22: AUQ | G22: 45425 | H22: AP Accruals | I22: INV-4990/62-ASOLU01 | K22: Q2 Truck driver cost | L22: INV-4990/62 | M22: SOLUTION ENTERTAINMENT | Q22: =ABS(E22) -> 22571.04 | S22: Hire - OK | V22: =IF(T22="Y",E22,"")
A23: AU001 | B23: AU032046 | C23: 5160011000 | D23: Business development | E23: 22571.04 | F23: AUQ | G23: 45614 | H23: AP Accruals | I23: INV-4990/74-ASOLU01 | K23: RaboTruck Driver Q4 | L23: INV-4990/74 | M23: SOLUTION ENTERTAINMENT | Q23: =ABS(E23) -> 22571.04 | S23: Hire - OK | V23: =IF(T23="Y",E23,"")
A24: AU001 | B24: AU032046 | C24: 5160011000 | D24: Business development | E24: 21953.6 | F24: AUQ | G24: 45526 | H24: AP Accruals | I24: INV-0314-ADUBB01 | K24: Sponsorship Fee | L24: INV-0314 | M24: DUBBO NATIONAL RAM SALE ASSOC | Q24: =ABS(E24) -> 21953.6 | S24: Sponsorship | V24: =IF(T24="Y",E24,"")
A25: AU001 | B25: AU032046 | C25: 5160011000 | D25: Business development | E25: 21234.66 | F25: AUQ | G25: 45548 | H25: AP Accruals | I25: 00013174-AQUAL08 | K25: Dowerin FDs marquee and furnit | L25: 00013174 | M25: QUALITY EVENT HIRE PTY LTD | Q25: =ABS(E25) -> 21234.66 | S25: Hire - OK | V25: =IF(T25="Y",E25,"")
A26: AU001 | B26: AU032046 | C26: 5160011000 | D26: Business development | E26: 21116.75 | F26: AUQ | G26: 45548 | H26: AP Accruals | I26: 00013173-AQUAL08 | K26: Newdegate FDs marquee and furn | L26: 00013173 | M26: QUALITY EVENT HIRE PTY LTD | Q26: =ABS(E26) -> 21116.75 | S26: Hire - OK | V26: =IF(T26="Y",E26,"")
A27: AU001 | B27: AU032046 | C27: 5160011000 | D27: Business development | E27: 20536.57 | F27: AUQ | G27: 45384 | H27: AP Accruals | I27: 00013024-AQUAL08 | L27: 00013024 | M27: QUALITY EVENT HIRE PTY LTD | Q27: =ABS(E27) -> 20536.57 | V27: =IF(T27="Y",E27,"")
A28: AU001 | B28: AU032046 | C28: 5160011000 | D28: Business development | E28: 19209.4 | F28: AUQ | G28: 45447 | H28: AP Accruals | I28: INV-9289-AAUSV01 | L28: INV-9289 | M28: AUSVEG LTD | Q28: =ABS(E28) -> 19209.4 | V28: =IF(T28="Y",E28,"")
A29: AU001 | B29: AU032046 | C29: 5160011000 | D29: Business development | E29: 19208.1 | F29: AUQ | G29: 45580 | H29: AP Accruals | I29: 00013204-AQUAL08 | K29: Marquee and furniture Speed (M | L29: 00013204 | M29: QUALITY EVENT HIRE PTY LTD | Q29: =ABS(E29) -> 19208.1 | V29: =IF(T29="Y",E29,"")
A30: AU001 | B30: AU032046 | C30: 5160011000 | D30: Business development | E30: 18606.96 | F30: AUQ | G30: 45538 | H30: AP Accruals | I30: 00013130-AQUAL08 | K30: Mingenew marquee & furniture | L30: 00013130 | M30: QUALITY EVENT HIRE PTY LTD | Q30: =ABS(E30) -> 18606.96 | V30: =IF(T30="Y",E30,"")
A31: AU001 | B31: AU032046 | C31: 5160011000 | D31: Business development | E31: 17727.53 | F31: AUQ | G31: 45425 | H31: AP Accruals | I31: INV-4990/64-ASOLU01 | K31: Q2 truck events production fee | L31: INV-4990/64 | M31: SOLUTION ENTERTAINMENT | Q31: =ABS(E31) -> 17727.53 | V31: =IF(T31="Y",E31,"")
A32: AU001 | B32: AU032046 | C32: 5160011000 | D32: Business development | E32: 17727.53 | F32: AUQ | G32: 45601 | H32: AP Accruals | I32: INV-4990/71-ASOLU01 | K32: Truck event activation Colbo H | L32: INV-4990/71 | M32: SOLUTION ENTERTAINMENT | Q32: =ABS(E32) -> 17727.53 | V32: =IF(T32="Y",E32,"")
A33: AU001 | B33: AU032046 | C33: 5160011000 | D33: Business development | E33: 17727.53 | F33: AUQ | G33: 45601 | H33: AP Accruals | I33: INV-4990/71-ASOLU01 | K33: Truck event Goulburn & Sarah W | L33: INV-4990/71 | M33: SOLUTION ENTERTAINMENT | Q33: =ABS(E33) -> 17727.53 | V33: =IF(T33="Y",E33,"")
A34: AU001 | B34: AU032046 | C34: 5160011000 | D34: Business development | E34: 16465.2 | F34: AUQ | G34: 45538 | H34: AP Accruals | I34: INV-10853-ANUFF00 | K34: Nuffield Australia Conference | L34: INV-10853 | M34: NUFFIELD AUSTRALIA | Q34: =ABS(E34) -> 16465.2 | V34: =IF(T34="Y",E34,"")
A35: AU001 | B35: AU032046 | C35: 5160011000 | D35: Business development | E35: 16465.2 | F35: AUQ | G35: 45629 | H35: AP Accruals | I35: 00008603-ANORT04 | K35: 2025 NTCA Conference Sponsorsh | L35: 00008603 | M35: NT CATTLEMENS ASSOCIATION INC | Q35: =ABS(E35) -> 16465.2 | V35: =IF(T35="Y",E35,"")
A36: AU001 | B36: AU032046 | C36: 5160011000 | D36: Business development | E36: 16112.73 | F36: AUQ | G36: 45629 | H36: AP Accruals | I36: PPB3282A-APORT07 | K36: pop up marquee x 7 QLD | L36: PPB3282A | M36: PORTABLE POP UP MARQUEES | Q36: =ABS(E36) -> 16112.73 | S36: Capital - these have been purchased | V36: =IF(T36="Y",E36,"") | AD36: =Q36 -> 16112.73
A37: AU001 | B37: AU032046 | C37: 5160011000 | D37: Business development | E37: 15567.1 | F37: AUQ | G37: 45414 | H37: AP Accruals | I37: INV-0626-AQFEE00 | L37: INV-0626 | M37: QFE EVENTS PTY LTD | Q37: =ABS(E37) -> 15567.1 | V37: =IF(T37="Y",E37,"")
A38: AU001 | B38: AU032046 | C38: 5160011000 | D38: Business development | E38: 15411.43 | F38: AUQ | G38: 45430 | H38: AP Accruals | I38: INV-1756-AROCK02 | K38: Catering Beef Australia Breakf | L38: INV-1756 | M38: ROCKY SPORTS CLUB LIMITED | Q38: =ABS(E38) -> 15411.43 | S38: Catering - sustenance for event OK | V38: =IF(T38="Y",E38,"")
A39: AU001 | B39: AU032046 | C39: 5160011000 | D39: Business development | E39: 14850.09 | F39: AUQ | G39: 45434 | H39: AP Accruals | I39: 00013074-AQUAL08 | K39: Agfest marquee & furniture | L39: 00013074 | M39: QUALITY EVENT HIRE PTY LTD | Q39: =ABS(E39) -> 14850.09 | V39: =IF(T39="Y",E39,"")
A40: AU001 | B40: AU032046 | C40: 5160011000 | D40: Business development | E40: 14827.36 | F40: AUQ | G40: 45547 | H40: AP Accruals | I40: 00013146-AQUAL08 | K40: Ag Quip marquee and furniture | L40: 00013146 | M40: QUALITY EVENT HIRE PTY LTD | Q40: =ABS(E40) -> 14827.36 | V40: =IF(T40="Y",E40,"")
A41: AU001 | B41: AU032046 | C41: 5160011000 | D41: Business development | E41: 14665 | F41: AUQ | G41: 45429 | H41: AP Accruals | I41: 00001920-AMADD00 | K41: Videography, photography, and | L41: 00001920 | M41: MAD DOG PRODUCTIONS PTY LTD | Q41: =ABS(E41) -> 14665 | V41: =IF(T41="Y",E41,"")
A42: AU001 | B42: AU032046 | C42: 5160011000 | D42: Business development | E42: 14469.42 | F42: AUQ | G42: 45637 | H42: AP Accruals | I42: 2668-ASOUT32 | K42: SEPWA Sponsorship Agreement - | L42: 2668 | M42: SOUTH EAST PREMIUM WHEAT GROWERS ASS | Q42: =ABS(E42) -> 14469.42 | V42: =IF(T42="Y",E42,"")
A43: AU001 | B43: AU032046 | C43: 5160011000 | D43: Business development | E43: 14244.88 | F43: AUQ | G43: 45384 | H43: AP Accruals | I43: 2357-ALIEB00 | K43: WA Marketing: Diamond Partners | L43: 2357 | M43: THE LIEBE GROUP | Q43: =ABS(E43) -> 14244.88 | V43: =IF(T43="Y",E43,"")
A44: AU001 | B44: AU032046 | C44: 5160011000 | D44: Business development | E44: 12074.48 | F44: AUQ | G44: 45505 | H44: AP Accruals | I44: IN153448-AROYA10 | K44: Feature Breed 2024 RAS | L44: IN153448 | M44: ROYAL AGRICULTURAL & HORTICULTURAL | Q44: =ABS(E44) -> 12074.48 | V44: =IF(T44="Y",E44,"")
A45: AU001 | B45: AU032046 | C45: 5160011000 | D45: Business development | E45: 11520.12 | F45: AUQ | G45: 45629 | H45: AP Accruals | I45: PPB3282B-APORT07 | K45: Pop up marquee x 5 VICTAS | L45: PPB3282B | M45: PORTABLE POP UP MARQUEES | Q45: =ABS(E45) -> 11520.12 | S45: Capital - these have been purchased | V45: =IF(T45="Y",E45,"") | AD45: =Q45 -> 11520.12
A46: AU001 | B46: AU032046 | C46: 5160011000 | D46: Business development | E46: 10976.8 | F46: AUQ | G46: 45392 | H46: AP Accruals | I46: 3257-AFACE01 | K46: WA Marketing: 2024 Sponsorship | L46: 3257 | M46: FACEY GROUP INC | Q46: =ABS(E46) -> 10976.8 | V46: =IF(T46="Y",E46,"")
A47: AU001 | B47: AU032046 | C47: 5160011000 | D47: Business development | E47: 10976.8 | F47: AUQ | G47: 45456 | H47: AP Accruals | I47: 5837-AMING03 | L47: 5837 | M47: MINGENEW IRWIN GROUP | Q47: =ABS(E47) -> 10976.8 | V47: =IF(T47="Y",E47,"")
A48: AU001 | B48: AU032046 | C48: 5160011000 | D48: Business development | E48: 10976.8 | F48: AUQ | G48: 45516 | H48: AP Accruals | I48: 202401-AGREA04 | K48: WA Sponsorship of WA Sheep Exp | L48: 202401 | M48: GREAT SOUTHERN MERINO SHEEPBREEDERS | Q48: =ABS(E48) -> 10976.8 | V48: =IF(T48="Y",E48,"")
A49: AU001 | B49: AU032046 | C49: 5160011000 | D49: Business development | E49: 10976.8 | F49: AUQ | G49: 45635 | H49: AP Accruals | I49: 0150000566-AWEST14 | K49: WA Marketing: WMG Sponsorship | L49: 0150000566 | M49: WEST MIDLANDS GROUP | Q49: =ABS(E49) -> 10976.8 | V49: =IF(T49="Y",E49,"")
A50: AU001 | B50: AU032046 | C50: 5160011000 | D50: Business development | E50: 10793.3 | F50: AUQ | G50: 45413 | H50: AP Accruals | I50: INV-4990/60-ASOLU01 | K50: extra driver cost | L50: INV-4990/60 | M50: SOLUTION ENTERTAINMENT | Q50: =ABS(E50) -> 10793.3 | V50: =IF(T50="Y",E50,"")
A51: AU001 | B51: AU032046 | C51: 5160011000 | D51: Business development | E51: 10373.08 | F51: AUQ | G51: 45609 | H51: AP Accruals | I51: 2677-ATURN01 | K51: Rabo Branded Lanyards | L51: 2677 | M51: TURNKEY PROMOTIONS | Q51: =ABS(E51) -> 10373.08 | V51: =IF(T51="Y",E51,"")
A52: AU052 | B52: AU032046 | C52: 5160011000 | D52: Business development | E52: 10318.19 | F52: AUQ | G52: 45402 | H52: AP Accruals | I52: INV-4990/61-ASOLU01 | K52: Mackay &amp; Emerald | L52: INV-4990/61 | M52: SOLUTION ENTERTAINMENT | Q52: =ABS(E52) -> 10318.19 | V52: =IF(T52="Y",E52,"")
A53: AU001 | B53: AU032046 | C53: 5160011000 | D53: Business development | E53: 10178.49 | F53: AUQ | G53: 45446 | H53: AP Accruals | I53: INV-0141-ANAME00 | J53: Meals for 20 Year Anniversary | L53: INV-0141 | M53: THE NAME YOUR ESCAPE TRUST | Q53: =ABS(E53) -> 10178.49 | S53: ME | T53: Y | U53: =B53 -> AU032046 | V53: =IF(T53="Y",E53,"") -> 10178.49
A54: AU001 | B54: AU032046 | C54: 5160011000 | D54: Business development | E54: 9879.12 | F54: AUQ | G54: 45609 | H54: AP Accruals | I54: INV-0059-ACLAR29 | K54: Sponsoring of Clarence Canegro | L54: INV-0059 | M54: CLARENCE CANE GROWERS ASSOCIATION INC | Q54: =ABS(E54) -> 9879.12 | V54: =IF(T54="Y",E54,"")
A55: AU001 | B55: AU032046 | C55: 5160011000 | D55: Business development | E55: 9252.1 | F55: AUQ | G55: 45391 | H55: AP Accruals | I55: 17705-ASWAN01 | K55: Wagin marquee and furniture | L55: 17705 | M55: SWAN EVENT HIRE | Q55: =ABS(E55) -> 9252.1 | V55: =IF(T55="Y",E55,"")
A56: AU052 | B56: AU032046 | C56: 5160011000 | D56: Business development | E56: 9000 | F56: AUQ | G56: 45618 | H56: CCMS | I56: TierneyA-Contributions & Club | J56: Dairies - 50% of order | O56: GRAZIHER PUBLISHING | Q56: =ABS(E56) -> 9000 | V56: =IF(T56="Y",E56,"")
A57: AU052 | B57: AU032046 | C57: 5160011000 | D57: Business development | E57: 9000 | F57: AUQ | G57: 45618 | H57: CCMS | I57: TierneyA-Contributions & Club | J57: Diaries - 50% of order | O57: GRAZIHER PUBLISHING | Q57: =ABS(E57) -> 9000 | V57: =IF(T57="Y",E57,"")
A58: AU001 | B58: AU032046 | C58: 5160011000 | D58: Business development | E58: 8863.77 | F58: AUQ | G58: 45425 | H58: AP Accruals | I58: INV-4990/64-ASOLU01 | K58: Event Productin fee - Casino | L58: INV-4990/64 | M58: SOLUTION ENTERTAINMENT | Q58: =ABS(E58) -> 8863.77 | V58: =IF(T58="Y",E58,"")
A59: AU001 | B59: AU032046 | C59: 5160011000 | D59: Business development | E59: 8863.77 | F59: AUQ | G59: 45425 | H59: AP Accruals | I59: INV-4990/64-ASOLU01 | K59: Event Productin fee - Cotton C | L59: INV-4990/64 | M59: SOLUTION ENTERTAINMENT | Q59: =ABS(E59) -> 8863.77 | V59: =IF(T59="Y",E59,"")
A60: AU001 | B60: AU032046 | C60: 5160011000 | D60: Business development | E60: 8863.77 | F60: AUQ | G60: 45425 | H60: AP Accruals | I60: INV-4990/64-ASOLU01 | K60: Event Productin fee - Moree | L60: INV-4990/64 | M60: SOLUTION ENTERTAINMENT | Q60: =ABS(E60) -> 8863.77 | V60: =IF(T60="Y",E60,"")
A61: AU001 | B61: AU032046 | C61: 5160011000 | D61: Business development | E61: 8863.77 | F61: AUQ | G61: 45447 | H61: AP Accruals | I61: INV-4990/65-ASOLU01 | K61: Event activation (Henty) | L61: INV-4990/65 | M61: SOLUTION ENTERTAINMENT | Q61: =ABS(E61) -> 8863.77 | V61: =IF(T61="Y",E61,"")
A62: AU001 | B62: AU032046 | C62: 5160011000 | D62: Business development | E62: 8863.77 | F62: AUQ | G62: 45447 | H62: AP Accruals | I62: INV-4990/65-ASOLU01 | K62: Event activation (St George) | L62: INV-4990/65 | M62: SOLUTION ENTERTAINMENT | Q62: =ABS(E62) -> 8863.77 | V62: =IF(T62="Y",E62,"")
A63: AU001 | B63: AU032046 | C63: 5160011000 | D63: Business development | E63: 8863.77 | F63: AUQ | G63: 45601 | H63: AP Accruals | I63: INV-4990/71-ASOLU01 | K63: Truck event SE Field days | L63: INV-4990/71 | M63: SOLUTION ENTERTAINMENT | Q63: =ABS(E63) -> 8863.77 | V63: =IF(T63="Y",E63,"")
A64: AU001 | B64: AU032046 | C64: 5160011000 | D64: Business development | E64: 8781.44 | F64: AUQ | G64: 45636 | H64: AP Accruals | I64: INV-1740-ASOUT15 | K64: WA Marketing: Southern Dirt Go | L64: INV-1740 | M64: SOUTHERN DIRT INCORPORATED | Q64: =ABS(E64) -> 8781.44 | V64: =IF(T64="Y",E64,"")
A65: AU001 | B65: AU032046 | C65: 5160011000 | D65: Business development | E65: 8766.08 | F65: AUQ | G65: 45425 | H65: AP Accruals | I65: 23242-APINI03 | K65: Red Meats Sponsorship | L65: 23242 | M65: PINION ADVISORY | Q65: =ABS(E65) -> 8766.08 | V65: =IF(T65="Y",E65,"")
A66: AU001 | B66: AU032046 | C66: 5160011000 | D66: Business development | E66: 8672.66 | F66: AUQ | G66: 45394 | H66: AP Accruals | I66: 00013036-AQUAL08 | K66: Farmworld marquee and furnitur | L66: 00013036 | M66: QUALITY EVENT HIRE PTY LTD | Q66: =ABS(E66) -> 8672.66 | V66: =IF(T66="Y",E66,"")
A67: AU001 | B67: AU032046 | C67: 5160011000 | D67: Business development | E67: 8648.97 | F67: AUQ | G67: 45425 | H67: AP Accruals | I67: 00013073-AQUAL08 | K67: Beef cutom made wall and print | L67: 00013073 | M67: QUALITY EVENT HIRE PTY LTD | Q67: =ABS(E67) -> 8648.97 | V67: =IF(T67="Y",E67,"")
A68: AU052 | B68: AU032046 | C68: 5160011000 | D68: Business development | E68: 8442.04 | F68: AUQ | G68: 45618 | H68: CCMS | I68: PaulgerA-Offshore Meals & Lodg | J68: Food Expense - Atherton 20 year anniversary Function | O68: TINAROO LAKE RESORT | Q68: =ABS(E68) -> 8442.04 | S68: ME | T68: Y | U68: =B68 -> AU032046 | V68: =IF(T68="Y",E68,"") -> 8442.04
A69: AU001 | B69: AU032046 | C69: 5160011000 | D69: Business development | E69: 8062.46 | F69: AUQ | G69: 45636 | H69: AP Accruals | I69: INV-0008-ABORD00 | K69: Frances Truck Event - Catering | L69: INV-0008 | M69: BORDER DISTRICTS FOOTBALL CLUB | Q69: =ABS(E69) -> 8062.46 | V69: =IF(T69="Y",E69,"")
A70: AU001 | B70: AU032046 | C70: 5160011000 | D70: Business development | E70: 7983.13 | F70: AUQ | G70: 45568 | H70: AP Accruals | I70: 65-AANGU01 | K70: World Angus Forum 8 x tickets | L70: 65 | M70: THE ANGUS SOCIETY OF AUSTRALIA | Q70: =ABS(E70) -> 7983.13 | S70: Accept this is a training seminar - industry insights, tech, etc. | V70: =IF(T70="Y",E70,"")
A71: AU052 | B71: AU032046 | C71: 5160011000 | D71: Business development | E71: 7880 | F71: AUQ | G71: 45391 | H71: AP Accruals | I71: 00202431-AMBCF00 | J71: Kadina 20 years event Catering | L71: 00202431 | M71: MBC FOODS | Q71: =ABS(E71) -> 7880 | S71: ME | T71: Y | U71: =B71 -> AU032046 | V71: =IF(T71="Y",E71,"") -> 7880
A72: AU001 | B72: AU032046 | C72: 5160011000 | D72: Business development | E72: 7683.76 | F72: AUQ | G72: 45614 | H72: AP Accruals | I72: 35-AAUST23 | K72: ADC2025 Rabo registration | L72: 35 | M72: AUSTRALIAN DAIRY CONFERENCE | Q72: =ABS(E72) -> 7683.76 | V72: =IF(T72="Y",E72,"")
A73: AU001 | B73: AU032046 | C73: 5160011000 | D73: Business development | E73: 7471.09 | F73: AUQ | G73: 45394 | H73: AP Accruals | I73: 1949-ASHAN05 | K73: Shannon Consulting Sponsorship | L73: 1949 | M73: SHANNON FARM CONSULTING | Q73: =ABS(E73) -> 7471.09 | V73: =IF(T73="Y",E73,"")
A74: AU001 | B74: AU032046 | C74: 5160011000 | D74: Business development | E74: 7258.53 | F74: AUQ | G74: 45394 | H74: AP Accruals | I74: 00013048-AQUAL08 | K74: East Gippsland Field Days marq | L74: 00013048 | M74: QUALITY EVENT HIRE PTY LTD | Q74: =ABS(E74) -> 7258.53 | V74: =IF(T74="Y",E74,"")
A75: AU001 | B75: AU032046 | C75: 5160011000 | D75: Business development | E75: 7045.11 | F75: AUQ | G75: 45531 | H75: AP Accruals | I75: INV-1442-AEMER09 | K75: NQNT Marketing expense, Emeral | L75: INV-1442 | M75: EMERALD STATE HIGH SCHOOL P & C ASSOC | Q75: =ABS(E75) -> 7045.11 | V75: =IF(T75="Y",E75,"")
A76: AU001 | B76: AU032046 | C76: 5160011000 | D76: Business development | E76: 6822.45 | F76: AUQ | G76: 45531 | H76: AP Accruals | I76: 1407-02/08/24-AMAYF03 | K76: NQNT Marketing expense, Emeral | L76: 1407-02/08/24 | M76: MAYFAIR RIDGE TAVERN | Q76: =ABS(E76) -> 6822.45 | V76: =IF(T76="Y",E76,"")
A77: AU001 | B77: AU032046 | C77: 5160011000 | D77: Business development | E77: 6750 | F77: AUQ | G77: 45637 | H77: AP Accruals | I77: RABO-06/12/24-ABROO06 | K77: Catering for Moree RaboTruck C | L77: RABO-06/12/24 | M77: BROOKER EQUITY GROUP | Q77: =ABS(E77) -> 6750 | S77: RaboTruck event - accept sustenance and for clients | V77: =IF(T77="Y",E77,"")
A78: AU001 | B78: AU032066 | C78: 5160011000 | D78: Business development | E78: 6541.32 | F78: AUQ | G78: 45449 | H78: AP Accruals | I78: 0046-AFATF00 | L78: 0046 | M78: FAT FARMERS RURAL HEALTH INITIATIVE | Q78: =ABS(E78) -> 6541.32 | V78: =IF(T78="Y",E78,"")
A79: AU001 | B79: AU032046 | C79: 5160011000 | D79: Business development | E79: 6233.72 | F79: AUQ | G79: 45413 | H79: AP Accruals | I79: INV-4990/60-ASOLU01 | K79: isolated event in SA Diesel (W | L79: INV-4990/60 | M79: SOLUTION ENTERTAINMENT | Q79: =ABS(E79) -> 6233.72 | V79: =IF(T79="Y",E79,"")
A80: AU001 | B80: AU032046 | C80: 5160011000 | D80: Business development | E80: 6000 | F80: AUQ | G80: 45531 | H80: AP Accruals | I80: RABO-23/07/24-AAUST108 | K80: ACAJ Sponsorship Fee | L80: RABO-23/07/24 | M80: AUSTRALIAN COUNCIL OF AGRICULTURAL | Q80: =ABS(E80) -> 6000 | V80: =IF(T80="Y",E80,"")
A81: AU001 | B81: AU032046 | C81: 5160011000 | D81: Business development | E81: 6000 | F81: AUQ | G81: 45597 | H81: AP Accruals | I81: 08/2024-AAUST108 | K81: ACAJ Star Prize Award | L81: 08/2024 | M81: AUSTRALIAN COUNCIL OF AGRICULTURAL | Q81: =ABS(E81) -> 6000 | V81: =IF(T81="Y",E81,"")
A82: AU001 | B82: AU032046 | C82: 5160011000 | D82: Business development | E82: 5966.99 | F82: AUQ | G82: 45453 | H82: AP Accruals | I82: INV-0062-AHOLB03 | L82: INV-0062 | M82: HOLBROOK HOTEL MOTEL PTY LTD | Q82: =ABS(E82) -> 5966.99 | V82: =IF(T82="Y",E82,"")
A83: AU001 | B83: AU032046 | C83: 5160011000 | D83: Business development | E83: 5917.1 | F83: AUQ | G83: 45387 | H83: AP Accruals | I83: 2243-ATURN01 | K83: 2000 x Rabobank branded lanyar | L83: 2243 | M83: TURNKEY PROMOTIONS | Q83: =ABS(E83) -> 5917.1 | V83: =IF(T83="Y",E83,"")
A84: AU001 | B84: AU032046 | C84: 5160011000 | D84: Business development | E84: 5488.4 | F84: AUQ | G84: 45456 | H84: AP Accruals | I84: 2024-59-ANORT37 | L84: 2024-59 | M84: NORTHERN AGRI GROUP | Q84: =ABS(E84) -> 5488.4 | V84: =IF(T84="Y",E84,"")
A85: AU001 | B85: AU032046 | C85: 5160011000 | D85: Business development | E85: 5488.4 | F85: AUQ | G85: 45544 | H85: AP Accruals | I85: INV-2743-ASOUT00 | K85: Southern Farming Systems Spons | L85: INV-2743 | M85: SOUTHERN FARMING SYSTEMS LTD | Q85: =ABS(E85) -> 5488.4 | V85: =IF(T85="Y",E85,"")
A86: AU001 | B86: AU032046 | C86: 5160011000 | D86: Business development | E86: 5488.4 | F86: AUQ | G86: 45635 | H86: AP Accruals | I86: INV-0103-AFITZ02 | K86: WA Marketing: FBG Sponsorship | L86: INV-0103 | M86: FITZGERALD BIOSPHERE GROUP INC | Q86: =ABS(E86) -> 5488.4 | V86: =IF(T86="Y",E86,"")
A87: AU001 | B87: AU032046 | C87: 5160011000 | D87: Business development | E87: 5478.8 | F87: AUQ | G87: 45387 | H87: AP Accruals | I87: 1576-APERE02 | K87: PPS Sponsorship Agreement - 20 | L87: 1576 | M87: PERENNIAL PASTURE SYSTEMS | Q87: =ABS(E87) -> 5478.8 | V87: =IF(T87="Y",E87,"")
A88: AU052 | B88: AU032046 | C88: 5160011000 | D88: Business development | E88: 5430 | F88: AUQ | G88: 45468 | H88: CCMS | I88: MCAULAYG-Offshore Meals & Lodg | J88: Catering Mrquee Beef | O88: FRESH READY MEALS | Q88: =ABS(E88) -> 5430 | V88: =IF(T88="Y",E88,"")
A89: AU001 | B89: AU032046 | C89: 5160011000 | D89: Business development | E89: -5396.65 | F89: AUQ | G89: 45419 | H89: AP Accruals | I89: INV-4990/60-ASOLU01 | K89: isolated event in SA Diesel (W | L89: INV-4990/60 | M89: SOLUTION ENTERTAINMENT | Q89: =ABS(E89) -> 5396.65 | V89: =IF(T89="Y",E89,"")
A90: AU001 | B90: AU032046 | C90: 5160011000 | D90: Business development | E90: 5310.03 | F90: AUQ | G90: 45636 | H90: AP Accruals | I90: 113947-ACORB00 | K90: Travel Luggage Tags | L90: 113947 | M90: CORBAN & BLAIR | Q90: =ABS(E90) -> 5310.03 | V90: =IF(T90="Y",E90,"")
A91: AU001 | B91: AU032046 | C91: 5160011000 | D91: Business development | E91: 5282.85 | F91: AUQ | G91: 45428 | H91: AP Accruals | I91: 10621-2-ACLYD00 | K91: Food and drinks for RaboTruck | L91: 10621-2 | M91: CLYDESDALE MOTEL AND STEAKHOUSE | Q91: =ABS(E91) -> 5282.85 | S91: RaboTruck event - accept sustenance and for clients | V91: =IF(T91="Y",E91,"")
A92: AU001 | B92: AU032046 | C92: 5160011000 | D92: Business development | E92: 5213.98 | F92: AUQ | G92: 45510 | H92: AP Accruals | I92: 657309-AMALT01 | K92: LambEx Networking Event | L92: 657309 | M92: MALT SHOVEL TAPHOUSE ADELAIDE | Q92: =ABS(E92) -> 5213.98 | V92: =IF(T92="Y",E92,"")
A93: AU052 | B93: AU032046 | C93: 5160011000 | D93: Business development | E93: 5159.1 | F93: AUQ | G93: 45402 | H93: AP Accruals | I93: INV-4990/61-ASOLU01 | K93: Casino | L93: INV-4990/61 | M93: SOLUTION ENTERTAINMENT | Q93: =ABS(E93) -> 5159.1 | V93: =IF(T93="Y",E93,"")
A94: AU052 | B94: AU032046 | C94: 5160011000 | D94: Business development | E94: 5159.1 | F94: AUQ | G94: 45402 | H94: AP Accruals | I94: INV-4990/61-ASOLU01 | K94: Cotton conference | L94: INV-4990/61 | M94: SOLUTION ENTERTAINMENT | Q94: =ABS(E94) -> 5159.1 | V94: =IF(T94="Y",E94,"")
A95: AU052 | B95: AU032046 | C95: 5160011000 | D95: Business development | E95: 5159.1 | F95: AUQ | G95: 45402 | H95: AP Accruals | I95: INV-4990/61-ASOLU01 | K95: Moree | L95: INV-4990/61 | M95: SOLUTION ENTERTAINMENT | Q95: =ABS(E95) -> 5159.1 | V95: =IF(T95="Y",E95,"")
A96: AU001 | B96: AU032046 | C96: 5160011000 | D96: Business development | E96: 5125 | F96: AUQ | G96: 45384 | H96: AP Accruals | I96: SP24038-AWEEW05 | K96: Sponsoring , MAC , Spring Plai | L96: SP24038 | M96: WEE WAA VOLENTEER SUPPORT GROUP | Q96: =ABS(E96) -> 5125 | V96: =IF(T96="Y",E96,"")
A97: AU001 | B97: AU032046 | C97: 5160011000 | D97: Business development | E97: 5120.08 | F97: AUQ | G97: 45635 | H97: AP Accruals | I97: 00013275-AQUAL08 | K97: marquee skins x 9 | L97: 00013275 | M97: QUALITY EVENT HIRE PTY LTD | Q97: =ABS(E97) -> 5120.08 | V97: =IF(T97="Y",E97,"")
A98: AU001 | B98: AU032046 | C98: 5160011000 | D98: Business development | E98: 5044.84 | F98: AUQ | G98: 45597 | H98: AP Accruals | I98: 440-ASPEC00 | J98: Catering Horsham 21 Year Celeb | L98: 440 | M98: THE SPECKLED DUCK | Q98: =ABS(E98) -> 5044.84 | S98: ME | T98: Y | U98: =B98 -> AU032046 | V98: =IF(T98="Y",E98,"") -> 5044.84
A99: AU001 | B99: AU032046 | C99: 5160011000 | D99: Business development | E99: 5026.58 | F99: AUQ | G99: 45629 | H99: AP Accruals | I99: INV-195087-AMCDO01 | K99: Rabo Orange Shirts - Aust Dair | L99: INV-195087 | M99: MCDOWALL STREET TRADERS PTY LTD | Q99: =ABS(E99) -> 5026.58 | V99: =IF(T99="Y",E99,"")
A100: AU001 | B100: AU032046 | C100: 5160011000 | D100: Business development | E100: 5000 | F100: AUQ | G100: 45391 | H100: AP Accruals | I100: RABO-21/03/24-AMOOR00 | K100: WA Marketing - 2024 Sponsorshi | L100: RABO-21/03/24 | M100: MOORA MILING PASTURE IMPROVEMENT GROUP | Q100: =ABS(E100) -> 5000 | V100: =IF(T100="Y",E100,"")
...

Sheet Public relations
A1: Account Number | C1: =Summary!A17 -> 5160999000
A2: Account Name | C2: =Summary!B17 -> Public relations | F2: Notes:
A3: GL Total | C3: 87806.65 | F3: No entertainment expenses included and all tax deductible | AC3: AU001 | AD3: =SUMIF($A$8:$A$20000,"AU001",AD8:AD20000) -> 0 | AE3: =SUMIF($A$8:$A$20000,"AU001",AE8:AE20000) -> 0
A4: Per TB | C4: =SUM(E:E) -> 87806.65 | T4: AU001 | V4: =SUMIF($A$10:$A$23974,"AU001",V9:V23973) -> 230.77 | AC4: AU052 | AD4: =SUMIF($A$8:$A$20000,"AU052",AD8:AD20000) -> 0 | AE4: =SUMIF($A$8:$A$20000,"AU052",AE8:AE20000) -> 0
A5: Variance | C5: =C3-C4 -> 0 | T5: AU052 | V5: =SUMIF($A$10:$A$23975,"AU052",V9:V23974) -> 9.33
AD6: Income tax purposes
A7: BUSINESS_UNIT_CODE | B7: OPERATING_UNIT_CODE | C7: ACCOUNT_CODE | D7: DESCRIPTION | E7: BASE_AMOUNT | F7: BASE_CURRENCY_CODE | G7: JOURNAL_DATE | H7: DESCR | I7: LINE_DESCR | J7: PURPOSE | K7: INVOICE_DESCR | L7: INVOICE_ID | M7: VENDOR_NAME | N7: EMPLOYEE_NAME | O7: CHARGE_DESCRIPTION | Q7: ABS | R7: Search Terms | S7: Tax Description | T7: ME? Y/N | U7: OU | V7: ME $ | W7: Not ME but other type of FB Y/N | X7: Not ME but other type of FB ==> $ | Y7: Nets to Nil in GL accts | Z7: s58P M&I or Bus Exp - notFB | AA7: ME | AB7: Car FB - addn op costs | AC7: CP Exp FB | AD7: Capital expenditure | AE7: No FBT and not ded | AF7: Additional Comments
A8: AU052 | B8: AU032045 | C8: 5160999000 | D8: Public relations | E8: 891 | F8: AUQ | G8: 45387 | H8: CCMS | I8: BANKSW-Contributions & Club Me | J8: Farming Ahead Subscription | O8: KONDININ INFO | Q8: =ABS(E8) -> 891 | S8: subscription - OK
A9: AU052 | B9: AU032045 | C9: 5160999000 | D9: Public relations | E9: 9.33 | F9: AUQ | G9: 45387 | H9: CCMS | I9: BANKSW-Offshore Meals & Lodgin | J9: Coffee with Savings.com Brooke Cooper | O9: MAS Espresso | Q9: =ABS(E9) -> 9.33 | S9: ME | T9: Y | U9: =B9 -> AU032045 | V9: =E9 -> 9.33
A10: AU052 | B10: AU032045 | C10: 5160999000 | D10: Public relations | E10: 457.36 | F10: AUQ | G10: 45394 | H10: CCMS | I10: BattenS-Default Licensee Merch | J10: Media Room green screen backdrop | O10: BACKDROPSOURCE AU | Q10: =ABS(E10) -> 457.36 | S10: subscription - OK
A11: AU052 | B11: AU032045 | C11: 5160999000 | D11: Public relations | E11: 181.02 | F11: AUQ | G11: 45426 | H11: CCMS | I11: BattenS-Default Licensee Merch | J11: Audio Music for internal videos x 10 | O11: ENVATO 68360304/2491170B28AF41761/27563644 | Q11: =ABS(E11) -> 181.02 | S11: subscription - OK
A12: AU052 | B12: AU032045 | C12: 5160999000 | D12: Public relations | E12: 177.27 | F12: AUQ | G12: 45436 | H12: CCMS | I12: BANKSW-Default Licensee Mercha | J12: ACM subscription | O12: web*qldcountrylife/STANDING AUTHORITY | Q12: =ABS(E12) -> 177.27 | S12: subscription - OK
A13: AU052 | B13: AU032045 | C13: 5160999000 | D13: Public relations | E13: 340.91 | F13: AUQ | G13: 45436 | H13: CCMS | I13: BANKSW-Default Licensee Mercha | J13: Global Food Forum Registration | O13: TICKETS*THE AUSTRA/krzn2n80 | Q13: =ABS(E13) -> 340.91 | S13: subscription - OK
A14: AU052 | B14: AU032045 | C14: 5160999000 | D14: Public relations | E14: 79.2 | F14: AUQ | G14: 45436 | H14: CCMS | I14: BANKSW-Entertainment Expense | J14: Beef 2024 - Entry Pass | O14: BEEFAUS* BEEFAUS24 TIX | Q14: =ABS(E14) -> 79.2 | S14: subscription - OK
A15: AU052 | B15: AU032045 | C15: 5160999000 | D15: Public relations | E15: 109.1 | F15: AUQ | G15: 45446 | H15: CCMS | I15: SHAWD-Default Licensee Merchan | J15: monthly Aus subscription | O15: NEWS PTY LIMITED | Q15: =ABS(E15) -> 109.1 | S15: subscription - OK
A16: AU052 | B16: AU032045 | C16: 5160999000 | D16: Public relations | E16: 54.55 | F16: AUQ | G16: 45446 | H16: CCMS | I16: SHAWD-Default Licensee Merchan | J16: monthly online Aus subscription | O16: NEWS PTY LIMITED | Q16: =ABS(E16) -> 54.55 | S16: subscription - OK
A17: AU052 | B17: AU032045 | C17: 5160999000 | D17: Public relations | E17: 43.65 | F17: AUQ | G17: 45446 | H17: CCMS | I17: SHAWD-Default Licensee Merchan | J17: monthly online Telegraph subscription | O17: NEWS PTY LIMITED | Q17: =ABS(E17) -> 43.65 | S17: subscription - OK
A18: AU001 | B18: AU032045 | C18: 5160999000 | D18: Public relations | E18: 11300.44 | F18: AUQ | G18: 45449 | H18: AP Accruals | I18: INV-18593-ASTEE00 | K18: Streem | L18: INV-18593 | O18: STREEM PTY LTD | Q18: =ABS(E18) -> 11300.44 | S18: subscription - OK
A19: AU052 | B19: AU032045 | C19: 5160999000 | D19: Public relations | E19: 177.27 | F19: AUQ | G19: 45454 | H19: CCMS | I19: SHAWD-Default Licensee Merchan | J19: annual Farm Online subscription | O19: web*farmonline/STANDING AUTHORITY | Q19: =ABS(E19) -> 177.27 | S19: subscription - OK
A20: AU052 | B20: AU032045 | C20: 5160999000 | D20: Public relations | E20: 54.55 | F20: AUQ | G20: 45454 | H20: CCMS | I20: SHAWD-Default Licensee Merchan | J20: monthly Aus subscription | O20: NEWS PTY LIMITED | Q20: =ABS(E20) -> 54.55 | S20: subscription - OK
A21: AU052 | B21: AU032045 | C21: 5160999000 | D21: Public relations | E21: 8.18 | F21: AUQ | G21: 45454 | H21: CCMS | I21: SHAWD-Other Personnel Expense | J21: Newspapers | O21: TARALGA GENERAL STORE | Q21: =ABS(E21) -> 8.18 | S21: subscription - OK
A22: AU001 | B22: AU032045 | C22: 5160999000 | D22: Public relations | E22: 1750 | F22: AUQ | G22: 45475 | H22: AP Accruals | I22: 03.24-AREBE03 | L22: 03.24 | Q22: =ABS(E22) -> 1750 | S22: subscription - OK
A23: AU052 | B23: AU032045 | C23: 5160999000 | D23: Public relations | E23: 209.09 | F23: AUQ | G23: 45539 | H23: CCMS | I23: SHAWD-Contributions & Club Mem | J23: annual online SMH subscription | O23: FAIRFAX SUBSCRIPTIONS/74564724204353116599668 | Q23: =ABS(E23) -> 209.09 | S23: subscription - OK
A24: AU052 | B24: AU032045 | C24: 5160999000 | D24: Public relations | E24: 109.1 | F24: AUQ | G24: 45539 | H24: CCMS | I24: SHAWD-Default Licensee Merchan | J24: monthly Aus subscription | O24: NEWS PTY LIMITED | Q24: =ABS(E24) -> 109.1 | S24: subscription - OK
A25: AU052 | B25: AU032045 | C25: 5160999000 | D25: Public relations | E25: 14.55 | F25: AUQ | G25: 45539 | H25: CCMS | I25: SHAWD-Default Licensee Merchan | J25: monthly online Telegraph/News.com subs | O25: NEWS PTY LIMITED | Q25: =ABS(E25) -> 14.55 | S25: subscription - OK
A26: AU052 | B26: AU032045 | C26: 5160999000 | D26: Public relations | E26: 14.55 | F26: AUQ | G26: 45539 | H26: CCMS | I26: SHAWD-Default Licensee Merchan | J26: monthly Telegraph/News Corp online subs | O26: NEWS PTY LIMITED | Q26: =ABS(E26) -> 14.55 | S26: subscription - OK
A27: AU001 | B27: AU032045 | C27: 5160999000 | D27: Public relations | E27: 11300.44 | F27: AUQ | G27: 45545 | H27: AP Accruals | I27: INV-19757-ASTEE00 | J27: Streem subscription | L27: INV-19757 | O27: STREEM PTY LTD | Q27: =ABS(E27) -> 11300.44 | S27: subscription - OK
A28: AU052 | B28: AU032045 | C28: 5160999000 | D28: Public relations | E28: 27.65 | F28: AUQ | G28: 45562 | H28: CCMS | I28: BANKSW-Default Licensee Mercha | J28: Telum Masterclass: AI Literacy | O28: EB *Masterclass AI Lit | Q28: =ABS(E28) -> 27.65 | S28: subscription - OK
A29: AU052 | B29: AU032045 | C29: 5160999000 | D29: Public relations | E29: 118.18 | F29: AUQ | G29: 45562 | H29: CCMS | I29: BANKSW-Other Personnel Expense | J29: Gen McAulay Flowers | O29: PERROTTS | Q29: =ABS(E29) -> 118.18 | S29: Accept - gift under $300
A30: AU001 | B30: AU032045 | C30: 5160999000 | D30: Public relations | E30: 1700 | F30: AUQ | G30: 45566 | H30: AP Accruals | I30: 05.24-AREBE03 | K30: RCS Q3 Media Releases | L30: 05.24 | Q30: =ABS(E30) -> 1700 | S30: subscription - OK
A31: AU052 | B31: AU032045 | C31: 5160999000 | D31: Public relations | E31: 54.55 | F31: AUQ | G31: 45567 | H31: CCMS | I31: SHAWD-Default Licensee Merchan | J31: monthly Aus subscription | O31: NEWS PTY LIMITED | Q31: =ABS(E31) -> 54.55 | S31: subscription - OK
A32: AU052 | B32: AU032045 | C32: 5160999000 | D32: Public relations | E32: 14.55 | F32: AUQ | G32: 45567 | H32: CCMS | I32: SHAWD-Default Licensee Merchan | J32: monthly Tele/News.com sub | O32: NEWS PTY LIMITED | Q32: =ABS(E32) -> 14.55 | S32: subscription - OK
A33: AU001 | B33: AU032045 | C33: 5160999000 | D33: Public relations | E33: 36139.57 | F33: AUQ | G33: 45569 | H33: AP Accruals | I33: MN2077532-AMEDI00 | J33: Medianet annual subscription | L33: MN2077532 | O33: MEDIANET AUSTRALIA PTY LTD | Q33: =ABS(E33) -> 36139.57 | S33: subscription - OK
A34: AU052 | B34: AU032045 | C34: 5160999000 | D34: Public relations | E34: 54.55 | F34: AUQ | G34: 45574 | H34: CCMS | I34: SHAWD-Default Licensee Merchan | J34: monthly online Aus subscription | O34: NEWS PTY LIMITED | Q34: =ABS(E34) -> 54.55 | S34: subscription - OK
A35: AU052 | B35: AU032045 | C35: 5160999000 | D35: Public relations | E35: 14.55 | F35: AUQ | G35: 45574 | H35: CCMS | I35: SHAWD-Default Licensee Merchan | J35: monthly Tele/News subscription | O35: NEWS PTY LIMITED | Q35: =ABS(E35) -> 14.55 | S35: subscription - OK
A36: AU052 | B36: AU032045 | C36: 5160999000 | D36: Public relations | E36: 645.44 | F36: AUQ | G36: 45596 | H36: CCMS | I36: SHAWD-Contributions & Club Mem | J36: Annual Bloomberg news subscription (billed in USD) | O36: BLOOMBERG* BB-2296-430 | Q36: =ABS(E36) -> 645.44 | S36: subscription - OK
A37: AU052 | B37: AU032045 | C37: 5160999000 | D37: Public relations | E37: 14.55 | F37: AUQ | G37: 45601 | H37: CCMS | I37: SHAWD-Default Licensee Merchan | J37: monthly online Telegraph subscription | O37: NEWS PTY LIMITED | Q37: =ABS(E37) -> 14.55 | S37: subscription - OK
A38: AU052 | B38: AU032045 | C38: 5160999000 | D38: Public relations | E38: 230.77 | F38: AUQ | G38: 45624 | H38: CCMS | I38: BANKSW-Contributions & Club Me | J38: Rural Press Club Lunch Tickets | O38: RURAL PRESS CLUB QLD | Q38: =ABS(E38) -> 230.77 | S38: ME | T38: Y | U38: =B38 -> AU032045 | V38: =E38 -> 230.77
A39: AU001 | B39: AU032045 | C39: 5160999000 | D39: Public relations | E39: 11300.44 | F39: AUQ | G39: 45629 | H39: AP Accruals | I39: INV-20881-ASTEE00 | J39: Streem subcription | L39: INV-20881 | M39: STREEM PTY LTD | Q39: =ABS(E39) -> 11300.44 | S39: subscription - OK
A40: AU001 | B40: AU032045 | C40: 5160999000 | D40: Public relations | E40: 8516.27 | F40: AUQ | G40: 45629 | H40: AP Accruals | I40: TMSYD9075-ATELU00 | J40: Telum annual subsctiption | L40: TMSYD9075 | M40: TELUM MEDIA AUSTRALIA PTY LIMITED | Q40: =ABS(E40) -> 8516.27 | S40: subscription - OK
A41: AU001 | B41: AU032045 | C41: 5160999000 | D41: Public relations | E41: 1501.27 | F41: AUQ | G41: 45630 | H41: AP Accruals | I41: INV-45-ACOUR00 | J41: Rural Confidence Survey Q4 | L41: INV-45 | M41: COURTYARD ON GIBRALTAR PTY LTD | Q41: =ABS(E41) -> 1501.27 | S41: subscription - OK
A42: AU052 | B42: AU032045 | C42: 5160999000 | D42: Public relations | E42: 109.1 | F42: AUQ | G42: 45635 | H42: CCMS | I42: SHAWD-Default Licensee Merchan | J42: monthly Aus subscription | O42: NEWS PTY LIMITED | Q42: =ABS(E42) -> 109.1 | S42: subscription - OK
A43: AU052 | B43: AU032045 | C43: 5160999000 | D43: Public relations | E43: 29.1 | F43: AUQ | G43: 45635 | H43: CCMS | I43: SHAWD-Default Licensee Merchan | J43: monthly online Tele/News.com subscription | O43: NEWS PTY LIMITED | Q43: =ABS(E43) -> 29.1 | S43: subscription - OK
A44: AU052 | B44: AU032045 | C44: 5160999000 | D44: Public relations | E44: 54.55 | F44: AUQ | G44: 45642 | H44: CCMS | I44: SHAWD-Default Licensee Merchan | J44: monthly Aus subscription | O44: NEWS PTY LIMITED | Q44: =ABS(E44) -> 54.55 | S44: subscription - OK

Sheet Membership
A1: Account Number | C1: =Summary!A19 -> 5190001000
A2: Account Name | C2: =Summary!B19 -> Contributions& club membership | G2: Notes:
A3: GL Total | C3: 324427.63 | G3: The cost of renewing practicing certificates, memberships and accreditations required to work in the in field have been treated as tax deductible and | T3: AU001 | V3: =SUMIF($A$10:$A$23974,"AU001",V8:V23972) -> 0 | AC3: AU001 | AD3: =SUMIF($A$8:$A$20000,"AU001",AD8:AD20000) -> 0 | AE3: =SUMIF($A$8:$A$20000,"AU001",AE8:AE20000) -> 0
A4: Per TB | C4: =SUM(E:E) -> 324427.63 | G4: no FBT on the basis that they are otherwise deductible. | T4: AU052 | V4: =SUMIF($A$10:$A$23975,"AU052",V8:V23973) -> 0 | AC4: AU052 | AD4: =SUMIF($A$8:$A$20000,"AU052",AD8:AD20000) -> 0 | AE4: =SUMIF($A$8:$A$20000,"AU052",AE8:AE20000) -> 352.15
A5: Variance | C5: =C3-C4 -> -5.2386895e-10 | G5: All other professional memberships and subscribtions have been treated as no FBT and tax deductible under s8-1
AD6: Income tax purposes
A7: BUSINESS_UNIT_CODE | B7: OPERATING_UNIT_CODE | C7: ACCOUNT_CODE | D7: DESCRIPTION | E7: BASE_AMOUNT | F7: BASE_CURRENCY_CODE | G7: JOURNAL_DATE | H7: DESCR | I7: LINE_DESCR | J7: PURPOSE | K7: INVOICE_DESCR | L7: INVOICE_ID | M7: VENDOR_NAME | N7: EMPLOYEE_NAME | O7: CHARGE_DESCRIPTION | Q7: ABS | R7: Search Terms | S7: Tax Description | T7: ME? Y/N | U7: OU | V7: ME $ | W7: Not ME but other type of FB Y/N | X7: Not ME but other type of FB ==> $ | Y7: Nets to Nil in GL accts | Z7: s58P M&I or Bus Exp - notFB | AA7: ME | AB7: Car FB - addn op costs | AC7: CP Exp FB | AD7: Capital expenditure | AE7: No FBT and not ded | AF7: Additional Comments
A8: AU001 | B8: AU020097 | C8: 5190001000 | D8: Contributions& club membershi | E8: 17114.07 | F8: AUQ | G8: 45392 | H8: AP Accruals | I8: 2024-0115-ARISK01 | K8: Risk Management Association 20 | L8: 2024-0115 | M8: RISK MANAGEMENT ASSOCIATION INC | Q8: =ABS(E8) -> 17114.07 | S8: OK - business expense
A9: AU052 | B9: AU010021 | C9: 5190001000 | D9: Contributions& club membershi | E9: 14700.38 | F9: AUQ | G9: 45628 | H9: AP Accruals | I9: 000036571-ADIVE03 | K9: DCA Membership 2025-2027 | L9: 000036571 | M9: DIVERSITY COUNCIL AUSTRALIA LIMITED | Q9: =ABS(E9) -> 14700.38 | S9: OK - business expense
A10: AU001 | B10: AU010010 | C10: 5190001000 | D10: Contributions& club membershi | E10: 14342.27 | F10: AUQ | G10: 45393 | H10: AP Accruals | I10: INV00730-AAUST11 | K10: Quarterly membership contribut | L10: INV00730 | M10: AUSTRALIAN BANKING ASSOCIATION INC | Q10: =ABS(E10) -> 14342.27 | S10: OK - business expense
A11: AU001 | B11: AU032045 | C11: 5190001000 | D11: Contributions& club membershi | E11: 13589.45 | F11: AUQ | G11: 45601 | H11: AP Accruals | I11: 6600170430-ACCHA01 | K11: Annual Political Alerts | L11: 6600170430 | M11: CCH AUSTRALIA LIMITED | Q11: =ABS(E11) -> 13589.45 | S11: OK - business expense
A12: AU052 | B12: AU020097 | C12: 5190001000 | D12: Contributions& club membershi | E12: 13420 | F12: AUQ | G12: 45642 | H12: Managers Round Table | I12: Managers Round Table | Q12: =ABS(E12) -> 13420 | S12: OK - business expense
A13: AU052 | B13: AU010021 | C13: 5190001000 | D13: Contributions& club membershi | E13: 12848.21 | F13: AUQ | G13: 45628 | H13: AP Accruals | I13: PID000948-AACON00 | K13: PID Membership 2025-2027 | L13: PID000948 | M13: ACON HEALTH LIMITED PRIDE IN DIVERSITY | Q13: =ABS(E13) -> 12848.21 | S13: OK - business expense
A14: AU001 | B14: AU020097 | C14: 5190001000 | D14: Contributions& club membershi | E14: 12821.71 | F14: AUQ | G14: 45553 | H14: AP Accruals | I14: 6111141-APERP03 | K14: AU Commercial Lending Risk Man | L14: 6111141 | M14: PERPETUAL SERVICES PTY LTD | Q14: =ABS(E14) -> 12821.71 | S14: OK - business expense
A15: AU001 | B15: AU020097 | C15: 5190001000 | D15: Contributions& club membershi | E15: 12609.82 | F15: AUQ | G15: 45447 | H15: AP Accruals | I15: 6067742-APERP03 | L15: 6067742 | M15: PERPETUAL SERVICES PTY LTD | Q15: =ABS(E15) -> 12609.82 | S15: OK - business expense
A16: AU001 | B16: AU020097 | C16: 5190001000 | D16: Contributions& club membershi | E16: 12453.88 | F16: AUQ | G16: 45456 | H16: AP Accruals | I16: 6082503-APERP03 | L16: 6082503 | M16: PERPETUAL SERVICES PTY LTD | Q16: =ABS(E16) -> 12453.88 | S16: OK - business expense
A17: AU001 | B17: AU050119 | C17: 5190001000 | D17: Contributions& club membershi | E17: 10927 | F17: AUQ | G17: 45413 | H17: AP Accruals | I17: Inv 3591-AAITH00 | K17: March 2024 and June 2024 Quart | L17: Inv 3591 | M17: AITHER PTY LTD | Q17: =ABS(E17) -> 10927 | S17: OK - business expense
A18: AU001 | B18: AU050119 | C18: 5190001000 | D18: Contributions& club membershi | E18: 10927 | F18: AUQ | G18: 45615 | H18: AP Accruals | I18: Inv 3854-AAITH00 | K18: Sept 2024 and December 2024 Qu | L18: Inv 3854 | M18: AITHER PTY LTD | Q18: =ABS(E18) -> 10927 | S18: OK - business expense
A19: AU052 | B19: AU061134 | C19: 5190001000 | D19: Contributions& club membershi | E19: 9991.66 | F19: AUQ | G19: 45526 | H19: K 592 490 141-6-ATELS01 | I19: 80881-AAFMA00 | Q19: =ABS(E19) -> 9991.66 | S19: OK - business expense
A20: AU052 | B20: AU050113 | C20: 5190001000 | D20: Contributions& club membershi | E20: 8800 | F20: AUQ | G20: 45642 | H20: Managers Round Table | I20: Managers Round Table | Q20: =ABS(E20) -> 8800 | S20: OK - business expense
A21: AU052 | B21: AU010025 | C21: 5190001000 | D21: Contributions& club membershi | E21: 6045.45 | F21: AUQ | G21: 45415 | H21: CCMS | I21: LOBOM-Default Licensee Merchan | K21: Renewal of ACC membership | M21: ACC Asia Pacific, Ltd. | Q21: =ABS(E21) -> 6045.45 | S21: OK - business expense
A22: AU001 | B22: AU070150 | C22: 5190001000 | D22: Contributions& club membershi | E22: 5395.32 | F22: AUQ | G22: 45583 | H22: AP Accruals | I22: 4INV-0057866-AFAIR11 | K22: 8 x Corporate Lending AFR and | L22: 4INV-0057866 | M22: FAIRFAX MEDIA PUBLICATIONS PTY LIMITED | Q22: =ABS(E22) -> 5395.32 | S22: OK - business expense
A23: AU001 | B23: AU030613 | C23: 5190001000 | D23: Contributions& club membershi | E23: 5075.79 | F23: AUQ | G23: 45617 | H23: AP Accruals | I23: RABO_241121-AGRAI04 | K23: Grainamarket Corporate Members | L23: RABO_241121 | M23: GRAIN MARKET PTY LTD | Q23: =ABS(E23) -> 5075.79 | S23: OK - business expense
A24: AU052 | B24: AU061134 | C24: 5190001000 | D24: Contributions& club membershi | E24: 4995.83 | F24: AUQ | G24: 45558 | H24: AP-PR 1987585-ADAVI21 | I24: 80881-AAFMA00 | Q24: =ABS(E24) -> 4995.83 | S24: OK - business expense
A25: AU052 | B25: AU061134 | C25: 5190001000 | D25: Contributions& club membershi | E25: 4995.83 | F25: AUQ | G25: 45591 | H25: AP-PR 1987585-ADAVI21 | I25: 80881-AAFMA00 | Q25: =ABS(E25) -> 4995.83 | S25: OK - business expense
A26: AU052 | B26: AU061134 | C26: 5190001000 | D26: Contributions& club membershi | E26: 4995.83 | F26: AUQ | G26: 45620 | H26: AP-PR 1987585-ADAVI21 | I26: 80881-AAFMA00 | Q26: =ABS(E26) -> 4995.83 | S26: OK - business expense
A27: AU052 | B27: AU061134 | C27: 5190001000 | D27: Contributions& club membershi | E27: 4995.83 | F27: AUQ | G27: 45641 | H27: 2220181-ATELU01 | I27: 80881-AAFMA00 | Q27: =ABS(E27) -> 4995.83 | S27: OK - business expense
A28: AU052 | B28: AU061134 | C28: 5190001000 | D28: Contributions& club membershi | E28: 4812.5 | F28: AUQ | G28: 45403 | H28: 10002093-AINFO11 | I28: 80186-AAFMA00 | Q28: =ABS(E28) -> 4812.5 | S28: OK - business expense
A29: AU052 | B29: AU061134 | C29: 5190001000 | D29: Contributions& club membershi | E29: 4812.5 | F29: AUQ | G29: 45439 | H29: 1987585-ADAVI21 | I29: 80186-AAFMA00 | Q29: =ABS(E29) -> 4812.5 | S29: OK - business expense
A30: AU052 | B30: AU061134 | C30: 5190001000 | D30: Contributions& club membershi | E30: 4812.5 | F30: AUQ | G30: 45467 | H30: 1987585-ADAVI21 | I30: 80186-AAFMA00 | Q30: =ABS(E30) -> 4812.5 | S30: OK - business expense
A31: AU052 | B31: AU061134 | C31: 5190001000 | D31: Contributions& club membershi | E31: 4812.5 | F31: AUQ | G31: 45498 | H31: AP-PR 1987585-ADAVI21 | I31: AP-PR 80186-AAFMA00 | Q31: =ABS(E31) -> 4812.5 | S31: OK - business expense
A32: AU052 | B32: AU061134 | C32: 5190001000 | D32: Contributions& club membershi | E32: -4812.5 | F32: AUQ | G32: 45505 | H32: AP-PR 1987585-ADAVI21 | I32: AP-PR 80186-AAFMA00 | Q32: =ABS(E32) -> 4812.5 | S32: OK - business expense
A33: AU001 | B33: AU030215 | C33: 5190001000 | D33: Contributions& club membershi | E33: 3891.69 | F33: AUQ | G33: 45583 | H33: AP Accruals | I33: 4INV-0057866-AFAIR11 | K33: 6 x subscribers Goulburn Branc | L33: 4INV-0057866 | M33: FAIRFAX MEDIA PUBLICATIONS PTY LIMITED | Q33: =ABS(E33) -> 3891.69 | S33: OK - business expense
A34: AU001 | B34: AU060777 | C34: 5190001000 | D34: Contributions& club membershi | E34: 2750 | F34: AUQ | G34: 45385 | H34: AP Accruals | I34: YB-21112-AYIEL01 | K34: Monthly Auction Dealer Fee for | L34: YB-21112 | M34: YIELD BROKER PTY LTD | Q34: =ABS(E34) -> 2750 | S34: OK - business expense
A35: AU001 | B35: AU060777 | C35: 5190001000 | D35: Contributions& club membershi | E35: 2750 | F35: AUQ | G35: 45421 | H35: AP Accruals | I35: YB-21311-AYIEL01 | K35: Monthly Auction Dealer Fee for | L35: YB-21311 | M35: YIELD BROKER PTY LTD | Q35: =ABS(E35) -> 2750 | S35: OK - business expense
A36: AU001 | B36: AU060777 | C36: 5190001000 | D36: Contributions& club membershi | E36: 2750 | F36: AUQ | G36: 45461 | H36: AP Accruals | I36: YB-21592-ATRAD00 | K36: Monthly Fee - Auction Dealer | L36: YB-21592 | M36: TRADEWEB AUSTRALIA PTY LTD | Q36: =ABS(E36) -> 2750 | S36: OK - business expense
A37: AU052 | B37: AU075166 | C37: 5190001000 | D37: Contributions& club membershi | E37: 2700 | F37: AUQ | G37: 45448 | H37: CCMS | I37: GrootJ5-Default Licensee Merch | K37: annual membership dutchlink | M37: DUTCHLINK PTY LTD | Q37: =ABS(E37) -> 2700 | S37: OK - business expense
A38: AU001 | B38: AU030613 | C38: 5190001000 | D38: Contributions& club membershi | E38: 2625.41 | F38: AUQ | G38: 45495 | H38: AP Accruals | I38: INV-20104818-AGRAI00 | K38: GIWA Corporate Membership 2024 | L38: INV-20104818 | M38: GRAIN INDUSTRY ASSOCIATION OF WA | Q38: =ABS(E38) -> 2625.41 | S38: OK - business expense
A39: AU001 | B39: AU071196 | C39: 5190001000 | D39: Contributions& club membershi | E39: 2027.07 | F39: AUQ | G39: 45403 | H39: 10002093-AINFO11 | I39: INV-118731-OSPGL00 | Q39: =ABS(E39) -> 2027.07 | S39: OK - business expense
A40: AU001 | B40: AU071196 | C40: 5190001000 | D40: Contributions& club membershi | E40: 2027.07 | F40: AUQ | G40: 45439 | H40: 1987585-ADAVI21 | I40: INV-118731-OSPGL00 | Q40: =ABS(E40) -> 2027.07 | S40: OK - business expense
A41: AU001 | B41: AU071196 | C41: 5190001000 | D41: Contributions& club membershi | E41: 2027.07 | F41: AUQ | G41: 45467 | H41: 1987585-ADAVI21 | I41: INV-118731-OSPGL00 | Q41: =ABS(E41) -> 2027.07 | S41: OK - business expense
A42: AU001 | B42: AU071196 | C42: 5190001000 | D42: Contributions& club membershi | E42: 2027.07 | F42: AUQ | G42: 45498 | H42: AP-PR 1987585-ADAVI21 | I42: INV-118731-OSPGL00 | Q42: =ABS(E42) -> 2027.07 | S42: OK - business expense
A43: AU001 | B43: AU071196 | C43: 5190001000 | D43: Contributions& club membershi | E43: 2027.07 | F43: AUQ | G43: 45526 | H43: K 592 490 141-6-ATELS01 | I43: INV-118731-OSPGL00 | Q43: =ABS(E43) -> 2027.07 | S43: OK - business expense
