Workbook

Sheet Summary
A1: Rabobank Australia
A2: FBT return for the year ended 31 March 2025
A3: WP4 - Entertainment sensitive GL Accounts for Jan 2025 to Mar 25 | E3: Tfrred to "WPE1 ME Summary - GL analysis ent accounts.xls" | P3: NOTE for ITR/HardCat ê
F4: =F29 -> 48484.75 | I4: =I29 -> 499.09 | P4: =P29 -> 3139.98 | Q4: =Q29 -> 5559.3
I5: Pty FB >$300 | P5: Income tax purposes
A6: Account# | B6: Account Description | C6: Per TB | D6: Tax Description | E6: ME? Y/N | F6: ME $ | G6: AU001 / MEC | H6: AU052 | I6: Not ME but other type of FB Y/N | J6: $ | K6: Nets to Nil in GL accts | L6: s58P M&I or Bus Exp - notFB | M6: ME | N6: Car FB - addn op costs | O6: CP Exp FB | P6: Capital expenditure | Q6: No FBT and not ded | R6: Additional Comments
A8: 5140001000 | B8: Training expenses | C8: 39393.88 | D8: Picked up in Tuition expese analysis - NFA
A9: 5140001010 | B9: External Training and Seminars | C9: 121158.59 | D9: No ME included. All tax deductible | E9: Y | F9: ='Ext Training'!V53 -> 0 | G9: ='Ext Training'!V4 -> 0 | H9: ='Ext Training'!V5 -> 0 | R9: Noted
A10: 5140001030 | B10: Training travel and lodging ex | C10: 60353.16 | D10: No ME included. All tax deductible | E10: N | F10: ='Training Trav&lodg'!V4+'Training Trav&lodg'!V5 -> 0 | G10: ='Training Trav&lodg'!V4 -> 0 | H10: ='Training Trav&lodg'!V5 -> 0 | R10: Noted
A11: 5160001000 | B11: Publicity/advertising | C11: 211952.47 | D11: No ME included. All tax deductible | E11: N | F11: ='Publicity&Advert''g'!U4+'Publicity&Advert''g'!U5 -> 0 | G11: ='Publicity&Advert''g'!U4 -> 0 | H11: ='Publicity&Advert''g'!U5 -> 0 | R11: Noted
A12: 5160006000 | B12: Opening jubilees own buildin | C12: 0 | D12: No expenses recorded | E12: N | F12: ='Open-Jubilees'!S4+'Open-Jubilees'!S5 -> 0 | G12: ='Open-Jubilees'!S4 -> 0 | H12: ='Open-Jubilees'!S5 -> 0 | R12: Noted
A13: 5160007000 | B13: Sponsoring | C13: 18398.38 | D13: Minor ME, some RE added back | E13: Y | F13: =Sponsoring!V3+Sponsoring!V4 -> 127.27 | G13: =Sponsoring!V3 -> 0 | H13: =Sponsoring!V4 -> 127.27 | Q13: =Sponsoring!AE4+Sponsoring!AE3 -> 0 | R13: Noted
A14: 5160008000 | B14: Promotional gifts | C14: 7059.24 | D14: No ME included. client gifts are exempt from FBT | E14: N | F14: ='Promo gifts'!U4+'Promo gifts'!U5 -> 0 | G14: ='Promo gifts'!U4 -> 0 | H14: ='Promo gifts'!U5 -> 0 | R14: Noted
A15: 5160010000 | B15: Marketing expense | C15: -4733.21 | D15: Includes meal entertainment subject to FBT using 50/50 method | E15: Y | F15: =Marketing!V2+Marketing!V3 -> 1340.71 | G15: =Marketing!V2 -> 0 | H15: =Marketing!V3 -> 1340.71 | R15: OK
A16: 5160011000 | B16: Business development | C16: 260399.01 | D16: Includes ME | E16: Y | F16: ='Bus Dev'!V3+'Bus Dev'!V4 -> 33301.99 | G16: ='Bus Dev'!V3 -> 8846.07 | H16: ='Bus Dev'!V4 -> 24455.92 | R16: OK
A17: 5160999000 | B17: Public relations | C17: 11669.68 | D17: No ME included. All tax deductible | E17: N | F17: ='PR exp'!V4+'PR exp'!V5 -> 0 | G17: ='PR exp'!V4 -> 0 | H17: ='PR exp'!V5 -> 0 | R17: Noted
A18: 5180003000 | B18: Advice Tax & Legal expenses | C18: 39168.87 | D18: Picked up in Invoices WPE3 expese analysis - NFA | E18: N | R18: Noted
A19: 5190001000 | B19: Contributions& club membership | C19: 36644.04 | D19: No ME included. All tax deductible | E19: N | F19: ='Club memship'!U3+'Club memship'!U4 -> 0 | G19: ='Club memship'!V3 -> 0 | H19: ='Club memship'!V4 -> 0 | R19: Noted
A20: 5200006000 | B20: Meeting costs | C20: 112631.6 | D20: Includes meal entertainment subject to FBT using 50/50 method | E20: Y | F20: ='Meeting costs'!V3+'Meeting costs'!V4 -> 12438.54 | G20: ='Meeting costs'!V3 -> 4862 | H20: ='Meeting costs'!V4 -> 7576.54 | R20: =SUM(R18:R19) -> 0
A21: 5200999000 | B21: Miscellaneous expenses | C21: -7588.44 | D21: No ME included. | E21: N | F21: ='Misc exp'!U4+'Misc exp'!U5 -> 0 | G21: ='Misc exp'!U4 -> 0 | H21: ='Misc exp'!U5 -> 0 | R21: Noted
A22: 5200999010 | B22: Sundry expenses | C22: 0 | D22: No expenses recorded | E22: Y | F22: =Sundry!V4+Sundry!V5 -> 0 | G22: =Sundry!V4 -> 0 | H22: =Sundry!V5 -> 0 | R22: Noted
A23: 5200999020 | B23: Miscellaneous expenses (2) | C23: 216944.09 | D23: Inlcudes ME and staff gifts which are exempt from FBT | E23: Y | F23: ='Misc exp (2)'!V2+'Misc exp (2)'!V3 -> 141.8 | G23: ='Misc exp (2)'!V2 -> 0 | H23: ='Misc exp (2)'!V3 -> 141.8 | I23: ='Misc exp (2)'!W4 -> 499.09 | P23: ='Misc exp (2)'!AD2+'Misc exp (2)'!AD3 -> 0 | Q23: ='Misc exp (2)'!AE2+'Misc exp (2)'!AE3 -> 5559.3 | R23: Noted
A24: 5900050000 | B24: Other non banking expenses | C24: 10292.09 | D24: No ME included. All tax deductible | E24: N | F24: ='Other non-bank exp'!U4+'Other non-bank exp'!U5 -> 0 | G24: ='Other non-bank exp'!U4 -> 0 | H24: ='Other non-bank exp'!U5 -> 0 | R24: OK
A25: 5100999000 | B25: Other office expenses | C25: 91319.73 | D25: Inlcudes ME, staff gifts which are exempt from FBT and capital expenditure | E25: Y | F25: ='Other exp'!V3+'Other exp'!V4 -> 1134.44 | G25: ='Other exp'!V3 -> 1063.33 | H25: ='Other exp'!V4 -> 71.11 | P25: ='Other exp'!AD3+'Other exp'!AD4 -> 3139.98 | Q25: ='Other exp'!AE3+'Other exp'!AE4 -> 0 | R25: OK
A26: 5190002000 | B26: Donations | C26: 9848.87 | D26: No ME | E26: N | F26: =Donations!V3+Donations!V4 -> 0 | R26: Noted
A27: 5160002000 | B27: Client periodicals/magazines | C27: 209.96 | D27: No ME | E27: N | F27: ='Client period'!V3+'Client period'!V4 -> 0 | R27: Noted
D29: Total | F29: =SUM(F7:F28) -> 48484.75 | G29: =SUM(G8:G25) -> 14771.4 | H29: =SUM(H8:H25) -> 33713.35 | I29: =SUM(I7:I28) -> 499.09 | J29: =SUM(J7:J28) -> 0 | K29: =SUM(K7:K28) -> 0 | L29: =SUM(L7:L28) -> 0 | M29: =SUM(M7:M28) -> 0 | N29: =SUM(N7:N28) -> 0 | O29: =SUM(O7:O28) -> 0 | P29: =SUM(P7:P28) -> 3139.98 | ... R29: =SUM(R7:R28) -> 0
M31: Prepared by | R31: Reviewed By
M32: LF: Queries dealt with and responses at WPE1. Largely agreed with questions raises but have not made major changes given stage of process. Agreed we need a separate GL account or something for food whilst travelling | R32: LF response to my queries noted and accept calc accordingly. AJL16/5

Sheet Ext Training
A1: Account Number | C1: =Summary!A9 -> 5140001010
A2: Account Name | C2: =Summary!B9 -> External Training and Seminars | H2: Notes: | S2: No ME included. All tax deductible
A3: GL Total | C3: 121158.59 | H3: Expenditure on university courses and other courses conferences attended by employees. These are not considered REAP but are in
A4: Per TB | C4: =SUM(E:E) -> 121158.59 | H4: relation to the employees current roles so would be otherwise deductible for income tax purposes. No FBT will apply to these expenses. | T4: AU001 | V4: =SUMIF($A$10:$A$23731,"AU001",V9:V23730) -> 0 | AC4: AU001 | AD4: =SUMIF($A$10:$A$23731,"AU001",AD9:AD23730) -> 0 | AE4: =SUMIF($A$10:$A$23731,"AU001",AE9:AE23730) -> 0
A5: Variance | C5: =C3-C4 -> 0 | T5: AU052 | V5: =SUMIF($A$10:$A$23732,"AU052",V9:V23731) -> 0 | AC5: AU052 | AD5: =SUMIF($A$10:$A$23732,"AU052",AD9:AD23731) -> 0 | AE5: =SUMIF($A$10:$A$23732,"AU052",AE9:AE23731) -> 0
AD6: Income tax purposes
A7: BUSINESS_UNIT_CODE | B7: OPERATING_UNIT_CODE | C7: ACCOUNT_CODE | D7: DESCRIPTION | E7: BASE_AMOUNT | F7: BASE_CURRENCY_CODE | G7: JOURNAL_DATE | H7: DESCR | I7: LINE_DESCR | J7: PURPOSE | K7: INVOICE_DESCR | L7: INVOICE_ID | M7: VENDOR_NAME | N7: EMPLOYEE_NAME | O7: CHARGE_DESCRIPTION | Q7: ABS | R7: Search Terms | S7: Tax Description | T7: ME? Y/N | U7: OU | V7: ME $ | W7: Not ME but other type of FB Y/N | X7: Not ME but other type of FB ==> $ | Y7: Nets to Nil in GL accts | Z7: s58P M&I or Bus Exp - notFB | AA7: ME | AB7: Car FB - addn op costs | AC7: CP Exp FB | AD7: Capital expenditure | AE7: No FBT and not ded | AF7: Additional Comments
A8: AU052 | B8: AU010029 | C8: 5140001010 | D8: External Training and Seminars | E8: -55000 | F8: AUQ | G8: 45658 | H8: ADP Monthly Invoice - Dec2024 | I8: Graduate development workshop | Q8: =ABS(E8) -> 55000
A9: AU052 | B9: AU010029 | C9: 5140001010 | D9: External Training and Seminars | E9: 55000 | F9: AUQ | G9: 45686 | H9: Rabobank CB Search Marketing | I9: Graduate development works | Q9: =ABS(E9) -> 55000
A10: AU052 | B10: AU010029 | C10: 5140001010 | D10: External Training and Seminars | E10: -55000 | F10: AUQ | G10: 45691 | H10: Rabobank CB Search Marketing | I10: Graduate development works | Q10: =ABS(E10) -> 55000
A11: AU052 | B11: AU030055 | C11: 5140001010 | D11: External Training and Seminars | E11: 53991.82 | F11: AUQ | G11: 45702 | H11: AP Accruals | I11: RABO-I0225236-OINCH01 | K11: CB AU LT Offsite | L11: RABO-I0225236 | M11: INCHIGO | Q11: =ABS(E11) -> 53991.82
A12: AU052 | B12: AU030055 | C12: 5140001010 | D12: External Training and Seminars | E12: 32601.11 | F12: AUQ | G12: 45691 | H12: AP Accruals | I12: INV-20619-AFINA09 | K12: FEP Enrolments CPD | L12: INV-20619 | M12: FINANCIAL EDUCATION PROFFESIONALS PTYLTD | Q12: =ABS(E12) -> 32601.11
A13: AU001 | B13: AU010029 | C13: 5140001010 | D13: External Training and Seminars | E13: 21793.51 | F13: AUQ | G13: 45692 | H13: AP Accruals | I13: 1255-ACAPP01 | K13: Graduate development program d | L13: 1255 | M13: CAPPFINITY PTY LTD | Q13: =ABS(E13) -> 21793.51
A14: AU001 | B14: AU010021 | C14: 5140001010 | D14: External Training and Seminars | E14: 10438.19 | F14: AUQ | G14: 45692 | H14: AP Accruals | I14: RABOB0060129-AHARR02 | K14: Furniture Hire for YELT BC1 | L14: RABOB0060129 | M14: HARRY THE HIRER | Q14: =ABS(E14) -> 10438.19
A15: AU052 | B15: AU030055 | C15: 5140001010 | D15: External Training and Seminars | E15: 8676.66 | F15: AUQ | G15: 45691 | H15: AP Accruals | I15: INV-20619-AFINA09 | K15: FEP Enrolments ACL CPD | L15: INV-20619 | M15: FINANCIAL EDUCATION PROFFESIONALS PTYLTD | Q15: =ABS(E15) -> 8676.66
A16: AU052 | B16: AU025104 | C16: 5140001010 | D16: External Training and Seminars | E16: 5737.51 | F16: AUQ | G16: 45691 | H16: AP Accruals | I16: INV-20619-AFINA09 | K16: FEP Enrolments CPD | L16: INV-20619 | M16: FINANCIAL EDUCATION PROFFESIONALS PTYLTD | Q16: =ABS(E16) -> 5737.51
A17: AU052 | B17: AU036742 | C17: 5140001010 | D17: External Training and Seminars | E17: 5061.95 | F17: AUQ | G17: 45677 | H17: AP Accruals | I17: INV-7143-ALANG01 | K17: Team strengths profiles | L17: INV-7143 | M17: LANGLEY GROUP PTY LTD | Q17: =ABS(E17) -> 5061.95
A18: AU001 | B18: AU010021 | C18: 5140001010 | D18: External Training and Seminars | E18: 2974.58 | F18: AUQ | G18: 45691 | H18: AP Accruals | I18: 33108063-01-AFOUR01 | K18: Hyatt Sydney First Deposit | L18: 33108063-01 | M18: EP2 MANAGEMENT TA HYATT REGENCY SYDNEY | Q18: =ABS(E18) -> 2974.58
A19: AU001 | B19: AU010021 | C19: 5140001010 | D19: External Training and Seminars | E19: 2974.58 | F19: AUQ | G19: 45709 | H19: AP Accruals | I19: 33108063-2-AFOUR01 | K19: YELT BC1 Venue deposit 2 | L19: 33108063-2 | M19: EP2 MANAGEMENT TA HYATT REGENCY SYDNEY | Q19: =ABS(E19) -> 2974.58
A20: AU001 | B20: AU010021 | C20: 5140001010 | D20: External Training and Seminars | E20: 2974.58 | F20: AUQ | G20: 45709 | H20: AP Accruals | I20: 33108063-3-AFOUR01 | K20: YELT BC 1 Venue Deposit 3 | L20: 33108063-3 | M20: EP2 MANAGEMENT TA HYATT REGENCY SYDNEY | Q20: =ABS(E20) -> 2974.58
A21: AU052 | B21: AU030055 | C21: 5140001010 | D21: External Training and Seminars | E21: 2794.08 | F21: AUQ | G21: 45691 | H21: AP Accruals | I21: INV-20619-AFINA09 | K21: FEP Enrolments RMs | L21: INV-20619 | M21: FINANCIAL EDUCATION PROFFESIONALS PTYLTD | Q21: =ABS(E21) -> 2794.08
A22: AU052 | B22: AU073158 | C22: 5140001010 | D22: External Training and Seminars | E22: 2600 | F22: AUQ | G22: 45691 | H22: AP Accruals | I22: INV-20619-AFINA09 | K22: FEP Enrolment, S Laidlow | L22: INV-20619 | M22: FINANCIAL EDUCATION PROFFESIONALS PTYLTD | Q22: =ABS(E22) -> 2600
A23: AU052 | B23: AU010021 | C23: 5140001010 | D23: External Training and Seminars | E23: 2181.36 | F23: AUQ | G23: 45701 | H23: AP Accruals | I23: INV-01748-AWESN00 | K23: Photography for YELT BC 1 | L23: INV-01748 | M23: WES NEL PHOTOGRAPHY PTY LTD | Q23: =ABS(E23) -> 2181.36
A24: AU052 | B24: AU070150 | C24: 5140001010 | D24: External Training and Seminars | E24: 1849 | F24: AUQ | G24: 45733 | H24: CCMS | I24: BARRACLOUGHD-Default Licensee | J24: Food and Grocery Australia 2025 Registration | O24: EZI*AUSTRALIAN FOOD &/828834783 | Q24: =ABS(E24) -> 1849
A25: AU052 | B25: AU030055 | C25: 5140001010 | D25: External Training and Seminars | E25: 1529.55 | F25: AUQ | G25: 45734 | H25: CCMS | I25: ArnottC1-Default Licensee Merc | J25: APLMA Financial Modelling Course | O25: WWW.APLMA.COM | Q25: =ABS(E25) -> 1529.55
A26: AU052 | B26: AU030055 | C26: 5140001010 | D26: External Training and Seminars | E26: 1529.55 | F26: AUQ | G26: 45744 | H26: CCMS | I26: KilbyJ-Default Licensee Mercha | J26: Staff Training - James Kilby | O26: WWW.APLMA.COM | Q26: =ABS(E26) -> 1529.55
A27: AU052 | B27: AU070150 | C27: 5140001010 | D27: External Training and Seminars | E27: 1510.11 | F27: AUQ | G27: 45701 | H27: AP Accruals | I27: INV-7231-ALANG01 | K27: Offsite | L27: INV-7231 | M27: LANGLEY GROUP PTY LTD | Q27: =ABS(E27) -> 1510.11
A28: AU052 | B28: AU071196 | C28: 5140001010 | D28: External Training and Seminars | E28: 1294.38 | F28: AUQ | G28: 45701 | H28: AP Accruals | I28: INV-7231-ALANG01 | K28: Offsite | L28: INV-7231 | M28: LANGLEY GROUP PTY LTD | Q28: =ABS(E28) -> 1294.38
A29: AU052 | B29: AU025104 | C29: 5140001010 | D29: External Training and Seminars | E29: 1185 | F29: AUQ | G29: 45666 | H29: AP Accruals | I29: INV-20336-AFINA09 | K29: FEP Enrolments | L29: INV-20336 | M29: FINANCIAL EDUCATION PROFFESIONALS PTYLTD | Q29: =ABS(E29) -> 1185
A30: AU052 | B30: AU025104 | C30: 5140001010 | D30: External Training and Seminars | E30: 1185 | F30: AUQ | G30: 45729 | H30: AP Accruals | I30: INV-20841-AFINA09 | K30: FEP- Generic Knowledge and Dep | L30: INV-20841 | M30: FINANCIAL EDUCATION PROFFESIONALS PTYLTD | Q30: =ABS(E30) -> 1185
A31: AU052 | B31: AU025080 | C31: 5140001010 | D31: External Training and Seminars | E31: 948.44 | F31: AUQ | G31: 45679 | H31: 2220181-ATELU01 | I31: 8025670-OINTE03 | Q31: =ABS(E31) -> 948.44
A32: AU052 | B32: AU025080 | C32: 5140001010 | D32: External Training and Seminars | E32: 948.44 | F32: AUQ | G32: 45711 | H32: 90848234-ADIME01 | I32: 8025670-OINTE03 | Q32: =ABS(E32) -> 948.44
A33: AU052 | B33: AU025080 | C33: 5140001010 | D33: External Training and Seminars | E33: 948.44 | F33: AUQ | G33: 45734 | H33: 113522301-17/07/24-ACGUW05 | I33: 8025670-OINTE03 | Q33: =ABS(E33) -> 948.44
A34: AU052 | B34: AU070150 | C34: 5140001010 | D34: External Training and Seminars | E34: 915.3 | F34: AUQ | G34: 45744 | H34: CCMS | I34: Haynest-Software | J34: 3 tickets to the Agfood Fund conf. | O34: AGFOOD FUND PTY LTD | Q34: =ABS(E34) -> 915.3
A35: AU052 | B35: AU070150 | C35: 5140001010 | D35: External Training and Seminars | E35: 793.1 | F35: AUQ | G35: 45734 | H35: CCMS | I35: LaoV-Default Licensee Merchant | J35: APLMA - Advanced Documentation Course | O35: WWW.APLMA.COM | Q35: =ABS(E35) -> 793.1
A36: AU052 | B36: AU073158 | C36: 5140001010 | D36: External Training and Seminars | E36: 767 | F36: AUQ | G36: 45701 | H36: AP Accruals | I36: INV-7231-ALANG01 | K36: Offsite | L36: INV-7231 | M36: LANGLEY GROUP PTY LTD | Q36: =ABS(E36) -> 767
A37: AU052 | B37: AU070150 | C37: 5140001010 | D37: External Training and Seminars | E37: 630.55 | F37: AUQ | G37: 45734 | H37: CCMS | I37: CookM-Entertainment Expense | J37: ticket to the NTCA | O37: AA&P EVENTS | Q37: =ABS(E37) -> 630.55
A38: AU052 | B38: AU074251 | C38: 5140001010 | D38: External Training and Seminars | E38: 606.78 | F38: AUQ | G38: 45701 | H38: AP Accruals | I38: INV-7231-ALANG01 | K38: Offsite | L38: INV-7231 | M38: LANGLEY GROUP PTY LTD | Q38: =ABS(E38) -> 606.78
A39: AU052 | B39: AU010023 | C39: 5140001010 | D39: External Training and Seminars | E39: 600 | F39: AUQ | G39: 45735 | H39: CCMS | I39: SchofieldL-Default Licensee Me | J39: Advanced LSL Training - Karenanne O'Neill | O39: THE ASSOCIATION FOR PA/631213524720 | Q39: =ABS(E39) -> 600
A40: AU052 | B40: AU030055 | C40: 5140001010 | D40: External Training and Seminars | E40: 570 | F40: AUQ | G40: 45729 | H40: AP Accruals | I40: INV-20841-AFINA09 | K40: FEP - RG146 Tier 2 Deposits (E | L40: INV-20841 | M40: FINANCIAL EDUCATION PROFFESIONALS PTYLTD | Q40: =ABS(E40) -> 570
A41: AU052 | B41: AU025104 | C41: 5140001010 | D41: External Training and Seminars | E41: 550 | F41: AUQ | G41: 45729 | H41: AP Accruals | I41: INV-20841-AFINA09 | K41: FEP -Tier 1 Deposits and Non C | L41: INV-20841 | M41: FINANCIAL EDUCATION PROFFESIONALS PTYLTD | Q41: =ABS(E41) -> 550
A42: AU052 | B42: AU032074 | C42: 5140001010 | D42: External Training and Seminars | E42: -454.55 | F42: AUQ | G42: 45720 | H42: VISA FEB 2025 | I42: DonponR-venue hire bond | Q42: =ABS(E42) -> 454.55
A43: AU052 | B43: AU030615 | C43: 5140001010 | D43: External Training and Seminars | E43: 418.18 | F43: AUQ | G43: 45740 | H43: CCMS | I43: MUSITANOJB-Default Licensee Me | J43: WA Lot Feeders Better Beef | O43: WA LOT FEEDERS | Q43: =ABS(E43) -> 418.18
A44: AU052 | B44: AU070150 | C44: 5140001010 | D44: External Training and Seminars | E44: 400 | F44: AUQ | G44: 45734 | H44: CCMS | I44: AshworthJ-Default Licensee Mer | J44: Capital Growth Forum | O44: EB *Growth Capital For | Q44: =ABS(E44) -> 400
A45: AU052 | B45: AU050119 | C45: 5140001010 | D45: External Training and Seminars | E45: 397.99 | F45: AUQ | G45: 45744 | H45: CCMS | I45: HonnefP-Default Licensee Merch | J45: Training | O45: ZEN*B2B-Aus Prop Instit S | Q45: =ABS(E45) -> 397.99
A46: AU052 | B46: AU025104 | C46: 5140001010 | D46: External Training and Seminars | E46: 395 | F46: AUQ | G46: 45691 | H46: AP Accruals | I46: INV-20619-AFINA09 | K46: FEP Enrolments RCC | L46: INV-20619 | M46: FINANCIAL EDUCATION PROFFESIONALS PTYLTD | Q46: =ABS(E46) -> 395
A47: AU052 | B47: AU025091 | C47: 5140001010 | D47: External Training and Seminars | E47: 348.69 | F47: AUQ | G47: 45729 | H47: AP Accruals | I47: INV-20841-AFINA09 | K47: Fep - AFSL Responsible Manager | L47: INV-20841 | M47: FINANCIAL EDUCATION PROFFESIONALS PTYLTD | Q47: =ABS(E47) -> 348.69
A48: AU052 | B48: AU025025 | C48: 5140001010 | D48: External Training and Seminars | E48: 342.31 | F48: AUQ | G48: 45729 | H48: AP Accruals | I48: INV-20841-AFINA09 | K48: Fep - AFSL Responsible Manager | L48: INV-20841 | M48: FINANCIAL EDUCATION PROFFESIONALS PTYLTD | Q48: =ABS(E48) -> 342.31
A49: AU052 | B49: AU032045 | C49: 5140001010 | D49: External Training and Seminars | E49: 218.18 | F49: AUQ | G49: 45734 | H49: CCMS | I49: SHAWD-Default Licensee Merchan | J49: March FarmWriters lunch event (NSW Premier) | O49: FARM WRITERS | Q49: =ABS(E49) -> 218.18
A50: AU001 | B50: AU036742 | C50: 5140001010 | D50: External Training and Seminars | E50: 187.08 | F50: AUQ | G50: 45691 | H50: AP Accruals | I50: INV-7183-ALANG01 | K50: STO Strength Profiles | L50: INV-7183 | M50: LANGLEY GROUP PTY LTD | Q50: =ABS(E50) -> 187.08
A51: AU052 | B51: AU050119 | C51: 5140001010 | D51: External Training and Seminars | E51: 175.85 | F51: AUQ | G51: 45747 | H51: CCMS | I51: ShawD1-Default Licensee Mercha | J51: Training and Education Courses | O51: ZEN*B2B-Aus Prop Instit S | Q51: =ABS(E51) -> 175.85
A52: AU052 | B52: AU030433 | C52: 5140001010 | D52: External Training and Seminars | E52: 140.68 | F52: AUQ | G52: 45734 | H52: CCMS | I52: KorffD-Default Licensee Mercha | J52: Leading Sheep Forum Longreach | O52: TRYBOOKING*DEPARTMENT OF/219549188453 | Q52: =ABS(E52) -> 140.68
A53: AU052 | B53: AU050119 | C53: 5140001010 | D53: External Training and Seminars | E53: 138.84 | F53: AUQ | G53: 45700 | H53: CCMS | I53: CroattoMJ-Default Licensee Mer | J53: sustainability training API | O53: ZEN*B2B-Aus Prop Instit S | Q53: =ABS(E53) -> 138.84
A54: AU052 | B54: AU032074 | C54: 5140001010 | D54: External Training and Seminars | E54: -109.09 | F54: AUQ | G54: 45741 | H54: DonponR-Default Licensee Merch | I54: DonponR-Default Licensee Merch | Q54: =ABS(E54) -> 109.09
A55: AU052 | B55: AU050119 | C55: 5140001010 | D55: External Training and Seminars | E55: 92.55 | F55: AUQ | G55: 45664 | H55: CCMS | I55: CroattoMJ-Default Licensee Mer | J55: API training | O55: ZEN*B2B-Aus Prop Instit S | Q55: =ABS(E55) -> 92.55
A56: AU052 | B56: AU030313 | C56: 5140001010 | D56: External Training and Seminars | E56: 72.73 | F56: AUQ | G56: 45706 | H56: CCMS | I56: RistromJ-Default Licensee Merc | J56: Gippsland Ag Group - Dinner | O56: SQ *GIPPSLAND AGRICULTURA | Q56: =ABS(E56) -> 72.73
A57: AU052 | B57: AU070150 | C57: 5140001010 | D57: External Training and Seminars | E57: 72.73 | F57: AUQ | G57: 45734 | H57: CCMS | I57: AshworthJ-Default Licensee Mer | J57: Agribuz event bio security | O57: EZI*EZIDEBIT MEMBERSHI/823627702 | Q57: =ABS(E57) -> 72.73
A58: AU052 | B58: AU070150 | C58: 5140001010 | D58: External Training and Seminars | E58: 72.73 | F58: AUQ | G58: 45734 | H58: CCMS | I58: CookM-Default Licensee Merchan | J58: Biosecurity update conference | O58: EZI*EZIDEBIT MEMBERSHI/824780508 | Q58: =ABS(E58) -> 72.73
A59: AU052 | B59: AU050119 | C59: 5140001010 | D59: External Training and Seminars | E59: 63.64 | F59: AUQ | G59: 45700 | H59: CCMS | I59: CroattoMJ-Default Licensee Mer | J59: RETS conference Melbourne | O59: EZI*EZIDEBIT MEMBERSHI/821940057 | Q59: =ABS(E59) -> 63.64
A60: AU052 | B60: AU025074 | C60: 5140001010 | D60: External Training and Seminars | E60: 24.48 | F60: AUQ | G60: 45726 | H60: CCMS | I60: KeastJ-Tuition (study) Reimbur | J60: Training - software capitalisation | O60: ACCOUNTINGTOOLS | Q60: =ABS(E60) -> 24.48

Sheet Training Trav&lodg
A1: Account Number | C1: =Summary!A10 -> 5140001030
A2: Account Name | C2: =Summary!B10 -> Training travel and lodging ex | G2: Notes: | S2: No ME included. All tax deductible
A3: GL Total | C3: 60353.16 | G3: Expenditure on university courses and other courses conferences attended by employees. These are not considered REAP but are in
A4: Per TB | C4: =SUM(E:E) -> 60353.16 | G4: relation to the employees current roles so would be otherwise deductible for income tax purposes. No FBT will apply to these expenses. | T4: AU001 | V4: =SUMIF($A$10:$A$23974,"AU001",V9:V23973) -> 0
A5: Variance | C5: =C3-C4 -> 0 | T5: AU052 | V5: =SUMIF($A$10:$A$23975,"AU052",V9:V23974) -> 0
AD6: Income tax purposes
A7: BUSINESS_UNIT_CODE | B7: OPERATING_UNIT_CODE | C7: ACCOUNT_CODE | D7: DESCRIPTION | E7: BASE_AMOUNT | F7: BASE_CURRENCY_CODE | G7: JOURNAL_DATE | H7: DESCR | I7: LINE_DESCR | J7: PURPOSE | K7: INVOICE_DESCR | L7: INVOICE_ID | M7: VENDOR_NAME | N7: EMPLOYEE_NAME | O7: CHARGE_DESCRIPTION | Q7: ABS | R7: Search Terms | S7: Tax Description | T7: ME? Y/N | U7: OU | V7: ME $ | W7: Not ME but other type of FB Y/N | X7: Not ME but other type of FB ==> $ | Y7: Nets to Nil in GL accts | Z7: s58P M&I or Bus Exp - notFB | AA7: ME | AB7: Car FB - addn op costs | AC7: CP Exp FB | AD7: Capital expenditure | AE7: No FBT and not ded | AF7: Additional Comments
A8: AU001 | B8: AU030510 | C8: 5140001030 | D8: Training travel and lodging ex | E8: 50879.85 | F8: AUQ | G8: 45663 | H8: AP Accruals | I8: 1009009-ABRID00 | K8: SANTNWV Offsite Deposit Feb 25 | L8: 1009009 | M8: BRIDGEPORT HOTEL | Q8: =ABS(E8) -> 50879.85
A9: AU052 | B9: AU036750 | C9: 5140001030 | D9: Training travel and lodging ex | E9: 1823.51 | F9: AUQ | G9: 45670 | H9: AP Accruals | I9: EEC-1160-EBRAD02 | K9: Hotel | L9: EEC-1160 | M9: ADAM BRADLEY | Q9: =ABS(E9) -> 1823.51
A10: AU001 | B10: AU070150 | C10: 5140001030 | D10: Training travel and lodging ex | E10: 1371.24 | F10: AUQ | G10: 45664 | H10: AP Accruals | I10: RABO-17/12/24-AINTE35 | K10: LT offsite accommodation | L10: RABO-17/12/24 | M10: INTERCONTINENTAL SYDNEY DOUBLE BAY | Q10: =ABS(E10) -> 1371.24
A11: AU001 | B11: AU073158 | C11: 5140001030 | D11: Training travel and lodging ex | E11: 1371.24 | F11: AUQ | G11: 45664 | H11: AP Accruals | I11: RABO-17/12/24-AINTE35 | K11: LT offsite accommodation | L11: RABO-17/12/24 | M11: INTERCONTINENTAL SYDNEY DOUBLE BAY | Q11: =ABS(E11) -> 1371.24
A12: AU001 | B12: AU074251 | C12: 5140001030 | D12: Training travel and lodging ex | E12: 1369.6 | F12: AUQ | G12: 45664 | H12: AP Accruals | I12: RABO-17/12/24-AINTE35 | K12: LT offsite accommodation | L12: RABO-17/12/24 | M12: INTERCONTINENTAL SYDNEY DOUBLE BAY | Q12: =ABS(E12) -> 1369.6
A13: AU001 | B13: AU071196 | C13: 5140001030 | D13: Training travel and lodging ex | E13: 1298.53 | F13: AUQ | G13: 45664 | H13: AP Accruals | I13: RABO-17/12/24-AINTE35 | K13: LT offsite accommodation | L13: RABO-17/12/24 | M13: INTERCONTINENTAL SYDNEY DOUBLE BAY | Q13: =ABS(E13) -> 1298.53
A14: AU052 | B14: AU061134 | C14: 5140001030 | D14: Training travel and lodging ex | E14: 829 | F14: AUQ | G14: 45720 | H14: AP Accruals | I14: 20250224-ACROW18 | K14: Crown Plaza Terrigal | L14: 20250224 | M14: CROWNE PLAZA TERRIGAL PACIFIC | Q14: =ABS(E14) -> 829
A15: AU001 | B15: AU032053 | C15: 5140001030 | D15: Training travel and lodging ex | E15: 463.01 | F15: AUQ | G15: 45727 | H15: AP Accruals | I15: CEC-14-ASPRI00 | K15: Return flights for NQNT CC mem | L15: CEC-14 | M15: SPRINGDALE LAND AND CATTLE CO | Q15: =ABS(E15) -> 463.01
A16: AU052 | B16: AU030055 | C16: 5140001030 | D16: Training travel and lodging ex | E16: 442.33 | F16: AUQ | G16: 45720 | H16: AP Accruals | I16: EEC-1312-EHOWA01 | K16: VICTAS offsite accommodation, | L16: EEC-1312 | Q16: =ABS(E16) -> 442.33
A17: AU052 | B17: AU036750 | C17: 5140001030 | D17: Training travel and lodging ex | E17: 325.53 | F17: AUQ | G17: 45670 | H17: AP Accruals | I17: EEC-1160-EBRAD02 | K17: Transport | L17: EEC-1160 | Q17: =ABS(E17) -> 325.53
A18: AU052 | B18: AU030310 | C18: 5140001030 | D18: Training travel and lodging ex | E18: 133.64 | F18: AUQ | G18: 45735 | H18: AP Accruals | I18: EEC-1430-EHARR00 | K18: Uber to training | L18: EEC-1430 | Q18: =ABS(E18) -> 133.64
A19: AU052 | B19: AU030710 | C19: 5140001030 | D19: Training travel and lodging ex | E19: 38.18 | F19: AUQ | G19: 45727 | H19: CCMS | I19: MccullochB-Company Car Parking | J19: Parking while at airport on training course | M19: Launceston Airport | Q19: =ABS(E19) -> 38.18
A20: AU052 | B20: AU030316 | C20: 5140001030 | D20: Training travel and lodging ex | E20: 7.5 | F20: AUQ | G20: 45673 | H20: CCMS | I20: WilsonE3-Airfares | J20: Egenica Booking Fee for Mt Gambier | M20: EGEN*AUSI142601669/AUBI2024348538423/AUBI2024348538423010 | Q20: =ABS(E20) -> 7.5

Sheet Publicity&Advert'g
A1: Account Number | C1: =Summary!A11 -> 5160001000
A2: Account Name | C2: =Summary!B11 -> Publicity/advertising | H2: Notes: | R2: No ME included. All tax deductible
A3: GL Total | C3: 211952.47 | H3: Rabobank truck expenses have been treated as deductible on the basis that they are a marketing expense under s8-1 | AB3: AU001 | AC3: =SUMIF($A$9:$A$175,"AU001",AC8:AC175) -> 0
A4: Per TB | C4: =SUM(E:E) -> 211952.47 | H4: No entertainment expenses included below - all relates to Rabotruck, marketing expences and items directly related to businss activities of Rabo | T4: AU001 | U4: =SUMIF($A$9:$A$175,"AU001",U8:U175) -> 0 | AB4: AU052 | AC4: =SUMIF($A$9:$A$175,"AU052",AC9:AC175) -> 0
A5: Variance | C5: =C3-C4 -> 0 | T5: AU052 | U5: =SUMIF($A$9:$A$175,"AU052",U8:U175) -> 0
AC6: Income tax purposes
A7: BUSINESS_UNIT_CODE | B7: OPERATING_UNIT_CODE | C7: ACCOUNT_CODE | D7: DESCRIPTION | E7: BASE_AMOUNT | F7: BASE_CURRENCY_CODE | G7: JOURNAL_DATE | H7: DESCR | I7: LINE_DESCR | J7: PURPOSE | K7: INVOICE_DESCR | L7: INVOICE_ID | M7: VENDOR_NAME | N7: EMPLOYEE_NAME | O7: CHARGE_DESCRIPTION | Q7: ABS | R7: Search Terms | S7: Tax Description | T7: ME? Y/N | U7: ME $ | V7: Not ME but other type of FB Y/N | W7: Not ME but other type of FB ==> $ | X7: Nets to Nil in GL accts | Y7: s58P M&I or Bus Exp - notFB | Z7: ME | AA7: Car FB - addn op costs | AB7: CP Exp FB | AC7: Capital expenditure | AD7: No FBT and not ded | AE7: Additional Comments
A8: AU001 | B8: AU032051 | C8: 5160001000 | D8: Publicity/advertising | E8: -242000 | F8: AUQ | G8: Wednesday, 1 January 2025 | H8: RaboTruck Operation (MNGT fee) | I8: Rabobank ROS Paid Media-Dec24 | Q8: =ABS(E8) -> 242000
A9: AU001 | B9: AU032046 | C9: 5160001000 | D9: Publicity/advertising | E9: -107045.4 | F9: AUQ | G9: Wednesday, 1 January 2025 | H9: RaboTruck Operation (MNGT fee) | I9: Rabo CB Paid Media-Brand-Oct24 | Q9: =ABS(E9) -> 107045.4
A10: AU001 | B10: AU032046 | C10: 5160001000 | D10: Publicity/advertising | E10: 107045.4 | F10: AUQ | G10: Wednesday, 29 January 2025 | H10: Rabobank CB Search Marketing | I10: Rabobank CB Paid Media Campaig | Q10: =ABS(E10) -> 107045.4
A11: AU001 | B11: AU032046 | C11: 5160001000 | D11: Publicity/advertising | E11: -107045.4 | F11: AUQ | G11: Monday, 3 February 2025 | H11: Rabobank CB Search Marketing | I11: Rabobank CB Paid Media Campaig | Q11: =ABS(E11) -> 107045.4
A12: AU001 | B12: AU032046 | C12: 5160001000 | D12: Publicity/advertising | E12: 106819.63 | F12: AUQ | G12: Wednesday, 19 February 2025 | H12: AP Accruals | I12: INV-14881-ABRYA02 | K12: 2024 accrual - CB brand campai | L12: INV-14881 | M12: BRYANT AND BROTHERS PTY LTD TA SPARRO | Q12: =ABS(E12) -> 106819.63
A13: AU001 | B13: AU032051 | C13: 5160001000 | D13: Publicity/advertising | E13: 92477.9 | F13: AUQ | G13: Wednesday, 29 January 2025 | H13: Rabobank CB Search Marketing | I13: Rabobank ROS Paid Media - Sear | Q13: =ABS(E13) -> 92477.9
A14: AU001 | B14: AU032051 | C14: 5160001000 | D14: Publicity/advertising | E14: -92477.9 | F14: AUQ | G14: Monday, 3 February 2025 | H14: Rabobank CB Search Marketing | I14: Rabobank ROS Paid Media - Sear | Q14: =ABS(E14) -> 92477.9
A15: AU001 | B15: AU032051 | C15: 5160001000 | D15: Publicity/advertising | E15: 92472.04 | F15: AUQ | G15: Wednesday, 19 February 2025 | H15: AP Accruals | I15: INV-14992-ABRYA02 | K15: 2024 accrual - ROS search mark | L15: INV-14992 | M15: BRYANT AND BROTHERS PTY LTD TA SPARRO | Q15: =ABS(E15) -> 92472.04
A16: AU001 | B16: AU032051 | C16: 5160001000 | D16: Publicity/advertising | E16: 90772.74 | F16: AUQ | G16: Wednesday, 29 January 2025 | H16: Rabobank CB Search Marketing | I16: Rabobank ROS Paid Media - Aff | Q16: =ABS(E16) -> 90772.74
A17: AU001 | B17: AU032051 | C17: 5160001000 | D17: Publicity/advertising | E17: -90772.74 | F17: AUQ | G17: Monday, 3 February 2025 | H17: Rabobank CB Search Marketing | I17: Rabobank ROS Paid Media - Aff | Q17: =ABS(E17) -> 90772.74
A18: AU001 | B18: AU032051 | C18: 5160001000 | D18: Publicity/advertising | E18: 90766.96 | F18: AUQ | G18: Wednesday, 19 February 2025 | H18: AP Accruals | I18: INV-14999-ABRYA02 | K18: 2024 accrual - ROS paid media | L18: INV-14999 | M18: BRYANT AND BROTHERS PTY LTD TA SPARRO | Q18: =ABS(E18) -> 90766.96
A19: AU001 | B19: AU032046 | C19: 5160001000 | D19: Publicity/advertising | E19: 66748.92 | F19: AUQ | G19: Monday, 3 March 2025 | H19: AP Accruals | I19: INV192145-AKG2P00 | K19: Brand Health - Invoice 2 | L19: INV192145 | M19: KISIMUL HOLDINGS PTY LTD | Q19: =ABS(E19) -> 66748.92
A20: AU001 | B20: AU036742 | C20: 5160001000 | D20: Publicity/advertising | E20: -65000 | F20: AUQ | G20: Wednesday, 1 January 2025 | H20: RaboTruck Operation (MNGT fee) | I20: Brand Health Survey - question | Q20: =ABS(E20) -> 65000
A21: AU001 | B21: AU036742 | C21: 5160001000 | D21: Publicity/advertising | E21: 65000 | F21: AUQ | G21: Wednesday, 29 January 2025 | H21: Rabobank CB Search Marketing | I21: Brand Health Survey - question | Q21: =ABS(E21) -> 65000
A22: AU001 | B22: AU036742 | C22: 5160001000 | D22: Publicity/advertising | E22: -65000 | F22: AUQ | G22: Monday, 3 February 2025 | H22: Rabobank CB Search Marketing | I22: Brand Health Survey - question | Q22: =ABS(E22) -> 65000
A23: AU001 | B23: AU036742 | C23: 5160001000 | D23: Publicity/advertising | E23: 63705.66 | F23: AUQ | G23: Tuesday, 18 February 2025 | H23: AP Accruals | I23: INV192133-AKG2P00 | K23: CB Brand Health Australia Invo | L23: INV192133 | M23: KISIMUL HOLDINGS PTY LTD | Q23: =ABS(E23) -> 63705.66
A24: AU001 | B24: AU032046 | C24: 5160001000 | D24: Publicity/advertising | E24: -61340.4 | F24: AUQ | G24: Wednesday, 1 January 2025 | H24: RaboTruck Operation (MNGT fee) | I24: The Land advertsing camp(NSW) | Q24: =ABS(E24) -> 61340.4
A25: AU001 | B25: AU032046 | C25: 5160001000 | D25: Publicity/advertising | E25: 61211.03 | F25: AUQ | G25: Tuesday, 7 January 2025 | H25: AP Accruals | I25: INV-14878-ABRYA02 | K25: NSW always on campaign medaia | L25: INV-14878 | M25: BRYANT AND BROTHERS PTY LTD TA SPARRO | Q25: =ABS(E25) -> 61211.03
A26: AU001 | B26: AU032046 | C26: 5160001000 | D26: Publicity/advertising | E26: -34777.19 | F26: AUQ | G26: Wednesday, 1 January 2025 | H26: RaboTruck Operation (MNGT fee) | I26: RaboTruck Operation (MNGT fee) | Q26: =ABS(E26) -> 34777.19
A27: AU001 | B27: AU032046 | C27: 5160001000 | D27: Publicity/advertising | E27: 34703.84 | F27: AUQ | G27: Tuesday, 7 January 2025 | H27: AP Accruals | I27: RABO2025/1-ASOLU01 | K27: RaboTruck Operation Q1 (Manage | L27: RABO2025/1 | M27: SOLUTION ENTERTAINMENT | Q27: =ABS(E27) -> 34703.84
A28: AU001 | B28: AU032046 | C28: 5160001000 | D28: Publicity/advertising | E28: 34650 | F28: AUQ | G28: Wednesday, 29 January 2025 | H28: Rabobank CB Search Marketing | I28: Nuffield Scholar Sponsorship | Q28: =ABS(E28) -> 34650
A29: AU001 | B29: AU032046 | C29: 5160001000 | D29: Publicity/advertising | E29: -34650 | F29: AUQ | G29: Monday, 3 February 2025 | H29: Rabobank CB Search Marketing | I29: Nuffield Scholar Sponsorship | Q29: =ABS(E29) -> 34650
A30: AU001 | B30: AU036740 | C30: 5160001000 | D30: Publicity/advertising | E30: 32997.9 | F30: AUQ | G30: Monday, 3 February 2025 | H30: AP Accruals | I30: 04001932-AFINA00 | K30: FAAA Roadshow sponsorship x 6 | L30: 4001932 | M30: FINANCIAL ADVICE ASSOCIATION | Q30: =ABS(E30) -> 32997.9
A31: AU001 | B31: AU032051 | C31: 5160001000 | D31: Publicity/advertising | E31: -30051 | F31: AUQ | G31: Wednesday, 1 January 2025 | H31: RaboTruck Operation (MNGT fee) | I31: Rabo Paid Media Reta Fee-Dec24 | Q31: =ABS(E31) -> 30051
A32: AU001 | B32: AU032051 | C32: 5160001000 | D32: Publicity/advertising | E32: 30048.8 | F32: AUQ | G32: Wednesday, 29 January 2025 | H32: Rabobank CB Search Marketing | I32: Rabobank Paid Media Retainer | Q32: =ABS(E32) -> 30048.8
A33: AU001 | B33: AU032051 | C33: 5160001000 | D33: Publicity/advertising | E33: -30048.8 | F33: AUQ | G33: Monday, 3 February 2025 | H33: Rabobank CB Search Marketing | I33: Rabobank Paid Media Retainer | Q33: =ABS(E33) -> 30048.8
A34: AU001 | B34: AU032051 | C34: 5160001000 | D34: Publicity/advertising | E34: 30046.89 | F34: AUQ | G34: Tuesday, 18 February 2025 | H34: AP Accruals | I34: INV-14844-ABRYA02 | K34: 2024 accrual - Paid media agen | L34: INV-14844 | M34: BRYANT AND BROTHERS PTY LTD TA SPARRO | Q34: =ABS(E34) -> 30046.89
A35: AU052 | B35: AU032056 | C35: 5160001000 | D35: Publicity/advertising | E35: 29899.45 | F35: AUQ | G35: Monday, 3 March 2025 | H35: AP Accruals | I35: INVKYNAU2228-AKYNE00 | K35: Rural Confidence Survey 24/25 | L35: INVKYNAU2228 | M35: KYNETEC AUSTRALIA PTY LTD | Q35: =ABS(E35) -> 29899.45
A36: AU001 | B36: AU032046 | C36: 5160001000 | D36: Publicity/advertising | E36: -29636.06 | F36: AUQ | G36: Wednesday, 1 January 2025 | H36: RaboTruck Operation (MNGT fee) | I36: RaboTruck Operation (Proj Mgr) | Q36: =ABS(E36) -> 29636.06
A37: AU001 | B37: AU032046 | C37: 5160001000 | D37: Publicity/advertising | E37: 29573.55 | F37: AUQ | G37: Tuesday, 7 January 2025 | H37: AP Accruals | I37: RABO2025/4-ASOLU01 | K37: RaboTruck Operation Q1 (Projec | L37: RABO2025/4 | M37: SOLUTION ENTERTAINMENT | Q37: =ABS(E37) -> 29573.55
A38: AU001 | B38: AU032046 | C38: 5160001000 | D38: Publicity/advertising | E38: -27500 | F38: AUQ | G38: Wednesday, 1 January 2025 | H38: RaboTruck Operation (MNGT fee) | I38: Cattle Australia sponsorship | Q38: =ABS(E38) -> 27500
A39: AU001 | B39: AU032046 | C39: 5160001000 | D39: Publicity/advertising | E39: 27500 | F39: AUQ | G39: Wednesday, 29 January 2025 | H39: Rabobank CB Search Marketing | I39: Cattle Australia sponsorship | Q39: =ABS(E39) -> 27500
A40: AU001 | B40: AU032046 | C40: 5160001000 | D40: Publicity/advertising | E40: -27500 | F40: AUQ | G40: Monday, 3 February 2025 | H40: Rabobank CB Search Marketing | I40: Cattle Australia sponsorship | Q40: =ABS(E40) -> 27500
A41: AU001 | B41: AU032046 | C41: 5160001000 | D41: Publicity/advertising | E41: -25930.77 | F41: AUQ | G41: Wednesday, 1 January 2025 | H41: RaboTruck Operation (MNGT fee) | I41: RaboTruck Operation (Driver) | Q41: =ABS(E41) -> 25930.77
A42: AU001 | B42: AU032046 | C42: 5160001000 | D42: Publicity/advertising | E42: -25926.48 | F42: AUQ | G42: Wednesday, 1 January 2025 | H42: RaboTruck Operation (MNGT fee) | I42: RaboTruck Operation (CabLease) | Q42: =ABS(E42) -> 25926.48
A43: AU001 | B43: AU032046 | C43: 5160001000 | D43: Publicity/advertising | E43: 25876.08 | F43: AUQ | G43: Tuesday, 7 January 2025 | H43: AP Accruals | I43: RABO2025/5-ASOLU01 | K43: RaboTruck Operation Q1 (Driver | L43: RABO2025/5 | M43: SOLUTION ENTERTAINMENT | Q43: =ABS(E43) -> 25876.08
A44: AU001 | B44: AU032046 | C44: 5160001000 | D44: Publicity/advertising | E44: 25871.8 | F44: AUQ | G44: Tuesday, 7 January 2025 | H44: AP Accruals | I44: RABO2025/3-ASOLU01 | K44: RaboTruck Operation Q1 (Cab Le | L44: RABO2025/3 | M44: SOLUTION ENTERTAINMENT | Q44: =ABS(E44) -> 25871.8
A45: AU001 | B45: AU032051 | C45: 5160001000 | D45: Publicity/advertising | E45: 24637.95 | F45: AUQ | G45: Wednesday, 29 January 2025 | H45: Rabobank CB Search Marketing | I45: Rabobank ROS Paid Media - Soci | Q45: =ABS(E45) -> 24637.95
A46: AU001 | B46: AU032051 | C46: 5160001000 | D46: Publicity/advertising | E46: -24637.95 | F46: AUQ | G46: Monday, 3 February 2025 | H46: Rabobank CB Search Marketing | I46: Rabobank ROS Paid Media - Soci | Q46: =ABS(E46) -> 24637.95
A47: AU001 | B47: AU032046 | C47: 5160001000 | D47: Publicity/advertising | E47: -24062.5 | F47: AUQ | G47: Wednesday, 1 January 2025 | H47: RaboTruck Operation (MNGT fee) | I47: Farm to Fork Videography | Q47: =ABS(E47) -> 24062.5
A48: AU001 | B48: AU032051 | C48: 5160001000 | D48: Publicity/advertising | E48: -24062.5 | F48: AUQ | G48: Wednesday, 1 January 2025 | H48: RaboTruck Operation (MNGT fee) | I48: Farm to Fork Videography - Far | Q48: =ABS(E48) -> 24062.5
A49: AU001 | B49: AU032051 | C49: 5160001000 | D49: Publicity/advertising | E49: 24062.5 | F49: AUQ | G49: Wednesday, 29 January 2025 | H49: Rabobank CB Search Marketing | I49: Farm to Fork Videography - Far | Q49: =ABS(E49) -> 24062.5
A50: AU001 | B50: AU032051 | C50: 5160001000 | D50: Publicity/advertising | E50: -24062.5 | F50: AUQ | G50: Monday, 3 February 2025 | H50: Rabobank CB Search Marketing | I50: Farm to Fork Videography - Far | Q50: =ABS(E50) -> 24062.5
A51: AU001 | B51: AU032051 | C51: 5160001000 | D51: Publicity/advertising | E51: 24060.97 | F51: AUQ | G51: Monday, 10 February 2025 | H51: AP Accruals | I51: INV-0219-ADUAL00 | K51: Farm to Fork farm testimonial, | L51: INV-0219 | M51: DUAL ENTERTAINMENT PTY LTD | Q51: =ABS(E51) -> 24060.97
A52: AU001 | B52: AU032051 | C52: 5160001000 | D52: Publicity/advertising | E52: 24060.97 | F52: AUQ | G52: Tuesday, 4 March 2025 | H52: AP Accruals | I52: INV-0225-ADUAL00 | K52: Farm to Fork Videography - Far | L52: INV-0225 | M52: DUAL ENTERTAINMENT PTY LTD | Q52: =ABS(E52) -> 24060.97
A53: AU001 | B53: AU032051 | C53: 5160001000 | D53: Publicity/advertising | E53: 24060.97 | F53: AUQ | G53: Tuesday, 4 March 2025 | H53: AP Accruals | I53: INV-0227-ADUAL00 | K53: Farm to Fork- Videography - Fa | L53: INV-0227 | M53: DUAL ENTERTAINMENT PTY LTD | Q53: =ABS(E53) -> 24060.97
A54: AU001 | B54: AU032046 | C54: 5160001000 | D54: Publicity/advertising | E54: 24011.75 | F54: AUQ | G54: Thursday, 16 January 2025 | H54: AP Accruals | I54: INV-0218-ADUAL00 | K54: client testimonial video and p | L54: INV-0218 | M54: DUAL ENTERTAINMENT PTY LTD | Q54: =ABS(E54) -> 24011.75
A55: AU001 | B55: AU032046 | C55: 5160001000 | D55: Publicity/advertising | E55: 24011.75 | F55: AUQ | G55: Friday, 7 March 2025 | H55: AP Accruals | I55: INV-0228-ADUAL00 | K55: Farm to Fork testimonial, phot | L55: INV-0228 | M55: DUAL ENTERTAINMENT PTY LTD | Q55: =ABS(E55) -> 24011.75
A56: AU001 | B56: AU032051 | C56: 5160001000 | D56: Publicity/advertising | E56: 21723.03 | F56: AUQ | G56: Wednesday, 19 February 2025 | H56: AP Accruals | I56: INV-14845-ABRYA02 | K56: 2024 accrual - ROS social - De | L56: INV-14845 | M56: BRYANT AND BROTHERS PTY LTD TA SPARRO | Q56: =ABS(E56) -> 21723.03
A57: AU052 | B57: AU032041 | C57: 5160001000 | D57: Publicity/advertising | E57: 19550.68 | F57: AUQ | G57: Friday, 14 February 2025 | H57: AP Accruals | I57: 79885-OSPRI00 | K57: Sprinklr Subscription | L57: 79885 | M57: SPRINKLR INC. | Q57: =ABS(E57) -> 19550.68
A58: AU052 | B58: AU032041 | C58: 5160001000 | D58: Publicity/advertising | E58: -19550.68 | F58: AUQ | G58: Thursday, 20 February 2025 | H58: AP Accruals | I58: 79885-OSPRI00 | K58: Sprinklr Subscription | L58: 79885 | M58: SPRINKLR INC. | Q58: =ABS(E58) -> 19550.68
A59: AU001 | B59: AU032046 | C59: 5160001000 | D59: Publicity/advertising | E59: -18700 | F59: AUQ | G59: Wednesday, 1 January 2025 | H59: RaboTruck Operation (MNGT fee) | I59: RaboTruck Gippsland event x 2 | Q59: =ABS(E59) -> 18700
A60: AU001 | B60: AU032051 | C60: 5160001000 | D60: Publicity/advertising | E60: 17158.91 | F60: AUQ | G60: Monday, 10 February 2025 | H60: AP Accruals | I60: INVCAN-900007394-ACANS00 | K60: ROS Canstar portal database fe | L60: INVCAN-900007394 | M60: CANSTAR PTY LIMITED | Q60: =ABS(E60) -> 17158.91
A61: AU001 | B61: AU032046 | C61: 5160001000 | D61: Publicity/advertising | E61: -15812.5 | F61: AUQ | G61: Wednesday, 1 January 2025 | H61: RaboTruck Operation (MNGT fee) | I61: Farm to Fork TV airing inc | Q61: =ABS(E61) -> 15812.5
A62: AU001 | B62: AU032051 | C62: 5160001000 | D62: Publicity/advertising | E62: -15812.5 | F62: AUQ | G62: Wednesday, 1 January 2025 | H62: RaboTruck Operation (MNGT fee) | I62: Farm to Fork TV airing Rabofac | Q62: =ABS(E62) -> 15812.5
A63: AU001 | B63: AU032051 | C63: 5160001000 | D63: Publicity/advertising | E63: 15811.49 | F63: AUQ | G63: Thursday, 16 January 2025 | H63: AP Accruals | I63: INV-0217-ADUAL00 | K63: Farm to Fork TV Airing - Inclu | L63: INV-0217 | M63: DUAL ENTERTAINMENT PTY LTD | Q63: =ABS(E63) -> 15811.49
A64: AU001 | B64: AU032051 | C64: 5160001000 | D64: Publicity/advertising | E64: 15811.49 | F64: AUQ | G64: Thursday, 16 January 2025 | H64: AP Accruals | I64: INV-0220-ADUAL00 | K64: - Farm to Fork TV Airing - Inc | L64: INV-0220 | M64: DUAL ENTERTAINMENT PTY LTD | Q64: =ABS(E64) -> 15811.49
A65: AU001 | B65: AU032051 | C65: 5160001000 | D65: Publicity/advertising | E65: 15811.49 | F65: AUQ | G65: Tuesday, 4 March 2025 | H65: AP Accruals | I65: INV-0224-ADUAL00 | K65: Farm to Fork | L65: INV-0224 | M65: DUAL ENTERTAINMENT PTY LTD | Q65: =ABS(E65) -> 15811.49
A66: AU001 | B66: AU032046 | C66: 5160001000 | D66: Publicity/advertising | E66: 15779.15 | F66: AUQ | G66: Tuesday, 4 March 2025 | H66: AP Accruals | I66: INV-0226-ADUAL00 | K66: Farm to Fork -TV Airing - Incl | L66: INV-0226 | M66: DUAL ENTERTAINMENT PTY LTD | Q66: =ABS(E66) -> 15779.15
A67: AU001 | B67: AU032046 | C67: 5160001000 | D67: Publicity/advertising | E67: 15779.15 | F67: AUQ | G67: Friday, 7 March 2025 | H67: AP Accruals | I67: INV-0229-ADUAL00 | K67: Farm to F0rk TV airing, social | L67: INV-0229 | M67: DUAL ENTERTAINMENT PTY LTD | Q67: =ABS(E67) -> 15779.15
A68: AU001 | B68: AU032051 | C68: 5160001000 | D68: Publicity/advertising | E68: 14916 | F68: AUQ | G68: Wednesday, 29 January 2025 | H68: Rabobank CB Search Marketing | I68: Rabobank ROS Paid Media - cre | Q68: =ABS(E68) -> 14916
A69: AU001 | B69: AU032051 | C69: 5160001000 | D69: Publicity/advertising | E69: -14916 | F69: AUQ | G69: Monday, 3 February 2025 | H69: Rabobank CB Search Marketing | I69: Rabobank ROS Paid Media - cre | Q69: =ABS(E69) -> 14916
A70: AU001 | B70: AU032051 | C70: 5160001000 | D70: Publicity/advertising | E70: 14915.05 | F70: AUQ | G70: Tuesday, 18 February 2025 | H70: AP Accruals | I70: INV-14960-ABRYA02 | K70: 2024 accrual - | L70: INV-14960 | M70: BRYANT AND BROTHERS PTY LTD TA SPARRO | Q70: =ABS(E70) -> 14915.05
A71: AU052 | B71: AU032046 | C71: 5160001000 | D71: Publicity/advertising | E71: -13200 | F71: AUQ | G71: Wednesday, 1 January 2025 | H71: RaboTruck Operation (MNGT fee) | I71: STCF Sponsorship | Q71: =ABS(E71) -> 13200
A72: AU052 | B72: AU032046 | C72: 5160001000 | D72: Publicity/advertising | E72: 13200 | F72: AUQ | G72: Wednesday, 29 January 2025 | H72: Rabobank CB Search Marketing | I72: STCF Sponsorship | Q72: =ABS(E72) -> 13200
A73: AU052 | B73: AU032046 | C73: 5160001000 | D73: Publicity/advertising | E73: -13200 | F73: AUQ | G73: Monday, 3 February 2025 | H73: Rabobank CB Search Marketing | I73: STCF Sponsorship | Q73: =ABS(E73) -> 13200
A74: AU001 | B74: AU032051 | C74: 5160001000 | D74: Publicity/advertising | E74: 10999.3 | F74: AUQ | G74: Friday, 24 January 2025 | H74: AP Accruals | I74: INV-0037-ASAVE01 | K74: Saveful - fridge full of recip | L74: INV-0037 | M74: SAVEFUL WORLDWIDE PTY LTD | Q74: =ABS(E74) -> 10999.3
A75: AU001 | B75: AU032046 | C75: 5160001000 | D75: Publicity/advertising | E75: 10925.35 | F75: AUQ | G75: Tuesday, 18 March 2025 | H75: 113522301-17/07/24-ACGUW05 | I75: 80354-OSPRI00 | Q75: =ABS(E75) -> 10925.35
A76: AU001 | B76: AU032046 | C76: 5160001000 | D76: Publicity/advertising | E76: 10427.96 | F76: AUQ | G76: Monday, 10 March 2025 | H76: AP Accruals | I76: INV-1369-AVNRP00 | K76: AIO video Rupert | L76: INV-1369 | M76: VNR PTY LTD TA VNR CREATIVE | Q76: =ABS(E76) -> 10427.96
A77: AU001 | B77: AU032046 | C77: 5160001000 | D77: Publicity/advertising | E77: -9350 | F77: AUQ | G77: Wednesday, 1 January 2025 | H77: RaboTruck Operation (MNGT fee) | I77: RaboTruck Angus Expo | Q77: =ABS(E77) -> 9350
A78: AU001 | B78: AU032046 | C78: 5160001000 | D78: Publicity/advertising | E78: -9350 | F78: AUQ | G78: Wednesday, 1 January 2025 | H78: RaboTruck Operation (MNGT fee) | I78: RaboTruck FNQ FDs | Q78: =ABS(E78) -> 9350
A79: AU001 | B79: AU032046 | C79: 5160001000 | D79: Publicity/advertising | E79: -9350 | F79: AUQ | G79: Wednesday, 1 January 2025 | H79: RaboTruck Operation (MNGT fee) | I79: RaboTruck Taroom Show | Q79: =ABS(E79) -> 9350
A80: AU001 | B80: AU032046 | C80: 5160001000 | D80: Publicity/advertising | E80: -8800 | F80: AUQ | G80: Wednesday, 1 January 2025 | H80: RaboTruck Operation (MNGT fee) | I80: Rabobank CB Srch Mrkt-Dec 2024 | Q80: =ABS(E80) -> 8800
A81: AU001 | B81: AU032051 | C81: 5160001000 | D81: Publicity/advertising | E81: 8799.44 | F81: AUQ | G81: Tuesday, 4 March 2025 | H81: AP Accruals | I81: INVRMK2946-ARAIN10 | K81: MoneyMag SMSF award ad s | L81: INVRMK2946 | M81: RAINMAKER INFORMATION PTY LTD | Q81: =ABS(E81) -> 8799.44
A82: AU001 | B82: AU032046 | C82: 5160001000 | D82: Publicity/advertising | E82: 8026 | F82: AUQ | G82: Wednesday, 29 January 2025 | H82: Rabobank CB Search Marketing | I82: Rabobank CB Search Marketing | Q82: =ABS(E82) -> 8026
A83: AU001 | B83: AU032046 | C83: 5160001000 | D83: Publicity/advertising | E83: -8026 | F83: AUQ | G83: Monday, 3 February 2025 | H83: Rabobank CB Search Marketing | I83: Rabobank CB Search Marketing | Q83: =ABS(E83) -> 8026
A84: AU001 | B84: AU032046 | C84: 5160001000 | D84: Publicity/advertising | E84: 8009.06 | F84: AUQ | G84: Wednesday, 19 February 2025 | H84: AP Accruals | I84: INV-14992-ABRYA02 | K84: 2024 accrual - CB search marke | L84: INV-14992 | M84: BRYANT AND BROTHERS PTY LTD TA SPARRO | Q84: =ABS(E84) -> 8009.06
A85: AU052 | B85: AU032041 | C85: 5160001000 | D85: Publicity/advertising | E85: -6516.88 | F85: AUQ | G85: Sunday, 23 February 2025 | H85: 79885-OSPRI00 | I85: 79885-OSPRI00 | Q85: =ABS(E85) -> 6516.88
A86: AU052 | B86: AU032041 | C86: 5160001000 | D86: Publicity/advertising | E86: 6516.88 | F86: AUQ | G86: Sunday, 23 February 2025 | H86: 90848234-ADIME01 | I86: 79885-OSPRI00 | Q86: =ABS(E86) -> 6516.88
A87: AU001 | B87: AU032051 | C87: 5160001000 | D87: Publicity/advertising | E87: -5500 | F87: AUQ | G87: Wednesday, 1 January 2025 | H87: RaboTruck Operation (MNGT fee) | I87: Farm to Fork Dinner Melbo | Q87: =ABS(E87) -> 5500 | S87: Income
A88: AU001 | B88: AU032051 | C88: 5160001000 | D88: Publicity/advertising | E88: 5500 | F88: AUQ | G88: Monday, 3 February 2025 | H88: AP Accruals | I88: 1000-ABENE01 | K88: Beneath The Brim Sponsorship b | L88: 1000 | M88: A DAUGHTERS WAY LTD TA BENEATH THE BRIM | Q88: =ABS(E88) -> 5500
A89: AU052 | B89: AU032051 | C89: 5160001000 | D89: Publicity/advertising | E89: 5000.01 | F89: AUQ | G89: Wednesday, 22 January 2025 | H89: 2220181-ATELU01 | I89: AP-PR 71451-OSPRI00 | Q89: =ABS(E89) -> 5000.01
A90: AU052 | B90: AU032051 | C90: 5160001000 | D90: Publicity/advertising | E90: -5000.01 | F90: AUQ | G90: Monday, 3 February 2025 | H90: 2220181-ATELU01 | I90: AP-PR 71451-OSPRI00 | Q90: =ABS(E90) -> 5000.01
A91: AU001 | B91: AU032046 | C91: 5160001000 | D91: Publicity/advertising | E91: 3892.3 | F91: AUQ | G91: Friday, 14 March 2025 | H91: AP Accruals | I91: 33880-APROD00 | K91: Outdoor cafe umbrella x 4 | L91: 33880 | M91: PRODEUCE PTY LTD | Q91: =ABS(E91) -> 3892.3
A92: AU052 | B92: AU032051 | C92: 5160001000 | D92: Publicity/advertising | E92: -3333.34 | F92: AUQ | G92: Wednesday, 1 January 2025 | H92: 2220181-ATELU01 | I92: AP-PR 71451-OSPRI00 | Q92: =ABS(E92) -> 3333.34
A93: AU001 | B93: AU032046 | C93: 5160001000 | D93: Publicity/advertising | E93: 2907.4 | F93: AUQ | G93: Wednesday, 19 February 2025 | H93: AP Accruals | I93: INV-14845-ABRYA02 | K93: 2024 accrual - CB boosted post | L93: INV-14845 | M93: BRYANT AND BROTHERS PTY LTD TA SPARRO | Q93: =ABS(E93) -> 2907.4
A94: AU001 | B94: AU032056 | C94: 5160001000 | D94: Publicity/advertising | E94: 1919.35 | F94: AUQ | G94: Monday, 3 March 2025 | H94: AP Accruals | I94: INV-51-ACOUR00 | K94: Q1 2025 Rabo Rural Confidence | L94: INV-51 | M94: COURTYARD ON GIBRALTAR PTY LTD | Q94: =ABS(E94) -> 1919.35
A95: AU001 | B95: AU032051 | C95: 5160001000 | D95: Publicity/advertising | E95: 1819.64 | F95: AUQ | G95: Friday, 7 March 2025 | H95: AP Accruals | I95: 621969-AVISI01 | K95: Vision6 subscription | L95: 621969 | M95: VISION 6 PTY LTD | Q95: =ABS(E95) -> 1819.64
A96: AU001 | B96: AU032051 | C96: 5160001000 | D96: Publicity/advertising | E96: 1804.56 | F96: AUQ | G96: Monday, 10 February 2025 | H96: AP Accruals | I96: 618839-AVISI01 | K96: Vision6 subscription | L96: 618839 | M96: VISION 6 PTY LTD | Q96: =ABS(E96) -> 1804.56
A97: AU001 | B97: AU032046 | C97: 5160001000 | D97: Publicity/advertising | E97: 1421.91 | F97: AUQ | G97: Monday, 10 March 2025 | H97: AP Accruals | I97: 89877-ANUNN00 | K97: Deposits rate ad | L97: 89877 | M97: NUNN MEDIA | Q97: =ABS(E97) -> 1421.91
A98: AU001 | B98: AU032051 | C98: 5160001000 | D98: Publicity/advertising | E98: 1224.43 | F98: AUQ | G98: Friday, 7 March 2025 | H98: AP Accruals | I98: 0216-WNICK00 | K98: Nick Baker | L98: 216 | M98: NICK BAKER | Q98: =ABS(E98) -> 1224.43
A99: AU001 | B99: AU032051 | C99: 5160001000 | D99: Publicity/advertising | E99: 1219.79 | F99: AUQ | G99: Wednesday, 8 January 2025 | H99: AP Accruals | I99: 0205-WNICK00 | K99: Nick Baker Digital Marketing F | L99: 205 | M99: NICK BAKER | Q99: =ABS(E99) -> 1219.79
A100: AU001 | B100: AU032051 | C100: 5160001000 | D100: Publicity/advertising | E100: 1216.88 | F100: AUQ | G100: Monday, 10 February 2025 | H100: AP Accruals | I100: 0211-WNICK00 | K100: Nick Baker | L100: 211 | M100: NICK BAKER | Q100: =ABS(E100) -> 1216.88
...

Sheet Open-Jubilees
A1: Account Number | C1: =Summary!A12 -> 5160006000
A2: Account Name | C2: =Summary!B12 -> Opening jubilees own buildin | G2: Notes:
A3: GL Total | C3: 0 | G3: No entertainment expenses
A4: Per TB | C4: =SUM(D:D) -> 0 | R4: AU001 | S4: =SUMIF($A$10:$A$23974,"AU001",S9:S23973) -> 0
A5: Variance | C5: =C3-C4 -> 0 | R5: AU052 | S5: =SUMIF($A$10:$A$23975,"AU052",S9:S23974) -> 0
AA6: Income tax purposes
A7: BUSINESS_UNIT_CODE | B7: ACCOUNT_CODE | C7: DESCRIPTION | D7: BASE_AMOUNT | E7: BASE_CURRENCY_CODE | F7: JOURNAL_DATE | G7: DESCR | H7: LINE_DESCR | I7: PURPOSE | J7: INVOICE_DESCR | K7: INVOICE_ID | L7: VENDOR_NAME | M7: EMPLOYEE_NAME | O7: ABS | P7: Search Terms | Q7: Tax Description | R7: ME? Y/N | S7: ME $ | T7: Not ME but other type of FB Y/N | U7: Not ME but other type of FB ==> $ | V7: Nets to Nil in GL accts | W7: s58P M&I or Bus Exp - notFB | X7: ME | Y7: Car FB - addn op costs | Z7: CP Exp FB | AA7: Capital expenditure | AB7: No FBT and not ded | AC7: Additional Comments

Sheet Promo gifts
A1: Account Number | C1: =Summary!A14 -> 5160008000
A2: Account Name | C2: =Summary!B14 -> Promotional gifts | G2: Notes: | S2: No ME included. All tax deductible
A3: GL Total | C3: 7059.24 | G3: No entertainment expenses included and all tax deductible
A4: Per TB | C4: =SUM(E:E) -> 7059.24 | T4: AU001 | U4: =SUMIF($A$10:$A$23973,"AU001",U9:U23972) -> 0
A5: Variance | C5: =C3-C4 -> 0 | T5: AU052 | U5: =SUMIF($A$10:$A$23974,"AU052",U9:U23973) -> 0
AC6: Income tax purposes
A7: BUSINESS_UNIT_CODE | B7: OPERATING_UNIT_CODE | C7: ACCOUNT_CODE | D7: DESCRIPTION | E7: BASE_AMOUNT | F7: BASE_CURRENCY_CODE | G7: JOURNAL_DATE | H7: DESCR | I7: LINE_DESCR | J7: PURPOSE | K7: INVOICE_DESCR | L7: INVOICE_ID | M7: VENDOR_NAME | N7: EMPLOYEE_NAME | O7: CHARGE_DESCRIPTION | Q7: ABS | R7: Search Terms | S7: Tax Description | T7: ME? Y/N | U7: ME $ | V7: Not ME but other type of FB Y/N | W7: Not ME but other type of FB ==> $ | X7: Nets to Nil in GL accts | Y7: s58P M&I or Bus Exp - notFB | Z7: ME | AA7: Car FB - addn op costs | AB7: CP Exp FB | AC7: Capital expenditure | AD7: No FBT and not ded | AE7: Additional Comments
A8: AU001 | B8: AU070150 | C8: 5160008000 | D8: Promotional gifts | E8: 451 | F8: AUQ | G8: 45737 | H8: AP Accruals | I8: 2852-ATURN01 | J8: Gift bags for WAB | L8: 2852 | O8: TURNKEY PROMOTIONS | Q8: =ABS(E8) -> 451 | S8: 50 bags - accept 58P
A9: AU052 | B9: AU071196 | C9: 5160008000 | D9: Promotional gifts | E9: 70.41 | F9: AUQ | G9: 45659 | H9: CCMS | I9: RigbyC-Office Supplies | J9: Maureen Wilde gift | O9: WOOLWORTHS/CNR 540 GEORGE | Q9: =ABS(E9) -> 70.41 | S9: 58P
A10: AU052 | B10: AU070150 | C10: 5160008000 | D10: Promotional gifts | E10: 1363.64 | F10: AUQ | G10: 45694 | H10: CCMS | I10: RigbyC-Default Licensee Mercha | J10: Ross Dawson - Global Food Forum TIckets | O10: TICKETS*THE AUSTRA/fs72t8tf | Q10: =ABS(E10) -> 1363.64 | S10: OK - for clients
A11: AU052 | B11: AU070150 | C11: 5160008000 | D11: Promotional gifts | E11: 177.27 | F11: AUQ | G11: 45694 | H11: CCMS | I11: RigbyC-Other Personnel Expense | J11: James Ashworth - Client Gift - Delia Sparkes Metcash | O11: SP LILAC AND WILLOW | Q11: =ABS(E11) -> 177.27 | S11: OK - for clients
A12: AU052 | B12: AU070150 | C12: 5160008000 | D12: Promotional gifts | E12: 99.01 | F12: AUQ | G12: 45723 | H12: CCMS | I12: RigbyC-Software | J12: Client Gift Kate Beddoe - Lunch and Learn | O12: SP LITTLE KOHA | Q12: =ABS(E12) -> 99.01 | S12: OK - for clients
A13: AU052 | B13: AU070150 | C13: 5160008000 | D13: Promotional gifts | E13: 2716.36 | F13: AUQ | G13: 45726 | H13: CCMS | I13: Haynest-Entertainment Expense | J13: WAB gifts - 36 wines | O13: CellarDoor.co | Q13: =ABS(E13) -> 2716.36 | S13: 58P
A14: AU052 | B14: AU030711 | C14: 5160008000 | D14: Promotional gifts | E14: 67.55 | F14: AUQ | G14: 45729 | H14: CCMS | I14: HumeH-Default Licensee Merchan | J14: Burbury Settlement Gift - wine glasses and card for hamper | O14: COCO BLUE | Q14: =ABS(E14) -> 67.55 | S14: OK - for clients
A15: AU052 | B15: AU030711 | C15: 5160008000 | D15: Promotional gifts | E15: 40.91 | F15: AUQ | G15: 45729 | H15: CCMS | I15: HumeH-Offshore Meals & Lodging | J15: Wine for Burburys | O15: SQ *MILTON VINEYARD | Q15: =ABS(E15) -> 40.91 | S15: OK - for clients
A16: AU052 | B16: AU032054 | C16: 5160008000 | D16: Promotional gifts | E16: 183.09 | F16: AUQ | G16: 45743 | H16: CCMS | I16: DoupeJ-Office Supplies | J16: Gifts for 2 clients for Sustainability Offsite | O16: SQ *HAIGH'S THE STRAND AR | Q16: =ABS(E16) -> 183.09 | S16: OK - for clients
A17: AU052 | B17: AU070150 | C17: 5160008000 | D17: Promotional gifts | E17: 1890 | F17: AUQ | G17: 45744 | H17: CCMS | I17: Haynest-Default Licensee Merch | J17: WAB shirt gifts | O17: R.M.Williams | Q17: =ABS(E17) -> 1890 | S17: 58P

Sheet Sponsoring
A1: Account Number | C1: =Summary!A13 -> 5160007000
A2: Account Name | C2: =Summary!B13 -> Sponsoring | G2: Notes:
A3: GL Total | C3: 18398.38 | G3: No entertainment expenses included and all tax deductible | T3: AU001 | V3: =SUMIF($A$10:$A$23974,"AU001",V8:V23972) -> 0 | AC3: AU001 | AD3: =SUMIF($A$10:$A$408,"AU001",AD8:AD407) -> 0 | AE3: =SUMIF($A$10:$A$408,"AU001",AE8:AE407) -> 0
A4: Per TB | C4: =SUM(E:E) -> 18398.38 | G4: Charity days/community days have not been treated as recreational activity (arguably does not meet ITAA definition) | T4: AU052 | V4: =SUMIF($A$10:$A$23975,"AU052",V8:V23973) -> 127.27 | AC4: AU052 | AD4: =SUMIF($A$10:$A$408,"AU052",AD9:AD407) -> 0 | AE4: =SUMIF($A$10:$A$408,"AU052",AE9:AE407) -> 0
A5: Variance | C5: =C3-C4 -> 0
AD6: Income tax purposes
A7: BUSINESS_UNIT_CODE | B7: OPERATING_UNIT_CODE | C7: ACCOUNT_CODE | D7: DESCRIPTION | E7: BASE_AMOUNT | F7: BASE_CURRENCY_CODE | G7: JOURNAL_DATE | H7: DESCR | I7: LINE_DESCR | J7: PURPOSE | K7: INVOICE_DESCR | L7: INVOICE_ID | M7: VENDOR_NAME | N7: EMPLOYEE_NAME | O7: CHARGE_DESCRIPTION | Q7: ABS | R7: Search Terms | S7: Tax Description | T7: ME? Y/N | U7: OU | V7: ME $ | W7: Not ME but other type of FB Y/N | X7: Not ME but other type of FB ==> $ | Y7: Nets to Nil in GL accts | Z7: s58P M&I or Bus Exp - notFB | AA7: ME | AB7: Car FB - addn op costs | AC7: CP Exp FB | AD7: Capital expenditure | AE7: No FBT and not ded | AF7: Additional Comments
A8: AU001 | B8: AU032063 | C8: 5160007000 | D8: Sponsoring | E8: 7500 | F8: AUQ | G8: 45719 | H8: AP Accruals | I8: ASCF-0078-AAUST86 | K8: NSW Client Council Sponsorship | L8: ASCF-0078 | M8: AUSTRALIAN SKIN CANCER FOUNDATION LTD | Q8: =ABS(E8) -> 7500
A9: AU001 | B9: AU032072 | C9: 5160007000 | D9: Sponsoring | E9: 9443.29 | F9: AUQ | G9: 45720 | H9: AP Accruals | I9: INV-1553-ARIDI01 | K9: 2024 Sponsorship of Riding for | L9: INV-1553 | M9: RIDING FOR THE DISABLED OF THE ACT INC | Q9: =ABS(E9) -> 9443.29
A10: AU001 | B10: AU032046 | C10: 5160007000 | D10: Sponsoring | E10: 400 | F10: AUQ | G10: 45723 | H10: AP Accruals | I10: 2060-ABOMB00 | K10: Bombala Show Society-Dog Trial | L10: 2060 | M10: BOMBALA EXHIBITION SOCIETY INC | Q10: =ABS(E10) -> 400
A11: AU052 | B11: AU030317 | C11: 5160007000 | D11: Sponsoring | E11: 127.27 | F11: AUQ | G11: 45706 | H11: CCMS | I11: BennettA-Entertainment Expense | J11: Gannon discussion group xmas drinks | M11: SQ *NERRENA CRICKET CLUB | Q11: =ABS(E11) -> 127.27 | S11: ME | T11: Y | U11: =B11 -> AU030317 | V11: =E11 -> 127.27
A12: AU052 | B12: AU030423 | C12: 5160007000 | D12: Sponsoring | E12: 500 | F12: AUQ | G12: 45707 | H12: CCMS | I12: KelleyM-Default Licensee Merch | J12: Sponsorship - Cotton Dinner | M12: TRYBOOKING*CHCGIA/219528771395 | Q12: =ABS(E12) -> 500
A13: AU052 | B13: AU030214 | C13: 5160007000 | D13: Sponsoring | E13: 427.82 | F13: AUQ | G13: 45734 | H13: CCMS | I13: HuntA-Contributions & Club Mem | J13: Parkes Ewe Comp Sponsorship | M13: Parkes Bowling Club | Q13: =ABS(E13) -> 427.82

Sheet Marketing
A1: Account Number | C1: =Summary!A15 -> 5160010000
A2: Account Name | C2: =Summary!B15 -> Marketing expense | H2: Notes: | T2: AU001 | V2: =SUMIF($A$8:$A$23958,"AU001",V8:V23958) -> 0
A3: GL Total | C3: -4733.21 | H3: All field day expenses have been treated as deductible | T3: AU052 | V3: =SUMIF($A$8:$A$23959,"AU052",V8:V23959) -> 1340.71
A4: Per TB | C4: =SUM(E:E) -> -4733.21 | H4: All branch Anniversary expenses have been treated as ME | V4: =V71+V3 -> 1340.71
A5: Variance | C5: =C3-C4 -> 0
AD6: Income tax purposes
A7: BUSINESS_UNIT_CODE | B7: OPERATING_UNIT_CODE | C7: ACCOUNT_CODE | D7: DESCRIPTION | E7: BASE_AMOUNT | F7: BASE_CURRENCY_CODE | G7: JOURNAL_DATE | H7: DESCR | I7: LINE_DESCR | J7: PURPOSE | K7: INVOICE_DESCR | L7: INVOICE_ID | M7: VENDOR_NAME | N7: EMPLOYEE_NAME | O7: CHARGE_DESCRIPTION | Q7: ABS | R7: Search Terms | S7: Tax Description | T7: ME? Y/N | U7: OU | V7: ME $ | W7: Not ME but other type of FB Y/N | X7: Not ME but other type of FB ==> $ | Y7: Nets to Nil in GL accts | Z7: s58P M&I or Bus Exp - notFB | AA7: ME | AB7: Car FB - addn op costs | AC7: CP Exp FB | AD7: Capital expenditure | AE7: No FBT and not ded | AF7: Additional Comments
A8: AU001 | B8: AU036740 | C8: 5160010000 | D8: Marketing expense | E8: 6599.58 | F8: AUQ | G8: 45677 | H8: AP Accruals | I8: AR001558-AAGRI25 | K8: Co hosting event with AgriFutu | L8: AR001558 | M8: AGRIFUTURES AUSTRALIA | Q8: =ABS(E8) -> 6599.58
A9: AU052 | B9: AU073158 | C9: 5160010000 | D9: Marketing expense | E9: 1565.5 | F9: AUQ | G9: 45705 | H9: CCMS | I9: OoiS-Default Licensee Merchant | J9: Wholesale SMS text to clients | O9: WholesaleSMS Pty Ltd | Q9: =ABS(E9) -> 1565.5
A10: AU052 | B10: AU030320 | C10: 5160010000 | D10: Marketing expense | E10: 1003.52 | F10: AUQ | G10: 45670 | H10: AP Accruals | I10: 14220-AHAMI04 | K10: Venue hire for client Christma | L10: 14220 | M10: HAMILTON PASTORAL AND AGRICULTURAL | Q10: =ABS(E10) -> 1003.52 | S10: ME | T10: Y | U10: =B10 -> AU030320 | V10: =E10 -> 1003.52
A11: AU052 | B11: AU073158 | C11: 5160010000 | D11: Marketing expense | E11: 909 | F11: AUQ | G11: 45677 | H11: CCMS | I11: OoiS-Default Licensee Merchant | J11: Wholesale SMS text to clients | O11: WholesaleSMS Pty Ltd | Q11: =ABS(E11) -> 909
A12: AU052 | B12: AU073158 | C12: 5160010000 | D12: Marketing expense | E12: 909 | F12: AUQ | G12: 45734 | H12: CCMS | I12: OoiS-Default Licensee Merchant | J12: Wholesale SMS text to clients | O12: WholesaleSMS Pty Ltd | Q12: =ABS(E12) -> 909
A13: AU001 | B13: AU030619 | C13: 5160010000 | D13: Marketing expense | E13: 819.8 | F13: AUQ | G13: 45664 | H13: AP Accruals | I13: 00000521-AWAGI03 | K13: Woolorama 2025: Young Judges S | L13: 00000521 | M13: WAGIN AGRICULTURAL SOCIETY INC | Q13: =ABS(E13) -> 819.8
A14: AU052 | B14: AU073158 | C14: 5160010000 | D14: Marketing expense | E14: 656.5 | F14: AUQ | G14: 45723 | H14: CCMS | I14: OoiS-Default Licensee Merchant | J14: Wholesale SMS text to clients | O14: WholesaleSMS Pty Ltd | Q14: =ABS(E14) -> 656.5
A15: AU052 | B15: AU073158 | C15: 5160010000 | D15: Marketing expense | E15: 656.5 | F15: AUQ | G15: 45744 | H15: CCMS | I15: OoiS-Default Licensee Merchant | J15: Wholesale SMS text to clients | O15: WholesaleSMS Pty Ltd | Q15: =ABS(E15) -> 656.5
A16: AU001 | B16: AU032061 | C16: 5160010000 | D16: Marketing expense | E16: 646.5 | F16: AUQ | G16: 45664 | H16: AP Accruals | I16: CEC-9-ASPUR00 | K16: NQNTClientCouncilMeeting_Towns | L16: CEC-9 | M16: SPURDLE FAMILY TRUST | Q16: =ABS(E16) -> 646.5
A17: AU001 | B17: AU030613 | C17: 5160010000 | D17: Marketing expense | E17: -500 | F17: AUQ | G17: 45665 | H17: YFFB-21 Wandel | I17: YFFB-10 Klug | Q17: =ABS(E17) -> 500
A18: AU001 | B18: AU030613 | C18: 5160010000 | D18: Marketing expense | E18: -500 | F18: AUQ | G18: 45665 | H18: YFFB-21 Wandel | I18: YFFB-11 Klug | Q18: =ABS(E18) -> 500
A19: AU001 | B19: AU030613 | C19: 5160010000 | D19: Marketing expense | E19: -500 | F19: AUQ | G19: 45665 | H19: YFFB-21 Wandel | I19: YFFB-18 Dare | Q19: =ABS(E19) -> 500
A20: AU001 | B20: AU030613 | C20: 5160010000 | D20: Marketing expense | E20: -500 | F20: AUQ | G20: 45665 | H20: YFFB-21 Wandel | I20: YFFB-19 Dare | Q20: =ABS(E20) -> 500
A21: AU001 | B21: AU030613 | C21: 5160010000 | D21: Marketing expense | E21: -500 | F21: AUQ | G21: 45665 | H21: YFFB-21 Wandel | I21: YFFB-21 Wandel | Q21: =ABS(E21) -> 500
A22: AU001 | B22: AU030613 | C22: 5160010000 | D22: Marketing expense | E22: -500 | F22: AUQ | G22: 45665 | H22: YFFB-21 Wandel | I22: YFFB-25 Partridge | Q22: =ABS(E22) -> 500
A23: AU001 | B23: AU030613 | C23: 5160010000 | D23: Marketing expense | E23: -500 | F23: AUQ | G23: 45665 | H23: YFFB-21 Wandel | I23: YFFB-26 Rowe | Q23: =ABS(E23) -> 500
A24: AU001 | B24: AU030613 | C24: 5160010000 | D24: Marketing expense | E24: -500 | F24: AUQ | G24: 45665 | H24: YFFB-21 Wandel | I24: YFFB-29 Newman | Q24: =ABS(E24) -> 500
A25: AU001 | B25: AU030613 | C25: 5160010000 | D25: Marketing expense | E25: -500 | F25: AUQ | G25: 45677 | H25: YFFB-20 Keeffe | I25: YFFB-12 Poole | Q25: =ABS(E25) -> 500
A26: AU001 | B26: AU030613 | C26: 5160010000 | D26: Marketing expense | E26: -500 | F26: AUQ | G26: 45677 | H26: YFFB-20 Keeffe | I26: YFFB-20 Keeffe | Q26: =ABS(E26) -> 500
A27: AU001 | B27: AU030613 | C27: 5160010000 | D27: Marketing expense | E27: -500 | F27: AUQ | G27: 45677 | H27: YFFB-20 Keeffe | I27: YFFB-22 Bradshaw | Q27: =ABS(E27) -> 500
A28: AU001 | B28: AU030613 | C28: 5160010000 | D28: Marketing expense | E28: -500 | F28: AUQ | G28: 45677 | H28: YFFB-20 Keeffe | I28: YFFB-23 Kenny | Q28: =ABS(E28) -> 500
... A57: AU001 | B57: AU030613 | C57: 5160010000 | D57: Marketing expense | E57: -500 | F57: AUQ | G57: 45740 | H57: YFFB-50 Dykes | I57: YFFB-50 Dykes | Q57: =ABS(E57) -> 500
A58: AU052 | B58: AU032053 | C58: 5160010000 | D58: Marketing expense | E58: 470.42 | F58: AUQ | G58: 45720 | H58: AP Accruals | I58: CEC-12-AANDR00 | K58: Return flights for Melissa Deg | L58: CEC-12 | M58: ANDREW AND MELISSA DEGUARA | Q58: =ABS(E58) -> 470.42
A59: AU001 | B59: AU032061 | C59: 5160010000 | D59: Marketing expense | E59: 344.2 | F59: AUQ | G59: 45665 | H59: AP Accruals | I59: CEC-10-AJMSL00 | K59: Return flights Richmond-Townsv | L59: CEC-10 | M59: JM AND SL BELLINGHAM | Q59: =ABS(E59) -> 344.2
A60: AU052 | B60: AU032046 | C60: 5160010000 | D60: Marketing expense | E60: 300 | F60: AUQ | G60: 45677 | H60: CCMS | I60: GruchyR-Default Licensee Merch | J60: cool room hire for Rabo Truck Xmas Moree | O60: JOCKS HIRE | Q60: =ABS(E60) -> 300 | S60: ME | T60: Y | U60: =B60 -> AU032046 | V60: =E60 -> 300
A61: AU052 | B61: AU030214 | C61: 5160010000 | D61: Marketing expense | E61: 186.27 | F61: AUQ | G61: 45664 | H61: CCMS | I61: RyanR-Other Personnel Expense | J61: RaboLive - Client Gift | O61: LS MARTHAS FOOD & HOME | Q61: =ABS(E61) -> 186.27
A62: AU001 | B62: AU030619 | C62: 5160010000 | D62: Marketing expense | E62: 168.93 | F62: AUQ | G62: 45721 | H62: AP Accruals | I62: 00000572-AWAGI03 | K62: Wagin Woolorama 2025: Addition | L62: 00000572 | M62: WAGIN AGRICULTURAL SOCIETY INC | Q62: =ABS(E62) -> 168.93
A63: AU052 | B63: AU032046 | C63: 5160010000 | D63: Marketing expense | E63: 129.55 | F63: AUQ | G63: 45677 | H63: CCMS | I63: TaylorF-Office Supplies | J63: Ice - Moree RaboTruck Event | O63: WOOLWORTHS/215 BALO ST | Q63: =ABS(E63) -> 129.55
A64: AU052 | B64: AU030214 | C64: 5160010000 | D64: Marketing expense | E64: 85.55 | F64: AUQ | G64: 45664 | H64: CCMS | I64: RyanR-Entertainment Expense | J64: RaboLive - Client Gift | O64: ORANGE CELLARS/153218026358 | Q64: =ABS(E64) -> 85.55
A65: AU052 | B65: AU032046 | C65: 5160010000 | D65: Marketing expense | E65: 66.4 | F65: AUQ | G65: 45677 | H65: CCMS | I65: TaylorF-Default Licensee Merch | J65: Lukcy door prizes - Moree RaboTruck event | O65: SMP*PR Interiors | Q65: =ABS(E65) -> 66.4
A66: AU052 | B66: AU030214 | C66: 5160010000 | D66: Marketing expense | E66: 50.83 | F66: AUQ | G66: 45719 | H66: CCMS | I66: RyanR-Default Licensee Merchan | J66: Branch Sponsorship | O66: SMP*Ricks Engraving a6b | Q66: =ABS(E66) -> 50.83
A67: AU052 | B67: AU032046 | C67: 5160010000 | D67: Marketing expense | E67: 49.73 | F67: AUQ | G67: 45677 | H67: CCMS | I67: TaylorF-Office Supplies | J67: Tea & Coffee Station - Moree RaboTruck event | O67: WOOLWORTHS/215 BALO ST | Q67: =ABS(E67) -> 49.73
A68: AU052 | B68: AU032046 | C68: 5160010000 | D68: Marketing expense | E68: 43.64 | F68: AUQ | G68: 45677 | H68: CCMS | I68: TaylorF-Airfares | J68: Lucky Door Prize - Moree RaboTruck Event | O68: TOURISM MOREE INC | Q68: =ABS(E68) -> 43.64
A69: AU052 | B69: AU032046 | C69: 5160010000 | D69: Marketing expense | E69: 37.19 | F69: AUQ | G69: 45677 | H69: CCMS | I69: TaylorF-Default Licensee Merch | J69: Table Xmas Decorations - Moree RaboTruck event | O69: ERAYNE TRADING PTY LTD | Q69: =ABS(E69) -> 37.19 | S69: ME | T69: Y | U69: =B69 -> AU032046 | V69: =E69 -> 37.19
A70: AU052 | B70: AU030619 | C70: 5160010000 | D70: Marketing expense | E70: 36.36 | F70: AUQ | G70: 45733 | H70: CCMS | I70: ParraM-Costs own Car Fleet | J70: Ice Bags Sundowner | O70: CALTEX WAGIN | Q70: =ABS(E70) -> 36.36
A71: AU052 | B71: AU032046 | C71: 5160010000 | D71: Marketing expense | E71: 31.82 | F71: AUQ | G71: 45666 | H71: CCMS | I71: SilvaKJ-Other Personnel Expens | J71: Flowers | O71: ELZIE FLORIST | Q71: =ABS(E71) -> 31.82

Sheet Bus Dev
A1: Account Number | C1: =Summary!A16 -> 5160011000
A2: Account Name | C2: =Summary!B16 -> Business development | G2: Notes:
A3: GL Total | C3: 260399.01 | G3: Marquees, furniture and other associated costs at field day events are a business expense and not a recreational event - treated as tax deductible and not subject to FBT | T3: AU001 | V3: =SUMIF($A$8:$A$23974,"AU001",V8:V23974) -> 8846.07
A4: Per TB | C4: =SUM(E:E) -> 260399.01 | G4: Sponsorship is deductible under s8-1 as it promotes the business and the expectation is that it will generate future business | T4: AU052 | V4: =SUMIF($A$8:$A$23974,"AU052",V8:V23974) -> 24455.92
A5: Variance | C5: =C3-C4 -> 0 | G5: Rabobank truck expenses have been treated as deductible on the basis that they are a marketing expense under s8-1. | V5: =SUM(V3:V4) -> 33301.99
G6: Field days include alcohol - but staff are not able to drink on jobs. Intention is to assist prospective clients or existing clients. Run sheets are available. Days usually wrap up mid afternoon. | AD6: Income tax purposes
A7: BUSINESS_UNIT_CODE | B7: OPERATING_UNIT_CODE | C7: ACCOUNT_CODE | D7: DESCRIPTION | E7: BASE_AMOUNT | F7: BASE_CURRENCY_CODE | G7: JOURNAL_DATE | H7: DESCR | I7: LINE_DESCR | J7: PURPOSE | K7: INVOICE_DESCR | L7: INVOICE_ID | M7: VENDOR_NAME | N7: EMPLOYEE_NAME | O7: CHARGE_DESCRIPTION | Q7: ABS | R7: Search Terms | S7: Tax Description | T7: ME? Y/N | U7: OU | V7: ME $ | W7: Not ME but other type of FB Y/N | X7: Not ME but other type of FB ==> $ | Y7: Nets to Nil in GL accts | Z7: s58P M&I or Bus Exp - notFB | AA7: ME | AB7: Car FB - addn op costs | AC7: CP Exp FB | AD7: Capital expenditure | AE7: No FBT and not ded | AF7: Additional Comments
A8: AU001 | B8: AU032046 | C8: 5160011000 | D8: Business development | E8: -34650 | F8: AUQ | G8: 45658 | H8: Nuffield Scholar Sponsorship | K8: Nuffield Scholar Sponsorship | Q8: =ABS(E8) -> 34650
A9: AU001 | B9: AU032046 | C9: 5160011000 | D9: Business development | E9: 34576.92 | F9: AUQ | G9: 45705 | H9: AP Accruals | I9: INV-10913-ANUFF00 | K9: Nuffield Australia Scholar Spo | L9: INV-10913 | M9: NUFFIELD AUSTRALIA | Q9: =ABS(E9) -> 34576.92
A10: AU001 | B10: AU032046 | C10: 5160011000 | D10: Business development | E10: 27442 | F10: AUQ | G10: 45709 | H10: AP Accruals | I10: INV-3384-ACATT03 | K10: Platinum Sponsorship - Cattle | L10: INV-3384 | M10: CATTLE AUSTRALIA | Q10: =ABS(E10) -> 27442
A11: AU001 | B11: AU032046 | C11: 5160011000 | D11: Business development | E11: 18660.56 | F11: AUQ | G11: 45664 | H11: AP Accruals | I11: RABO2025/6-ASOLU01 | K11: RaboTruck Gippsland event x 2 | L11: RABO2025/6 | M11: SOLUTION ENTERTAINMENT | Q11: =ABS(E11) -> 18660.56
A12: AU001 | B12: AU036740 | C12: 5160011000 | D12: Business development | E12: 14992.05 | F12: AUQ | G12: 45730 | H12: AP Accruals | I12: 2826-ATURN01 | K12: Deposit merchandise for the FA | L12: 2826 | M12: TURNKEY PROMOTIONS | Q12: =ABS(E12) -> 14992.05
A13: AU001 | B13: AU032046 | C13: 5160011000 | D13: Business development | E13: 13172.16 | F13: AUQ | G13: 45708 | H13: AP Accruals | I13: 2101-ASTIR00 | K13: Accrued from 2024: STCF Gold S | L13: 2101 | M13: STIRLINGS TO COAST FARMERS | Q13: =ABS(E13) -> 13172.16
A14: AU001 | B14: AU032046 | C14: 5160011000 | D14: Business development | E14: 9330.28 | F14: AUQ | G14: 45664 | H14: AP Accruals | I14: RABO2025/6-ASOLU01 | K14: RaboTruck Angus Expo | L14: RABO2025/6 | M14: SOLUTION ENTERTAINMENT | Q14: =ABS(E14) -> 9330.28
A15: AU001 | B15: AU032046 | C15: 5160011000 | D15: Business development | E15: 9330.28 | F15: AUQ | G15: 45664 | H15: AP Accruals | I15: RABO2025/6-ASOLU01 | K15: RaboTruck FNQ FDs | L15: RABO2025/6 | M15: SOLUTION ENTERTAINMENT | Q15: =ABS(E15) -> 9330.28
A16: AU001 | B16: AU032046 | C16: 5160011000 | D16: Business development | E16: 9330.28 | F16: AUQ | G16: 45664 | H16: AP Accruals | I16: RABO2025/6-ASOLU01 | K16: RaboTruck Taroom Show | L16: RABO2025/6 | M16: SOLUTION ENTERTAINMENT | Q16: =ABS(E16) -> 9330.28
A17: AU052 | B17: AU032046 | C17: 5160011000 | D17: Business development | E17: 9100.01 | F17: AUQ | G17: 45744 | H17: CCMS | I17: EllisT-Offshore Meals & Lodgin | J17: Griffith Client Dinner - with RaboResearch, Ben Picton | O17: LA SCALA RESTAURANT | Q17: =ABS(E17) -> 9100.01 | S17: ME | T17: Y | U17: =B17 -> AU032046 | V17: =E17 -> 9100.01
A18: AU001 | B18: AU032046 | C18: 5160011000 | D18: Business development | E18: 7683.76 | F18: AUQ | G18: 45698 | H18: AP Accruals | I18: INV-0035-AGROW01 | K18: GROWQ Sponsorship Fee | L18: INV-0035 | M18: GROWQ ASSOCIATION INC | Q18: =ABS(E18) -> 7683.76
A19: AU001 | B19: AU032051 | C19: 5160011000 | D19: Business development | E19: 5499.65 | F19: AUQ | G19: 45664 | H19: AP Accruals | I19: INV-0215-ADUAL00 | K19: Farm to Fork Deposit dinner | L19: INV-0215 | M19: DUAL ENTERTAINMENT PTY LTD | Q19: =ABS(E19) -> 5499.65 | S19: ME | T19: Y | U19: =B19 -> AU032051 | V19: =E19 -> 5499.65
A20: AU001 | B20: AU032046 | C20: 5160011000 | D20: Business development | E20: 5488.4 | F20: AUQ | G20: 45677 | H20: AP Accruals | I20: 00000412-ANORT51 | K20: Darwin Branch sponsorship 2025 | L20: 412 | M20: NORTHERN TERRITORY FARMERS ASSOCIATION | Q20: =ABS(E20) -> 5488.4
A21: AU001 | B21: AU032046 | C21: 5160011000 | D21: Business development | E21: 4989.45 | F21: AUQ | G21: 45706 | H21: AP Accruals | I21: 2063-ASHAN05 | K21: North East Dairy Business grou | L21: 2063 | M21: SHANNON FARM CONSULTING | Q21: =ABS(E21) -> 4989.45
A22: AU001 | B22: AU032046 | C22: 5160011000 | D22: Business development | E22: 4390.72 | F22: AUQ | G22: 45677 | H22: AP Accruals | I22: 610-AGIPP00 | K22: Gippsland Red Meat Conference | L22: 610 | M22: GIPPSLAND AGRICULTURAL GROUP (182920421) | Q22: =ABS(E22) -> 4390.72
A23: AU001 | B23: AU032046 | C23: 5160011000 | D23: Business development | E23: 4390.72 | F23: AUQ | G23: 45677 | H23: AP Accruals | I23: 610-AGIPP02 | K23: Gippsland Red Meat Conference | L23: 610 | M23: GIPPSLAND AGRICULTURAL GROUP INC | Q23: =ABS(E23) -> 4390.72
A24: AU001 | B24: AU032046 | C24: 5160011000 | D24: Business development | E24: -4390.72 | F24: AUQ | G24: 45679 | H24: AP Accruals | I24: 610-AGIPP00 | K24: Gippsland Red Meat Conference | L24: 610 | M24: GIPPSLAND AGRICULTURAL GROUP (182920421) | Q24: =ABS(E24) -> 4390.72
A25: AU001 | B25: AU032046 | C25: 5160011000 | D25: Business development | E25: 4379.74 | F25: AUQ | G25: 45705 | H25: AP Accruals | I25: 2774-ATURN01 | K25: Sunscreen promo items for CC i | L25: 2774 | M25: TURNKEY PROMOTIONS | Q25: =ABS(E25) -> 4379.74
A26: AU001 | B26: AU032046 | C26: 5160011000 | D26: Business development | E26: 4008.73 | F26: AUQ | G26: 45706 | H26: AP Accruals | I26: INV1287-ATHEF04 | K26: World Angus Forum - Presenter | L26: INV1287 | M26: THE FINANCIAL BLOKE GROUP PTY LTD | Q26: =ABS(E26) -> 4008.73
A27: AU052 | B27: AU032046 | C27: 5160011000 | D27: Business development | E27: 3264 | F27: AUQ | G27: 45734 | H27: CCMS | I27: TierneyA-Default Licensee Merc | J27: NTCA Reg Fee x 4 + credit card fee | O27: AAP Events | Q27: =ABS(E27) -> 3264
A28: AU001 | B28: AU032046 | C28: 5160011000 | D28: Business development | E28: 3128.39 | F28: AUQ | G28: 45726 | H28: AP Accruals | I28: 000425990-AUNIV02 | K28: Feeder steer school 2.0 comerc | L28: 425990 | M28: UNIVERSITY OF NEW ENGLAND | Q28: =ABS(E28) -> 3128.39
A29: AU001 | B29: AU032046 | C29: 5160011000 | D29: Business development | E29: 3017.12 | F29: AUQ | G29: 45664 | H29: AP Accruals | I29: INV-905-ACAFE00 | K29: Christmas party for clients | L29: INV-905 | M29: CAFE GRAY | Q29: =ABS(E29) -> 3017.12 | S29: ME | T29: Y | U29: =B29 -> AU032046 | V29: =E29 -> 3017.12
A30: AU001 | B30: AU032046 | C30: 5160011000 | D30: Business development | E30: 3000 | F30: AUQ | G30: 45720 | H30: AP Accruals | I30: INV-1109-ASOUT23 | K30: SE Field Days sponorship | L30: INV-1109 | M30: SOUTH EAST FIELD DAYS | Q30: =ABS(E30) -> 3000
A31: AU001 | B31: AU032046 | C31: 5160011000 | D31: Business development | E31: 2893.88 | F31: AUQ | G31: 45734 | H31: AP Accruals | I31: 00003390-AWHAR00 | K31: NTCA Catering for pre conf eve | L31: 3390 | M31: WHARF ONE FOOD & WINE IL LIDO BAR PIZZA | Q31: =ABS(E31) -> 2893.88 | S31: Accept business - part of seminar
A32: AU001 | B32: AU032046 | C32: 5160011000 | D32: Business development | E32: 2870 | F32: AUQ | G32: 45674 | H32: AP Accruals | I32: INV-2002-AWARR | K32: Local branch event RaboTruck M | L32: INV-2002 | M32: WARROO PARTNERSHIP | Q32: =ABS(E32) -> 2870
A33: AU001 | B33: AU032046 | C33: 5160011000 | D33: Business development | E33: 2802.22 | F33: AUQ | G33: 45706 | H33: AP Accruals | I33: INV-030721-ACENT02 | K33: Events Air invoice | L33: INV-030721 | M33: CENTIUM SOFTWARE PTY LTD TA EVENTSAIR | Q33: =ABS(E33) -> 2802.22
A34: AU001 | B34: AU032046 | C34: 5160011000 | D34: Business development | E34: 2744.2 | F34: AUQ | G34: 45698 | H34: AP Accruals | I34: I-250108-003-ABRAN06 | K34: Sponsorship Fee | L34: I-250108-003 | M34: AUSTRALIAN BRANGUS CATTLE ASSOCIATION | Q34: =ABS(E34) -> 2744.2
A35: AU001 | B35: AU032051 | C35: 5160011000 | D35: Business development | E35: 2692.96 | F35: AUQ | G35: 45701 | H35: AP Accruals | I35: INV-10370_AU_202411-ATRAC01 | K35: Tracksuit invoice (difference | L35: INV-10370_AU_20241101 | M35: TRACKSUIT LIMITED | Q35: =ABS(E35) -> 2692.96
A36: AU001 | B36: AU032046 | C36: 5160011000 | D36: Business development | E36: 2500 | F36: AUQ | G36: 45691 | H36: AP Accruals | I36: 1000-ABENE01 | K36: Beneath The Brim Sponsorship b | L36: 1000 | M36: A DAUGHTERS WAY LTD TA BENEATH THE BRIM | Q36: =ABS(E36) -> 2500
A37: AU001 | B37: AU032046 | C37: 5160011000 | D37: Business development | E37: 2195.36 | F37: AUQ | G37: 45701 | H37: AP Accruals | I37: INV-0689-AMONA08 | K37: 2025 Sponsorship of Monaro Far | L37: INV-0689 | M37: MONARO FARMING SYSTEMS | Q37: =ABS(E37) -> 2195.36
A38: AU001 | B38: AU032046 | C38: 5160011000 | D38: Business development | E38: 2195.36 | F38: AUQ | G38: 45734 | H38: AP Accruals | I38: PSI-000380-AMURR07 | K38: Murray Dairy Limited - Goulbu | L38: PSI-000380 | M38: MURRAY DAIRY LIMITED | Q38: =ABS(E38) -> 2195.36
A39: AU052 | B39: AU030619 | C39: 5160011000 | D39: Business development | E39: 2180 | F39: AUQ | G39: 45740 | H39: CCMS | I39: BriginshawZ-Offshore Meals & L | J39: Woolorama plater supplies. Noting difference between invoice and payment is card fees to visa/ maste | O39: NARROGIN FRUIT MARKET | Q39: =ABS(E39) -> 2180
A40: AU052 | B40: AU032046 | C40: 5160011000 | D40: Business development | E40: 2035.76 | F40: AUQ | G40: 45664 | H40: AP Accruals | I40: 00018230-ARURA00 | K40: Agfest Tax Invoice - Site Paym | L40: 18230 | M40: RURAL YOUTH ORGANISATION OF TASMANIA INC | Q40: =ABS(E40) -> 2035.76
A41: AU001 | B41: AU032046 | C41: 5160011000 | D41: Business development | E41: 2000 | F41: AUQ | G41: 45730 | H41: AP Accruals | I41: 101-AYOUN01 | K41: Sponsorship of Young Agri Prof | L41: 101 | M41: YOUNG AGRI PROFESSIONALS | Q41: =ABS(E41) -> 2000
A42: AU001 | B42: AU032046 | C42: 5160011000 | D42: Business development | E42: 1975.97 | F42: AUQ | G42: 45732 | H42: AP Accruals | I42: INV-5953-AARVE00 | K42: coffee cups AngusEXPO | L42: INV-5953 | M42: ARVEEJAY INDUSTRIES PTY LTD | Q42: =ABS(E42) -> 1975.97
A43: AU001 | B43: AU032046 | C43: 5160011000 | D43: Business development | E43: 1892.4 | F43: AUQ | G43: 45674 | H43: AP Accruals | I43: INV-0917-AJTHA00 | K43: Equipment Hire for Moree RaboT | L43: INV-0917 | M43: JT HAYNE AND KM SIMSHAUSER | Q43: =ABS(E43) -> 1892.4
A44: AU052 | B44: AU030213 | C44: 5160011000 | D44: Business development | E44: 1820 | F44: AUQ | G44: 45670 | H44: CCMS | I44: MitchellB-Offshore Meals & Lod | J44: Temora Client Christmas Party | O44: The Railway Hotel Temo | Q44: =ABS(E44) -> 1820 | S44: ME | T44: Y | U44: =B44 -> AU030213 | V44: =E44 -> 1820
A45: AU001 | B45: AU032046 | C45: 5160011000 | D45: Business development | E45: 1737.7 | F45: AUQ | G45: 45723 | H45: AP Accruals | I45: 19-AALLB02 | K45: Atherton Branch s/ship All Bre | L45: 19 | M45: ALL BREEDS DAIRY COMMITTEE INC | Q45: =ABS(E45) -> 1737.7
A46: AU001 | B46: AU032046 | C46: 5160011000 | D46: Business development | E46: 1646.52 | F46: AUQ | G46: 45706 | H46: AP Accruals | I46: INV-1144-AICPA06 | K46: ICPA Spons Payment | L46: INV-1144 | M46: ICPA QLD INC | Q46: =ABS(E46) -> 1646.52
A47: AU001 | B47: AU032046 | C47: 5160011000 | D47: Business development | E47: -1643.64 | F47: AUQ | G47: 45705 | H47: AP Closed Vouchers | I47: INV-0245-ADECC00 | K47: 2023 Tamworth Rural Women's Da | L47: INV-0245 | M47: DEC COMMUNICATIONS PTY LTD | Q47: =ABS(E47) -> 1643.64
A48: AU001 | B48: AU032046 | C48: 5160011000 | D48: Business development | E48: 1600 | F48: AUQ | G48: 45723 | H48: AP Accruals | I48: INV-0007-ATOOL00 | K48: Roma Branch S/ship of Tooloomb | L48: INV-0007 | M48: TOOLOOMBILLA RODEO AND CAMPDRAFT ASSINC | Q48: =ABS(E48) -> 1600
A49: AU001 | B49: AU032046 | C49: 5160011000 | D49: Business development | E49: 1572.38 | F49: AUQ | G49: 45706 | H49: AP Accruals | I49: 241118-ATURN01 | K49: Collateral for Truck event and | L49: 241118 | M49: TURNKEY PROMOTIONS | Q49: =ABS(E49) -> 1572.38
A50: AU001 | B50: AU032046 | C50: 5160011000 | D50: Business development | E50: 1521.78 | F50: AUQ | G50: 45719 | H50: AP Accruals | I50: 2025058-AWIMM00 | K50: Horsham Wimmera Field Days 202 | L50: 2025058 | M50: WIMMERA MACHINERY FIELD DAYS INC | Q50: =ABS(E50) -> 1521.78
A51: AU052 | B51: AU032046 | C51: 5160011000 | D51: Business development | E51: 1397.13 | F51: AUQ | G51: 45744 | H51: CCMS | I51: GrahamMJ-Offshore Meals & Lodg | K51: Young farmer networking event with Rabo Research - catering 11/03/2025 | O51: JUNEE HOTEL/17-21 SEIGNOI | Q51: =ABS(E51) -> 1397.13 | S51: ME | T51: Y | U51: =B51 -> AU032046 | V51: =E51 -> 1397.13
A52: AU052 | B52: AU030213 | C52: 5160011000 | D52: Business development | E52: 1321.35 | F52: AUQ | G52: 45678 | H52: CCMS | I52: TwomeyGJ-Offshore Meals & Lodg | K52: CB AU - Client Dinner Jugiong | O52: Sir George Hotel | Q52: =ABS(E52) -> 1321.35 | S52: ME | T52: Y | U52: =B52 -> AU030213 | V52: =E52 -> 1321.35
A53: AU001 | B53: AU032046 | C53: 5160011000 | D53: Business development | E53: 1317.22 | F53: AUQ | G53: 45706 | H53: AP Accruals | I53: 2650-AGANN00 | K53: Gannon Discussion Group | L53: 2650 | M53: GANNON AGRIBUSINESS | Q53: =ABS(E53) -> 1317.22
A54: AU052 | B54: AU032046 | C54: 5160011000 | D54: Business development | E54: 1241.82 | F54: AUQ | G54: 45744 | H54: CCMS | I54: GallowayM-Offshore Meals & Lod | K54: Dinner - Visiting Experts Ben Picton and Ash Fenwick | O54: LS Spare | Q54: =ABS(E54) -> 1241.82 | S54: ME | T54: Y | U54: =B54 -> AU032046 | V54: =E54 -> 1241.82
A55: AU001 | B55: AU032046 | C55: 5160011000 | D55: Business development | E55: 1197.47 | F55: AUQ | G55: 45740 | H55: AP Accruals | I55: 1052656-AANGU01 | K55: WAF Teys Shout Out Tickets | L55: 1052656 | M55: THE ANGUS SOCIETY OF AUSTRALIA | Q55: =ABS(E55) -> 1197.47
A56: AU052 | B56: AU032046 | C56: 5160011000 | D56: Business development | E56: 1102.27 | F56: AUQ | G56: 45679 | H56: CCMS | I56: McconvilleP-Offshore Meals & L | K56: Julia Creek End of Year Client Function - Catering | O56: CORRINAS | Q56: =ABS(E56) -> 1102.27 | S56: ME | T56: Y | U56: =B56 -> AU032046 | V56: =E56 -> 1102.27
A57: AU001 | B57: AU032046 | C57: 5160011000 | D57: Business development | E57: 1097.68 | F57: AUQ | G57: 45734 | H57: AP Accruals | I57: INV 016-AGREE00 | K57: Campdraft Sponsorship 2025 | L57: INV 016 | M57: GREENVALE RODEO & CAMPDRAFTING CLUB INC | Q57: =ABS(E57) -> 1097.68
A58: AU052 | B58: AU032046 | C58: 5160011000 | D58: Business development | E58: 1097.68 | F58: AUQ | G58: 45709 | H58: AP Accruals | I58: INV-0141-ABUCK02 | K58: BFIG Sponsorship INV0141 | L58: INV-0141 | M58: BUCKLEBOO FARM IMPROVEMENT GROUP INC | Q58: =ABS(E58) -> 1097.68
A59: AU001 | B59: AU032046 | C59: 5160011000 | D59: Business development | E59: 1096.58 | F59: AUQ | G59: 45706 | H59: AP Accruals | I59: INV-0515-ANORT07 | K59: Sponsorship of the Night at th | L59: INV-0515 | M59: NORTH STAR SPORTING CLUB LIMITED | Q59: =ABS(E59) -> 1096.58
A60: AU001 | B60: AU032046 | C60: 5160011000 | D60: Business development | E60: 1071.34 | F60: AUQ | G60: 45665 | H60: AP Accruals | I60: 00013259-AQUAL08 | K60: Logo flag (pole flag) | L60: 13259 | M60: QUALITY EVENT HIRE PTY LTD | Q60: =ABS(E60) -> 1071.34
A61: AU052 | B61: AU032049 | C61: 5160011000 | D61: Business development | E61: 1061.82 | F61: AUQ | G61: 45726 | H61: CCMS | I61: DulmEJK2-Default Licensee Merc | J61: Gimble camera | M61: Van Dulm Eileen | O61: SP JB HI-FI ONLINE | Q61: =ABS(E61) -> 1061.82
A62: AU052 | B62: AU032046 | C62: 5160011000 | D62: Business development | E62: 1018.23 | F62: AUQ | G62: 45679 | H62: CCMS | I62: GroganC-Printing | K62: Ayr Branch - Women in Ag Advertorial | M62: Grogan Clarke | O62: MYO*CORE PUBLISHING E/219504337834 | Q62: =ABS(E62) -> 1018.23
A63: AU001 | B63: AU032046 | C63: 5160011000 | D63: Business development | E63: 1002.73 | F63: AUQ | G63: 45691 | H63: AP Accruals | I63: 269-AAUST23 | K63: ADC Reg Alistair Miller MAC Ql | L63: 269 | M63: AUSTRALIAN DAIRY CONFERENCE | Q63: =ABS(E63) -> 1002.73
A64: AU001 | B64: AU032046 | C64: 5160011000 | D64: Business development | E64: 1000 | F64: AUQ | G64: 45723 | H64: AP Accruals | I64: INV-1671-AALPH03 | K64: Emerald Branch 2025 S/Ship Alp | L64: INV-1671 | M64: ALPHA SHOW SOCIETY | Q64: =ABS(E64) -> 1000
A65: AU001 | B65: AU032046 | C65: 5160011000 | D65: Business development | E65: 997.89 | F65: AUQ | G65: 45691 | H65: AP Accruals | I65: 1327563-ARYDG05 | K65: Deposit for Ekka Function | L65: 1327563 | M65: RYDGES FORTITUDE VALLEY | Q65: =ABS(E65) -> 997.89
A66: AU001 | B66: AU032046 | C66: 5160011000 | D66: Business development | E66: 995 | F66: AUQ | G66: 45705 | H66: AP Accruals | I66: 00019468-AROYA06 | K66: Twba Branch 2025 s/ship Twba R | L66: 19468 | M66: ROYAL AGRICULTURAL SOCIETY OF QUEENSLAND | Q66: =ABS(E66) -> 995
A67: AU001 | B67: AU032046 | C67: 5160011000 | D67: Business development | E67: 990 | F67: AUQ | G67: 45706 | H67: AP Accruals | I67: INV-0556-AWALG00 | K67: Sponsorship of Walgett Show | L67: INV-0556 | M67: WALGETT SHOW SOCIETY INC | Q67: =ABS(E67) -> 990
A68: AU001 | B68: AU032046 | C68: 5160011000 | D68: Business development | E68: 987.91 | F68: AUQ | G68: 45674 | H68: AP Accruals | I68: 250006-AWOOD08 | K68: Sponsorship of Mid Lachlan Flo | L68: 250006 | M68: WOODSTOCK MEMORIAL SHOW INC | Q68: =ABS(E68) -> 987.91
A69: AU001 | B69: AU032046 | C69: 5160011000 | D69: Business development | E69: 987.91 | F69: AUQ | G69: 45701 | H69: AP Accruals | I69: 1-2112-AGLEN04 | K69: Sponsorship of Glenn Innes Sho | L69: 77433 | M69: GLEN INNES SHOW SOCIETY INC | Q69: =ABS(E69) -> 987.91
A70: AU052 | B70: AU032046 | C70: 5160011000 | D70: Business development | E70: 987.91 | F70: AUQ | G70: 45691 | H70: AP Accruals | I70: C011/1-OOUTS00 | K70: AIO video | L70: C011/1 | M70: OUTSOURCED SOLUTIONS PRIVATE LIMITED | Q70: =ABS(E70) -> 987.91
A71: AU052 | B71: AU032046 | C71: 5160011000 | D71: Business development | E71: 987.91 | F71: AUQ | G71: 45691 | H71: AP Accruals | I71: C011/2-OOUTS00 | K71: AIO video invoice two | L71: C011/2 | M71: OUTSOURCED SOLUTIONS PRIVATE LIMITED | Q71: =ABS(E71) -> 987.91
A72: AU052 | B72: AU030213 | C72: 5160011000 | D72: Business development | E72: 957.99 | F72: AUQ | G72: 45744 | H72: CCMS | I72: TwomeyGJ-Offshore Meals & Lodg | J72: Client Function Sir George Hotel | M72: Sir George Hotel | Q72: =ABS(E72) -> 957.99 | S72: ME | T72: Y | U72: =B72 -> AU030213 | V72: =E72 -> 957.99
A73: AU052 | B73: AU032046 | C73: 5160011000 | D73: Business development | E73: 921.45 | F73: AUQ | G73: 45733 | H73: CCMS | I73: McDougallJ-Office Supplies | J73: Drinks Hamilton Client Christmas Function | M73: HAMILTON CELLARBRATION/153931170307 | Q73: =ABS(E73) -> 921.45 | S73: ME | T73: Y | U73: =B73 -> AU032046 | V73: =E73 -> 921.45
A74: AU052 | B74: AU030214 | C74: 5160011000 | D74: Business development | E74: 921.18 | F74: AUQ | G74: 45726 | H74: CCMS | I74: HarrisM-Offshore Meals & Lodgi | J74: meals and drinks Condobalin Ewe and Crop Competition | M74: CONDOBOLIN SPORTS CL | Q74: =ABS(E74) -> 921.18 | S74: ME | T74: Y | U74: =B74 -> AU030214 | V74: =E74 -> 921.18
A75: AU052 | B75: AU030213 | C75: 5160011000 | D75: Business development | E75: 916.7 | F75: AUQ | G75: 45678 | H75: CCMS | I75: TwomeyGJ-Offshore Meals & Lodg | J75: CB AU Temora Event | O75: The Railway Hotel Temo | Q75: =ABS(E75) -> 916.7 | S75: ME | T75: Y | U75: =B75 -> AU030213 | V75: =E75 -> 916.7
A76: AU001 | B76: AU032046 | C76: 5160011000 | D76: Business development | E76: 900 | F76: AUQ | G76: 45691 | H76: AP Accruals | I76: 5025-AGUYR00 | K76: Sponsorship of Guyra Show | L76: 5025 | M76: GUYRA SHOW SOCIETY | Q76: =ABS(E76) -> 900
A77: AU001 | B77: AU030211 | C77: 5160011000 | D77: Business development | E77: 900 | F77: AUQ | G77: 45708 | H77: AP Accruals | I77: 11/02/2025(1)-AANDR16 | K77: Staff Photo's | L77: 11/02/2025(1) | M77: ANDREW PEARSON PHOTOGRAPHY | Q77: =ABS(E77) -> 900
A78: AU001 | B78: AU032046 | C78: 5160011000 | D78: Business development | E78: 828.75 | F78: AUQ | G78: 45706 | H78: AP Accruals | I78: INV-22354-ASOUP01 | K78: truck stubby holder Gippsland | L78: INV-22354 | M78: SOUPCAN PTY LTD | Q78: =ABS(E78) -> 828.75
A79: AU001 | B79: AU032046 | C79: 5160011000 | D79: Business development | E79: 828.75 | F79: AUQ | G79: 45706 | H79: AP Accruals | I79: INV-22354-ASOUP01 | K79: truck stubby holder Goulburn | L79: INV-22354 | M79: SOUPCAN PTY LTD | Q79: =ABS(E79) -> 828.75
A80: AU001 | B80: AU032046 | C80: 5160011000 | D80: Business development | E80: 823.26 | F80: AUQ | G80: 45699 | H80: AP Accruals | I80: INV-0225-AEPIC06 | K80: Sponsorship of Epic Horse Sale | L80: INV-0225 | M80: EPIC HORSE SALE AND CAMPDRAFT PTY LTD | Q80: =ABS(E80) -> 823.26
A81: AU001 | B81: AU032046 | C81: 5160011000 | D81: Business development | E81: 800 | F81: AUQ | G81: 45723 | H81: AP Accruals | I81: CW002-24/02/25-ATRUN00 | K81: Sponsorship of the Walcha Show | L81: CW002-24/02/25 | M81: TRUNDLE P & A SOCIETY | Q81: =ABS(E81) -> 800
A82: AU001 | B82: AU032046 | C82: 5160011000 | D82: Business development | E82: 750 | F82: AUQ | G82: 45691 | H82: AP Accruals | I82: 198-AMORE23 | K82: Moree on a Plate Sponsorship | L82: 198 | M82: MOREE ON A PLATE INCORPORATED | Q82: =ABS(E82) -> 750
A83: AU001 | B83: AU032046 | C83: 5160011000 | D83: Business development | E83: 684.95 | F83: AUQ | G83: 45723 | H83: AP Accruals | I83: 33862-APROD00 | K83: Pull up banner sugar Mackay | L83: 33862 | M83: PRODEUCE PTY LTD | Q83: =ABS(E83) -> 684.95
A84: AU001 | B84: AU032046 | C84: 5160011000 | D84: Business development | E84: 670.68 | F84: AUQ | G84: 45705 | H84: AP Accruals | I84: 00066992-ALIGH03 | K84: Cattle Cards Armidale branch | L84: 66992 | M84: LIGHTHOUSE PRINT GROUP | Q84: =ABS(E84) -> 670.68
A85: AU001 | B85: AU032046 | C85: 5160011000 | D85: Business development | E85: 647.63 | F85: AUQ | G85: 45722 | H85: AP Accruals | I85: 1-022882-AWIRR00 | K85: Wirruna Poll Hereford - catalo | L85: 1-022882 | M85: WIRRUNA POLL HEREFORD STUD | Q85: =ABS(E85) -> 647.63
A86: AU052 | B86: AU030431 | C86: 5160011000 | D86: Business development | E86: 611.2 | F86: AUQ | G86: 45670 | H86: CCMS | I86: McconvilleP-Domestic & Oversea | J86: Julia Creek End of Year Client Function - Venue & Accommodation - Peter Mcconville | O86: KOPPEN CONSTRUCTION PT | Q86: =ABS(E86) -> 611.2 | S86: ME | T86: Y | U86: =B86 -> AU030431 | V86: =E86 -> 611.2
A87: AU052 | B87: AU032046 | C87: 5160011000 | D87: Business development | E87: 593.45 | F87: AUQ | G87: 45734 | H87: CCMS | I87: TierneyA-Default Licensee Merc | J87: NTCA Dinner Reg Fee - F Young & J Webb | O87: AAP Events | Q87: =ABS(E87) -> 593.45 | S87: ME | T87: Y | U87: =B87 -> AU032046 | V87: =E87 -> 593.45
A88: AU052 | B88: AU032046 | C88: 5160011000 | D88: Business development | E88: 589.4 | F88: AUQ | G88: 45678 | H88: CCMS | I88: HodgeM-Offshore Meals & Lodgin | J88: Raboresearch dairy event - Client | O88: SQ *CLYDESDALE HOTEL | Q88: =ABS(E88) -> 589.4
A89: AU001 | B89: AU032046 | C89: 5160011000 | D89: Business development | E89: 588.36 | F89: AUQ | G89: 45732 | H89: AP Accruals | I89: INV-5953-AARVE00 | K89: Ag fest,Gippsland event | L89: INV-5953 | M89: ARVEEJAY INDUSTRIES PTY LTD | Q89: =ABS(E89) -> 588.36
A90: AU001 | B90: AU032046 | C90: 5160011000 | D90: Business development | E90: 548.84 | F90: AUQ | G90: 45674 | H90: AP Accruals | I90: INV-0099-AMORE00 | K90: Sponsorship of Moree Show Soci | L90: INV-0099 | M90: MOREE SHOW SOCIETY INC | Q90: =ABS(E90) -> 548.84
A91: AU001 | B91: AU032046 | C91: 5160011000 | D91: Business development | E91: 548.84 | F91: AUQ | G91: 45730 | H91: AP Accruals | I91: 1-000918-ATULL03 | K91: Sponsorship of the Tullibigeal | L91: 1-000918 | M91: TULLIBIGEAL PICNIC RACE CLUB INC | Q91: =ABS(E91) -> 548.84
A92: AU001 | B92: AU032046 | C92: 5160011000 | D92: Business development | E92: 548.84 | F92: AUQ | G92: 45734 | H92: AP Accruals | I92: 3617-AMALA01 | K92: Atherton Branch S/Ship - 2025 | L92: 3617 | M92: MALANDA PASTORAL AGRICULTURAL | Q92: =ABS(E92) -> 548.84
A93: AU001 | B93: AU032046 | C93: 5160011000 | D93: Business development | E93: 500 | F93: AUQ | G93: 45691 | H93: AP Accruals | I93: 2522-AARMI09 | K93: Sponsorship of Armidale Campdr | L93: 2522 | M93: ARMIDALE CAMPDRAFT CLUB INC | Q93: =ABS(E93) -> 500
A94: AU001 | B94: AU030213 | C94: 5160011000 | D94: Business development | E94: 500 | F94: AUQ | G94: 45698 | H94: AP Accruals | I94: 6-26/01/25-ACANA01 | K94: Can Assist Header Drivers Spon | L94: 6-26/01/25 | M94: CAN ASSIST | Q94: =ABS(E94) -> 500
A95: AU001 | B95: AU032046 | C95: 5160011000 | D95: Business development | E95: 500 | F95: AUQ | G95: 45699 | H95: AP Accruals | I95: 125-ABARR00 | K95: Sponsorship of Barraba Show | L95: 125 | M95: BARRABA P A & H ASSOCIATION INC | Q95: =ABS(E95) -> 500
A96: AU001 | B96: AU032046 | C96: 5160011000 | D96: Business development | E96: 500 | F96: AUQ | G96: 45699 | H96: AP Accruals | I96: INV-0365-ASOUT24 | K96: Sponsorship of Cotton Growers | L96: INV-0365 | M96: SOUTHERN VALLEYS COTTON GROWERS ASS | Q96: =ABS(E96) -> 500
A97: AU001 | B97: AU032046 | C97: 5160011000 | D97: Business development | E97: 500 | F97: AUQ | G97: 45701 | H97: AP Accruals | I97: 00000661-ANYNG00 | K97: Sponsorship of Nyngan Show Spe | L97: 661 | M97: NYNGAN SHOW SOCIETY INC | Q97: =ABS(E97) -> 500
A98: AU001 | B98: AU032046 | C98: 5160011000 | D98: Business development | E98: 500 | F98: AUQ | G98: 45723 | H98: AP Accruals | I98: 245-AWALC00 | K98: Sponsorship of the Walcha Show | L98: 245 | M98: WALCHA SHOW SOCIETY INC. | Q98: =ABS(E98) -> 500
A99: AU001 | B99: AU032046 | C99: 5160011000 | D99: Business development | E99: 500 | F99: AUQ | G99: 45723 | H99: AP Accruals | I99: 25026-ABARC01 | K99: Longreach Branch S/Ship 2025 B | L99: 25026 | M99: BARCOO PASTORAL SOCIETY | Q99: =ABS(E99) -> 500
A100: AU001 | B100: AU032046 | C100: 5160011000 | D100: Business development | E100: 500 | F100: AUQ | G100: 45723 | H100: AP Accruals | I100: INV-0053-AICPA06 | K100: Cloncurry Branch S/Ship of ICP | L100: INV-0053 | M100: ICPA QLD INC | Q100: =ABS(E100) -> 500
...

Sheet PR exp
A1: Account Number | C1: =Summary!A17 -> 5160999000
A2: Account Name | C2: =Summary!B17 -> Public relations | F2: Notes:
A3: GL Total | C3: 11669.68 | F3: No entertainment expenses included and all tax deductible
A4: Per TB | C4: =SUM(E:E) -> 11669.68 | T4: AU001 | V4: =SUMIF($A$10:$A$23974,"AU001",V9:V23973) -> 0
A5: Variance | C5: =C3-C4 -> 0 | T5: AU052 | V5: =SUMIF($A$10:$A$23975,"AU052",V9:V23974) -> 0
AD6: Income tax purposes
A7: BUSINESS_UNIT_CODE | B7: OPERATING_UNIT_CODE | C7: ACCOUNT_CODE | D7: DESCRIPTION | E7: BASE_AMOUNT | F7: BASE_CURRENCY_CODE | G7: JOURNAL_DATE | H7: DESCR | I7: LINE_DESCR | J7: PURPOSE | K7: INVOICE_DESCR | L7: INVOICE_ID | M7: VENDOR_NAME | N7: EMPLOYEE_NAME | O7: CHARGE_DESCRIPTION | Q7: ABS | R7: Search Terms | S7: Tax Description | T7: ME? Y/N | U7: OU | V7: ME $ | W7: Not ME but other type of FB Y/N | X7: Not ME but other type of FB ==> $ | Y7: Nets to Nil in GL accts | Z7: s58P M&I or Bus Exp - notFB | AA7: ME | AB7: Car FB - addn op costs | AC7: CP Exp FB | AD7: Capital expenditure | AE7: No FBT and not ded | AF7: Additional Comments
A8: AU001 | B8: AU032045 | C8: 5160999000 | D8: Public relations | E8: 11300.44 | F8: AUQ | G8: 45734 | H8: AP Accruals | I8: INV-22088-ASTEE00 | K8: Streem subscription | L8: INV-22088 | M8: STREEM PTY LTD | Q8: =ABS(E8) -> 11300.44 | S8: subscription - OK
A9: AU052 | B9: AU032045 | C9: 5160999000 | D9: Public relations | E9: 15.67 | F9: AUQ | G9: 45674 | H9: CCMS | I9: SHAWD-Default Licensee Merchan | J9: publication on markets and implications of Tump tariff issues | O9: SYD201 | Q9: =ABS(E9) -> 15.67 | S9: OK
A10: AU052 | B10: AU032045 | C10: 5160999000 | D10: Public relations | E10: 14.55 | F10: AUQ | G10: 45686 | H10: CCMS | I10: SHAWD-Default Licensee Merchan | J10: monthly online Tele News.com subscription | O10: NEWS PTY LIMITED | Q10: =ABS(E10) -> 14.55 | S10: subscription - OK
A11: AU052 | B11: AU032045 | C11: 5160999000 | D11: Public relations | E11: 99.09 | F11: AUQ | G11: 45694 | H11: CCMS | I11: SHAWD-Contributions & Club Mem | J11: annual Weekly Times subscription | O11: NEWS LIMITED | Q11: =ABS(E11) -> 99.09 | S11: subscription - OK
A12: AU052 | B12: AU032045 | C12: 5160999000 | D12: Public relations | E12: 54.55 | F12: AUQ | G12: 45694 | H12: CCMS | I12: SHAWD-Default Licensee Merchan | J12: monthly Aus subscription | O12: NEWS PTY LIMITED | Q12: =ABS(E12) -> 54.55 | S12: subscription - OK
A13: AU052 | B13: AU032045 | C13: 5160999000 | D13: Public relations | E13: 14.55 | F13: AUQ | G13: 45694 | H13: CCMS | I13: SHAWD-Default Licensee Merchan | J13: monthly Teleg/News.com subscription | O13: NEWS PTY LIMITED | Q13: =ABS(E13) -> 14.55 | S13: subscription - OK
A14: AU052 | B14: AU032045 | C14: 5160999000 | D14: Public relations | E14: 109.1 | F14: AUQ | G14: 45734 | H14: CCMS | I14: SHAWD-Default Licensee Merchan | J14: monthly Aus subscription | O14: NEWS PTY LIMITED | Q14: =ABS(E14) -> 109.1 | S14: subscription - OK
A15: AU052 | B15: AU032045 | C15: 5160999000 | D15: Public relations | E15: 14.55 | F15: AUQ | G15: 45734 | H15: CCMS | I15: SHAWD-Default Licensee Merchan | J15: monthly digital Tele/News.com sub | O15: NEWS PTY LIMITED | Q15: =ABS(E15) -> 14.55 | S15: subscription - OK
A16: AU052 | B16: AU030616 | C16: 5160999000 | D16: Public relations | E16: 47.18 | F16: AUQ | G16: 45736 | H16: CCMS | I16: ThompsonP-Office Supplies | J16: Flowers - Major & Carpenter | O16: WOOLWORTHS/DOG ROCK S/C L | Q16: =ABS(E16) -> 47.18 | S16: OK

Sheet Club memship
A1: Account Number | C1: =Summary!A19 -> 5190001000
A2: Account Name | C2: =Summary!B19 -> Contributions& club membership | G2: Notes:
A3: GL Total | C3: 36644.04 | G3: The cost of renewing practicing certificates, memberships and accreditations required to work in the in field have been treated as tax deductible and | T3: AU001 | V3: =SUMIF($A$10:$A$23974,"AU001",V8:V23972) -> 0
A4: Per TB | C4: =SUM(E:E) -> 36644.04 | G4: no FBT on the basis that they are otherwise deductible. | T4: AU052 | V4: =SUMIF($A$10:$A$23975,"AU052",V8:V23973) -> 0
A5: Variance | C5: =C3-C4 -> 0 | G5: All other professional memberships and subscribtions have been treated as no FBT and tax deductible under s8-1
AD6: Income tax purposes
A7: BUSINESS_UNIT_CODE | B7: OPERATING_UNIT_CODE | C7: ACCOUNT_CODE | D7: DESCRIPTION | E7: BASE_AMOUNT | F7: BASE_CURRENCY_CODE | G7: JOURNAL_DATE | H7: DESCR | I7: LINE_DESCR | J7: PURPOSE | K7: INVOICE_DESCR | L7: INVOICE_ID | M7: VENDOR_NAME | N7: EMPLOYEE_NAME | O7: CHARGE_DESCRIPTION | Q7: ABS | R7: Search Terms | S7: Tax Description | T7: ME? Y/N | U7: OU | V7: ME $ | W7: Not ME but other type of FB Y/N | X7: Not ME but other type of FB ==> $ | Y7: Nets to Nil in GL accts | Z7: s58P M&I or Bus Exp - notFB | AA7: ME | AB7: Car FB - addn op costs | AC7: CP Exp FB | AD7: Capital expenditure | AE7: No FBT and not ded | AF7: Additional Comments
A8: AU001 | B8: AU020097 | C8: 5190001000 | D8: Contributions& club membershi | E8: 18964.51 | F8: AUQ | G8: 45736 | H8: AP Accruals | I8: 2026-0017Cancelled-ARISK01 | K8: RMA Australia Membership Fees | L8: 2026-0017Cancelled | M8: RISK MANAGEMENT ASSOCIATION INC | Q8: =ABS(E8) -> 18964.51
A9: AU001 | B9: AU020097 | C9: 5190001000 | D9: Contributions& club membershi | E9: -18964.51 | F9: AUQ | G9: 45742 | H9: AP Closed Vouchers | I9: 2026-0017Cancelled-ARISK01 | K9: RMA Australia Membership Fees | L9: 2026-0017Cancelled | M9: RISK MANAGEMENT ASSOCIATION INC | Q9: =ABS(E9) -> 18964.51
A10: AU052 | B10: AU020097 | C10: 5190001000 | D10: Contributions& club membershi | E10: -13420 | F10: AUQ | G10: 45658 | H10: Managers Round Table | I10: Managers Round Table | Q10: =ABS(E10) -> 13420
A11: AU001 | B11: AU020097 | C11: 5190001000 | D11: Contributions& club membershi | E11: 12821.71 | F11: AUQ | G11: 45664 | H11: AP Accruals | I11: 6134322-APERP03 | K11: AU Commercial Lending Risk Ma | L11: 6134322 | M11: PERPETUAL SERVICES PTY LTD | Q11: =ABS(E11) -> 12821.71
A12: AU001 | B12: AU020097 | C12: 5190001000 | D12: Contributions& club membershi | E12: 12821.71 | F12: AUQ | G12: 45733 | H12: AP Accruals | I12: 6156298-APERP03 | K12: AU COMMERCIAL LENDING RISK MAN | L12: 6156298 | M12: PERPETUAL SERVICES PTY LTD | Q12: =ABS(E12) -> 12821.71
A13: AU052 | B13: AU020080 | C13: 5190001000 | D13: Contributions& club membershi | E13: 12340.51 | F13: AUQ | G13: 45677 | H13: CCMS | I13: CLEMENTSP-Default Licensee Mer | J13: CPA Membership renewals for 2025 - names included in the attached | O13: CPA AUSTRALIA | Q13: =ABS(E13) -> 12340.51
A14: AU052 | B14: AU020080 | C14: 5190001000 | D14: Contributions& club membershi | E14: -12340.51 | F14: AUQ | G14: 45693 | H14: CLEMENTSP-Default Licensee Mer | I14: CLEMENTSP-Default Licensee Mer | Q14: =ABS(E14) -> 12340.51
A15: AU052 | B15: AU050113 | C15: 5190001000 | D15: Contributions& club membershi | E15: -8800 | F15: AUQ | G15: 45658 | H15: Managers Round Table | I15: Managers Round Table | Q15: =ABS(E15) -> 8800
A16: AU052 | B16: AU061134 | C16: 5190001000 | D16: Contributions& club membershi | E16: 4995.83 | F16: AUQ | G16: 45679 | H16: 2220181-ATELU01 | I16: 80881-AAFMA00 | Q16: =ABS(E16) -> 4995.83
A17: AU052 | B17: AU061134 | C17: 5190001000 | D17: Contributions& club membershi | E17: 4995.83 | F17: AUQ | G17: 45711 | H17: 90848234-ADIME01 | I17: 80881-AAFMA00 | Q17: =ABS(E17) -> 4995.83
A18: AU052 | B18: AU061134 | C18: 5190001000 | D18: Contributions& club membershi | E18: 4995.83 | F18: AUQ | G18: 45734 | H18: 113522301-17/07/24-ACGUW05 | I18: 80881-AAFMA00 | Q18: =ABS(E18) -> 4995.83
A19: AU052 | B19: AU071197 | C19: 5190001000 | D19: Contributions& club membershi | E19: 4222.02 | F19: AUQ | G19: 45733 | H19: CCMS | I19: KeoC-Default Licensee Merchant | J19: Stratamarkets Almond Report | O19: IN *STRATAMARKETS/5170/AAKT5P9L | Q19: =ABS(E19) -> 4222.02
A20: AU001 | B20: AU075166 | C20: 5190001000 | D20: Contributions& club membershi | E20: 3000 | F20: AUQ | G20: 45677 | H20: AP Accruals | I20: CAL2025RAB-ADUTC00 | K20: Membership Renewal - Jos Groot | L20: CAL2025RAB | M20: DUTCHLINK LIMITED | Q20: =ABS(E20) -> 3000
A21: AU052 | B21: AU071197 | C21: 5190001000 | D21: Contributions& club membershi | E21: 2647.07 | F21: AUQ | G21: 45714 | H21: CCMS | I21: JoulesMR-Default Licensee Merc | J21: Fertilizer Australia Annual Membership | O21: FERTILIZER AUSTRALIA | Q21: =ABS(E21) -> 2647.07
A22: AU001 | B22: AU030619 | C22: 5190001000 | D22: Contributions& club membershi | E22: 2272.49 | F22: AUQ | G22: 45706 | H22: AP Accruals | I22: 0025480-ACOMP10 | K22: Compass Ag Corporate membershi | L22: 0025480 | M22: COMPASS AGRICULTURAL ALLIANCE | Q22: =ABS(E22) -> 2272.49
A23: AU052 | B23: AU030055 | C23: 5190001000 | D23: Contributions& club membershi | E23: 890.37 | F23: AUQ | G23: 45672 | H23: CCMS | I23: FIRTHG-Default Licensee Mercha | J23: API Invoice | O23: ZEN*B2B-Aus Prop Instit S | Q23: =ABS(E23) -> 890.37
A24: AU052 | B24: AU050119 | C24: 5190001000 | D24: Contributions& club membershi | E24: 890.37 | F24: AUQ | G24: 45691 | H24: CCMS | I24: ScottHS-Default Licensee Merch | J24: API Valuers License | O24: ZEN*B2B-Aus Prop Instit S | Q24: =ABS(E24) -> 890.37
A25: AU052 | B25: AU020088 | C25: 5190001000 | D25: Contributions& club membershi | E25: 860.71 | F25: AUQ | G25: 45670 | H25: AP Accruals | I25: EEC-1163-EYUNG01 | K25: CPA membership Fee | L25: EEC-1163 | M25: HELEN YUNG | Q25: =ABS(E25) -> 860.71
A26: AU052 | B26: AU060120 | C26: 5190001000 | D26: Contributions& club membershi | E26: 798.76 | F26: AUQ | G26: 45677 | H26: CCMS | I26: AlamsyahS-Default Licensee Mer | J26: CPA memberships | O26: CPA AUSTRALIA | Q26: =ABS(E26) -> 798.76
A27: AU052 | B27: AU071196 | C27: 5190001000 | D27: Contributions& club membershi | E27: 717.88 | F27: AUQ | G27: 45699 | H27: CCMS | I27: VilliersR-Audit Fees | J27: Annual membership fees for SAICA as discussed with Mark W | O27: https://www.saica.co.z | Q27: =ABS(E27) -> 717.88
A28: AU052 | B28: AU020080 | C28: 5190001000 | D28: Contributions& club membershi | E28: 659.09 | F28: AUQ | G28: 45733 | H28: CCMS | I28: MUD-Tuition (study) Reimbursem | J28: AICD annual membership fee | O28: COMPANY DIRECTOR | Q28: =ABS(E28) -> 659.09
A29: AU052 | B29: AU070150 | C29: 5190001000 | D29: Contributions& club membershi | E29: 252.35 | F29: AUQ | G29: 45700 | H29: CCMS | I29: BARRACLOUGHD-Contributions & C | J29: harvard subscription | O29: HBR/BT_YQTXXSNPVSQZ80/94302840 | Q29: =ABS(E29) -> 252.35
A30: AU052 | B30: AU030215 | C30: 5190001000 | D30: Contributions& club membershi | E30: 177.27 | F30: AUQ | G30: 45736 | H30: CCMS | I30: CrokerC-Default Licensee Merch | J30: Digital The Land Subscription | O30: web*The Land/STANDING AUTHORITY | Q30: =ABS(E30) -> 177.27
A31: AU052 | B31: AU031752 | C31: 5190001000 | D31: Contributions& club membershi | E31: 177.27 | F31: AUQ | G31: 45737 | H31: CCMS | I31: FelanT-Default Licensee Mercha | J31: The Land Subscription | O31: web*The Land/STANDING AUTHORITY | Q31: =ABS(E31) -> 177.27
A32: AU052 | B32: AU030613 | C32: 5190001000 | D32: Contributions& club membershi | E32: 127.28 | F32: AUQ | G32: 45708 | H32: CCMS | I32: McfarlaneT-Default Licensee Me | J32: Fishing License | O32: DEPARTMENT OF PRIMARY | Q32: =ABS(E32) -> 127.28
A33: AU001 | B33: AU030618 | C33: 5190001000 | D33: Contributions& club membershi | E33: 85 | F33: AUQ | G33: 45707 | H33: AP Accruals | I33: 632-AMOOR01 | K33: Member listing for community c | L33: 632 | M33: MOORA CHAMBER OF COMMERCE INC. | Q33: =ABS(E33) -> 85
A34: AU052 | B34: AU050119 | C34: 5190001000 | D34: Contributions& club membershi | E34: 83.3 | F34: AUQ | G34: 45663 | H34: CCMS | I34: PetterssonT-Default Licensee M | J34: API CPV valuer licence compliance | O34: ZEN*B2B-Aus Prop Instit S | Q34: =ABS(E34) -> 83.3
A35: AU052 | B35: AU010011 | C35: 5190001000 | D35: Contributions& club membershi | E35: 59.08 | F35: AUQ | G35: 45699 | H35: CCMS | I35: SACCHETTIL-Contributions & Clu | J35: AFR monthly subscription for Geerten Battjes | O35: FAIRFAX SUBSCRIPTIONS/74564724316353115664500 | Q35: =ABS(E35) -> 59.08
A36: AU052 | B36: AU010011 | C36: 5190001000 | D36: Contributions& club membershi | E36: 59.08 | F36: AUQ | G36: 45699 | H36: CCMS | I36: SACCHETTIL-Contributions & Clu | J36: AFR monthly subscription for Geerten Battjes | O36: FAIRFAX SUBSCRIPTIONS/74564725009353105484280 | Q36: =ABS(E36) -> 59.08
A37: AU052 | B37: AU071197 | C37: 5190001000 | D37: Contributions& club membershi | E37: 55.51 | F37: AUQ | G37: 45733 | H37: CCMS | I37: KeoC-Default Licensee Merchant | J37: Shuttertock monthly subscription - 5 Image pack | O37: SHUTTERSTOCK IRELAND LIMI | Q37: =ABS(E37) -> 55.51
A38: AU052 | B38: AU071197 | C38: 5190001000 | D38: Contributions& club membershi | E38: 49.84 | F38: AUQ | G38: 45694 | H38: CCMS | I38: KeoC-Default Licensee Merchant | J38: Shutterstock (2 extra image pack) | O38: SHUTTERSTOCK IRELAND LIMI | Q38: =ABS(E38) -> 49.84
A39: AU052 | B39: AU071197 | C39: 5190001000 | D39: Contributions& club membershi | E39: 32.85 | F39: AUQ | G39: 45694 | H39: CCMS | I39: KeoC-Default Licensee Merchant | J39: Shutterstock monthly subscription (10 images download pack) | O39: STK*Shutterstock/149422299 | Q39: =ABS(E39) -> 32.85
A40: AU052 | B40: AU071197 | C40: 5190001000 | D40: Contributions& club membershi | E40: 32.85 | F40: AUQ | G40: 45714 | H40: CCMS | I40: KeoC-Default Licensee Merchant | J40: Shutterstock Monthly Subscription (10 Downloads) | O40: STK*Shutterstock/149843309 | Q40: =ABS(E40) -> 32.85
A41: AU052 | B41: AU071197 | C41: 5190001000 | D41: Contributions& club membershi | E41: 32.85 | F41: AUQ | G41: 45744 | H41: CCMS | I41: KeoC-Default Licensee Merchant | J41: Shutterstock 10 downloads per March | O41: STK*Shutterstock/150247840 | Q41: =ABS(E41) -> 32.85
A42: AU052 | B42: AU071197 | C42: 5190001000 | D42: Contributions& club membershi | E42: 24.92 | F42: AUQ | G42: 45705 | H42: CCMS | I42: KeoC-Default Licensee Merchant | J42: Shutterstock (2 extra image pack) | O42: SHUTTERSTOCK IRELAND LIMI | Q42: =ABS(E42) -> 24.92
A43: AU052 | B43: AU071197 | C43: 5190001000 | D43: Contributions& club membershi | E43: 24.92 | F43: AUQ | G43: 45714 | H43: CCMS | I43: KeoC-Default Licensee Merchant | J43: Shutterstock (2 extra image pack) | O43: SHUTTERSTOCK IRELAND LIMI | Q43: =ABS(E43) -> 24.92
A44: AU052 | B44: AU071197 | C44: 5190001000 | D44: Contributions& club membershi | E44: -9.08 | F44: AUQ | G44: 45714 | H44: CCMS | I44: KeoC-Contributions & Club Memb | J44: Incorrect charge disputed with Westpac & Amazon refund | O44: AMZNPRIMEAU MEMBERSHIP | Q44: =ABS(E44) -> 9.08
A45: AU052 | B45: AU071197 | C45: 5190001000 | D45: Contributions& club membershi | E45: 9.08 | F45: AUQ | G45: 45715 | H45: KeoC-Contributions & Club Memb | I45: KeoC-Contributions & Club Memb | Q45: =ABS(E45) -> 9.08

Sheet Meeting costs
A1: Account Number | C1: =Summary!A20 -> 5200006000
A2: Account Name | C2: =Summary!B20 -> Meeting costs | F2: Notes:
A3: GL Total | C3: 112631.6 | F3: Costs associated with Client Council events such as accomodation, catering, venue hire, flights have been treated as tax deductible and no FBT on the basis that they are a business expense. | T3: AU001 | V3: =SUMIF($A$8:$A$23971,"AU001",V8:V23971) -> 4862
A4: Per TB | C4: =SUM(E:E) -> 112631.6 | F4: Costs associated with staff conferences are tax deductible if the conference is greater than 4 hours. The offsite is for an entire day so greater than 4 hours. The dinner and drinks in the evening have been classified | T4: AU052 | V4: =SUMIF($A$7:$A$23972,"AU052",V8:V23973)+V8 -> 7576.54
A5: Variance | C5: =C3-C4 -> 0 | F5: as meal entertainment and subject to FBT using 50/50 method. | V5: =SUM(V3:V4) -> 12438.54
AD6: Income tax purposes
A7: BUSINESS_UNIT_CODE | B7: OPERATING_UNIT_CODE | C7: ACCOUNT_CODE | D7: DESCRIPTION | E7: BASE_AMOUNT | F7: BASE_CURRENCY_CODE | G7: JOURNAL_DATE | H7: DESCR | I7: LINE_DESCR | J7: PURPOSE | K7: INVOICE_DESCR | L7: INVOICE_ID | M7: VENDOR_NAME | N7: EMPLOYEE_NAME | O7: CHARGE_DESCRIPTION | Q7: ABS | R7: Search Terms | S7: Tax Description | T7: ME? Y/N | U7: OU | V7: ME $ | W7: Not ME but other type of FB Y/N | X7: Not ME but other type of FB ==> $ | Y7: Nets to Nil in GL accts | Z7: s58P M&I or Bus Exp - notFB | AA7: ME | AB7: Car FB - addn op costs | AC7: CP Exp FB | AD7: Capital expenditure | AE7: No FBT and not ded | AF7: Additional Comments
A8: AU001 | B8: AU030310 | C8: 5200006000 | D8: Meeting costs | E8: 58612.91 | F8: AUQ | G8: 45720 | H8: AP Accruals | I8: 1103783-ACHAP00 | K8: Accommodation, catering and ve | L8: 1103783 | M8: CHAPTER PLACE | Q8: =ABS(E8) -> 58612.91
A9: AU052 | B9: AU010010 | C9: 5200006000 | D9: Meeting costs | E9: 19323.37 | F9: AUQ | G9: 45720 | H9: AP Accruals | I9: INV-1839-AGRAM01 | K9: ET workshop facilitation | L9: INV-1839 | M9: GRAM CONSULTING GROUP PTY LTD | Q9: =ABS(E9) -> 19323.37
A10: AU052 | B10: AU010010 | C10: 5200006000 | D10: Meeting costs | E10: 7993.81 | F10: AUQ | G10: 45694 | H10: CCMS | I10: SACCHETTIL-Default Licensee Me | J10: ET Offsite | O10: Pier One Sydney FP | Q10: =ABS(E10) -> 7993.81 | S10: Accept business
A11: AU052 | B11: AU030214 | C11: 5200006000 | D11: Meeting costs | E11: 5437.97 | F11: AUQ | G11: 45736 | H11: CCMS | I11: EllisT-Domestic & Overseas lod | J11: Final Venue Payment for 2025 NSW State Offsite | AV | O11: Rydges Hunter OPI | Q11: =ABS(E11) -> 5437.97 | S11: Accept business
A12: AU001 | B12: AU070150 | C12: 5200006000 | D12: Meeting costs | E12: 4862 | F12: AUQ | G12: 45733 | H12: AP Accruals | I12: 1010418-AMOUN00 | K12: final WAB costs for dinners | L12: 1010418 | M12: MOUNT LOFTY OPERATIONS PTY LTD | Q12: =ABS(E12) -> 4862 | S12: ME | T12: Y | U12: =B12 -> AU070150 | V12: =E12 -> 4862
A13: AU001 | B13: AU032066 | C13: 5200006000 | D13: Meeting costs | E13: 2034.75 | F13: AUQ | G13: 45720 | H13: AP Accruals | I13: 230976470-APULL02 | K13: 21Feb Accom Dinner SANTNWV CC | L13: 230976470 | M13: PULLMAN ADELAIDE | Q13: =ABS(E13) -> 2034.75
A14: AU052 | B14: AU030310 | C14: 5200006000 | D14: Meeting costs | E14: 1981.82 | F14: AUQ | G14: 45737 | H14: CCMS | I14: MckinnonR-Airfares | J14: Coach hire | Transport to activity and dinner for the VICTAS offsite | Feb 2025 | O14: SNOWBUS | Q14: =ABS(E14) -> 1981.82 | S14: Facilitating ME | T14: Y | U14: =B14 -> AU030310 | V14: =E14 -> 1981.82
A15: AU052 | B15: AU010010 | C15: 5200006000 | D15: Meeting costs | E15: 1800.99 | F15: AUQ | G15: 45735 | H15: CCMS | I15: SACCHETTIL-Default Licensee Me | J15: ET Offsite AV hire | O15: Pier One Sydney FP | Q15: =ABS(E15) -> 1800.99
A16: AU052 | B16: AU030510 | C16: 5200006000 | D16: Meeting costs | E16: 1767.27 | F16: AUQ | G16: 45722 | H16: CCMS | I16: PriceC-Entertainment Expense | J16: Wine offsite dinner Feb 25 2 Nights Client Support | O16: PINDARIE PTY LTD | Q16: =ABS(E16) -> 1767.27 | S16: ME | T16: Y | U16: =B16 -> AU030510 | V16: =E16 -> 1767.27
A17: AU052 | B17: AU050118 | C17: 5200006000 | D17: Meeting costs | E17: 1291.48 | F17: AUQ | G17: 45740 | H17: CCMS | I17: ROSSR-Domestic & Overseas lodg | J17: REGIONAL RISK LT STRATEGY OFFSITE - MEETING COSTS | O17: Q STATION | Q17: =ABS(E17) -> 1291.48
A18: AU052 | B18: AU071197 | C18: 5200006000 | D18: Meeting costs | E18: 913.5 | F18: AUQ | G18: 45694 | H18: CCMS | I18: HARVEYMF-Entertainment Expense | J18: 2025 Australian Dairy Conference Registration | O18: AUST DAIRY CONFERENCE | Q18: =ABS(E18) -> 913.5
A19: AU052 | B19: AU025064 | C19: 5200006000 | D19: Meeting costs | E19: 441.14 | F19: AUQ | G19: 45740 | H19: CCMS | I19: HallidayA-Default Licensee Mer | J19: Crockery for Board | O19: MYER SYDNEY CITY | Q19: =ABS(E19) -> 441.14
A20: AU052 | B20: AU025109 | C20: 5200006000 | D20: Meeting costs | E20: 373.95 | F20: AUQ | G20: 45708 | H20: AP Accruals | I20: EEC-1289-EROBE00 | K20: Team Function - BI Planning Da | L20: EEC-1289 | M20: CHLOE ROBERTS | Q20: =ABS(E20) -> 373.95 | S20: ME | T20: Y | U20: =B20 -> AU025109 | V20: =E20 -> 373.95
A21: AU052 | B21: AU010010 | C21: 5200006000 | D21: Meeting costs | E21: 347.55 | F21: AUQ | G21: 45694 | H21: CCMS | I21: SACCHETTIL-Default Licensee Me | J21: ET offsite - additonal cost for facilitators | O21: Pier One Sydney FP | Q21: =ABS(E21) -> 347.55
A22: AU052 | B22: AU030510 | C22: 5200006000 | D22: Meeting costs | E22: 329.83 | F22: AUQ | G22: 45722 | H22: CCMS | I22: PriceC-Office Supplies | J22: SANTNWV Offsite Cert Frames Post IT Flip Charts Markers | O22: OFFICEWORKS | Q22: =ABS(E22) -> 329.83
A23: AU052 | B23: AU030510 | C23: 5200006000 | D23: Meeting costs | E23: 271.45 | F23: AUQ | G23: 45722 | H23: CCMS | I23: PriceC-Default Licensee Mercha | J23: SANTNWV Engraving & Perp. Shields x 2 | O23: CITY TROPHIES | Q23: =ABS(E23) -> 271.45
A24: AU052 | B24: AU020087 | C24: 5200006000 | D24: Meeting costs | E24: 258.29 | F24: AUQ | G24: 45740 | H24: CCMS | I24: ROSSR-Domestic & Overseas lodg | J24: REGIONAL RISK LT STRATEGY OFFSITE - MEETING COSTS | O24: Q STATION | Q24: =ABS(E24) -> 258.29
A25: AU052 | B25: AU020097 | C25: 5200006000 | D25: Meeting costs | E25: 258.29 | F25: AUQ | G25: 45740 | H25: CCMS | I25: ROSSR-Domestic & Overseas lodg | J25: REGIONAL RISK LT STRATEGY OFFSITE - MEETING COSTS | O25: Q STATION | Q25: =ABS(E25) -> 258.29
A26: AU052 | B26: AU020098 | C26: 5200006000 | D26: Meeting costs | E26: 258.29 | F26: AUQ | G26: 45740 | H26: CCMS | I26: ROSSR-Domestic & Overseas lodg | J26: REGIONAL RISK LT STRATEGY OFFSITE - MEETING COSTS | O26: Q STATION | Q26: =ABS(E26) -> 258.29
A27: AU052 | B27: AU020099 | C27: 5200006000 | D27: Meeting costs | E27: 258.29 | F27: AUQ | G27: 45740 | H27: CCMS | I27: ROSSR-Domestic & Overseas lodg | J27: REGIONAL RISK LT STRATEGY OFFSITE - MEETING COSTS | O27: Q STATION | Q27: =ABS(E27) -> 258.29
A28: AU052 | B28: AU050110 | C28: 5200006000 | D28: Meeting costs | E28: 258.29 | F28: AUQ | G28: 45740 | H28: CCMS | I28: ROSSR-Domestic & Overseas lodg | J28: REGIONAL RISK LT STRATEGY OFFSITE - MEETING COSTS | O28: Q STATION | Q28: =ABS(E28) -> 258.29
A29: AU052 | B29: AU050113 | C29: 5200006000 | D29: Meeting costs | E29: 258.29 | F29: AUQ | G29: 45740 | H29: CCMS | I29: ROSSR-Domestic & Overseas lodg | J29: REGIONAL RISK LT STRATEGY OFFSITE - MEETING COSTS | O29: Q STATION | Q29: =ABS(E29) -> 258.29
A30: AU052 | B30: AU050119 | C30: 5200006000 | D30: Meeting costs | E30: 258.29 | F30: AUQ | G30: 45740 | H30: CCMS | I30: ROSSR-Domestic & Overseas lodg | J30: REGIONAL RISK LT STRATEGY OFFSITE - MEETING COSTS | O30: Q STATION | Q30: =ABS(E30) -> 258.29
A31: AU052 | B31: AU010014 | C31: 5200006000 | D31: Meeting costs | E31: 258.29 | F31: AUQ | G31: 45740 | H31: CCMS | I31: ROSSR-Domestic & Overseas lodg | J31: REGIONAL RISK LT STRATEGY OFFSITE - MEETING COSTS - ED WARNER | O31: Q STATION | Q31: =ABS(E31) -> 258.29
A32: AU052 | B32: AU025064 | C32: 5200006000 | D32: Meeting costs | E32: 240 | F32: AUQ | G32: 45733 | H32: CCMS | I32: HallidayA-Offshore Meals & Lod | J32: Coffee | O32: SP BUN COFFEE AUSTRALI | Q32: =ABS(E32) -> 240
... A35: AU052 | B35: AU030510 | C35: 5200006000 | D35: Meeting costs | E35: 197.18 | F35: AUQ | G35: 45722 | H35: CCMS | I35: PriceC-Office Supplies | J35: SANTNWV Offsite Feb 25 Presenter Thank you gifts | O35: CHARLESWORTH NUTS PT | Q35: =ABS(E35) -> 197.18
A36: AU052 | B36: AU030415 | C36: 5200006000 | D36: Meeting costs | E36: 196.11 | F36: AUQ | G36: 45727 | H36: CCMS | I36: HamiltonS-Offshore Meals & Lod | J36: Rockhampton Bundaberg Strategy Day food expenses | O36: GOOD GROUNDS CATERING/219541390784 | Q36: =ABS(E36) -> 196.11 | S36: ME | T36: Y | U36: =B36 -> AU030415 | V36: =E36 -> 196.11
A37: AU052 | B37: AU036750 | C37: 5200006000 | D37: Meeting costs | E37: 193.79 | F37: AUQ | G37: 45679 | H37: AP Accruals | I37: EEC-1178-EWATE00 | K37: Perth Fraud Team Christmas Lun | L37: EEC-1178 | M37: HAMISH WATERS | Q37: =ABS(E37) -> 193.79 | S37: ME | T37: Y | U37: =B37 -> AU036750 | V37: =E37 -> 193.79
A38: AU052 | B38: AU030415 | C38: 5200006000 | D38: Meeting costs | E38: 183.42 | F38: AUQ | G38: 45727 | H38: CCMS | I38: HamiltonS-Offshore Meals & Lod | J38: Rockhampton Bundaberg Strategy Day food expenses | O38: GOOD GROUNDS CATERING/219541407071 | Q38: =ABS(E38) -> 183.42 | S38: ME | T38: Y | U38: =B38 -> AU030415 | V38: =E38 -> 183.42
A39: AU052 | B39: AU025064 | C39: 5200006000 | D39: Meeting costs | E39: 180 | F39: AUQ | G39: 45712 | H39: CCMS | I39: BradaricS-Offshore Meals & Lod | J39: Other | O39: SP BUN COFFEE AUSTRALI | Q39: =ABS(E39) -> 180
A40: AU052 | B40: AU032066 | C40: 5200006000 | D40: Meeting costs | E40: 178.18 | F40: AUQ | G40: 45726 | H40: CCMS | I40: PriceC-Offshore Meals & Lodgin | J40: Client Council FEb 25 Meeting - Breakfast and Day Refreshments | O40: VELOCE PANINO | Q40: =ABS(E40) -> 178.18
A41: AU052 | B41: AU025064 | C41: 5200006000 | D41: Meeting costs | E41: 174.55 | F41: AUQ | G41: 45687 | H41: CCMS | I41: HallidayA-Offshore Meals & Lod | J41: Coffee | O41: SP BUN COFFEE AUSTRALI | Q41: =ABS(E41) -> 174.55
A42: AU052 | B42: AU025064 | C42: 5200006000 | D42: Meeting costs | E42: 145.05 | F42: AUQ | G42: 45720 | H42: CCMS | I42: HallidayA-Office Supplies | J42: guest Relations | O42: Woolworths Online | Q42: =ABS(E42) -> 145.05
A43: AU052 | B43: AU071197 | C43: 5200006000 | D43: Meeting costs | E43: 127.27 | F43: AUQ | G43: 45674 | H43: CCMS | I43: Gidley-BairdA-Default Licensee | J43: Farm Writers Event Ticket for David Foote AU Future for Red Meat | O43: FARM WRITERS | Q43: =ABS(E43) -> 127.27
A44: AU052 | B44: AU071197 | C44: 5200006000 | D44: Meeting costs | E44: -127.27 | F44: AUQ | G44: 45685 | H44: CCMS | I44: Gidley-BairdA-Default Licensee | J44: Farm Writers Event Ticket for David Foote AU Future for Red Meat - Refund | O44: FARM WRITERS | Q44: =ABS(E44) -> 127.27
A45: AU052 | B45: AU025064 | C45: 5200006000 | D45: Meeting costs | E45: 119.93 | F45: AUQ | G45: 45740 | H45: CCMS | I45: HallidayA-Default Licensee Mer | J45: Power Boards for Board | O45: SUNLITE MITRE 10 YORK | Q45: =ABS(E45) -> 119.93
A46: AU052 | B46: AU010013 | C46: 5200006000 | D46: Meeting costs | E46: 108 | F46: AUQ | G46: 45664 | H46: AP Accruals | I46: EEC-1154-EKHAS07 | K46: Parking CHC | L46: EEC-1154 | M46: WAQAS KHAN | Q46: =ABS(E46) -> 108 | S46: business travel
A47: AU052 | B47: AU010013 | C47: 5200006000 | D47: Meeting costs | E47: 96.49 | F47: AUQ | G47: 45664 | H47: AP Accruals | I47: EEC-1154-EKHAS07 | K47: Airport Parking SYD | L47: EEC-1154 | M47: WAQAS KHAN | Q47: =ABS(E47) -> 96.49 | S47: business travel
A48: AU052 | B48: AU025064 | C48: 5200006000 | D48: Meeting costs | E48: 65.29 | F48: AUQ | G48: 45740 | H48: CCMS | I48: HallidayA-Default Licensee Mer | J48: Teapots | O48: MYER SYDNEY CITY | Q48: =ABS(E48) -> 65.29
A49: AU052 | B49: AU010013 | C49: 5200006000 | D49: Meeting costs | E49: 42 | F49: AUQ | G49: 45664 | H49: AP Accruals | I49: EEC-1154-EKHAS07 | K49: Lunch 14DEC24 | L49: EEC-1154 | M49: WAQAS KHAN | Q49: =ABS(E49) -> 42 | S49: business travel
A50: AU052 | B50: AU010013 | C50: 5200006000 | D50: Meeting costs | E50: 31 | F50: AUQ | G50: 45664 | H50: AP Accruals | I50: EEC-1154-EKHAS07 | K50: Dinner 18DEC24 | L50: EEC-1154 | M50: WAQAS KHAN | Q50: =ABS(E50) -> 31 | S50: business travel
A51: AU052 | B51: AU010013 | C51: 5200006000 | D51: Meeting costs | E51: 29 | F51: AUQ | G51: 45664 | H51: AP Accruals | I51: EEC-1154-EKHAS07 | K51: Dinner 16DEC24 | L51: EEC-1154 | M51: WAQAS KHAN | Q51: =ABS(E51) -> 29 | S51: business travel
A52: AU052 | B52: AU010013 | C52: 5200006000 | D52: Meeting costs | E52: 26 | F52: AUQ | G52: 45664 | H52: AP Accruals | I52: EEC-1154-EKHAS07 | K52: Dinner 19DEC24 | L52: EEC-1154 | M52: WAQAS KHAN | Q52: =ABS(E52) -> 26 | S52: business travel
A53: AU052 | B53: AU030415 | C53: 5200006000 | D53: Meeting costs | E53: 24.14 | F53: AUQ | G53: 45727 | H53: CCMS | I53: HamiltonS-Office Supplies | J53: Rockhampton Bundaberg Strategy Day food expenses | O53: WOOLWORTHS/106 FE WALKER | Q53: =ABS(E53) -> 24.14
A54: AU052 | B54: AU025064 | C54: 5200006000 | D54: Meeting costs | E54: 22.73 | F54: AUQ | G54: 45740 | H54: CCMS | I54: HallidayA-Office Supplies | J54: Berries for ET | O54: WOOLWORTHS/CNR 540 GEORGE | Q54: =ABS(E54) -> 22.73
A55: AU052 | B55: AU010013 | C55: 5200006000 | D55: Meeting costs | E55: 21 | F55: AUQ | G55: 45664 | H55: AP Accruals | I55: EEC-1154-EKHAS07 | K55: Dinner 17DEC24 | L55: EEC-1154 | M55: WAQAS KHAN | Q55: =ABS(E55) -> 21 | S55: business travel
A56: AU052 | B56: AU030510 | C56: 5200006000 | D56: Meeting costs | E56: 17.91 | F56: AUQ | G56: 45723 | H56: CCMS | I56: HardmanJ-Domestic & Overseas l | J56: State offsite - Murray Bridge - general offsite expense | O56: Bridgeport Hotel | Q56: =ABS(E56) -> 17.91
A57: AU052 | B57: AU032066 | C57: 5200006000 | D57: Meeting costs | E57: 17.82 | F57: AUQ | G57: 45726 | H57: CCMS | I57: PriceC-Office Supplies | J57: Client Council Feb 25 Morning Tea selections | O57: WOOLWORTHS/SIR DONALD BRA | Q57: =ABS(E57) -> 17.82
A58: AU052 | B58: AU010013 | C58: 5200006000 | D58: Meeting costs | E58: 17.5 | F58: AUQ | G58: 45664 | H58: AP Accruals | I58: EEC-1154-EKHAS07 | K58: Dinner 15DEC24 | L58: EEC-1154 | M58: WAQAS KHAN | Q58: =ABS(E58) -> 17.5 | S58: business travel
A59: AU052 | B59: AU010029 | C59: 5200006000 | D59: Meeting costs | E59: 7.95 | F59: AUQ | G59: 45705 | H59: CCMS | I59: HallidayA-Default Licensee Mer | J59: Balls for Grad Induction Day | O59: BIG W/CRN OF GEORGE & PAR | Q59: =ABS(E59) -> 7.95
A60: AU052 | B60: AU030325 | C60: 5200006000 | D60: Meeting costs | E60: 4.09 | F60: AUQ | G60: 45740 | H60: CCMS | I60: KokC-Costs own Car Fleet | J60: Milk for Morning Tea - Gippsland Area Team get together. | O60: EG GROUP/53 SMITH ST | Q60: =ABS(E60) -> 4.09

Sheet Misc exp
A1: Account Number | C1: =Summary!A21 -> 5200999000
A2: Account Name | C2: =Summary!B21 -> Miscellaneous expenses | G2: Notes:
A3: GL Total | C3: -7588.44 | G3: No meal entertainment or capital expenditure
A4: Per TB | C4: =SUM(E:E) -> -7588.44 | G4: One amount for sustainability benefit. Check against HR report | T4: AU001 | U4: =SUMIF($A$10:$A$23974,"AU001",U9:U23973) -> 0
A5: Variance | C5: =C3-C4 -> 1.0004442e-11 | T5: AU052 | U5: =SUMIF($A$10:$A$23975,"AU052",U9:U23974) -> 0
AC6: Income tax purposes
A7: BUSINESS_UNIT_CODE | B7: OPERATING_UNIT_CODE | C7: ACCOUNT_CODE | D7: DESCRIPTION | E7: BASE_AMOUNT | F7: BASE_CURRENCY_CODE | G7: JOURNAL_DATE | H7: DESCR | I7: LINE_DESCR | J7: PURPOSE | K7: INVOICE_DESCR | L7: INVOICE_ID | M7: VENDOR_NAME | N7: EMPLOYEE_NAME | O7: CHARGE_DESCRIPTION | Q7: ABS | R7: Search Terms | S7: Tax Description | T7: ME? Y/N | U7: ME $ | V7: Not ME but other type of FB Y/N | W7: Not ME but other type of FB ==> $ | X7: Nets to Nil in GL accts | Y7: s58P M&I or Bus Exp - notFB | Z7: ME | AA7: Car FB - addn op costs | AB7: CP Exp FB | AC7: Capital expenditure | AD7: No FBT and not ded | AE7: Additional Comments
A8: AU052 | B8: AU073158 | C8: 5200999000 | D8: Miscellaneous expenses | E8: 168548.84 | F8: AUQ | G8: 45742 | H8: 18755-ORABO00 | I8: 18755-ORABO00 | Q8: =ABS(E8) -> 168548.84 | S8: Business expense
A9: AU052 | B9: AU073158 | C9: 5200999000 | D9: Miscellaneous expenses | E9: -152218.23 | F9: AUQ | G9: 45735 | H9: Market data 2024 Recharges | I9: 18755-ORABO00 | Q9: =ABS(E9) -> 152218.23 | S9: Business expense
A10: AU001 | B10: AU025085 | C10: 5200999000 | D10: Miscellaneous expenses | E10: -148419 | F10: AUQ | G10: 45744 | H10: ASX INV LTI | I10: ASX INV LTI | Q10: =ABS(E10) -> 148419 | S10: Business expense
A11: AU001 | B11: AU030430 | C11: 5200999000 | D11: Miscellaneous expenses | E11: -110631.99 | F11: AUQ | G11: 45717 | H11: T24 Australia | I11: 9999999 | Q11: =ABS(E11) -> 110631.99 | S11: Business expense
A12: AU001 | B12: AU030430 | C12: 5200999000 | D12: Miscellaneous expenses | E12: 110631.99 | F12: AUQ | G12: 45715 | H12: T24 Australia | I12: 9999999 | Q12: =ABS(E12) -> 110631.99 | S12: Business expense
A13: AU001 | B13: AU025085 | C13: 5200999000 | D13: Miscellaneous expenses | E13: 99387.03 | F13: AUQ | G13: 45737 | H13: DAILY I/CHANGE FEES | I13: ASX INV ACS0550743 | Q13: =ABS(E13) -> 99387.03 | S13: Business expense
A14: AU052 | B14: AU060124 | C14: 5200999000 | D14: Miscellaneous expenses | E14: -60691.13 | F14: AUQ | G14: 45714 | H14: SING recharges_2024 pmt | I14: FC2313/11/24-ORABO01 | Q14: =ABS(E14) -> 60691.13 | S14: Business expense
A15: AU001 | B15: AU025085 | C15: 5200999000 | D15: Miscellaneous expenses | E15: 46590.98 | F15: AUQ | G15: 45709 | H15: DAILY I/CHANGE FEES | I15: ASX INV ACS0550628 | Q15: =ABS(E15) -> 46590.98 | S15: Business expense
A16: AU052 | B16: AU060120 | C16: 5200999000 | D16: Miscellaneous expenses | E16: 42952.83 | F16: AUQ | G16: 45742 | H16: 18755-ORABO00 | I16: 18755-ORABO00 | Q16: =ABS(E16) -> 42952.83 | S16: Business expense
A17: AU052 | B17: AU060120 | C17: 5200999000 | D17: Miscellaneous expenses | E17: -42670.28 | F17: AUQ | G17: 45735 | H17: Market data 2024 Recharges | I17: 18755-ORABO00 | Q17: =ABS(E17) -> 42670.28 | S17: Business expense
A18: AU052 | B18: AU010010 | C18: 5200999000 | D18: Miscellaneous expenses | E18: 23359.05 | F18: AUQ | G18: 45746 | H18: NT BBB Insur Feb 25 | I18: NSW BBB Insur Feb 25 | Q18: =ABS(E18) -> 23359.05 | S18: Business expense
A19: AU052 | B19: AU010010 | C19: 5200999000 | D19: Miscellaneous expenses | E19: -23359.05 | F19: AUQ | G19: 45736 | H19: RAB BBB Insur Feb 25 | I19: NSW BBB Insur Feb 25 | Q19: =ABS(E19) -> 23359.05 | S19: Business expense
... A24: AU001 | B24: AU030619 | C24: 5200999000 | D24: Miscellaneous expenses | E24: -11365.43 | F24: AUQ | G24: 45744 | H24: T24 Australia | I24: 9999999 | Q24: =ABS(E24) -> 11365.43 | S24: Business expense
A25: AU001 | B25: AU030619 | C25: 5200999000 | D25: Miscellaneous expenses | E25: 11365.43 | F25: AUQ | G25: 45736 | H25: T24 Australia | Q25: =ABS(E25) -> 11365.43 | S25: Business expense
A26: AU052 | B26: AU061134 | C26: 5200999000 | D26: Miscellaneous expenses | E26: 9104.43 | F26: AUQ | G26: 45742 | H26: 18755-ORABO00 | I26: 18755-ORABO00 | Q26: =ABS(E26) -> 9104.43 | S26: Business expense
A27: AU052 | B27: AU020087 | C27: 5200999000 | D27: Miscellaneous expenses | E27: 8730.18 | F27: AUQ | G27: 45742 | H27: 18755-ORABO00 | I27: 18755-ORABO00 | Q27: =ABS(E27) -> 8730.18 | S27: Business expense
A28: AU052 | B28: AU061134 | C28: 5200999000 | D28: Miscellaneous expenses | E28: -8222.32 | F28: AUQ | G28: 45735 | H28: Market data 2024 Recharges | I28: 18755-ORABO00 | Q28: =ABS(E28) -> 8222.32 | S28: Business expense
A29: AU052 | B29: AU020087 | C29: 5200999000 | D29: Miscellaneous expenses | E29: -8089.35 | F29: AUQ | G29: 45735 | H29: Market data 2024 Recharges | I29: 18755-ORABO00 | Q29: =ABS(E29) -> 8089.35 | S29: Business expense
A30: AU052 | B30: AU071196 | C30: 5200999000 | D30: Miscellaneous expenses | E30: 6718.29 | F30: AUQ | G30: 45742 | H30: 18755-ORABO00 | I30: 18755-ORABO00 | Q30: =ABS(E30) -> 6718.29 | S30: Business expense
A31: AU052 | B31: AU071196 | C31: 5200999000 | D31: Miscellaneous expenses | E31: -6407.11 | F31: AUQ | G31: 45735 | H31: Market data 2024 Recharges | I31: 18755-ORABO00 | Q31: =ABS(E31) -> 6407.11 | S31: Business expense
A32: AU001 | B32: AU025100 | C32: 5200999000 | D32: Miscellaneous expenses | E32: -6000 | F32: AUQ | G32: 45681 | H32: T24 Australia | I32: 9999999 | Q32: =ABS(E32) -> 6000 | S32: Business expense
A33: AU052 | B33: AU025100 | C33: 5200999000 | D33: Miscellaneous expenses | E33: 5214.74 | F33: AUQ | G33: 45742 | H33: 18755-ORABO00 | I33: 18755-ORABO00 | Q33: =ABS(E33) -> 5214.74 | S33: Business expense
A34: AU052 | B34: AU025100 | C34: 5200999000 | D34: Miscellaneous expenses | E34: -4716.52 | F34: AUQ | G34: 45735 | H34: Market data 2024 Recharges | I34: 18755-ORABO00 | Q34: =ABS(E34) -> 4716.52 | S34: Business expense
A35: AU052 | B35: AU025085 | C35: 5200999000 | D35: Miscellaneous expenses | E35: 4167.71 | F35: AUQ | G35: 45734 | H35: DAILY I/CHANGE FEES | I35: RANE 0225 | Q35: =ABS(E35) -> 4167.71 | S35: Business expense
A36: AU052 | B36: AU025085 | C36: 5200999000 | D36: Miscellaneous expenses | E36: 3679.19 | F36: AUQ | G36: 45677 | H36: DAILY I/CHANGE FEES | I36: RANE 1224 | Q36: =ABS(E36) -> 3679.19 | S36: Business expense
A37: AU052 | B37: AU025085 | C37: 5200999000 | D37: Miscellaneous expenses | E37: 3220.16 | F37: AUQ | G37: 45706 | H37: DAILY I/CHANGE FEES | I37: RANE 0125 | Q37: =ABS(E37) -> 3220.16 | S37: Business expense
... A50: AU052 | B50: AU025085 | C50: 5200999000 | D50: Miscellaneous expenses | E50: 1992.1 | F50: AUQ | G50: 45678 | H50: ASX INV ACL0319949 | I50: ASX INV ACL0319951 | Q50: =ABS(E50) -> 1992.1 | S50: Business expense
A51: AU001 | B51: AU030619 | C51: 5200999000 | D51: Miscellaneous expenses | E51: 1870 | F51: AUQ | G51: 45686 | H51: T24 Australia | Q51: =ABS(E51) -> 1870 | S51: Business expense
A52: AU052 | B52: AU010010 | C52: 5200999000 | D52: Miscellaneous expenses | E52: 1856.89 | F52: AUQ | G52: 45746 | H52: NT BBB Insur Feb 25 | I52: SA BBB Insur Feb 25 | Q52: =ABS(E52) -> 1856.89 | S52: Business expense
A53: AU052 | B53: AU010010 | C53: 5200999000 | D53: Miscellaneous expenses | E53: -1856.89 | F53: AUQ | G53: 45736 | H53: RAB BBB Insur Feb 25 | I53: SA BBB Insur Feb 25 | Q53: =ABS(E53) -> 1856.89 | S53: Business expense
A54: AU001 | B54: AU025100 | C54: 5200999000 | D54: Miscellaneous expenses | E54: -1855.53 | F54: AUQ | G54: 45686 | H54: T24 Australia | I54: 9999999 | Q54: =ABS(E54) -> 1855.53 | S54: Business expense
A55: AU001 | B55: AU036740 | C55: 5200999000 | D55: Miscellaneous expenses | E55: 1521.39 | F55: AUQ | G55: 45747 | H55: Incorrect Mapping | I55: Clear returned funds | Q55: =ABS(E55) -> 1521.39 | S55: Business expense
A56: AU052 | B56: AU073158 | C56: 5200999000 | D56: Miscellaneous expenses | E56: -1393.63 | F56: AUQ | G56: 45747 | H56: PL Reval Journals | I56: GL Revaluation | Q56: =ABS(E56) -> 1393.63 | S56: Business expense
A57: AU001 | B57: AU025085 | C57: 5200999000 | D57: Miscellaneous expenses | E57: 1272.51 | F57: AUQ | G57: 45677 | H57: DAILY I/CHANGE FEES | I57: RABL 1224 | Q57: =ABS(E57) -> 1272.51 | S57: Business expense
A58: AU052 | B58: AU025085 | C58: 5200999000 | D58: Miscellaneous expenses | E58: 1030 | F58: AUQ | G58: 45678 | H58: ASX INV ACL0319949 | I58: ASX INV ACL0318564 | Q58: =ABS(E58) -> 1030 | S58: Business expense
A59: AU052 | B59: AU025085 | C59: 5200999000 | D59: Miscellaneous expenses | E59: 1030 | F59: AUQ | G59: 45709 | H59: DAILY I/CHANGE FEES | I59: ASX INV ACL0321404 | Q59: =ABS(E59) -> 1030 | S59: Business expense
A60: AU052 | B60: AU025085 | C60: 5200999000 | D60: Miscellaneous expenses | E60: 1030 | F60: AUQ | G60: 45737 | H60: DAILY I/CHANGE FEES | I60: ASX INV ACL0322715 | Q60: =ABS(E60) -> 1030 | S60: Business expense
A61: AU001 | B61: AU025085 | C61: 5200999000 | D61: Miscellaneous expenses | E61: 966.47 | F61: AUQ | G61: 45734 | H61: DAILY I/CHANGE FEES | I61: RABL 0225 | Q61: =ABS(E61) -> 966.47 | S61: Business expense
A62: AU001 | B62: AU030322 | C62: 5200999000 | D62: Miscellaneous expenses | E62: 950 | F62: AUQ | G62: 45743 | H62: T24 Australia | I62: 1026801 | Q62: =ABS(E62) -> 950 | S62: Business expense
A63: AU052 | B63: AU025085 | C63: 5200999000 | D63: Miscellaneous expenses | E63: -914.45 | F63: AUQ | G63: 45716 | H63: SERVICE DETAIL SCH | I63: SERVICE DETAIL SCH | Q63: =ABS(E63) -> 914.45 | S63: Business expense
... A87: AU001 | B87: AU025100 | C87: 5200999000 | D87: Miscellaneous expenses | E87: -294 | F87: AUQ | G87: 45693 | H87: T24 Australia | I87: 9999999 | Q87: =ABS(E87) -> 294 | S87: Business expense
A88: AU001 | B88: AU030611 | C88: 5200999000 | D88: Miscellaneous expenses | E88: 294 | F88: AUQ | G88: 45693 | H88: T24 Australia | Q88: =ABS(E88) -> 294 | S88: Business expense
A89: AU052 | B89: AU060120 | C89: 5200999000 | D89: Miscellaneous expenses | E89: 199.51 | F89: AUQ | G89: 45742 | H89: PL Reval Journals | I89: GL Revaluation | Q89: =ABS(E89) -> 199.51 | S89: Business expense
A90: AU001 | B90: AU025100 | C90: 5200999000 | D90: Miscellaneous expenses | E90: 190.53 | F90: AUQ | G90: 45691 | H90: T24 Australia | I90: 9999999 | Q90: =ABS(E90) -> 190.53 | S90: Business expense
A91: AU052 | B91: AU071197 | C91: 5200999000 | D91: Miscellaneous expenses | E91: -173.23 | F91: AUQ | G91: 45747 | H91: PL Reval Journals | I91: GL Revaluation | Q91: =ABS(E91) -> 173.23 | S91: Business expense
A92: AU001 | B92: AU025100 | C92: 5200999000 | D92: Miscellaneous expenses | E92: -160 | F92: AUQ | G92: 45712 | H92: T24 Australia | I92: 9999999 | Q92: =ABS(E92) -> 160 | S92: Business expense
A93: AU001 | B93: AU030710 | C93: 5200999000 | D93: Miscellaneous expenses | E93: 160 | F93: AUQ | G93: 45707 | H93: T24 Australia | I93: 9999999 | Q93: =ABS(E93) -> 160 | S93: Business expense
A94: AU052 | B94: AU073158 | C94: 5200999000 | D94: Miscellaneous expenses | E94: 146.81 | F94: AUQ | G94: 45743 | H94: PL Reval Journals | I94: GL Revaluation | Q94: =ABS(E94) -> 146.81 | S94: Business expense
A95: AU052 | B95: AU060120 | C95: 5200999000 | D95: Miscellaneous expenses | E95: 144.39 | F95: AUQ | G95: 45741 | H95: PL Reval Journals | I95: GL Revaluation | Q95: =ABS(E95) -> 144.39 | S95: Business expense
A96: AU052 | B96: AU060120 | C96: 5200999000 | D96: Miscellaneous expenses | E96: -132.22 | F96: AUQ | G96: 45746 | H96: PL Reval Journals | I96: GL Revaluation | Q96: =ABS(E96) -> 132.22 | S96: Business expense
A97: AU052 | B97: AU036750 | C97: 5200999000 | D97: Miscellaneous expenses | E97: -117.24 | F97: AUQ | G97: 45747 | H97: PL Reval Journals | I97: GL Revaluation | Q97: =ABS(E97) -> 117.24 | S97: Business expense
A98: AU052 | B98: AU010013 | C98: 5200999000 | D98: Miscellaneous expenses | E98: -111.08 | F98: AUQ | G98: 45715 | H98: Tsf K.Martin Feb25 | I98: ByrneC-Airfares | Q98: =ABS(E98) -> 111.08 | S98: Business expense
A99: AU052 | B99: AU010015 | C99: 5200999000 | D99: Miscellaneous expenses | E99: 111.08 | F99: AUQ | G99: 45715 | H99: Tsf K.Martin Feb25 | I99: ByrneC-Airfares | Q99: =ABS(E99) -> 111.08 | S99: Business expense
A100: AU001 | B100: AU025100 | C100: 5200999000 | D100: Miscellaneous expenses | E100: 94.57 | F100: AUQ | G100: 45716 | H100: T24 Australia | I100: 9999999 | Q100: =ABS(E100) -> 94.57 | S100: Business expense
... A106: AU001 | B106: AU030430 | C106: 5200999000 | D106: Miscellaneous expenses | E106: -69.64 | F106: AUQ | G106: 45720 | H106: T24 Australia | I106: 9999999 | Q106: =ABS(E106) -> 69.64 | S106: Business expense
A107: AU001 | B107: AU030430 | C107: 5200999000 | D107: Miscellaneous expenses | E107: 69.64 | F107: AUQ | G107: 45719 | H107: T24 Australia | Q107: =ABS(E107) -> 69.64 | S107: Business expense
A108: AU052 | B108: AU071197 | C108: 5200999000 | D108: Miscellaneous expenses | E108: 64.03 | F108: AUQ | G108: 45741 | H108: PL Reval Journals | I108: GL Revaluation | Q108: =ABS(E108) -> 64.03 | S108: Business expense
A109: AU052 | B109: AU025104 | C109: 5200999000 | D109: Miscellaneous expenses | E109: -62.87 | F109: AUQ | G109: 45688 | H109: Sustainability Prov used | I109: OU change from 24104 to 25103 | Q109: =ABS(E109) -> 62.87 | S109: Business expense
A110: AU052 | B110: AU025103 | C110: 5200999000 | D110: Miscellaneous expenses | E110: 62.87 | F110: AUQ | G110: 45688 | H110: Sustainability Prov used | I110: OU change from 24104 to 25103 | Q110: =ABS(E110) -> 62.87 | S110: Business expense
A111: AU052 | B111: AU036750 | C111: 5200999000 | D111: Miscellaneous expenses | E111: 59.87 | F111: AUQ | G111: 45742 | H111: PL Reval Journals | I111: GL Revaluation | Q111: =ABS(E111) -> 59.87 | S111: Business expense
A112: AU052 | B112: AU071196 | C112: 5200999000 | D112: Miscellaneous expenses | E112: -58.66 | F112: AUQ | G112: 45747 | H112: PL Reval Journals | I112: GL Revaluation | Q112: =ABS(E112) -> 58.66 | S112: Sustainability benefit
A113: AU052 | B113: AU071197 | C113: 5200999000 | D113: Miscellaneous expenses | E113: -58.63 | F113: AUQ | G113: 45746 | H113: PL Reval Journals | I113: GL Revaluation | Q113: =ABS(E113) -> 58.63 | S113: Business expense
A114: AU052 | B114: AU073158 | C114: 5200999000 | D114: Miscellaneous expenses | E114: -55.75 | F114: AUQ | G114: 45739 | H114: PL Reval Journals | I114: GL Revaluation | Q114: =ABS(E114) -> 55.75 | S114: Business expense
A115: AU001 | B115: AU030613 | C115: 5200999000 | D115: Miscellaneous expenses | E115: 54.34 | F115: AUQ | G115: 45727 | H115: T24 Australia | I115: 1163569 | Q115: =ABS(E115) -> 54.34 | S115: Business expense
A116: AU001 | B116: AU030055 | C116: 5200999000 | D116: Miscellaneous expenses | E116: 50 | F116: AUQ | G116: 45700 | H116: T24 Australia | I116: 1303838 | Q116: =ABS(E116) -> 50 | S116: Business expense
A117: AU052 | B117: AU036750 | C117: 5200999000 | D117: Miscellaneous expenses | E117: 43.33 | F117: AUQ | G117: 45741 | H117: PL Reval Journals | I117: GL Revaluation | Q117: =ABS(E117) -> 43.33 | S117: Business expense
A118: AU052 | B118: AU025100 | C118: 5200999000 | D118: Miscellaneous expenses | E118: -43.18 | F118: AUQ | G118: 45747 | H118: PL Reval Journals | I118: GL Revaluation | Q118: =ABS(E118) -> 43.18 | S118: Business expense
A119: AU001 | B119: AU030312 | C119: 5200999000 | D119: Miscellaneous expenses | E119: 42.2 | F119: AUQ | G119: 45695 | H119: T24 Australia | I119: 9999999 | Q119: =ABS(E119) -> 42.2 | S119: Business expense
... A152: AU001 | B152: AU025100 | C152: 5200999000 | D152: Miscellaneous expenses | E152: 14.47 | F152: AUQ | G152: 45737 | H152: T24 Australia | I152: 9999999 | Q152: =ABS(E152) -> 14.47 | S152: Business expense
A153: AU001 | B153: AU030317 | C153: 5200999000 | D153: Miscellaneous expenses | E153: 14.45 | F153: AUQ | G153: 45674 | H153: T24 Australia | Q153: =ABS(E153) -> 14.45 | S153: Business expense
A154: AU001 | B154: AU030324 | C154: 5200999000 | D154: Miscellaneous expenses | E154: 14.45 | F154: AUQ | G154: 45737 | H154: T24 Australia | I154: 9999999 | Q154: =ABS(E154) -> 14.45 | S154: Business expense
A155: AU001 | B155: AU033731 | C155: 5200999000 | D155: Miscellaneous expenses | E155: -14.38 | F155: AUQ | G155: 45746 | H155: clear suspense bal | I155: fix NONsuspense trade ref | Q155: =ABS(E155) -> 14.38 | S155: Business expense
A156: AU052 | B156: AU010014 | C156: 5200999000 | D156: Miscellaneous expenses | E156: -14.3 | F156: AUQ | G156: 45743 | H156: C013/1-OOUTS00 | I156: lobelsonb-Default Licensee Mer | Q156: =ABS(E156) -> 14.3 | S156: Business expense
A157: AU052 | B157: AU010015 | C157: 5200999000 | D157: Miscellaneous expenses | E157: 14.3 | F157: AUQ | G157: 45743 | H157: C013/1-OOUTS00 | I157: lobelsonb-Default Licensee Mer | Q157: =ABS(E157) -> 14.3 | S157: Business expense
A158: AU001 | B158: AU025100 | C158: 5200999000 | D158: Miscellaneous expenses | E158: 14.17 | F158: AUQ | G158: 45708 | H158: T24 Australia | I158: 9999999 | Q158: =ABS(E158) -> 14.17 | S158: Business expense
A159: AU001 | B159: AU030219 | C159: 5200999000 | D159: Miscellaneous expenses | E159: 12.42 | F159: AUQ | G159: 45705 | H159: T24 Australia | I159: 4013367 | Q159: =ABS(E159) -> 12.42 | S159: Business expense
A160: AU052 | B160: AU036750 | C160: 5200999000 | D160: Miscellaneous expenses | E160: 12.35 | F160: AUQ | G160: 45743 | H160: PL Reval Journals | I160: GL Revaluation | Q160: =ABS(E160) -> 12.35 | S160: Business expense
A161: AU052 | B161: AU010015 | C161: 5200999000 | D161: Miscellaneous expenses | E161: 10.35 | F161: AUQ | G161: 45715 | H161: Tsf K.Martin Feb25 | I161: WarnerE-Ground Travel | Q161: =ABS(E161) -> 10.35 | S161: Business expense
A162: AU052 | B162: AU071197 | C162: 5200999000 | D162: Miscellaneous expenses | E162: -10.19 | F162: AUQ | G162: 45740 | H162: PL Reval Journals | I162: GL Revaluation | Q162: =ABS(E162) -> 10.19 | S162: Business expense
A163: AU052 | B163: AU010013 | C163: 5200999000 | D163: Miscellaneous expenses | E163: -9.31 | F163: AUQ | G163: 45715 | H163: Tsf K.Martin Feb25 | I163: WarnerE-Ground Travel | Q163: =ABS(E163) -> 9.31 | S163: Business expense
A164: AU052 | B164: AU061134 | C164: 5200999000 | D164: Miscellaneous expenses | E164: 7.93 | F164: AUQ | G164: 45743 | H164: PL Reval Journals | I164: GL Revaluation | Q164: =ABS(E164) -> 7.93 | S164: Business expense
A165: AU052 | B165: AU020087 | C165: 5200999000 | D165: Miscellaneous expenses | E165: 7.8 | F165: AUQ | G165: 45743 | H165: PL Reval Journals | I165: GL Revaluation | Q165: =ABS(E165) -> 7.8 | S165: Business expense
... A221: AU052 | B221: AU010010 | C221: 5200999000 | D221: Miscellaneous expenses | E221: -0.01 | F221: AUQ | G221: 45747 | H221: PL Reval Journals | I221: GL Revaluation | Q221: =ABS(E221) -> 0.01 | S221: Business expense

Sheet Sundry
A1: Account Number | C1: =Summary!A22 -> 5200999010
A2: Account Name | C2: =Summary!B22 -> Sundry expenses | G2: Notes:
A3: GL Total | C3: =SUMIFS(#REF!,#REF!,C1) -> #REF! | G3: Staff function treated as staff entertainment
A4: Per TB | C4: =SUM(E:E) -> 0 | T4: AU001 | V4: =SUMIF($A$10:$A$23974,"AU001",V9:V23973) -> 0
A5: Variance | C5: =C3-C4 -> #REF! | T5: AU052 | V5: =SUMIF($A$10:$A$23975,"AU052",V9:V23974) -> 0
AD6: Income tax purposes
A7: BUSINESS_UNIT_CODE | B7: OPERATING_UNIT_CODE | C7: ACCOUNT_CODE | D7: DESCRIPTION | E7: BASE_AMOUNT | F7: BASE_CURRENCY_CODE | G7: JOURNAL_DATE | H7: DESCR | I7: LINE_DESCR | J7: PURPOSE | K7: INVOICE_DESCR | L7: INVOICE_ID | M7: VENDOR_NAME | N7: EMPLOYEE_NAME | O7: CHARGE_DESCRIPTION | Q7: ABS | R7: Search Terms | S7: Tax Description | T7: ME? Y/N | U7: OU | V7: ME $ | W7: Not ME but other type of FB Y/N | X7: Not ME but other type of FB ==> $ | Y7: Nets to Nil in GL accts | Z7: s58P M&I or Bus Exp - notFB | AA7: ME | AB7: Car FB - addn op costs | AC7: CP Exp FB | AD7: Capital expenditure | AE7: No FBT and not ded | AF7: Additional Comments

Sheet Misc exp (2)
A1: Account Number | C1: =Summary!A23 -> 5200999020
A2: Account Name | C2: =Summary!B23 -> Miscellaneous expenses (2) | G2: Notes: | T2: AU001 | V2: =SUMIF($A$8:$A$23953,"AU001",V9:V23954) -> 0 | W2: =SUMIF($A$8:$A$23953,"AU001",W9:W23954) -> 0 | AC2: AU001 | AD2: =SUMIF($A$8:$A$99998,"AU001",$AD$8:$AD$99998) -> 0 | AE2: =SUMIF($A$8:$A$99998,"AU001",$AE$8:$AE$99998) -> 0
A3: GL Total | C3: 216944.09 | G3: Rabobank has organised the following tours - cotton tour (Top End Cotton Tour TECT), Canadian grains tour (CGT), Executive Development Program (EDP25M1 or CNEDP25M1), Farm Management Program (FMP18),Mini Masterclass Bundaberg (MMCB), Mini Masterclass Riverina (MMCR), BMP Alumni Tour (BMPAT24) . All costs associated with these programs are treated as deductible. | T3: AU052 | V3: =SUMIF($A$8:$A$23954,"AU052",V9:V23955) -> 141.8 | W3: =SUMIF($A$8:$A$23954,"AU052",W9:W23955) -> 499.09 | AC3: AU052 | AD3: =SUMIF($A$8:$A$99998,"AU052",$AD$8:$AD$99998) -> 0 | AE3: =SUMIF($A$8:$A$99998,"AU052",$AE$8:$AE$99998) -> 5559.3
A4: Per TB | C4: =SUM(E:E) -> 216944.09 | G4: Clients pay to attend the above events and all client contributions have been treated as assessable on the basis that the payments relate to the ordinary business activities of Rabobank. | V4: =SUM(V2:V3) -> 141.8 | W4: =SUM(W2:W3) -> 499.09 | AE4: =SUM(AE2:AE3) -> 5559.3
A5: Variance | C5: =C3-C4 -> 0
AD6: Income tax purposes
A7: BUSINESS_UNIT_CODE | B7: OPERATING_UNIT_CODE | C7: ACCOUNT_CODE | D7: DESCRIPTION | E7: BASE_AMOUNT | F7: BASE_CURRENCY_CODE | G7: JOURNAL_DATE | H7: DESCR | I7: LINE_DESCR | J7: PURPOSE | K7: INVOICE_DESCR | L7: INVOICE_ID | M7: VENDOR_NAME | N7: EMPLOYEE_NAME | O7: CHARGE_DESCRIPTION | Q7: ABS | R7: Search Terms | S7: Tax Description | T7: ME? Y/N | U7: OU | V7: ME $ | W7: Pty FB | X7: Not ME but other type of FB ==> $ | Y7: Nets to Nil in GL accts | Z7: s58P M&I or Bus Exp - notFB | AA7: ME | AB7: Car FB - addn op costs | AC7: CP Exp FB | AD7: Capital expenditure | AE7: No FBT and not ded | AF7: Additional Comments
A8: AU001 | B8: AU032042 | C8: 5200999020 | D8: Miscellaneous expenses | E8: 225053.11 | F8: AUQ | G8: 45726 | H8: AP Accruals | I8: 43573-AEVEN00 | K8: Booking of all ground and air | L8: 43573 | M8: EVENT TRAVEL MANAGEMENT | Q8: =ABS(E8) -> 225053.11
A9: AU052 | B9: AU020087 | C9: 5200999020 | D9: Miscellaneous expenses | E9: 215093.72 | F9: AUQ | G9: 45730 | H9: AP Accruals | I9: HK/AUS/1189-ORABO03 | K9: 2024 Regional Recharge | L9: HK/AUS/1189 | M9: RABOBANK HONG KONG | Q9: =ABS(E9) -> 215093.72
A10: AU052 | B10: AU020087 | C10: 5200999020 | D10: Miscellaneous expenses | E10: -194868.55 | F10: AUQ | G10: 45735 | H10: Asia Support Rchgs 2024 | I10: HK/AUS/1189-ORABO03 | Q10: =ABS(E10) -> 194868.55
A11: AU052 | B11: AU073158 | C11: 5200999020 | D11: Miscellaneous expenses | E11: 168548.84 | F11: AUQ | G11: 45735 | H11: AP Accruals | I11: 18755-ORABO00 | K11: H2 2024 Market Data Recharges | L11: 18755 | M11: RABOBANK LONDON | Q11: =ABS(E11) -> 168548.84
A12: AU052 | B12: AU073158 | C12: 5200999020 | D12: Miscellaneous expenses | E12: -168548.84 | F12: AUQ | G12: 45742 | H12: 18755-ORABO00 | I12: 18755-ORABO00 | Q12: =ABS(E12) -> 168548.84
A13: AU052 | B13: AU020080 | C13: 5200999020 | D13: Miscellaneous expenses | E13: -95000 | F13: AUQ | G13: 45658 | H13: General Expense Accrual | I13: General Expense Accrual | Q13: =ABS(E13) -> 95000
A14: AU052 | B14: AU020080 | C14: 5200999020 | D14: Miscellaneous expenses | E14: 95000 | F14: AUQ | G14: 45685 | H14: General Expense Accrual | I14: General Expense Accrual | Q14: =ABS(E14) -> 95000
A15: AU052 | B15: AU020080 | C15: 5200999020 | D15: Miscellaneous expenses | E15: -95000 | F15: AUQ | G15: 45691 | H15: General Expense Accrual | I15: General Expense Accrual | Q15: =ABS(E15) -> 95000
A16: AU052 | B16: AU020080 | C16: 5200999020 | D16: Miscellaneous expenses | E16: 95000 | F16: AUQ | G16: 45713 | H16: General Expense Accrual | I16: General Expense Accrual | Q16: =ABS(E16) -> 95000
A17: AU052 | B17: AU020080 | C17: 5200999020 | D17: Miscellaneous expenses | E17: -95000 | F17: AUQ | G17: 45719 | H17: General Expense Accrual | I17: General Expense Accrual | Q17: =ABS(E17) -> 95000
A18: AU052 | B18: AU060124 | C18: 5200999020 | D18: Miscellaneous expenses | E18: 67791.01 | F18: AUQ | G18: 45708 | H18: AP Accruals | I18: FC2313/11/24-ORABO01 | K18: 2024 Regional Support | L18: FC2313/11/24 | M18: RABOBANK SINGAPORE | Q18: =ABS(E18) -> 67791.01
A19: AU001 | B19: AU032042 | C19: 5200999020 | D19: Miscellaneous expenses | E19: 50000 | F19: AUQ | G19: 45720 | H19: AP Accruals | I19: 43470-AEVEN00 | K19: Brazil cotton Tour Travel Mana | L19: 43470 | M19: EVENT TRAVEL MANAGEMENT | Q19: =ABS(E19) -> 50000
A20: AU052 | B20: AU060120 | C20: 5200999020 | D20: Miscellaneous expenses | E20: 42952.83 | F20: AUQ | G20: 45735 | H20: AP Accruals | I20: 18755-ORABO00 | K20: H2 2024 Market Data Recharges | L20: 18755 | M20: RABOBANK LONDON | Q20: =ABS(E20) -> 42952.83
A21: AU052 | B21: AU060120 | C21: 5200999020 | D21: Miscellaneous expenses | E21: -42952.83 | F21: AUQ | G21: 45742 | H21: 18755-ORABO00 | I21: 18755-ORABO00 | Q21: =ABS(E21) -> 42952.83
A22: AU001 | B22: AU032042 | C22: 5200999020 | D22: Miscellaneous expenses | E22: 41250 | F22: AUQ | G22: 45722 | H22: AP Accruals | I22: 1336170-AYARR00 | K22: FMP20 Second Venue Hire Paymen | L22: 1336170 | M22: YARRA VALLEY LODGE RE SANDHURST TRUSTEES | Q22: =ABS(E22) -> 41250
A23: AU001 | B23: AU025126 | C23: 5200999020 | D23: Miscellaneous expenses | E23: 32843.36 | F23: AUQ | G23: 45664 | H23: AP Accruals | I23: IN028193-AINDU00 | K23: CBM testing support (Indue & F | L23: IN028193 | M23: INDUE LIMITED | Q23: =ABS(E23) -> 32843.36
A24: AU001 | B24: AU025126 | C24: 5200999020 | D24: Miscellaneous expenses | E24: -32843.36 | F24: AUQ | G24: 45684 | H24: IN028193-AINDU00 | I24: IN028193-AINDU00 | Q24: =ABS(E24) -> 32843.36
A25: AU052 | B25: AU071197 | C25: 5200999020 | D25: Miscellaneous expenses | E25: 20913.52 | F25: AUQ | G25: 45735 | H25: AP Accruals | I25: 18755-ORABO00 | K25: H2 2024 Market Data Recharges | L25: 18755 | M25: RABOBANK LONDON | Q25: =ABS(E25) -> 20913.52
A26: AU052 | B26: AU071197 | C26: 5200999020 | D26: Miscellaneous expenses | E26: -20913.52 | F26: AUQ | G26: 45742 | H26: 18755-ORABO00 | I26: 18755-ORABO00 | Q26: =ABS(E26) -> 20913.52
A27: AU001 | B27: AU036740 | C27: 5200999020 | D27: Miscellaneous expenses | E27: 18088.96 | F27: AUQ | G27: 45720 | H27: AP Accruals | I27: 15740480-AVEDA00 | K27: Equifax invoice for February 2 | L27: 15740480 | M27: EQUIFAX AUSTRALIA INFORMATION SERVICES | Q27: =ABS(E27) -> 18088.96
A28: AU001 | B28: AU036740 | C28: 5200999020 | D28: Miscellaneous expenses | E28: 17110.28 | F28: AUQ | G28: 45691 | H28: AP Accruals | I28: 15724985-AVEDA00 | K28: Equifax invoice for January 20 | L28: 15724985 | M28: EQUIFAX AUSTRALIA INFORMATION SERVICES | Q28: =ABS(E28) -> 17110.28
A29: AU001 | B29: AU032042 | C29: 5200999020 | D29: Miscellaneous expenses | E29: -15750 | F29: AUQ | G29: 45671 | H29: BCT25 -11 Robertson | I29: BCT25 -10 Phelps | Q29: =ABS(E29) -> 15750
A30: AU001 | B30: AU032042 | C30: 5200999020 | D30: Miscellaneous expenses | E30: -15750 | F30: AUQ | G30: 45693 | H30: FMP20-3 Foley | I30: BCT25-13 Quigley | Q30: =ABS(E30) -> 15750
A31: AU001 | B31: AU032042 | C31: 5200999020 | D31: Miscellaneous expenses | E31: -15750 | F31: AUQ | G31: 45702 | H31: FMP20-3 Foley | I31: BCT25-15 Burrel | Q31: =ABS(E31) -> 15750
A32: AU001 | B32: AU032042 | C32: 5200999020 | D32: Miscellaneous expenses | E32: -15750 | F32: AUQ | G32: 45702 | H32: FMP20-3 Foley | I32: BCT25-16 Seigmeier | Q32: =ABS(E32) -> 15750
A33: AU001 | B33: AU032042 | C33: 5200999020 | D33: Miscellaneous expenses | E33: -15750 | F33: AUQ | G33: 45726 | H33: BCT25-18 Barlow | I33: BCT25-19 Harris | Q33: =ABS(E33) -> 15750
A34: AU001 | B34: AU032042 | C34: 5200999020 | D34: Miscellaneous expenses | E34: -15750 | F34: AUQ | G34: 45741 | H34: BCT25-18 Barlow | I34: BCT25-21 McIntyre | Q34: =ABS(E34) -> 15750
A35: AU001 | B35: AU032042 | C35: 5200999020 | D35: Miscellaneous expenses | E35: -15750 | F35: AUQ | G35: 45741 | H35: BCT25-18 Barlow | I35: BCT25-22 Geldard | Q35: =ABS(E35) -> 15750
A36: AU001 | B36: AU036740 | C36: 5200999020 | D36: Miscellaneous expenses | E36: 14894.37 | F36: AUQ | G36: 45664 | H36: AP Accruals | I36: 15709373-AVEDA00 | K36: Equifax invoice for Dec 2024 | L36: 15709373 | M36: EQUIFAX AUSTRALIA INFORMATION SERVICES | Q36: =ABS(E36) -> 14894.37
A37: AU052 | B37: AU036750 | C37: 5200999020 | D37: Miscellaneous expenses | E37: 14026.68 | F37: AUQ | G37: 45735 | H37: AP Accruals | I37: 18755-ORABO00 | K37: H2 2024 Market Data Recharges | L37: 18755 | M37: RABOBANK LONDON | Q37: =ABS(E37) -> 14026.68
A38: AU052 | B38: AU036750 | C38: 5200999020 | D38: Miscellaneous expenses | E38: -14026.68 | F38: AUQ | G38: 45742 | H38: 18755-ORABO00 | I38: 18755-ORABO00 | Q38: =ABS(E38) -> 14026.68
A39: AU001 | B39: AU032042 | C39: 5200999020 | D39: Miscellaneous expenses | E39: -9250 | F39: AUQ | G39: 45659 | H39: BCT25 -11 Robertson | I39: BCT25 -11 Robertson | Q39: =ABS(E39) -> 9250
A40: AU001 | B40: AU032042 | C40: 5200999020 | D40: Miscellaneous expenses | E40: -9250 | F40: AUQ | G40: 45723 | H40: BCT25-18 Barlow | I40: BCT25-18 Barlow | Q40: =ABS(E40) -> 9250
A41: AU001 | B41: AU032042 | C41: 5200999020 | D41: Miscellaneous expenses | E41: -9250 | F41: AUQ | G41: 45733 | H41: BCT25-18 Barlow | I41: BCT25-20 Bolton | Q41: =ABS(E41) -> 9250
A42: AU052 | B42: AU061134 | C42: 5200999020 | D42: Miscellaneous expenses | E42: 9104.43 | F42: AUQ | G42: 45735 | H42: AP Accruals | I42: 18755-ORABO00 | K42: H2 2024 Market Data Recharges | L42: 18755 | M42: RABOBANK LONDON | Q42: =ABS(E42) -> 9104.43
A43: AU052 | B43: AU061134 | C43: 5200999020 | D43: Miscellaneous expenses | E43: -9104.43 | F43: AUQ | G43: 45742 | H43: 18755-ORABO00 | I43: 18755-ORABO00 | Q43: =ABS(E43) -> 9104.43
A44: AU052 | B44: AU020087 | C44: 5200999020 | D44: Miscellaneous expenses | E44: 8730.18 | F44: AUQ | G44: 45735 | H44: AP Accruals | I44: 18755-ORABO00 | K44: H2 2024 Market Data Recharges | L44: 18755 | M44: RABOBANK LONDON | Q44: =ABS(E44) -> 8730.18
A45: AU052 | B45: AU020087 | C45: 5200999020 | D45: Miscellaneous expenses | E45: -8730.18 | F45: AUQ | G45: 45742 | H45: 18755-ORABO00 | I45: 18755-ORABO00 | Q45: =ABS(E45) -> 8730.18
A46: AU001 | B46: AU032042 | C46: 5200999020 | D46: Miscellaneous expenses | E46: -7875 | F46: AUQ | G46: 45714 | H46: FMP20-3 Foley | I46: BCT25-17 Kahl | Q46: =ABS(E46) -> 7875
A47: AU052 | B47: AU071196 | C47: 5200999020 | D47: Miscellaneous expenses | E47: 6718.29 | F47: AUQ | G47: 45735 | H47: AP Accruals | I47: 18755-ORABO00 | K47: H2 2024 Market Data Recharges | L47: 18755 | M47: RABOBANK LONDON | Q47: =ABS(E47) -> 6718.29
A48: AU052 | B48: AU071196 | C48: 5200999020 | D48: Miscellaneous expenses | E48: -6718.29 | F48: AUQ | G48: 45742 | H48: 18755-ORABO00 | I48: 18755-ORABO00 | Q48: =ABS(E48) -> 6718.29
A49: AU001 | B49: AU032042 | C49: 5200999020 | D49: Miscellaneous expenses | E49: -6363.64 | F49: AUQ | G49: 45709 | H49: FMP20-3 Foley | I49: FMP20-3 Foley | Q49: =ABS(E49) -> 6363.64
A50: AU001 | B50: AU032042 | C50: 5200999020 | D50: Miscellaneous expenses | E50: -6363.64 | F50: AUQ | G50: 45714 | H50: FMP20-3 Foley | I50: FMP20-2 Liphuyzen | Q50: =ABS(E50) -> 6363.64
A51: AU001 | B51: AU032042 | C51: 5200999020 | D51: Miscellaneous expenses | E51: -6363.64 | F51: AUQ | G51: 45717 | H51: BCT25-18 Barlow | I51: FMP20-4 Crees | Q51: =ABS(E51) -> 6363.64
A52: AU001 | B52: AU032042 | C52: 5200999020 | D52: Miscellaneous expenses | E52: -6363.64 | F52: AUQ | G52: 45717 | H52: BCT25-18 Barlow | I52: FMP20-7 Ferguson | Q52: =ABS(E52) -> 6363.64
A53: AU001 | B53: AU030055 | C53: 5200999020 | D53: Miscellaneous expenses | E53: 6121.49 | F53: AUQ | G53: 45679 | H53: AP Accruals | I53: FTF00021664-ACANO00 | K53: RSA token invoice for period e | L53: FTF00021664 | M53: CANON BUSINESS SERVICES AUSTRALIA PTY | Q53: =ABS(E53) -> 6121.49
A54: AU001 | B54: AU032042 | C54: 5200999020 | D54: Miscellaneous expenses | E54: -5909.09 | F54: AUQ | G54: 45717 | H54: BCT25-18 Barlow | I54: FMP20-5 Russell | Q54: =ABS(E54) -> 5909.09
A55: AU001 | B55: AU030510 | C55: 5200999020 | D55: Miscellaneous expenses | E55: 5436.44 | F55: AUQ | G55: 45720 | H55: AP Accruals | I55: INV-0037-ALEAD01 | K55: SANTNWV Offsite Guest Speaker | L55: INV-0037 | M55: LEADWELL PEOPLE PTY LTD | Q55: =ABS(E55) -> 5436.44
A56: AU052 | B56: AU025100 | C56: 5200999020 | D56: Miscellaneous expenses | E56: 5214.74 | F56: AUQ | G56: 45735 | H56: AP Accruals | I56: 18755-ORABO00 | K56: H2 2024 Market Data Recharges | L56: 18755 | M56: RABOBANK LONDON | Q56: =ABS(E56) -> 5214.74
A57: AU052 | B57: AU025100 | C57: 5200999020 | D57: Miscellaneous expenses | E57: -5214.74 | F57: AUQ | G57: 45742 | H57: 18755-ORABO00 | I57: 18755-ORABO00 | Q57: =ABS(E57) -> 5214.74
A58: AU052 | B58: AU030214 | C58: 5200999020 | D58: Miscellaneous expenses | E58: 4959.3 | F58: AUQ | G58: 45736 | H58: CCMS | I58: EllisT-Default Licensee Mercha | K58: Movie Night Decorations | 2025 NSW State Offsite - Hunter Valley | M58: BLUEBERRY EVENTS PTY L | Q58: =ABS(E58) -> 4959.3 | S58: RE - under $300 ea | AE58: =E58 -> 4959.3
A59: AU001 | B59: AU025126 | C59: 5200999020 | D59: Miscellaneous expenses | E59: 4259.32 | F59: AUQ | G59: 45664 | H59: AP Accruals | I59: IN028176-AINDU00 | K59: CBM Project invoice | L59: IN028176 | M59: INDUE LIMITED | Q59: =ABS(E59) -> 4259.32
A60: AU001 | B60: AU032042 | C60: 5200999020 | D60: Miscellaneous expenses | E60: -4250 | F60: AUQ | G60: 45693 | H60: FMP20-3 Foley | I60: BCT25-14 Rummery | Q60: =ABS(E60) -> 4250
A61: AU001 | B61: AU025100 | C61: 5200999020 | D61: Miscellaneous expenses | E61: 3130.33 | F61: AUQ | G61: 45679 | H61: AP Accruals | I61: IN028237-AINDU00 | K61: Visa test support October 2024 | L61: IN028237 | M61: INDUE LIMITED | Q61: =ABS(E61) -> 3130.33
A62: AU001 | B62: AU030211 | C62: 5200999020 | D62: Miscellaneous expenses | E62: 2520.87 | F62: AUQ | G62: 45672 | H62: AP Accruals | I62: INV-0528-ANORT001 | K62: Monthly Retainer | L62: INV-0528 | M62: NORTH WEST FINANCE PL TA NORTH WEST AGRI | Q62: =ABS(E62) -> 2520.87
A63: AU001 | B63: AU030211 | C63: 5200999020 | D63: Miscellaneous expenses | E63: 2520.87 | F63: AUQ | G63: 45694 | H63: AP Accruals | I63: INV-0530-ANORT001 | K63: Monthly Retainer | L63: INV-0530 | M63: NORTH WEST FINANCE PL TA NORTH WEST AGRI | Q63: =ABS(E63) -> 2520.87
A64: AU001 | B64: AU030211 | C64: 5200999020 | D64: Miscellaneous expenses | E64: 2520.87 | F64: AUQ | G64: 45722 | H64: AP Accruals | I64: INV-0533-ANORT001 | K64: Monthly Retainer | L64: INV-0533 | M64: NORTH WEST FINANCE PL TA NORTH WEST AGRI | Q64: =ABS(E64) -> 2520.87
A65: AU001 | B65: AU010060 | C65: 5200999020 | D65: Miscellaneous expenses | E65: 2273.97 | F65: AUQ | G65: 45673 | H65: AP Accruals | I65: FTF00021100-ACANO00 | K65: Mailhouse ? CB/ROS letters | L65: FTF00021100 | M65: CANON BUSINESS SERVICES AUSTRALIA PTY | Q65: =ABS(E65) -> 2273.97
A66: AU001 | B66: AU030055 | C66: 5200999020 | D66: Miscellaneous expenses | E66: 1512.25 | F66: AUQ | G66: 45734 | H66: AP Accruals | I66: FTF00022549-ACANO00 | K66: RSA TOKEN INVOICE PERIOD ENDIN | L66: FTF00022549 | M66: CANON BUSINESS SERVICES AUSTRALIA PTY | Q66: =ABS(E66) -> 1512.25
A67: AU052 | B67: AU020087 | C67: 5200999020 | D67: Miscellaneous expenses | E67: -1481.37 | F67: AUQ | G67: 45735 | H67: PL Reval Journals | I67: GL Revaluation | Q67: =ABS(E67) -> 1481.37
A68: AU052 | B68: AU032042 | C68: 5200999020 | D68: Miscellaneous expenses | E68: 1461.82 | F68: AUQ | G68: 45734 | H68: CCMS | I68: ShepherdD-Default Licensee Mer | K68: Payment to Whitsundays Regional Council for use of Flagstaff Hill Convention Centre in Bowen as venu | M68: WRC CVALE CS | Q68: =ABS(E68) -> 1461.82
A69: AU052 | B69: AU025063 | C69: 5200999020 | D69: Miscellaneous expenses | E69: 1424.5 | F69: AUQ | G69: 45736 | H69: CCMS | I69: PitkethleyS-Software | K69: Mental Health Employee Intervention - Counselling | M69: CENTRE FOR CORPORATE H | Q69: =ABS(E69) -> 1424.5
A70: AU052 | B70: AU020087 | C70: 5200999020 | D70: Miscellaneous expenses | E70: 1120.37 | F70: AUQ | G70: 45742 | H70: PL Reval Journals | I70: GL Revaluation | Q70: =ABS(E70) -> 1120.37
A71: AU001 | B71: AU030055 | C71: 5200999020 | D71: Miscellaneous expenses | E71: 1052.67 | F71: AUQ | G71: 45663 | H71: AP Accruals | I71: 1013689113-AAUST02 | K71: OTC monthly invoice period end | L71: 1013689113 | M71: AUSTRALIA POST 5869859 | Q71: =ABS(E71) -> 1052.67
A72: AU052 | B72: AU020087 | C72: 5200999020 | D72: Miscellaneous expenses | E72: -1045.67 | F72: AUQ | G72: 45747 | H72: PL Reval Journals | I72: GL Revaluation | Q72: =ABS(E72) -> 1045.67
A73: AU052 | B73: AU020087 | C73: 5200999020 | D73: Miscellaneous expenses | E73: -796.71 | F73: AUQ | G73: 45736 | H73: PL Reval Journals | I73: GL Revaluation | Q73: =ABS(E73) -> 796.71
A74: AU052 | B74: AU020087 | C74: 5200999020 | D74: Miscellaneous expenses | E74: -796.7 | F74: AUQ | G74: 45739 | H74: PL Reval Journals | I74: GL Revaluation | Q74: =ABS(E74) -> 796.7
A75: AU052 | B75: AU030310 | C75: 5200999020 | D75: Miscellaneous expenses | E75: 613.64 | F75: AUQ | G75: 45737 | H75: CCMS | I75: MckinnonR-Default Licensee Mer | K75: St John Ambulance Course | Melbourne Office | Gemma, Tyson & Lucas | M75: PAYPAL/7CRUZUMU4BLB | Q75: =ABS(E75) -> 613.64
A76: AU052 | B76: AU071197 | C76: 5200999020 | D76: Miscellaneous expenses | E76: 600 | F76: AUQ | G76: 45733 | H76: CCMS | I76: KeoC-Offshore Meals & Lodging | K76: Team Offsite - Fish Market Tour | M76: SYDNEYFISHMAR* RXL97F3 | Q76: =ABS(E76) -> 600 | S76: RE - under $300 ea | AE76: =E76 -> 600
A77: AU052 | B77: AU030055 | C77: 5200999020 | D77: Miscellaneous expenses | E77: 499.09 | F77: AUQ | G77: 45740 | H77: CCMS | I77: DoremaeleMLM1-Default Licensee | K77: Brad James retirement gift from Mark, Marcel & CBAU LT | M77: DAVID JONES LIMITED | Q77: =ABS(E77) -> 499.09 | S77: Brad James >$300 | W77: =Q77 -> 499.09
A78: AU052 | B78: AU020087 | C78: 5200999020 | D78: Miscellaneous expenses | E78: -485.49 | F78: AUQ | G78: 45741 | H78: PL Reval Journals | I78: GL Revaluation | Q78: =ABS(E78) -> 485.49
A79: AU052 | B79: AU032042 | C79: 5200999020 | D79: Miscellaneous expenses | E79: -454.55 | F79: AUQ | G79: 45747 | H79: ShepherdD-Default Licensee Mer | I79: ShepherdD-Default Licensee Mer | Q79: =ABS(E79) -> 454.55
A80: AU001 | B80: AU032042 | C80: 5200999020 | D80: Miscellaneous expenses | E80: 400 | F80: AUQ | G80: 45691 | H80: AP Accruals | I80: 0691-AMURP01 | K80: BMP Brochure 2025 Design (50%) | L80: 0691 | M80: MURPHY CARLISLE | Q80: =ABS(E80) -> 400
A81: AU001 | B81: AU030055 | C81: 5200999020 | D81: Miscellaneous expenses | E81: 396.11 | F81: AUQ | G81: 45664 | H81: AP Accruals | I81: FTF00021266-ACANO00 | K81: RSA token invoice for November | L81: FTF00021266 | M81: CANON BUSINESS SERVICES AUSTRALIA PTY | Q81: =ABS(E81) -> 396.11
A82: AU052 | B82: AU020087 | C82: 5200999020 | D82: Miscellaneous expenses | E82: -361.01 | F82: AUQ | G82: 45743 | H82: PL Reval Journals | I82: GL Revaluation | Q82: =ABS(E82) -> 361.01
A83: AU052 | B83: AU020087 | C83: 5200999020 | D83: Miscellaneous expenses | E83: -361.01 | F83: AUQ | G83: 45746 | H83: PL Reval Journals | I83: GL Revaluation | Q83: =ABS(E83) -> 361.01
A84: AU001 | B84: AU025109 | C84: 5200999020 | D84: Miscellaneous expenses | E84: 260 | F84: AUQ | G84: 45664 | H84: AP Accruals | I84: 0679-AMURP01 | K84: Collateral update by external | L84: 0679 | M84: MURPHY CARLISLE | Q84: =ABS(E84) -> 260
A85: AU001 | B85: AU025109 | C85: 5200999020 | D85: Miscellaneous expenses | E85: 260 | F85: AUQ | G85: 45722 | H85: AP Accruals | I85: 0694-AMURP01 | K85: Collateral update by external | L85: 0694 | M85: MURPHY CARLISLE | Q85: =ABS(E85) -> 260
A86: AU052 | B86: AU020087 | C86: 5200999020 | D86: Miscellaneous expenses | E86: 236.52 | F86: AUQ | G86: 45740 | H86: PL Reval Journals | I86: GL Revaluation | Q86: =ABS(E86) -> 236.52
A87: AU052 | B87: AU030325 | C87: 5200999020 | D87: Miscellaneous expenses | E87: 218.57 | F87: AUQ | G87: 45713 | H87: CCMS | I87: SturgissH-Default Licensee Mer | J87: Branch plants, rubbish bins, broom | M87: BUNNINGS 568000 | Q87: =ABS(E87) -> 218.57 | S87: OK
A88: AU052 | B88: AU030055 | C88: 5200999020 | D88: Miscellaneous expenses | E88: 117.95 | F88: AUQ | G88: 45740 | H88: CCMS | I88: McCallumA-Default Licensee Mer | K88: Congratulatory baby gift for Dragana Bursac | M88: COUNTRY ROAD | Q88: =ABS(E88) -> 117.95 | S88: Under $300
A89: AU052 | B89: AU030420 | C89: 5200999020 | D89: Miscellaneous expenses | E89: 107.27 | F89: AUQ | G89: 45740 | H89: CCMS | I89: McCallumA-Default Licensee Mer | K89: Sympathy flowers for Senior Rural Manager Rebecca Murray following passing of her Father. | O89: Lilly & Lotus | Q89: =ABS(E89) -> 107.27 | S89: OK
A90: AU052 | B90: AU030420 | C90: 5200999020 | D90: Miscellaneous expenses | E90: 105.91 | F90: AUQ | G90: 45687 | H90: CCMS | I90: McCallumA-Default Licensee Mer | K90: Sympathy flowers for Merrill Phillips - QLD RCM following the passing of her husband. | M90: SQ *SHANNON HAWKES ARTISA | Q90: =ABS(E90) -> 105.91 | S90: OK
A91: AU052 | B91: AU071197 | C91: 5200999020 | D91: Miscellaneous expenses | E91: 101.89 | F91: AUQ | G91: 45694 | H91: CCMS | I91: KeoC-Office Supplies | J91: Sydney Team BBQ - Cheese platter | M91: LOCALI BY ROMEOS | Q91: =ABS(E91) -> 101.89 | S91: ME | T91: Y | U91: =B91 -> AU071197 | V91: =E91 -> 101.89
A92: AU052 | B92: AU020090 | C92: 5200999020 | D92: Miscellaneous expenses | E92: 99.09 | F92: AUQ | G92: 45685 | H92: CCMS | I92: SlackS-Default Licensee Mercha | K92: External Hard Drive to support Security Incident Investigations and Forensics | M92: SP JB HI-FI ONLINE | Q92: =ABS(E92) -> 99.09 | S92: OK
A93: AU052 | B93: AU030220 | C93: 5200999020 | D93: Miscellaneous expenses | E93: 90.91 | F93: AUQ | G93: 45736 | H93: CCMS | I93: NeilsonS-Default Licensee Merc | K93: Duncan Whan Fathers Funeral | M93: BERNARD LAVERTY PL | Q93: =ABS(E93) -> 90.91 | S93: OK
A94: AU052 | B94: AU025063 | C94: 5200999020 | D94: Miscellaneous expenses | E94: 77.73 | F94: AUQ | G94: 45736 | H94: CCMS | I94: PitkethleyS-Office Supplies | J94: Hampers for Hope - Chocolates donation | M94: COLES 4166 | Q94: =ABS(E94) -> 77.73 | S94: OK
A95: AU052 | B95: AU030321 | C95: 5200999020 | D95: Miscellaneous expenses | E95: 59.44 | F95: AUQ | G95: 45686 | H95: CCMS | I95: WarrenL-Office Supplies | J95: fertiliser and spray for Renmark Branch 26 plants | M95: RENMARK FOODLAND IGA | Q95: =ABS(E95) -> 59.44 | S95: OK
A96: AU052 | B96: AU020090 | C96: 5200999020 | D96: Miscellaneous expenses | E96: 50.78 | F96: AUQ | G96: 45685 | H96: CCMS | I96: SlackS-Default Licensee Mercha | J96: FLRS Community Leave event | M96: BUNNINGS GROUP LTD | Q96: =ABS(E96) -> 50.78 | S96: OK
A97: AU052 | B97: AU071197 | C97: 5200999020 | D97: Miscellaneous expenses | E97: 35.36 | F97: AUQ | G97: 45694 | H97: CCMS | I97: KeoC-Default Licensee Merchant | J97: Sydney Team BBQ - Cheese Tray | M97: VICTORIAS BASEMENT | Q97: =ABS(E97) -> 35.36 | S97: ME | T97: Y | U97: =B97 -> AU071197 | V97: =E97 -> 35.36
A98: AU052 | B98: AU030432 | C98: 5200999020 | D98: Miscellaneous expenses | E98: 29.09 | F98: AUQ | G98: 45734 | H98: CCMS | I98: GroganC-Default Licensee Merch | J98: Newspaper subscription | M98: NEWS PTY LIMITED | Q98: =ABS(E98) -> 29.09
A99: AU052 | B99: AU031752 | C99: 5200999020 | D99: Miscellaneous expenses | E99: 21.68 | F99: AUQ | G99: 45737 | H99: CCMS | I99: FelanT-Office Supplies | J99: Water & sunscreen - Client visits | M99: BAROOGA IGA XPRESS | Q99: =ABS(E99) -> 21.68
A100: AU052 | B100: AU030710 | C100: 5200999020 | D100: Miscellaneous expenses | E100: 20 | F100: AUQ | G100: 45744 | H100: LimbuP-Ground Travel | I100: MccullochB-Offshore Meals & Lo | Q100: =ABS(E100) -> 20
...

Sheet Other non-bank exp
A1: Account Number | C1: =Summary!A24 -> 5900050000
A2: Account Name | C2: =Summary!B24 -> Other non banking expenses | G2: Notes:
A3: GL Total | C3: 10292.09 | G3: All business expenses. Treat as deductible
A4: Per TB | C4: =SUM(E:E) -> 10292.09 | T4: AU001 | U4: =SUMIF($A$10:$A$23773,"AU001",U9:U23772) -> 0
A5: Variance | C5: =C3-C4 -> 1.1095835e-10 | T5: AU052 | U5: =SUMIF($A$10:$A$23774,"AU052",U9:U23773) -> 0
AC6: Income tax purposes
A7: BUSINESS_UNIT_CODE | B7: OPERATING_UNIT_CODE | C7: ACCOUNT_CODE | D7: DESCRIPTION | E7: BASE_AMOUNT | F7: BASE_CURRENCY_CODE | G7: JOURNAL_DATE | H7: DESCR | I7: LINE_DESCR | J7: PURPOSE | K7: INVOICE_DESCR | L7: INVOICE_ID | M7: VENDOR_NAME | N7: EMPLOYEE_NAME | O7: CHARGE_DESCRIPTION | Q7: ABS | R7: Search Terms | S7: Tax Description | T7: ME? Y/N | U7: ME $ | V7: Not ME but other type of FB Y/N | W7: Not ME but other type of FB ==> $ | X7: Nets to Nil in GL accts | Y7: s58P M&I or Bus Exp - notFB | Z7: ME | AA7: Car FB - addn op costs | AB7: CP Exp FB | AC7: Capital expenditure | AD7: No FBT and not ded | AE7: Additional Comments
A8: AU001 | B8: AU030210 | C8: 5900050000 | D8: Other non banking expenses | E8: 0.2 | F8: AUQ | G8: 45667 | H8: DAILY I/CHANGE FEES | I8: FRAUD CS-3681670 | Q8: =E8 -> 0.2 | R8: Business expenses | S8: No FBT, Tax deductible | T8: N
A9: AU001 | B9: AU030210 | C9: 5900050000 | D9: Other non banking expenses | E9: 30 | F9: AUQ | G9: 45667 | H9: DAILY I/CHANGE FEES | I9: FRAUD CS-3683673 | Q9: =E9 -> 30 | R9: Business expenses | S9: No FBT, Tax deductible | T9: N
A10: AU001 | B10: AU030210 | C10: 5900050000 | D10: Other non banking expenses | E10: 150.63 | F10: AUQ | G10: 45691 | H10: DAILY I/CHANGE FEES | I10: FRAUD CS-3723413 | Q10: =E10 -> 150.63 | R10: Business expenses | S10: No FBT, Tax deductible | T10: N
A11: AU001 | B11: AU030210 | C11: 5900050000 | D11: Other non banking expenses | E11: 44.36 | F11: AUQ | G11: 45694 | H11: DAILY I/CHANGE FEES | I11: FRAUD CS-3733415 | Q11: =E11 -> 44.36 | R11: Business expenses | S11: No FBT, Tax deductible | T11: N
A12: AU001 | B12: AU030210 | C12: 5900050000 | D12: Other non banking expenses | E12: 46.45 | F12: AUQ | G12: 45702 | H12: DAILY I/CHANGE FEES | I12: FRAUD CS-3739293 | Q12: =E12 -> 46.45 | R12: Business expenses | S12: No FBT, Tax deductible | T12: N
A13: AU001 | B13: AU030210 | C13: 5900050000 | D13: Other non banking expenses | E13: 42.04 | F13: AUQ | G13: 45707 | H13: DAILY I/CHANGE FEES | I13: FRAUD CS-3760259 | Q13: =E13 -> 42.04 | R13: Business expenses | S13: No FBT, Tax deductible | T13: N
A14: AU001 | B14: AU030210 | C14: 5900050000 | D14: Other non banking expenses | E14: 10.45 | F14: AUQ | G14: 45721 | H14: DAILY I/CHANGE FEES | I14: FRAUD CS-3792823 | Q14: =E14 -> 10.45 | R14: Business expenses | S14: No FBT, Tax deductible | T14: N
A15: AU001 | B15: AU030210 | C15: 5900050000 | D15: Other non banking expenses | E15: 578 | F15: AUQ | G15: 45722 | H15: DAILY I/CHANGE FEES | I15: FRAUD CS-3769195 | Q15: =E15 -> 578 | R15: Business expenses | S15: No FBT, Tax deductible | T15: N
A16: AU001 | B16: AU030210 | C16: 5900050000 | D16: Other non banking expenses | E16: 50 | F16: AUQ | G16: 45723 | H16: DAILY I/CHANGE FEES | I16: FRAUD CS-3798118 | Q16: =E16 -> 50 | R16: Business expenses | S16: No FBT, Tax deductible | T16: N
A17: AU001 | B17: AU030210 | C17: 5900050000 | D17: Other non banking expenses | E17: 1 | F17: AUQ | G17: 45743 | H17: DAILY I/CHANGE FEES | I17: FRAUD CS-3845226 | Q17: =E17 -> 1 | R17: Business expenses | S17: No FBT, Tax deductible | T17: N
A18: AU052 | B18: AU010010 | C18: 5900050000 | D18: Other non banking expenses | E18: -399533 | F18: AUQ | G18: 45658 | H18: Misc. Expense Accrual | I18: Misc. Expense Accrual | Q18: =E18 -> -399533 | R18: Business expenses | S18: No FBT, Tax deductible | T18: N
A19: AU052 | B19: AU010012 | C19: 5900050000 | D19: Other non banking expenses | E19: -1801332.8 | F19: AUQ | G19: 45658 | H19: Misc. Expense Accrual | I19: Misc. Expense Accrual | Q19: =E19 -> -1801332.8 | R19: Business expenses | S19: No FBT, Tax deductible | T19: N
... A30: AU052 | B30: AU073158 | C30: 5900050000 | D30: Other non banking expenses | E30: 2801.69 | F30: AUQ | G30: 45746 | H30: DP3 Central Allocation | I30: DP3 Central Allocation | Q30: =E30 -> 2801.69 | R30: Business expenses | S30: No FBT, Tax deductible | T30: N

Sheet Other exp
A1: Account Number | C1: =Summary!A25 -> 5100999000
A2: Account Name | C2: =Summary!B25 -> Other office expenses | F2: Notes:
A3: GL Total | C3: 91319.73 | F3: Office consumables such as milk, fruit, tea, coffee, plant rental are treated as tax deductible and not subject to FBT on the basis that they are not entertainment expenses. | T3: AU001 | V3: =SUMIF($A$10:$A$23974,"AU001",V8:V23972) -> 1063.33 | AC3: AU001 | AD3: =SUMIF($A$8:$A$100000,"AU001",$AD$8:$AD$100000) -> 0 | AE3: =SUMIF($A$8:$A$100000,"AU001",$AE$8:$AE$100000) -> 0
A4: Per TB | C4: =SUM(E:E) -> 91319.73 | F4: Onsite sustenance such as working lunches, onsite morning and afternoon teas are treated as tax deductible on the basis that they are not entertainment expenses. | T4: AU052 | V4: =SUMIF($A$10:$A$23975,"AU052",V8:V23973) -> 71.11 | AC4: AU052 | AD4: =SUMIF($A$8:$A$100000,"AU052",$AD$8:$AD$100000) -> 3139.98 | AE4: =SUMIF($A$8:$A$100000,"AU052",$AE$8:$AE$100000) -> 0
A5: Variance | C5: =C3-C4 -> -2.6193447e-10 | V5: =SUM(V3:V4) -> 1134.44 | AD5: =SUM(AD3:AD4) -> 3139.98
AD6: Income tax purposes
A7: BUSINESS_UNIT_CODE | B7: OPERATING_UNIT_CODE | C7: ACCOUNT_CODE | D7: DESCRIPTION | E7: BASE_AMOUNT | F7: BASE_CURRENCY_CODE | G7: JOURNAL_DATE | H7: DESCR | I7: LINE_DESCR | J7: PURPOSE | K7: INVOICE_DESCR | L7: INVOICE_ID | M7: VENDOR_NAME | N7: EMPLOYEE_NAME | O7: CHARGE_DESCRIPTION | Q7: ABS | R7: Search Terms | S7: Tax Description | T7: ME? Y/N | U7: OU | V7: ME $ | W7: Not ME but other type of FB Y/N | X7: Not ME but other type of FB ==> $ | Y7: Nets to Nil in GL accts | Z7: s58P M&I or Bus Exp - notFB | AA7: ME | AB7: Car FB - addn op costs | AC7: CP Exp FB | AD7: Capital expenditure | AE7: No FBT and not ded | AF7: Additional Comments
A8: AU052 | B8: AU025064 | C8: 5100999000 | D8: Other office expenses | E8: 3536 | F8: AUQ | G8: 45706 | H8: AP Accruals | I8: 52421876-ANESP01 | K8: Nepresso Pods | L8: 52421876 | M8: NESPRESSO CLUB | Q8: =ABS(E8) -> 3536
A9: AU052 | B9: AU025067 | C9: 5100999000 | D9: Other office expenses | E9: 3272 | F9: AUQ | G9: 45677 | H9: AP Accruals | I9: 52140141-ANESP01 | K9: Nespresso Pods for DP3 | L9: 52140141 | M9: NESPRESSO CLUB | Q9: =ABS(E9) -> 3272
A10: AU052 | B10: AU025064 | C10: 5100999000 | D10: Other office expenses | E10: 3128 | F10: AUQ | G10: 45733 | H10: AP Accruals | I10: 52657757-ANESP01 | K10: Nespresso Pods for DP3 | L10: 52657757 | M10: NESPRESSO CLUB | Q10: =ABS(E10) -> 3128
A11: AU001 | B11: AU036740 | C11: 5100999000 | D11: Other office expenses | E11: 3073.15 | F11: AUQ | G11: 45733 | H11: AP Accruals | I11: FTF00022550-ACANO00 | K11: Welcome packs, Additional PAM | L11: FTF00022550 | M11: CANON BUSINESS SERVICES AUSTRALIA PTY | Q11: =ABS(E11) -> 3073.15
A12: AU001 | B12: AU036740 | C12: 5100999000 | D12: Other office expenses | E12: 3024.47 | F12: AUQ | G12: 45681 | H12: AP Accruals | I12: FTF00021665-ACANO00 | K12: Welcome packs and secure code | L12: FTF00021665 | M12: CANON BUSINESS SERVICES AUSTRALIA PTY | Q12: =ABS(E12) -> 3024.47
A13: AU052 | B13: AU025067 | C13: 5100999000 | D13: Other office expenses | E13: 2292.44 | F13: AUQ | G13: 45719 | H13: AP Accruals | I13: 3358645-ATHEF03 | K13: Fruit and Milk Delivery to DP | L13: 3358645 | M13: THE FRUIT BOX GROUP PTY LTD | Q13: =ABS(E13) -> 2292.44
A14: AU001 | B14: AU050110 | C14: 5100999000 | D14: Other office expenses | E14: 2062.63 | F14: AUQ | G14: 45726 | H14: AP Accruals | I14: AUD625387-AIRON01 | K14: Iron Mountain - Feb 25 | L14: AUD625387 | M14: IRON MOUNTAIN AUSTRALIA GROUP PTY LTD | Q14: =ABS(E14) -> 2062.63
A15: AU001 | B15: AU036740 | C15: 5100999000 | D15: Other office expenses | E15: 1886.48 | F15: AUQ | G15: 45664 | H15: AP Accruals | I15: FTF00021267-ACANO00 | K15: Welcome packs, Secure code let | L15: FTF00021267 | M15: CANON BUSINESS SERVICES AUSTRALIA PTY | Q15: =ABS(E15) -> 1886.48
A16: AU052 | B16: AU025064 | C16: 5100999000 | D16: Other office expenses | E16: 1860.85 | F16: AUQ | G16: 45680 | H16: AP Accruals | I16: 52033924-ANESP01 | K16: Nespresso Coffee Machine Repai | L16: 52033924 | M16: NESPRESSO CLUB | Q16: =ABS(E16) -> 1860.85
A17: AU001 | B17: AU050110 | C17: 5100999000 | D17: Other office expenses | E17: 1811.69 | F17: AUQ | G17: 45712 | H17: AP Accruals | I17: AUD609996-AIRON01 | K17: Iron Mountain - Jan 25 | L17: AUD609996 | M17: IRON MOUNTAIN AUSTRALIA GROUP PTY LTD | Q17: =ABS(E17) -> 1811.69
A18: AU001 | B18: AU050110 | C18: 5100999000 | D18: Other office expenses | E18: 1733.77 | F18: AUQ | G18: 45677 | H18: AP Accruals | I18: AUD594816-AIRON01 | K18: Iron Mountain - Dec 24 | L18: AUD594816 | M18: IRON MOUNTAIN AUSTRALIA GROUP PTY LTD | Q18: =ABS(E18) -> 1733.77
A19: AU052 | B19: AU025067 | C19: 5100999000 | D19: Other office expenses | E19: 1679.35 | F19: AUQ | G19: 45691 | H19: AP Accruals | I19: 3345241-ATHEF03 | K19: Fruit & Milk Deliver to DP3 | L19: 3345241 | M19: THE FRUIT BOX GROUP PTY LTD | Q19: =ABS(E19) -> 1679.35
... A27: AU001 | B27: AU050116 | C27: 5100999000 | D27: Other office expenses | E27: 1004.39 | F27: AUQ | G27: 45726 | H27: AP Accruals | I27: AUD625387-AIRON01 | K27: Iron Mountain - Feb 25 | L27: AUD625387 | M27: IRON MOUNTAIN AUSTRALIA GROUP PTY LTD | Q27: =ABS(E27) -> 1004.39
A28: AU052 | B28: AU025067 | C28: 5100999000 | D28: Other office expenses | E28: 939.3 | F28: AUQ | G28: 45736 | H28: CCMS | I28: VosR5-Default Licensee Merchan | J28: DP3 Kitchen Cutlery and glasses | M28: NISBETS AUSTRALIA/B11Q66GDW8GM | Q28: =ABS(E28) -> 939.3 | AD28: =Q28 -> 939.3
A29: AU001 | B29: AU030318 | C29: 5100999000 | D29: Other office expenses | E29: 924.39 | F29: AUQ | G29: 45726 | H29: AP Accruals | I29: AUD634389-AIRON01 | K29: Iron Mountain - Feb 25 | L29: AUD634389 | M29: IRON MOUNTAIN AUSTRALIA GROUP PTY LTD | Q29: =ABS(E29) -> 924.39
A30: AU052 | B30: AU025064 | C30: 5100999000 | D30: Other office expenses | E30: 875.11 | F30: AUQ | G30: 45680 | H30: AP Accruals | I30: 52033857-ANESP01 | K30: Nespresso Coffee Machine Repai | L30: 52033857 | M30: NESPRESSO CLUB | Q30: =ABS(E30) -> 875.11
A31: AU052 | B31: AU025064 | C31: 5100999000 | D31: Other office expenses | E31: 875.11 | F31: AUQ | G31: 45741 | H31: AP Accruals | I31: 52705067-ANESP01 | K31: Nespresso Pods | L31: 52705067 | M31: NESPRESSO CLUB | Q31: =ABS(E31) -> 875.11
A32: AU001 | B32: AU031755 | C32: 5100999000 | D32: Other office expenses | E32: 870.25 | F32: AUQ | G32: 45726 | H32: AP Accruals | I32: AUD634389-AIRON01 | K32: Iron Mountain - Feb 25 | L32: AUD634389 | M32: IRON MOUNTAIN AUSTRALIA GROUP PTY LTD | Q32: =ABS(E32) -> 870.25
A33: AU001 | B33: AU030613 | C33: 5100999000 | D33: Other office expenses | E33: 868.76 | F33: AUQ | G33: 45726 | H33: AP Accruals | I33: AUD634389-AIRON01 | K33: Iron Mountain - Feb 25 | L33: AUD634389 | M33: IRON MOUNTAIN AUSTRALIA GROUP PTY LTD | Q33: =ABS(E33) -> 868.76
A34: AU001 | B34: AU030810 | C34: 5100999000 | D34: Other office expenses | E34: 867.62 | F34: AUQ | G34: 45712 | H34: AP Accruals | I34: AUD618982-AIRON01 | K34: Iron Mountain - Jan 25 | L34: AUD618982 | M34: IRON MOUNTAIN AUSTRALIA GROUP PTY LTD | Q34: =ABS(E34) -> 867.62
A35: AU001 | B35: AU030712 | C35: 5100999000 | D35: Other office expenses | E35: 853.67 | F35: AUQ | G35: 45726 | H35: AP Accruals | I35: AUD634389-AIRON01 | K35: Iron Mountain - Feb 25 | L35: AUD634389 | M35: IRON MOUNTAIN AUSTRALIA GROUP PTY LTD | Q35: =ABS(E35) -> 853.67
A36: AU052 | B36: AU030433 | C36: 5100999000 | D36: Other office expenses | E36: 802.73 | F36: AUQ | G36: 45707 | H36: CCMS | I36: KorffD-Default Licensee Mercha | J36: Boardroom TV | M36: HARVEY NORMAN AV/IT | Q36: =ABS(E36) -> 802.73 | AD36: =Q36 -> 802.73
A37: AU001 | B37: AU030510 | C37: 5100999000 | D37: Other office expenses | E37: 711.78 | F37: AUQ | G37: 45712 | H37: AP Accruals | I37: AUD618982-AIRON01 | K37: Iron Mountain - Jan 25 | L37: AUD618982 | M37: IRON MOUNTAIN AUSTRALIA GROUP PTY LTD | Q37: =ABS(E37) -> 711.78
A38: AU052 | B38: AU030220 | C38: 5100999000 | D38: Other office expenses | E38: 682.68 | F38: AUQ | G38: 45744 | H38: CCMS | I38: ArmstrongT-Office Supplies | J38: Toner Cartridge - Printer - Office Express | M38: OFFICE EXPRESS ARMIDAL | Q38: =ABS(E38) -> 682.68 | S38: consumables
A39: AU001 | B39: AU030312 | C39: 5100999000 | D39: Other office expenses | E39: 632.93 | F39: AUQ | G39: 45677 | H39: AP Accruals | I39: AUD603806-AIRON01 | K39: Iron Mountain - Dec 24 | L39: AUD603806 | M39: IRON MOUNTAIN AUSTRALIA GROUP PTY LTD | Q39: =ABS(E39) -> 632.93
A40: AU052 | B40: AU025064 | C40: 5100999000 | D40: Other office expenses | E40: 597.41 | F40: AUQ | G40: 45680 | H40: AP Accruals | I40: 51989680-ANESP01 | K40: Nespresso Coffee Machine Hire | L40: 51989680 | M40: NESPRESSO CLUB | Q40: =ABS(E40) -> 597.41
A41: AU052 | B41: AU025067 | C41: 5100999000 | D41: Other office expenses | E41: 597.41 | F41: AUQ | G41: 45691 | H41: AP Accruals | I41: 52262402-ANESP01 | K41: Nespresso Pods for DP3 | L41: 52262402 | M41: NESPRESSO CLUB | Q41: =ABS(E41) -> 597.41
A42: AU052 | B42: AU025067 | C42: 5100999000 | D42: Other office expenses | E42: 597.41 | F42: AUQ | G42: 45726 | H42: AP Accruals | I42: 52540762-ANESP01 | K42: Nespresso Order for DP3 | L42: 52540762 | M42: NESPRESSO CLUB | Q42: =ABS(E42) -> 597.41
A43: AU001 | B43: AU036740 | C43: 5100999000 | D43: Other office expenses | E43: 553.24 | F43: AUQ | G43: 45712 | H43: AP Accruals | I43: AUD609996-AIRON01 | K43: Iron Mountain - Jan 25 | L43: AUD609996 | M43: IRON MOUNTAIN AUSTRALIA GROUP PTY LTD | Q43: =ABS(E43) -> 553.24
A44: AU001 | B44: AU036740 | C44: 5100999000 | D44: Other office expenses | E44: 553.24 | F44: AUQ | G44: 45726 | H44: AP Accruals | I44: AUD625387-AIRON01 | K44: Iron Mountain - Feb 25 | L44: AUD625387 | M44: IRON MOUNTAIN AUSTRALIA GROUP PTY LTD | Q44: =ABS(E44) -> 553.24
A45: AU001 | B45: AU036740 | C45: 5100999000 | D45: Other office expenses | E45: 553.17 | F45: AUQ | G45: 45677 | H45: AP Accruals | I45: AUD594816-AIRON01 | K45: Iron Mountain - Dec 24 | L45: AUD594816 | M45: IRON MOUNTAIN AUSTRALIA GROUP PTY LTD | Q45: =ABS(E45) -> 553.17
A46: AU001 | B46: AU030514 | C46: 5100999000 | D46: Other office expenses | E46: 541.95 | F46: AUQ | G46: 45712 | H46: AP Accruals | I46: AUD618982-AIRON01 | K46: Iron Mountain - Jan 25 | L46: AUD618982 | M46: IRON MOUNTAIN AUSTRALIA GROUP PTY LTD | Q46: =ABS(E46) -> 541.95
A47: AU001 | B47: AU030612 | C47: 5100999000 | D47: Other office expenses | E47: 523.28 | F47: AUQ | G47: 45712 | H47: AP Accruals | I47: AUD618982-AIRON01 | K47: Iron Mountain - Jan 25 | L47: AUD618982 | M47: IRON MOUNTAIN AUSTRALIA GROUP PTY LTD | Q47: =ABS(E47) -> 523.28
A48: AU001 | B48: AU030217 | C48: 5100999000 | D48: Other office expenses | E48: 516.7 | F48: AUQ | G48: 45726 | H48: AP Accruals | I48: AUD634389-AIRON01 | K48: Iron Mountain - Feb 25 | L48: AUD634389 | M48: IRON MOUNTAIN AUSTRALIA GROUP PTY LTD | Q48: =ABS(E48) -> 516.7
A49: AU001 | B49: AU030611 | C49: 5100999000 | D49: Other office expenses | E49: 500 | F49: AUQ | G49: 45740 | H49: AP Accruals | I49: 133151-AGIBS01 | K49: Water bottles for water cooler | L49: 133151 | M49: GIBSON SOAK WATER COMPANY | Q49: =ABS(E49) -> 500
A50: AU001 | B50: AU030612 | C50: 5100999000 | D50: Other office expenses | E50: 476.81 | F50: AUQ | G50: 45726 | H50: AP Accruals | I50: AUD634389-AIRON01 | K50: Iron Mountain - Feb 25 | L50: AUD634389 | M50: IRON MOUNTAIN AUSTRALIA GROUP PTY LTD | Q50: =ABS(E50) -> 476.81
A51: AU052 | B51: AU030711 | C51: 5100999000 | D51: Other office expenses | E51: 470.91 | F51: AUQ | G51: 45729 | H51: CCMS | I51: PearceD-Default Licensee Merch | J51: Furniture | M51: HARVEY NORMAN FURNIT | Q51: =ABS(E51) -> 470.91 | AD51: =Q51 -> 470.91
A52: AU001 | B52: AU030312 | C52: 5100999000 | D52: Other office expenses | E52: 463.75 | F52: AUQ | G52: 45712 | H52: AP Accruals | I52: AUD618982-AIRON01 | K52: Iron Mountain - Jan 25 | L52: AUD618982 | M52: IRON MOUNTAIN AUSTRALIA GROUP PTY LTD | Q52: =ABS(E52) -> 463.75
A53: AU001 | B53: AU036740 | C53: 5100999000 | D53: Other office expenses | E53: 452.24 | F53: AUQ | G53: 45664 | H53: AP Accruals | I53: FTF00021265-ACANO00 | K53: PAM Letters - additional work | L53: FTF00021265 | M53: CANON BUSINESS SERVICES AUSTRALIA PTY | Q53: =ABS(E53) -> 452.24
A54: AU001 | B54: AU030711 | C54: 5100999000 | D54: Other office expenses | E54: 446.53 | F54: AUQ | G54: 45712 | H54: AP Accruals | I54: AUD618982-AIRON01 | K54: Iron Mountain - Jan 25 | L54: AUD618982 | M54: IRON MOUNTAIN AUSTRALIA GROUP PTY LTD | Q54: =ABS(E54) -> 446.53
A55: AU001 | B55: AU030312 | C55: 5100999000 | D55: Other office expenses | E55: 445.68 | F55: AUQ | G55: 45726 | H55: AP Accruals | I55: AUD634389-AIRON01 | K55: Iron Mountain - Feb 25 | L55: AUD634389 | M55: IRON MOUNTAIN AUSTRALIA GROUP PTY LTD | Q55: =ABS(E55) -> 445.68
A56: AU001 | B56: AU050116 | C56: 5100999000 | D56: Other office expenses | E56: 445.51 | F56: AUQ | G56: 45712 | H56: AP Accruals | I56: AUD609996-AIRON01 | K56: Iron Mountain - Jan 25 | L56: AUD609996 | M56: IRON MOUNTAIN AUSTRALIA GROUP PTY LTD | Q56: =ABS(E56) -> 445.51
A57: AU001 | B57: AU050116 | C57: 5100999000 | D57: Other office expenses | E57: 445.47 | F57: AUQ | G57: 45677 | H57: AP Accruals | I57: AUD594816-AIRON01 | K57: Iron Mountain - Dec 24 | L57: AUD594816 | M57: IRON MOUNTAIN AUSTRALIA GROUP PTY LTD | Q57: =ABS(E57) -> 445.47
A58: AU001 | B58: AU030514 | C58: 5100999000 | D58: Other office expenses | E58: 416.26 | F58: AUQ | G58: 45726 | H58: AP Accruals | I58: AUD634389-AIRON01 | K58: Iron Mountain - Feb 25 | L58: AUD634389 | M58: IRON MOUNTAIN AUSTRALIA GROUP PTY LTD | Q58: =ABS(E58) -> 416.26
A59: AU052 | B59: AU030711 | C59: 5100999000 | D59: Other office expenses | E59: 383.66 | F59: AUQ | G59: 45729 | H59: CCMS | I59: TabererC1-Office Supplies | K59: Branch Set Up Items | M59: COLES 7523 | Q59: =ABS(E59) -> 383.66
A60: AU001 | B60: AU030810 | C60: 5100999000 | D60: Other office expenses | E60: 360.41 | F60: AUQ | G60: 45726 | H60: AP Accruals | I60: AUD634389-AIRON01 | K60: Iron Mountain - Feb 25 | L60: AUD634389 | M60: IRON MOUNTAIN AUSTRALIA GROUP PTY LTD | Q60: =ABS(E60) -> 360.41
A61: AU052 | B61: AU025064 | C61: 5100999000 | D61: Other office expenses | E61: 360 | F61: AUQ | G61: 45740 | H61: CCMS | I61: BradaricS-Offshore Meals & Lod | K61: Coffee | M61: SP BUN COFFEE AUSTRALI | Q61: =ABS(E61) -> 360
A62: AU052 | B62: AU030055 | C62: 5100999000 | D62: Other office expenses | E62: 357.81 | F62: AUQ | G62: 45715 | H62: CCMS | I62: HallidayA-Entertainment Expens | J62: Gifts for leaving and long serving staff | M62: Ivy Bottleshop | Q62: =ABS(E62) -> 357.81 | S62: ME | T62: Y | U62: =B62 -> AU030055 | V62: =E62 -> 357.81
A63: AU052 | B63: AU030510 | C63: 5100999000 | D63: Other office expenses | E63: 349.77 | F63: AUQ | G63: 45720 | H63: CCMS | I63: ROBINSONPJ-Office Supplies | K63: Adelaide office - Milk, Fruit, Drinks | M63: Woolworths Online | Q63: =ABS(E63) -> 349.77
A64: AU001 | B64: AU036740 | C64: 5100999000 | D64: Other office expenses | E64: 348.91 | F64: AUQ | G64: 45707 | H64: AP Accruals | I64: FTF00022078-ACANO00 | K64: Additional PAM letters Februar | L64: FTF00022078 | M64: CANON BUSINESS SERVICES AUSTRALIA PTY | Q64: =ABS(E64) -> 348.91
A65: AU052 | B65: AU030414 | C65: 5100999000 | D65: Other office expenses | E65: 338.73 | F65: AUQ | G65: 45663 | H65: CCMS | I65: CarterJ1-Offshore Meals & Lodg | K65: Dalby Community Event - Circles of Care | M65: ASHTONS DALBY | Q65: =ABS(E65) -> 338.73
A66: AU052 | B66: AU030619 | C66: 5100999000 | D66: Other office expenses | E66: 331.13 | F66: AUQ | G66: 45713 | H66: CCMS | I66: ThomasJ1-Office Supplies | K66: Info Session - catering requirements | M66: COLES 0396 | Q66: =ABS(E66) -> 331.13
A67: AU052 | B67: AU025064 | C67: 5100999000 | D67: Other office expenses | E67: 328.05 | F67: AUQ | G67: 45736 | H67: CCMS | I67: VosR5-Office Supplies | K67: DP3 Kitchen consumables | M67: Woolworths Online | Q67: =ABS(E67) -> 328.05
A68: AU052 | B68: AU030213 | C68: 5100999000 | D68: Other office expenses | E68: 323.62 | F68: AUQ | G68: 45734 | H68: CCMS | I68: GallowayM-Office Supplies | J68: Replacement projector with connectors | M68: OFFICEWORKS 0238 | Q68: =ABS(E68) -> 323.62 | AD68: =Q68 -> 323.62
A69: AU052 | B69: AU030433 | C69: 5100999000 | D69: Other office expenses | E69: 307.97 | F69: AUQ | G69: 45694 | H69: CCMS | I69: KorffD-Default Licensee Mercha | J69: Boardroom Microphone | M69: SP RODE MICROPHONES | Q69: =ABS(E69) -> 307.97 | AD69: =Q69 -> 307.97
A70: AU001 | B70: AU030421 | C70: 5100999000 | D70: Other office expenses | E70: 306.57 | F70: AUQ | G70: 45726 | H70: AP Accruals | I70: AUD634389-AIRON01 | K70: Iron Mountain - Feb 25 | L70: AUD634389 | M70: IRON MOUNTAIN AUSTRALIA GROUP PTY LTD | Q70: =ABS(E70) -> 306.57
A71: AU052 | B71: AU030711 | C71: 5100999000 | D71: Other office expenses | E71: 300.68 | F71: AUQ | G71: 45729 | H71: CCMS | I71: TabererC1-Default Licensee Mer | K71: Branch Set Up Items | M71: KMART 1009 | Q71: =ABS(E71) -> 300.68
A72: AU052 | B72: AU030433 | C72: 5100999000 | D72: Other office expenses | E72: 295.45 | F72: AUQ | G72: 45726 | H72: CCMS | I72: KorffD-Default Licensee Mercha | J72: Longreach Branch Event Esky | M72: SP EVAKOOL AUSTRALIA | Q72: =ABS(E72) -> 295.45 | AD72: =Q72 -> 295.45
A73: AU052 | B73: AU030618 | C73: 5100999000 | D73: Other office expenses | E73: 290.13 | F73: AUQ | G73: 45734 | H73: CCMS | I73: HudsonM1-Office Supplies | K73: Foodworks Moora Branch | M73: FARMER JACKS FOODWORKS | Q73: =ABS(E73) -> 290.13
A74: AU001 | B74: AU030619 | C74: 5100999000 | D74: Other office expenses | E74: 285.53 | F74: AUQ | G74: 45726 | H74: AP Accruals | I74: AUD634389-AIRON01 | K74: Iron Mountain - Feb 25 | L74: AUD634389 | M74: IRON MOUNTAIN AUSTRALIA GROUP PTY LTD | Q74: =ABS(E74) -> 285.53
A75: AU001 | B75: AU030618 | C75: 5100999000 | D75: Other office expenses | E75: 285.44 | F75: AUQ | G75: 45726 | H75: AP Accruals | I75: AUD634389-AIRON01 | K75: Iron Mountain - Feb 25 | L75: AUD634389 | M75: IRON MOUNTAIN AUSTRALIA GROUP PTY LTD | Q75: =ABS(E75) -> 285.44
A76: AU052 | B76: AU030619 | C76: 5100999000 | D76: Other office expenses | E76: 281.55 | F76: AUQ | G76: 45713 | H76: CCMS | I76: ThomasJ1-Offshore Meals & Lodg | K76: Pop Up Information sessions - catering requirements | M76: NARROGIN FRUIT MARKET | Q76: =ABS(E76) -> 281.55
A77: AU052 | B77: AU030220 | C77: 5100999000 | D77: Other office expenses | E77: 272.72 | F77: AUQ | G77: 45733 | H77: CCMS | I77: DavisM2-Entertainment Expense | K77: branch supplies | M77: DAN MURPHY'S/218 BEARDY S | Q77: =ABS(E77) -> 272.72 | S77: ME | T77: Y | U77: =B77 -> AU030220 | V77: =E77 -> 272.72
A78: AU052 | B78: AU025064 | C78: 5100999000 | D78: Other office expenses | E78: 259.53 | F78: AUQ | G78: 45698 | H78: AP Accruals | I78: CSYD2129183-AALSC00 | K78: Monthly Linen Hire for L16 Exe | L78: CSYD2129183 | M78: ALSCO SYDNEY T A ALSCO PTY LTD | Q78: =ABS(E78) -> 259.53
A79: AU001 | B79: AU076173 | C79: 5100999000 | D79: Other office expenses | E79: 258.84 | F79: AUQ | G79: 45677 | H79: AP Accruals | I79: AUD594816-AIRON01 | K79: Iron Mountain - Dec 24 | L79: AUD594816 | M79: IRON MOUNTAIN AUSTRALIA GROUP PTY LTD | Q79: =ABS(E79) -> 258.84
A80: AU001 | B80: AU030616 | C80: 5100999000 | D80: Other office expenses | E80: 244.31 | F80: AUQ | G80: 45726 | H80: AP Accruals | I80: AUD634389-AIRON01 | K80: Iron Mountain - Feb 25 | L80: AUD634389 | M80: IRON MOUNTAIN AUSTRALIA GROUP PTY LTD | Q80: =ABS(E80) -> 244.31
A81: AU001 | B81: AU030617 | C81: 5100999000 | D81: Other office expenses | E81: 239.29 | F81: AUQ | G81: 45726 | H81: AP Accruals | I81: AUD634389-AIRON01 | K81: Iron Mountain - Feb 25 | L81: AUD634389 | M81: IRON MOUNTAIN AUSTRALIA GROUP PTY LTD | Q81: =ABS(E81) -> 239.29
A82: AU001 | B82: AU010025 | C82: 5100999000 | D82: Other office expenses | E82: 226.12 | F82: AUQ | G82: 45712 | H82: AP Accruals | I82: AUD609996-AIRON01 | K82: Iron Mountain - Jan 25 | L82: AUD609996 | M82: IRON MOUNTAIN AUSTRALIA GROUP PTY LTD | Q82: =ABS(E82) -> 226.12
A83: AU001 | B83: AU010025 | C83: 5100999000 | D83: Other office expenses | E83: 226.12 | F83: AUQ | G83: 45726 | H83: AP Accruals | I83: AUD625387-AIRON01 | K83: Iron Mountain - Feb 25 | L83: AUD625387 | M83: IRON MOUNTAIN AUSTRALIA GROUP PTY LTD | Q83: =ABS(E83) -> 226.12
A84: AU001 | B84: AU010025 | C84: 5100999000 | D84: Other office expenses | E84: 226.09 | F84: AUQ | G84: 45677 | H84: AP Accruals | I84: AUD594816-AIRON01 | K84: Iron Mountain - Dec 24 | L84: AUD594816 | M84: IRON MOUNTAIN AUSTRALIA GROUP PTY LTD | Q84: =ABS(E84) -> 226.09
A85: AU052 | B85: AU030212 | C85: 5100999000 | D85: Other office expenses | E85: 221.17 | F85: AUQ | G85: 45721 | H85: AP Accruals | I85: SN00 4046 0203 2025-ATALB00 | K85: Newspapers for Dubbo Branch | L85: SN00 4046 0203 2025 | M85: TALBRAGAR STREET NEWSAGENCY | Q85: =ABS(E85) -> 221.17
A86: AU052 | B86: AU030619 | C86: 5100999000 | D86: Other office expenses | E86: 215.43 | F86: AUQ | G86: 45713 | H86: CCMS | I86: ThomasJ1-Entertainment Expense | K86: Info Session - catering requirements | M86: PALACE HOTEL WAGIN/144119026316 | Q86: =ABS(E86) -> 215.43 | S86: ME | T86: Y | U86: =B86 -> AU030619 | V86: =E86 -> 215.43
A87: AU001 | B87: AU030212 | C87: 5100999000 | D87: Other office expenses | E87: 214.4 | F87: AUQ | G87: 45712 | H87: AP Accruals | I87: AUD609996-AIRON01 | K87: Iron Mountain - Jan 25 | L87: AUD609996 | M87: IRON MOUNTAIN AUSTRALIA GROUP PTY LTD | Q87: =ABS(E87) -> 214.4
A88: AU001 | B88: AU030212 | C88: 5100999000 | D88: Other office expenses | E88: 214.4 | F88: AUQ | G88: 45726 | H88: AP Accruals | I88: AUD625387-AIRON01 | K88: Iron Mountain - Feb 25 | L88: AUD625387 | M88: IRON MOUNTAIN AUSTRALIA GROUP PTY LTD | Q88: =ABS(E88) -> 214.4
A89: AU001 | B89: AU030212 | C89: 5100999000 | D89: Other office expenses | E89: 214.37 | F89: AUQ | G89: 45677 | H89: AP Accruals | I89: AUD594816-AIRON01 | K89: Iron Mountain - Dec 24 | L89: AUD594816 | M89: IRON MOUNTAIN AUSTRALIA GROUP PTY LTD | Q89: =ABS(E89) -> 214.37
A90: AU001 | B90: AU030410 | C90: 5100999000 | D90: Other office expenses | E90: 210.55 | F90: AUQ | G90: 45712 | H90: AP Accruals | I90: AUD618982-AIRON01 | K90: Iron Mountain - Jan 25 | L90: AUD618982 | M90: IRON MOUNTAIN AUSTRALIA GROUP PTY LTD | Q90: =ABS(E90) -> 210.55
A91: AU052 | B91: AU030212 | C91: 5100999000 | D91: Other office expenses | E91: 202.09 | F91: AUQ | G91: 45691 | H91: AP Accruals | I91: SN00 4046 0202 2025-ATALB00 | K91: Newspapers for Dubbo Branch | L91: SN00 4046 0202 2025 | M91: TALBRAGAR STREET NEWSAGENCY | Q91: =ABS(E91) -> 202.09
A92: AU052 | B92: AU030212 | C92: 5100999000 | D92: Other office expenses | E92: 197.92 | F92: AUQ | G92: 45663 | H92: AP Accruals | I92: SN00 4046 2912 2024-ATALB00 | K92: Newspapers for Dubbo Branch | L92: SN00 4046 2912 2024 | M92: TALBRAGAR STREET NEWSAGENCY | Q92: =ABS(E92) -> 197.92
A93: AU001 | B93: AU030616 | C93: 5100999000 | D93: Other office expenses | E93: 197.87 | F93: AUQ | G93: 45712 | H93: AP Accruals | I93: AUD618982-AIRON01 | K93: Iron Mountain - Jan 25 | L93: AUD618982 | M93: IRON MOUNTAIN AUSTRALIA GROUP PTY LTD | Q93: =ABS(E93) -> 197.87
A94: AU052 | B94: AU025064 | C94: 5100999000 | D94: Other office expenses | E94: 195.59 | F94: AUQ | G94: 45726 | H94: AP Accruals | I94: CSYD2136351-AALSC00 | K94: Monthly Linen Hire for L16 Exe | L94: CSYD2136351 | M94: ALSCO SYDNEY T A ALSCO PTY LTD | Q94: =ABS(E94) -> 195.59
A95: AU052 | B95: AU030220 | C95: 5100999000 | D95: Other office expenses | E95: 194.55 | F95: AUQ | G95: 45693 | H95: CCMS | I95: DavisM2-Entertainment Expense | J95: branch supplies | M95: LIQUORLAND 3536 | Q95: =ABS(E95) -> 194.55 | S95: ME | T95: Y | U95: =B95 -> AU030220 | V95: =E95 -> 194.55
A96: AU001 | B96: AU030213 | C96: 5100999000 | D96: Other office expenses | E96: 188.38 | F96: AUQ | G96: 45692 | H96: AP Accruals | I96: 500316-ATOPS03 | K96: Newspaper account | L96: 500316 | M96: TOPSY TURVEY PTY LTD | Q96: =ABS(E96) -> 188.38
A97: AU001 | B97: AU030423 | C97: 5100999000 | D97: Other office expenses | E97: 187.98 | F97: AUQ | G97: 45726 | H97: AP Accruals | I97: AUD634389-AIRON01 | K97: Iron Mountain - Feb 25 | L97: AUD634389 | M97: IRON MOUNTAIN AUSTRALIA GROUP PTY LTD | Q97: =ABS(E97) -> 187.98
A98: AU001 | B98: AU030325 | C98: 5100999000 | D98: Other office expenses | E98: 187.85 | F98: AUQ | G98: 45677 | H98: AP Accruals | I98: AUD603806-AIRON01 | K98: Iron Mountain - Dec 24 | L98: AUD603806 | M98: IRON MOUNTAIN AUSTRALIA GROUP PTY LTD | Q98: =ABS(E98) -> 187.85
A99: AU001 | B99: AU030432 | C99: 5100999000 | D99: Other office expenses | E99: 187.08 | F99: AUQ | G99: 45726 | H99: AP Accruals | I99: AUD634389-AIRON01 | K99: Iron Mountain - Feb 25 | L99: AUD634389 | M99: IRON MOUNTAIN AUSTRALIA GROUP PTY LTD | Q99: =ABS(E99) -> 187.08
A100: AU052 | B100: AU030510 | C100: 5100999000 | D100: Other office expenses | E100: 183.64 | F100: AUQ | G100: 45688 | H100: CCMS | I100: ROBINSONPJ-Office Supplies | J100: Adelaide office - Milk, Fruit, Drinks | M100: Woolworths Online | Q100: =ABS(E100) -> 183.64
A101: AU001 | B101: AU030218 | C101: 5100999000 | D101: Other office expenses | E101: 174.95 | F101: AUQ | G101: 45726 | H101: AP Accruals | I101: AUD634389-AIRON01 | K101: Iron Mountain - Feb 25 | L101: AUD634389 | M101: IRON MOUNTAIN AUSTRALIA GROUP PTY LTD | Q101: =ABS(E101) -> 174.95
A102: AU052 | B102: AU030616 | C102: 5100999000 | D102: Other office expenses | E102: 174.64 | F102: AUQ | G102: 45686 | H102: CCMS | I102: BowmanR-Office Supplies | J102: Branch consumables/groceries | M102: Woolworths Online | Q102: =ABS(E102) -> 174.64
